Workbook

Sheet Hinweise
A1: C-Grundlagenkataster – institutionelle Ausgangslage | B1: Stand: 14.10.2026 (verifizierte Fassung)
A2: Zweck | B2: Arbeitskataster C1–C5 für Niklas Assignment 01; kein fertiges Tragfähigkeitsrating.
A3: Hierarchie | B3: Bund → Kantone Uri / Basel-Landschaft / St. Gallen → Pilotgemeinden Seelisberg / Münchenstein / Wil.
A4: Datenlage | B4: Offizielle Links wurden recherchiert; Portal-Links sind ausdrücklich keine Belege für spezifische Einzelangaben.
A5: Geltung | B5: Rechtsfassungen, Berichtsjahre und konkrete Werte vor Verwendung prüfen.
A6: Tragfähigkeit | B6: Noch nicht bewertet, da Kennzahlen und qualitative Befunde nicht vollständig erhoben wurden.
A7: Confidence | B7: Confidence bewertet die Aussagekraft der Katalogzeile, nicht die Gemeindequalität.
A8: Aufgabenprofil | B8: C1 Finanzen, C2 Boden, C3 Governance, C4 Verwaltung, C5 Politik; Kennzahlen/Reifegrade begründen.
A9: Peer-Logik | B9: Ausgangshypothese: C1 Kanton × Grössenklasse plus Richtwerte; C2–C5 ohne Peer.
A10: Zusammenarbeit | B10: A-Daten von Lias und Luucy-/B-Daten von Nikolaos übernehmen, nicht neu erheben.
A11: Datenanfrage | B11: Blatt Gemeindeanfragen enthält pro Pilotgemeinde benötigte Ergänzungen.
A12: Quellenkonvention | B12: Herkunft unterscheidet öffentliche Webrecherche von methodischen Ableitungen aus Aufgabenprofil und Grundlagendokument.
... A22: Konsistenz (Formel) | B22: Soll = Zeilen in der Gesamtübersicht, die zur Gemeinde gehören; Ist = Zeilen im Gemeindeblatt.
A23: Seelisberg | B23: ="Soll "&(COUNTIF('Gesamtübersicht'!$B:$B,"Bund")+COUNTIFS('Gesamtübersicht'!$B:$B,"Kanton",'Gesamtübersicht'!$D:$D,"Uri")+COUNTIFS('Gesamtübersicht'!$B:$B,"Gemeinde",'Gesamtübersicht'!$E:$E,"Seelisberg"))&" / Ist "&(COUNTA('Seelisberg'!$A:$A)-1)&" – "&IF((COUNTIF('Gesamtübersicht'!$B:$B,"Bund")+COUNTIFS('Gesamtübersicht'!$B:$B,"Kanton",'Gesamtübersicht'!$D:$D,"Uri")+COUNTIFS('Gesamtübersicht'!$B:$B,"Gemeinde",'Gesamtübersicht'!$E:$E,"Seelisberg"))=(COUNTA('Seelisberg'!$A:$A)-1),"OK","ABWEICHUNG: Ansicht neu erzeugen")
A24: Münchenstein | B24: ="Soll "&(COUNTIF('Gesamtübersicht'!$B:$B,"Bund")+COUNTIFS('Gesamtübersicht'!$B:$B,"Kanton",'Gesamtübersicht'!$D:$D,"Basel-Landschaft")+COUNTIFS('Gesamtübersicht'!$B:$B,"Gemeinde",'Gesamtübersicht'!$E:$E,"Münchenstein"))&" / Ist "&(COUNTA('Münchenstein'!$A:$A)-1)&" – "&IF((COUNTIF('Gesamtübersicht'!$B:$B,"Bund")+COUNTIFS('Gesamtübersicht'!$B:$B,"Kanton",'Gesamtübersicht'!$D:$D,"Basel-Landschaft")+COUNTIFS('Gesamtübersicht'!$B:$B,"Gemeinde",'Gesamtübersicht'!$E:$E,"Münchenstein"))=(COUNTA('Münchenstein'!$A:$A)-1),"OK","ABWEICHUNG: Ansicht neu erzeugen")
A25: Wil | B25: ="Soll "&(COUNTIF('Gesamtübersicht'!$B:$B,"Bund")+COUNTIFS('Gesamtübersicht'!$B:$B,"Kanton",'Gesamtübersicht'!$D:$D,"St. Gallen")+COUNTIFS('Gesamtübersicht'!$B:$B,"Gemeinde",'Gesamtübersicht'!$E:$E,"Wil"))&" / Ist "&(COUNTA('Wil'!$A:$A)-1)&" – "&IF((COUNTIF('Gesamtübersicht'!$B:$B,"Bund")+COUNTIFS('Gesamtübersicht'!$B:$B,"Kanton",'Gesamtübersicht'!$D:$D,"St. Gallen")+COUNTIFS('Gesamtübersicht'!$B:$B,"Gemeinde",'Gesamtübersicht'!$E:$E,"Wil"))=(COUNTA('Wil'!$A:$A)-1),"OK","ABWEICHUNG: Ansicht neu erzeugen")

Sheet Gesamtübersicht
A1: ID | B1: Ebene | C1: Schweiz | D1: Kanton | E1: Gemeinde | F1: C-Dimension | G1: Themenfeld | H1: Dokument / Datengrundlage | I1: Dokumenttyp | J1: Dokumentstatus | K1: Rechts- / Verbindlichkeitsstatus | L1: Herausgeber / Zuständigkeit | M1: Link / Quelle | N1: Bezugsjahr / Stand | O1: Aktualität geprüft am | P1: Konkrete Aussage / Relevanz | Q1: Kennzahl / Prüfkriterium | R1: Erhebungs- / Bewertungsmethode | S1: Vergleichsmassstab | T1: Reifegrad / Tragfähigkeit | U1: Confidence | V1: Datenlücke / Gemeindeanfrage | W1: Verbindung A / B / Q | X1: Sprint-2-Verwendung | Y1: Prüfstatus / nächste Aktion | Z1: Herkunft / Nachweis | AA1: Weitere C-Dimensionen | AB1: Veröffentlichungsdatum | AC1: Offizielle Fundstelle | AD1: Linkstatus | AE1: HTTP-Status | AF1: Finale URL (nach Weiterleitung) | AG1: Dateityp | AH1: Inhaltsprüfung | AI1: Inhaltsprüfung – Nachweis | AJ1: Erkannter Dokumenttitel | AK1: Erkannte Jahresangaben | AL1: Linkstabilität | AM1: Letzte Linkprüfung | AN1: Quellenverfügbarkeit | AO1: Einheit / Bezugsjahr | AP1: Prüfnachweis (belegbare Aussage) | AQ1: Bewertungsbegründung | AR1: Gemeindeanfrage erforderlich | AS1: Zuständige Stelle | AT1: Bearbeitungsstatus | AU1: Recherchehinweis | AV1: Gleiche Quelle wie (ID) | AW1: Änderungsprotokoll
A2: CH-C1-01 | B2: Bund | C2: Schweiz | D2: Alle | E2: Alle | F2: C1 | G2: Öffentliche Finanzstatistik | H2: Finanzstatistik: Daten der Eidgenössischen Finanzverwaltung | I2: Datenportal | J2: Offizielle Quelle recherchiert | K2: Orientierung / Datengrundlage | L2: Bund | M2: https://www.efv.admin.ch/de/finanzstatistik-daten | N2: Zu prüfen | O2: 2026-10-14 | P2: Harmonisierte Finanzstatistik als Kontext und methodische Vergleichsbasis | Q2: Finanzkennzahlen, Ausgaben, Einnahmen | R2: Zeitreihen und Aufgabenabgrenzung prüfen | S2: Kanton × Grössenklasse; Richtwerte | T2: Noch nicht bewertet | U2: Hoch | W2: A1/A2; C1 | X2: Finanziellen Spielraum und DYN-Korridor plausibilisieren | Y2: Dokument auswerten; Aktualität und Geltung prüfen | Z2: Offizielles Bundesportal; methodische Auswahl | AC2: https://www.efv.admin.ch/ | AD2: Verifiziert | AE2: 200 | AG2: HTML | AH2: Bestätigt | AI2: Schlüsselwörter 1/1 gefunden (Finanzstatistik) | AJ2: Übersicht über die Daten der Finanzstatistik | Übersicht über die Daten der Finanzstatistik | AK2: 2008, 2026, 2025, 2014 | AL2: Mittel (Webseite) | AM2: 2026-10-14 13:53 | AN2: Öffentlich verfügbar und verifiziert | AO2: Zu prüfen | AP2: Belegt Existenz und Zugänglichkeit der Quelle; inhaltliche Aussagen erst nach Auswertung. | AQ2: Keine Einstufung: Kennzahlen/Befunde noch nicht ausgewertet; Schwellen der Bewertungslogik noch nicht validiert. | AR2: Nein | AS2: Bund | AT2: In Prüfung
A3: CH-C1-02 | B3: Bund | C3: Schweiz | D3: Alle | E3: Alle | F3: C1 | G3: Rechnungslegung | H3: EFV: Methodik und Vergleichbarkeit der Finanzstatistik | I3: Methodik | J3: Offizielle Quelle recherchiert | K3: Orientierung / Datengrundlage | L3: Bund | M3: https://www.efv.admin.ch/de/was-ist-die-finanzstatistik | N3: Zu prüfen | O3: 2026-10-14 | P3: Kantonale Aufgabenverteilung begrenzt Vergleichbarkeit | Q3: HRM / Aufgabenabgrenzung | R3: Vergleichbarkeit explizit dokumentieren | S3: Kanton × Grössenklasse | T3: Noch nicht bewertet | U3: Hoch | W3: A1; C1 | X3: Vergleichsregeln absichern | Y3: Dokument auswerten; Aktualität und Geltung prüfen | Z3: Offizielles Bundesportal; methodische Auswahl | AD3: Verifiziert | AE3: 200 | AG3: HTML | AH3: Bestätigt | AI3: Schlüsselwörter 1/1 gefunden (Finanzstatistik) | AJ3: Was ist die Finanzstatistik? | Was ist die Finanzstatistik? | AK3: 2014, 2010, 2026, 2024, 2023, 2025 | AL3: Mittel (Webseite) | AM3: 2026-10-14 13:53 | AN3: Öffentlich verfügbar und verifiziert | AO3: Zu prüfen | AP3: Belegt Existenz und Zugänglichkeit der Quelle; inhaltliche Aussagen erst nach Auswertung. | AQ3: Keine Einstufung: Kennzahlen/Befunde noch nicht ausgewertet; Schwellen der Bewertungslogik noch nicht validiert. | AR3: Nein | AS3: Bund | AT3: In Prüfung
A4: CH-C1-03 | B4: Bund | C4: Schweiz | D4: Alle | E4: Alle | F4: C1 | G4: Finanzstatistik Methode | H4: EFV: Methoden der Finanzstatistik (FS-Modell, HRM2-Zuordnung) | I4: Methodik | J4: Webseite | K4: Methodische Grundlage | L4: Eidgenössische Finanzverwaltung (EFV) | M4: https://www.efv.admin.ch/de/methoden-finanzstatistik | O4: 2026-10-14 | P4: Definitionen der Kennzahlen und HRM2-Abbildung für Vergleichbarkeit | Q4: Kennzahlendefinitionen | S4: Kanton × Grössenklasse | T4: Noch nicht bewertet | U4: Hoch | W4: C1 | X4: Vergleichsregeln C1 | Y4: Dokument auswerten; Aktualität und Geltung prüfen | Z4: Automatische Recherche GitHub Actions (Discovery), Fundstelle siehe Spalte Offizielle Fundstelle | AC4: https://www.efv.admin.ch/de/finanzstatistik-daten | AD4: Verifiziert | AE4: 200 | AG4: HTML | AH4: Bestätigt | AI4: Schlüsselwörter 2/2 gefunden (Methode, Finanzstatistik) | AJ4: Methoden der Finanzstatistik | Methoden der Finanzstatistik | AK4: 2016, 2026, 2015, 2020, 2014, 2025 | AL4: Mittel (Webseite) | AM4: 2026-10-14 13:54 | AN4: Öffentlich verfügbar und verifiziert | AP4: Belegt Existenz und Zugänglichkeit der Quelle; inhaltliche Aussagen erst nach Auswertung. | AQ4: Keine Einstufung: Kennzahlen/Befunde noch nicht ausgewertet; Schwellen der Bewertungslogik noch nicht validiert. | AR4: Nein | AS4: Eidgenössische Finanzverwaltung (EFV) | AT4: In Prüfung | AU4: Früherer PDF-Link zum FS-Methodenband (efv.admin.ch/dam/…) liefert HTTP 502 (Website-Umbau); Methodenseite über EFV-Finanzstatistik ermittelt. | AW4: 2026-10-14: neu aufgenommen
A5: CH-C1-04 | B5: Bund | C5: Schweiz | D5: Alle | E5: Alle | F5: C1 | G5: Finanzdaten Gemeinden | H5: EFV: Detaillierte Daten FS- und GFS-Modell (Open Government Data) | I5: Datensatz | J5: Direktes Dokument | K5: Datengrundlage | L5: EFV / opendata.swiss | M5: https://opendata.swiss/en/dataset/detaillierte-daten-fs-und-gfs-modell-standardauswertungen | O5: 2026-10-14 | P5: Maschinenlesbare Finanzdaten für Peer-Vergleich | Q5: Einnahmen, Ausgaben, Schulden | S5: Kanton × Grössenklasse | T5: Noch nicht bewertet | U5: Mittel | Y5: Dokument auswerten; Aktualität und Geltung prüfen | Z5: Websuche 14.10.2026 (URL im Suchergebnis gefunden) | AD5: Verifiziert | AE5: 200 | AG5: HTML | AH5: Bestätigt | AI5: Schlüsselwörter 2/2 gefunden (FS, GFS) | AJ5: Detailed data FS and GFS model: Regular tables | opendata.swiss | Detailed data FS and GFS model: Regular tables | AK5: 2008, 2025, 2014, 2023 | AL5: Mittel (Webseite) | AM5: 2026-10-14 13:54 | AN5: Öffentlich verfügbar und verifiziert | AP5: Belegt Existenz und Zugänglichkeit der Quelle; inhaltliche Aussagen erst nach Auswertung. | AQ5: Keine Einstufung: Kennzahlen/Befunde noch nicht ausgewertet; Schwellen der Bewertungslogik noch nicht validiert. | AR5: Nein | AS5: EFV / opendata.swiss | AT5: In Prüfung | AW5: 2026-10-14: neu aufgenommen
A6: CH-C2-01 | B6: Bund | C6: Schweiz | D6: Alle | E6: Alle | F6: C2 | G6: Eigentumsrechte | H6: Schweizerisches Zivilgesetzbuch (ZGB) | I6: Bundesgesetz | J6: Offizielle Quelle recherchiert | K6: Bundesgesetz (verbindlich) | L6: Bund | M6: https://www.fedlex.admin.ch/eli/cc/24/233_245_233/de | N6: SR 210, geltende Fassung | O6: 2026-10-14 | P6: Eigentum, Dienstbarkeiten und Baurechte als rechtlicher Rahmen | Q6: Baurecht, Dienstbarkeit, Eigentum | R6: Grundbuch und Verträge gemeindespezifisch prüfen | S6: Kein Peer-Vergleich | T6: Noch nicht bewertet | U6: Hoch | W6: B; Q1 | X6: Bodenmobilisierung / Verfügung prüfen | Y6: Dokument auswerten; Aktualität und Geltung prüfen | Z6: Offizielles Bundesportal; methodische Auswahl | AD6: Verifiziert | AE6: 200 | AG6: HTML | AH6: Bestätigt | AI6: Titel via Fedlex-SPARQL (https://fedlex.data.admin.ch/eli/cc/24/233_245_233); Schlüsselwörter 1/1 gefunden (Zivilgesetzbuch) | AJ6: Schweizerisches Zivilgesetzbuch vom 10. Dezember 1907 (ZGB) | AL6: Hoch (ELI-Permalink) | AM6: 2026-10-14 13:53 | AN6: Öffentlich verfügbar und verifiziert | AO6: SR 210, geltende Fassung | AP6: Belegt Existenz und Zugänglichkeit der Quelle; inhaltliche Aussagen erst nach Auswertung. | AQ6: Keine Einstufung: Kennzahlen/Befunde noch nicht ausgewertet; Schwellen der Bewertungslogik noch nicht validiert. | AR6: Nein | AS6: Bund | AT6: In Prüfung
A7: CH-C2-02 | B7: Bund | C7: Schweiz | D7: Alle | E7: Alle | F7: C2 | G7: Raumplanung / Baulandmobilisierung | H7: Bundesgesetz über die Raumplanung (RPG), SR 700 | I7: Bundesgesetz | J7: Direktes Dokument | K7: Bundesgesetz (verbindlich) | L7: Bund | M7: https://www.fedlex.admin.ch/eli/cc/1979/1573_1573_1573/de | N7: SR 700, geltende Fassung | O7: 2026-10-14 | P7: Art. 15a RPG: Förderung der Verfügbarkeit von Bauland; Mehrwertausgleich Art. 5 | Q7: Bauverpflichtung, Mehrwertabgabe | S7: Kein Peer-Vergleich | T7: Noch nicht bewertet | U7: Hoch | W7: B; Q1 | Y7: Dokument auswerten; Aktualität und Geltung prüfen | Z7: ELI-Permalink Fedlex; Identität per Fedlex-SPARQL geprüft | AD7: Verifiziert | AE7: 200 | AG7: HTML | AH7: Bestätigt | AI7: Titel via Fedlex-SPARQL (https://fedlex.data.admin.ch/eli/cc/1979/1573_1573_1573); Schlüsselwörter 1/1 gefunden (Raumplanung) | AJ7: Bundesgesetz vom 22. Juni 1979 über die Raumplanung (Raumplanungsgesetz, RPG) (RPG) | AL7: Hoch (ELI-Permalink) | AM7: 2026-10-14 13:54 | AN7: Öffentlich verfügbar und verifiziert | AO7: SR 700, geltende Fassung | AP7: Belegt Existenz und Zugänglichkeit der Quelle; inhaltliche Aussagen erst nach Auswertung. | AQ7: Keine Einstufung: Kennzahlen/Befunde noch nicht ausgewertet; Schwellen der Bewertungslogik noch nicht validiert. | AR7: Nein | AS7: Bund | AT7: In Prüfung | AW7: 2026-10-14: neu aufgenommen
A8: CH-C3-01 | B8: Bund | C8: Schweiz | D8: Alle | E8: Alle | F8: C3 | G8: Interkommunale Zusammenarbeit | H8: Bundesverfassung der Schweizerischen Eidgenossenschaft | I8: Bundesverfassung | J8: Offizielle Quelle recherchiert | K8: Bundesverfassung (verbindlich) | L8: Bund | M8: https://www.fedlex.admin.ch/eli/cc/1999/404/de | N8: SR 101, geltende Fassung | O8: 2026-10-14 | P8: Grundlagen von Föderalismus und Gemeindeautonomie; Details kantonal | Q8: Zuständigkeits- und Kooperationsregeln | R8: Kantonale Gemeindeerlasse ergänzen | S8: Qualitative Reifegradskala | T8: Noch nicht bewertet | U8: Hoch | W8: Q6; C4 | X8: Trägerschaft und Kooperation beurteilen | Y8: Dokument auswerten; Aktualität und Geltung prüfen | Z8: Offizielles Bundesportal; methodische Auswahl | AA8: C5 | AD8: Verifiziert | AE8: 200 | AG8: HTML | AH8: Bestätigt | AI8: Titel via Fedlex-SPARQL (https://fedlex.data.admin.ch/eli/cc/1999/404); Schlüsselwörter 1/1 gefunden (Bundesverfassung) | AJ8: Bundesverfassung der Schweizerischen Eidgenossenschaft vom 18. April 1999 (BV) | AL8: Hoch (ELI-Permalink) | AM8: 2026-10-14 13:53 | AN8: Öffentlich verfügbar und verifiziert | AO8: SR 101, geltende Fassung | AP8: Belegt Existenz und Zugänglichkeit der Quelle; inhaltliche Aussagen erst nach Auswertung. | AQ8: Keine Einstufung: Kennzahlen/Befunde noch nicht ausgewertet; Schwellen der Bewertungslogik noch nicht validiert. | AR8: Nein | AS8: Bund | AT8: In Prüfung | AV8: CH-C5-01
A9: CH-C4-01 | B9: Bund | C9: Schweiz | D9: Alle | E9: Alle | F9: C4 | G9: Öffentliche Beschaffung | H9: Bundesgesetz über das öffentliche Beschaffungswesen (BöB) | I9: Bundesgesetz | J9: Offizielle Quelle recherchiert | K9: Bundesgesetz (verbindlich für Bundesbeschaffungen; Gemeinden: IVöB/kantonales Recht) | L9: Bund | M9: https://www.fedlex.admin.ch/eli/cc/2020/126/de | N9: SR 172.056.1, geltende Fassung | O9: 2026-10-14 | P9: Beschaffungsrechtlicher Orientierungsrahmen; kommunale Geltung kantonal prüfen | Q9: Beschaffungsprozess, Zuständigkeit | R9: Kantonales Beschaffungsrecht vorrangig auf Geltung prüfen | S9: Qualitative Reifegradskala | T9: Noch nicht bewertet | U9: Hoch | W9: Q6; C3 | X9: Bestellerkompetenz / Umsetzungsorganisation | Y9: Dokument auswerten; Aktualität und Geltung prüfen | Z9: Offizielles Bundesportal; methodische Auswahl | AD9: Verifiziert | AE9: 200 | AG9: HTML | AH9: Bestätigt | AI9: Titel via Fedlex-SPARQL (https://fedlex.data.admin.ch/eli/cc/2020/126); Schlüsselwörter 1/1 gefunden (öffentliche Beschaffungswesen) | AJ9: Bundesgesetz vom 21. Juni 2019 über das öffentliche Beschaffungswesen (BöB) (BöB) | AK9: 2019 | AL9: Hoch (ELI-Permalink) | AM9: 2026-10-14 13:53 | AN9: Öffentlich verfügbar und verifiziert | AO9: SR 172.056.1, geltende Fassung | AP9: Belegt Existenz und Zugänglichkeit der Quelle; inhaltliche Aussagen erst nach Auswertung. | AQ9: Keine Einstufung: Kennzahlen/Befunde noch nicht ausgewertet; Schwellen der Bewertungslogik noch nicht validiert. | AR9: Nein | AS9: Bund | AT9: In Prüfung
A10: CH-C4-02 | B10: Bund | C10: Schweiz | D10: Alle | E10: Alle | F10: C4 | G10: Gemeindekennzahlen | H10: BFS: Regionalporträts – Kennzahlen aller Gemeinden (Datensatz) | I10: Datensatz | J10: Direktes Dokument | K10: Datengrundlage | L10: Bundesamt für Statistik (BFS) | M10: https://ckan.opendata.swiss/dataset/regionalportrats-2021-kennzahlen-aller-gemeinden | N10: 2021 (neuere Ausgabe prüfen) | O10: 2026-10-14 | P10: Strukturdaten (Einwohner, Fläche) zur Bildung der Grössenklassen | S10: Grössenklasse | T10: Noch nicht bewertet | U10: Mittel | Y10: Dokument auswerten; Aktualität und Geltung prüfen | Z10: Websuche 14.10.2026 (URL im Suchergebnis gefunden) | AA10: C1 | AD10: Verifiziert | AE10: 200 | AG10: HTML | AH10: Bestätigt | AI10: Schlüsselwörter 1/1 gefunden (Regionalporträts) | AJ10: Regional portraits 2021: key data of all communes - Dataset - opendata.swiss | Regional portraits 2021: key data of all communes | AK10: 2021, 2019, 2004 | AL10: Mittel (Webseite) | AM10: 2026-10-14 13:54 | AN10: Öffentlich verfügbar und verifiziert | AO10: 2021 (neuere Ausgabe prüfen) | AP10: Belegt Existenz und Zugänglichkeit der Quelle; inhaltliche Aussagen erst nach Auswertung. | AQ10: Keine Einstufung: Kennzahlen/Befunde noch nicht ausgewertet; Schwellen der Bewertungslogik noch nicht validiert. | AR10: Nein | AS10: Bundesamt für Statistik (BFS) | AT10: In Prüfung | AU10: Ausgabe 2021; aktuelle Ausgabe beim BFS prüfen. | AW10: 2026-10-14: neu aufgenommen
A11: CH-C5-01 | B11: Bund | C11: Schweiz | D11: Alle | E11: Alle | F11: C5 | G11: Politische Rechte | H11: Bundesverfassung der Schweizerischen Eidgenossenschaft | I11: Bundesverfassung | J11: Offizielle Quelle recherchiert | K11: Bundesverfassung (verbindlich) | L11: Bund | M11: https://www.fedlex.admin.ch/eli/cc/1999/404/de | N11: SR 101, geltende Fassung | O11: 2026-10-14 | P11: Demokratische Grundrechte und Beteiligung; konkrete kommunale Verfahren kantonal | Q11: Mitwirkung / Legitimation | R11: Kommunale und kantonale Bestimmungen ergänzen | S11: Qualitative Reifegradskala | T11: Noch nicht bewertet | U11: Hoch | W11: Q1; C3 | X11: Politische Machbarkeit | Y11: Dokument auswerten; Aktualität und Geltung prüfen | Z11: Offizielles Bundesportal; methodische Auswahl | AA11: C3 | AD11: Verifiziert | AE11: 200 | AG11: HTML | AH11: Bestätigt | AI11: Titel via Fedlex-SPARQL (https://fedlex.data.admin.ch/eli/cc/1999/404); Schlüsselwörter 1/1 gefunden (Bundesverfassung) | AJ11: Bundesverfassung der Schweizerischen Eidgenossenschaft vom 18. April 1999 (BV) | AL11: Hoch (ELI-Permalink) | AM11: 2026-10-14 13:53 | AN11: Öffentlich verfügbar und verifiziert | AO11: SR 101, geltende Fassung | AP11: Belegt Existenz und Zugänglichkeit der Quelle; inhaltliche Aussagen erst nach Auswertung. | AQ11: Keine Einstufung: Kennzahlen/Befunde noch nicht ausgewertet; Schwellen der Bewertungslogik noch nicht validiert. | AR11: Nein | AS11: Bund | AT11: In Prüfung | AU11: Gleiche Quelle wie CH-C3-01; bewusst doppelt geführt (Zuordnung C5 politische Rechte). | AV11: CH-C3-01
A12: UR-C1-01 | B12: Kanton | C12: Schweiz | D12: Uri | E12: Alle | F12: C1 | G12: Finanzstatistik | H12: Gemeindefinanzstatistik Uri | I12: Statistik | J12: Offizielle Quelle recherchiert | K12: Orientierung / Datengrundlage | L12: Kanton Uri | M12: https://www.ur.ch/publikationen/6680 | N12: Zu prüfen | O12: 2026-10-14 | P12: Kennzahlen aller Urner Gemeinden | Q12: Selbstfinanzierung, Verschuldung, Investitionen | R12: Jahreswerte für Seelisberg extrahieren | S12: Kanton × Grössenklasse / Richtwerte | T12: Noch nicht bewertet | U12: Mittel | V12: Geltende kantonale Detailgrundlage und Datenstand prüfen | W12: A1; C1 | X12: Finanztragfähigkeit | Y12: Dokument auswerten; Aktualität und Geltung prüfen | Z12: Webrecherche 14.10.2026 | AD12: Verifiziert | AE12: 200 | AG12: HTML | AH12: Bestätigt | AI12: Schlüsselwörter 1/1 gefunden (Gemeindefinanzstatistik); Ort/Zuständigkeit: Uri | AJ12: Kanton Uri - Gemeindefinanzstatistik | Kontakt | AK12: 2023, 2025, 2026, 2024, 2022, 2021 | AL12: Mittel (CMS-Dokumentlink) | AM12: 2026-10-14 13:53 | AN12: Öffentlich verfügbar und verifiziert | AO12: Zu prüfen | AP12: Belegt Existenz und Zugänglichkeit der Quelle; inhaltliche Aussagen erst nach Auswertung. | AQ12: Keine Einstufung: Kennzahlen/Befunde noch nicht ausgewertet; Schwellen der Bewertungslogik noch nicht validiert. | AR12: Nein | AS12: Kanton Uri | AT12: In Prüfung
A13: UR-C1-02 | B13: Kanton | C13: Schweiz | D13: Uri | E13: Alle | F13: C1 | G13: Steuerkraft | H13: Steuerstatistiken Kanton Uri | I13: Statistik | J13: Offizielle Quelle recherchiert | K13: Orientierung / Datengrundlage | L13: Kanton Uri | M13: https://www.ur.ch/finanzen/1588 | N13: Zu prüfen | O13: 2026-10-14 | P13: Steuerbasis als Kontext zur Finanzkraft | Q13: Steuerbares Einkommen und Vermögen | R13: Lias-Daten übernehmen, nicht neu erheben | S13: Kanton × Grössenklasse | T13: Noch nicht bewertet | U13: Mittel | V13: Geltende kantonale Detailgrundlage und Datenstand prüfen | W13: A1/A2 | X13: DYN-Finanzkontext | Y13: Dokument auswerten; Aktualität und Geltung prüfen | Z13: Webrecherche 14.10.2026 | AD13: Verifiziert | AE13: 200 | AG13: HTML | AH13: Bestätigt | AI13: Schlüsselwörter 1/1 gefunden (Steuerstatistik); Ort/Zuständigkeit: Uri | AJ13: Kanton Uri - Steuerstatistiken | Kontakt | AK13: 2009, 2010, 2011, 2012, 2013, 2014 | AL13: Mittel (Webseite) | AM13: 2026-10-14 13:53 | AN13: Öffentlich verfügbar und verifiziert | AO13: Zu prüfen | AP13: Belegt Existenz und Zugänglichkeit der Quelle; inhaltliche Aussagen erst nach Auswertung. | AQ13: Keine Einstufung: Kennzahlen/Befunde noch nicht ausgewertet; Schwellen der Bewertungslogik noch nicht validiert. | AR13: Nein | AS13: Kanton Uri | AT13: In Prüfung
A14: UR-C1-03 | B14: Kanton | C14: Schweiz | D14: Uri | E14: Alle | F14: C1 | G14: Finanzkennzahlen Gemeinden | H14: Kennzahlen Einwohnergemeinden Uri 2025 (Finanzkontrolle) | I14: Statistik / Bericht | J14: Direktes Dokument | K14: Datengrundlage | L14: Kanton Uri, Finanzkontrolle | M14: https://www.ur.ch/_doc/451636 | N14: Rechnungsjahr 2025 (publ. 2026) | O14: 2026-10-14 | P14: Kennzahlen je Urner Gemeinde inkl. Seelisberg (Selbstfinanzierung, Kapitaldienst) | Q14: Selbstfinanzierungsanteil, Kapitaldienstanteil, Steuern/Kopf | S14: Kanton × Grössenklasse | T14: Noch nicht bewertet | U14: Hoch | W14: A1; C1 | X14: Finanztragfähigkeit Seelisberg im Kantonsvergleich | Y14: Dokument auswerten; Aktualität und Geltung prüfen | Z14: Websuche 14.10.2026 (URL im Suchergebnis gefunden) | AC14: https://www.ur.ch/publikationen/6680 | AD14: Weiterleitung | AE14: 200 | AF14: https://www.ur.ch/_docn/451636/Gemeindekennzahlen_2025_signiert.pdf | AG14: PDF | AH14: Bestätigt | AI14: Schlüsselwörter 2/2 gefunden (Kennzahlen, Seelisberg); Ort/Zuständigkeit: Uri | AJ14: Microsoft Word - Brief Versand Kennzahlen.docx | AK14: 2025, 2026, 2013, 2019, 2024 | AL14: Mittel (Webseite) | AM14: 2026-10-14 13:54 | AN14: Öffentlich verfügbar und verifiziert | AO14: Rechnungsjahr 2025 (publ. 2026) | AP14: Belegt Existenz und Zugänglichkeit der Quelle; inhaltliche Aussagen erst nach Auswertung. | AQ14: Keine Einstufung: Kennzahlen/Befunde noch nicht ausgewertet; Schwellen der Bewertungslogik noch nicht validiert. | AR14: Nein | AS14: Kanton Uri, Finanzkontrolle | AT14: In Prüfung | AW14: 2026-10-14: neu aufgenommen
A15: UR-C1-04 | B15: Kanton | C15: Schweiz | D15: Uri | E15: Alle | F15: C1 | G15: Finanzkennzahlen Gemeinden | H15: Kennzahlen Einwohnergemeinden Uri 2024 (Finanzkontrolle) | I15: Statistik / Bericht | J15: Direktes Dokument | K15: Datengrundlage | L15: Kanton Uri, Finanzkontrolle | M15: https://www.ur.ch/_doc/420775 | N15: Rechnungsjahr 2024 | O15: 2026-10-14 | P15: Vorjahreswerte für Zeitreihe | Q15: wie UR-C1-03 | S15: Kanton × Grössenklasse | T15: Noch nicht bewertet | U15: Hoch | Y15: Dokument auswerten; Aktualität und Geltung prüfen | Z15: Websuche 14.10.2026 (URL im Suchergebnis gefunden) | AC15: https://www.ur.ch/publikationen/6680 | AD15: Weiterleitung | AE15: 200 | AF15: https://www.ur.ch/_docn/420775/Gemeindekennzahlen_2024_signiert.pdf | AG15: PDF | AH15: Bestätigt | AI15: Schlüsselwörter 2/2 gefunden (Kennzahlen, Seelisberg); Ort/Zuständigkeit: Uri | AJ15: Gemeindekennzahlen 2024_final.xlsx | AK15: 2024, 2025, 2013, 2018 | AL15: Mittel (Webseite) | AM15: 2026-10-14 13:54 | AN15: Öffentlich verfügbar und verifiziert | AO15: Rechnungsjahr 2024 | AP15: Belegt Existenz und Zugänglichkeit der Quelle; inhaltliche Aussagen erst nach Auswertung. | AQ15: Keine Einstufung: Kennzahlen/Befunde noch nicht ausgewertet; Schwellen der Bewertungslogik noch nicht validiert. | AR15: Nein | AS15: Kanton Uri, Finanzkontrolle | AT15: In Prüfung | AW15: 2026-10-14: neu aufgenommen
A16: UR-C1-05 | B16: Kanton | C16: Schweiz | D16: Uri | E16: Alle | F16: C1 | G16: Rechnungslegung Gemeinden | H16: Reglement über das Rechnungswesen der Einwohnergemeinden (RRE), RB 3.2115 | I16: Kantonales Reglement | J16: Direktes Dokument | K16: Kantonales Recht (verbindlich) | L16: Regierungsrat Uri | M16: https://rechtsbuch.ur.ch/api/de/versions/776/pdf_file | N16: Version 776 (Stand prüfen) | O16: 2026-10-14 | P16: Rechtsgrundlage HRM2 und kantonale Finanzaufsicht über Gemeinden (Uri kennt kein separates FHGG) | S16: Kanton × Grössenklasse | T16: Noch nicht bewertet | U16: Hoch | Y16: Dokument auswerten; Aktualität und Geltung prüfen | Z16: Websuche 14.10.2026 (URL im Suchergebnis gefunden) | AC16: https://www.ur.ch/dienstleistungen/3150 | AD16: Verifiziert | AE16: 200 | AG16: PDF | AH16: Bestätigt | AI16: Schlüsselwörter 2/2 gefunden (Rechnungswesen, Einwohnergemeinden) | AJ16: 3.2115 - Reglement über das Rechnungswesen der Einwohnergemeinden | AK16: 2010, 2021, 2009, 2008 | AL16: Hoch (Erlassnummer) | AM16: 2026-10-14 13:54 | AN16: Öffentlich verfügbar und verifiziert | AO16: Version 776 (Stand prüfen) | AP16: Belegt Existenz und Zugänglichkeit der Quelle; inhaltliche Aussagen erst nach Auswertung. | AQ16: Keine Einstufung: Kennzahlen/Befunde noch nicht ausgewertet; Schwellen der Bewertungslogik noch nicht validiert. | AR16: Nein | AS16: Regierungsrat Uri | AT16: In Prüfung | AU16: Versions-PDF: prüfen, ob dies die geltende Fassung ist. | AW16: 2026-10-14: neu aufgenommen
A17: UR-C1-06 | B17: Kanton | C17: Schweiz | D17: Uri | E17: Alle | F17: C1 | G17: Finanzausgleich | H17: Gesetz über den Finanz- und Lastenausgleich zwischen dem Kanton und den Gemeinden (FiLaG), RB 3.2131 | I17: Kantonales Gesetz | J17: Direktes Dokument | K17: Kantonales Recht (verbindlich) | L17: Kanton Uri | M17: https://rechtsbuch.ur.ch/app/de/texts_of_law/3.2131 | N17: geltende Fassung | O17: 2026-10-14 | P17: Art. 22: Sonderbeitrag an Seelisberg (Abgeschiedenheit); Ressourcen- und Lastenausgleich | Q17: Ausgleichszahlungen | S17: Kanton × Grössenklasse | T17: Noch nicht bewertet | U17: Hoch | Y17: Dokument auswerten; Aktualität und Geltung prüfen | Z17: URL nach dokumentiertem Schema der amtlichen Rechtssammlung gebildet; Identität per Runner geprüft | AD17: Verifiziert | AE17: 200 | AG17: HTML | AH17: Bestätigt | AI17: Titel via LexWork-API (https://rechtsbuch.ur.ch/api/de/texts_of_law/3.2131); Schlüsselwörter 1/1 gefunden (Lastenausgleich) | AJ17: Gesetz über den Finanz- und Lastenausgleich zwischen dem Kanton und den Gemeinden | AK17: 2007, 2026, 2025, 2008 | AL17: Hoch (Erlassnummer) | AM17: 2026-10-14 13:54 | AN17: Öffentlich verfügbar und verifiziert | AO17: geltende Fassung | AP17: Belegt Existenz und Zugänglichkeit der Quelle; inhaltliche Aussagen erst nach Auswertung. | AQ17: Keine Einstufung: Kennzahlen/Befunde noch nicht ausgewertet; Schwellen der Bewertungslogik noch nicht validiert. | AR17: Nein | AS17: Kanton Uri | AT17: In Prüfung | AW17: 2026-10-14: neu aufgenommen
A18: UR-C1-07 | B18: Kanton | C18: Schweiz | D18: Uri | E18: Alle | F18: C1 | G18: Finanzausgleich | H18: Finanz- und Lastenausgleich (FiLa) 2025 – Berechnung je Gemeinde | I18: Berechnungstabelle | J18: Direktes Dokument | K18: Datengrundlage | L18: Kanton Uri, Finanzdirektion | M18: https://www.ur.ch/_docn/426685/Berechnung_FiLa_2025.pdf | N18: 2025 | O18: 2026-10-14 | P18: Höhe der Ausgleichszahlungen an Seelisberg | Q18: Ressourcenausgleich, Lastenausgleich CHF | S18: Kanton × Grössenklasse | T18: Noch nicht bewertet | U18: Hoch | Y18: Dokument auswerten; Aktualität und Geltung prüfen | Z18: Websuche 14.10.2026 (URL im Suchergebnis gefunden) | AD18: Verifiziert | AE18: 200 | AG18: PDF | AH18: Bestätigt | AI18: Schlüsselwörter 2/2 gefunden (2025, Seelisberg); Ort/Zuständigkeit: Uri | AJ18: FINANZDIREKTION Beilage 2 | AK18: 2025, 2024, 2023, 2021, 2015, 2008 | AL18: Mittel (CMS-Dokumentlink) | AM18: 2026-10-14 13:54 | AN18: Öffentlich verfügbar und verifiziert | AO18: 2025 | AP18: Belegt Existenz und Zugänglichkeit der Quelle; inhaltliche Aussagen erst nach Auswertung. | AQ18: Keine Einstufung: Kennzahlen/Befunde noch nicht ausgewertet; Schwellen der Bewertungslogik noch nicht validiert. | AR18: Nein | AS18: Kanton Uri, Finanzdirektion | AT18: In Prüfung | AW18: 2026-10-14: neu aufgenommen
A19: UR-C2-01 | B19: Kanton | C19: Schweiz | D19: Uri | E19: Alle | F19: C2 | G19: Geodaten / Eigentum | H19: Geoportal Uri: Liegenschaften und Nutzungsplanung | I19: Geodatenportal | J19: Offizielle Quelle recherchiert | K19: Orientierung / Datengrundlage | L19: Kanton Uri | M19: https://geo.ur.ch/ | N19: Zu prüfen | O19: 2026-10-14 | P19: Räumliche Parzellenstruktur; kein Nachweis kommunalen Eigentums | Q19: Parzellen, ÖBA-Zonen | R19: Luucy übernehmen, Eigentum separat belegen | S19: Kein Peer | T19: Noch nicht bewertet | U19: Mittel | V19: Geltende kantonale Detailgrundlage und Datenstand prüfen | W19: B; Q1 | X19: Bodenpotenzial | Y19: Dokument auswerten; Aktualität und Geltung prüfen | Z19: Webrecherche 14.10.2026 | AD19: Verifiziert | AE19: 200 | AG19: HTML | AH19: Bestätigt | AI19: Schlüsselwörter 1/1 gefunden (Geo); Ort/Zuständigkeit: geo.ur | AJ19: geo.ur | AL19: Mittel (Startseite, kein Dokument) | AM19: 2026-10-14 13:53 | AN19: Öffentlich verfügbar und verifiziert | AO19: Zu prüfen | AP19: Belegt Existenz und Zugänglichkeit der Quelle; inhaltliche Aussagen erst nach Auswertung. | AQ19: Keine Einstufung: Kennzahlen/Befunde noch nicht ausgewertet; Schwellen der Bewertungslogik noch nicht validiert. | AR19: Nein | AS19: Kanton Uri | AT19: In Prüfung | AU19: Kartenportal (JavaScript); Inhaltsprüfung nur eingeschränkt möglich. Kein Eigentumsnachweis.
A20: UR-C2-02 | B20: Kanton | C20: Schweiz | D20: Uri | E20: Alle | F20: C2 | G20: Raumplanung / Baulandmobilisierung | H20: Planungs- und Baugesetz (PBG) des Kantons Uri, RB 40.1111 | I20: Kantonales Gesetz | J20: Direktes Dokument | K20: Kantonales Recht (verbindlich) | L20: Kanton Uri | M20: https://rechtsbuch.ur.ch/app/de/texts_of_law/40.1111 | N20: geltende Fassung | O20: 2026-10-14 | P20: Bauverpflichtung/Baulandmobilisierung, Mehrwertausgleich | S20: Kein Peer-Vergleich | T20: Noch nicht bewertet | U20: Hoch | W20: B; Q1 | Y20: Dokument auswerten; Aktualität und Geltung prüfen | Z20: Websuche 14.10.2026 (URL im Suchergebnis gefunden) | AD20: Verifiziert | AE20: 200 | AG20: HTML | AH20: Bestätigt | AI20: Titel via LexWork-API (https://rechtsbuch.ur.ch/api/de/texts_of_law/40.1111); Schlüsselwörter 1/1 gefunden (Planungs) | AJ20: Planungs- und Baugesetz | AK20: 2010, 2022, 2012, 2021 | AL20: Hoch (Erlassnummer) | AM20: 2026-10-14 13:54 | AN20: Öffentlich verfügbar und verifiziert | AO20: geltende Fassung | AP20: Belegt Existenz und Zugänglichkeit der Quelle; inhaltliche Aussagen erst nach Auswertung. | AQ20: Keine Einstufung: Kennzahlen/Befunde noch nicht ausgewertet; Schwellen der Bewertungslogik noch nicht validiert. | AR20: Nein | AS20: Kanton Uri | AT20: In Prüfung | AW20: 2026-10-14: neu aufgenommen
A21: UR-C2-03 | B21: Kanton | C21: Schweiz | D21: Uri | E21: Alle | F21: C2 | G21: Bauland | H21: Kanton Uri: Baulanddatenbank (unbebaute Bauzonen, Raum+) | I21: Datenbank / Webseite | J21: Webseite | K21: Information | L21: Kanton Uri, Amt für Raumentwicklung | M21: https://www.ur.ch/dienstleistungen/4297 | O21: 2026-10-14 | P21: Unüberbaute Bauzonenreserven; kein Nachweis kommunalen Eigentums | S21: Kein Peer-Vergleich | T21: Noch nicht bewertet | U21: Mittel | Y21: Dokument auswerten; Aktualität und Geltung prüfen | Z21: Websuche 14.10.2026 (URL im Suchergebnis gefunden) | AD21: Verifiziert | AE21: 200 | AG21: HTML | AH21: Bestätigt | AI21: Schlüsselwörter 1/1 gefunden (Bauland); Ort/Zuständigkeit: Uri | AJ21: Kanton Uri - Baulanddatenbank | Kontakt | AK21: 2030, 2023, 2025, 2027, 2026 | AL21: Mittel (Webseite) | AM21: 2026-10-14 13:54 | AN21: Öffentlich verfügbar und verifiziert | AP21: Belegt Existenz und Zugänglichkeit der Quelle; inhaltliche Aussagen erst nach Auswertung. | AQ21: Keine Einstufung: Kennzahlen/Befunde noch nicht ausgewertet; Schwellen der Bewertungslogik noch nicht validiert. | AR21: Nein | AS21: Kanton Uri, Amt für Raumentwicklung | AT21: In Prüfung | AW21: 2026-10-14: neu aufgenommen
A22: UR-C3-01 | B22: Kanton | C22: Schweiz | D22: Uri | E22: Alle | F22: C3 | G22: Gemeinderecht | H22: Gemeindegesetz (GEG) des Kantons Uri, RB 1.1111 | I22: Kantonales Gesetz | J22: Offizielle Quelle recherchiert | K22: Kantonales Gesetz (verbindlich) | L22: Kanton Uri | M22: https://rechtsbuch.ur.ch/app/de/texts_of_law/1.1111 | N22: vom 21.5.2017; geltende Fassung | O22: 2026-10-14 | P22: Gemeinderechtliche Grundlagen und Zuständigkeiten recherchieren | Q22: Zuständigkeiten / Kooperation | R22: Konkrete Erlasse und geltende Fassung identifizieren | S22: Qualitativ | T22: Noch nicht bewertet | U22: Mittel | V22: Geltende kantonale Detailgrundlage und Datenstand prüfen | W22: Q6; C5 | X22: Governance | Y22: Dokument auswerten; Aktualität und Geltung prüfen | Z22: URL nach dokumentiertem Schema der amtlichen Rechtssammlung gebildet; Identität per Runner geprüft | AD22: Verifiziert | AE22: 200 | AG22: HTML | AH22: Bestätigt | AI22: Titel via LexWork-API (https://rechtsbuch.ur.ch/api/de/texts_of_law/1.1111); Schlüsselwörter 1/1 gefunden (Gemeindegesetz) | AJ22: Gemeindegesetz | AK22: 2017, 2026, 2025 | AL22: Hoch (Erlassnummer) | AM22: 2026-10-14 13:53 | AN22: Öffentlich verfügbar und verifiziert | AO22: vom 21.5.2017; geltende Fassung | AP22: Belegt Existenz und Zugänglichkeit der Quelle; inhaltliche Aussagen erst nach Auswertung. | AQ22: Keine Einstufung: Kennzahlen/Befunde noch nicht ausgewertet; Schwellen der Bewertungslogik noch nicht validiert. | AR22: Nein | AS22: Kanton Uri | AT22: In Prüfung | AW22: 2026-10-14: Link ersetzt (vorher https://rechtsbuch.ur.ch/). Grund: Startseite der Rechtssammlung durch direkten Erlass ersetzt (Gemeindegesetz, RB 1.1111).
A23: UR-C3-02 | B23: Kanton | C23: Schweiz | D23: Uri | E23: Alle | F23: C3 | G23: Kantonsverfassung | H23: Verfassung des Kantons Uri, RB 1.1101 | I23: Kantonsverfassung | J23: Direktes Dokument | K23: Kantonales Recht (verbindlich) | L23: Kanton Uri | M23: https://rechtsbuch.ur.ch/app/de/texts_of_law/1.1101 | N23: vom 28.10.1984; geltende Fassung | O23: 2026-10-14 | P23: Gemeindeautonomie; Art. 58 Finanzplanung der Gemeinden; Art. 110 Rechtsetzung Gemeinden | S23: Kein Peer-Vergleich | T23: Noch nicht bewertet | U23: Hoch | Y23: Dokument auswerten; Aktualität und Geltung prüfen | Z23: URL nach dokumentiertem Schema der amtlichen Rechtssammlung gebildet; Identität per Runner geprüft | AA23: C1, C5 | AD23: Verifiziert | AE23: 200 | AG23: HTML | AH23: Bestätigt | AI23: Titel via LexWork-API (https://rechtsbuch.ur.ch/api/de/texts_of_law/1.1101); Schlüsselwörter 1/1 gefunden (Verfassung) | AJ23: Verfassung des Kantons Uri | AK23: 2023, 2018 | AL23: Hoch (Erlassnummer) | AM23: 2026-10-14 13:54 | AN23: Öffentlich verfügbar und verifiziert | AO23: vom 28.10.1984; geltende Fassung | AP23: Belegt Existenz und Zugänglichkeit der Quelle; inhaltliche Aussagen erst nach Auswertung. | AQ23: Keine Einstufung: Kennzahlen/Befunde noch nicht ausgewertet; Schwellen der Bewertungslogik noch nicht validiert. | AR23: Nein | AS23: Kanton Uri | AT23: In Prüfung | AW23: 2026-10-14: neu aufgenommen
A24: UR-C4-01 | B24: Kanton | C24: Schweiz | D24: Uri | E24: Alle | F24: C4 | G24: Verwaltung | H24: Kanton Uri: Submissionsrecht (IVöB 2019, in Kraft seit 1.6.2023) | I24: Behördeninformation | J24: Offizielle Quelle recherchiert | K24: Information zu verbindlichem Recht | L24: Kanton Uri | M24: https://www.ur.ch/dienstleistungen/8444 | N24: Zu prüfen | O24: 2026-10-14 | P24: Rahmenbedingungen und interkommunale Aufgaben | Q24: Verwaltungsaufgaben / Organisation | R24: Gemeindespezifische Unterlagen ergänzen | S24: Qualitativ | T24: Noch nicht bewertet | U24: Mittel | V24: Geltende kantonale Detailgrundlage und Datenstand prüfen | W24: C3; Q6 | X24: Verwaltungskapazität | Y24: Dokument auswerten; Aktualität und Geltung prüfen | Z24: Webrecherche 14.10.2026 | AD24: Verifiziert | AE24: 200 | AG24: HTML | AH24: Bestätigt | AI24: Schlüsselwörter 1/1 gefunden (Submission); Ort/Zuständigkeit: Uri | AJ24: Kanton Uri - Submissionsrecht | Kontakt | AK24: 2023, 2030, 2025, 2027, 2026 | AL24: Mittel (Webseite) | AM24: 2026-10-14 13:53 | AN24: Öffentlich verfügbar und verifiziert | AO24: Zu prüfen | AP24: Belegt Existenz und Zugänglichkeit der Quelle; inhaltliche Aussagen erst nach Auswertung. | AQ24: Keine Einstufung: Kennzahlen/Befunde noch nicht ausgewertet; Schwellen der Bewertungslogik noch nicht validiert. | AR24: Nein | AS24: Kanton Uri | AT24: In Prüfung | AW24: 2026-10-14: Link ersetzt (vorher https://www.ur.ch/). Grund: Allgemeine Startseite ur.ch durch themenspezifische Seite zum Beschaffungsrecht ersetzt.
A25: UR-C4-02 | B25: Kanton | C25: Schweiz | D25: Uri | E25: Alle | F25: C4 | G25: Beschaffung | H25: Interkantonale Vereinbarung über das öffentliche Beschaffungswesen (IVöB 2019), RB 3.3111 | I25: Interkantonales Recht | J25: Direktes Dokument | K25: Interkantonales Recht (verbindlich) | L25: Kanton Uri | M25: https://rechtsbuch.ur.ch/app/de/texts_of_law/3.3111 | O25: 2026-10-14 | P25: Beschaffungsrecht für Gemeinden (Schwellenwerte, Verfahren) | S25: Kein Peer-Vergleich | T25: Noch nicht bewertet | U25: Hoch | Y25: Dokument auswerten; Aktualität und Geltung prüfen | Z25: URL nach dokumentiertem Schema der amtlichen Rechtssammlung gebildet; Identität per Runner geprüft | AD25: Verifiziert | AE25: 200 | AG25: HTML | AH25: Bestätigt | AI25: Titel via LexWork-API (https://rechtsbuch.ur.ch/api/de/texts_of_law/3.3111); Schlüsselwörter 1/1 gefunden (Beschaffungswesen) | AJ25: Interkantonale Vereinbarung über das öffentliche Beschaffungswesen | AK25: 2023, 2019 | AL25: Hoch (Erlassnummer) | AM25: 2026-10-14 13:54 | AN25: Öffentlich verfügbar und verifiziert | AP25: Belegt Existenz und Zugänglichkeit der Quelle; inhaltliche Aussagen erst nach Auswertung. | AQ25: Keine Einstufung: Kennzahlen/Befunde noch nicht ausgewertet; Schwellen der Bewertungslogik noch nicht validiert. | AR25: Nein | AS25: Kanton Uri | AT25: In Prüfung | AW25: 2026-10-14: neu aufgenommen
A26: UR-C5-01 | B26: Kanton | C26: Schweiz | D26: Uri | E26: Alle | F26: C5 | G26: Politische Rechte | H26: Gesetz über die geheimen Wahlen, Abstimmungen und die Volksrechte (WAVG), RB 2.1201 | I26: Kantonales Gesetz | J26: Offizielle Quelle recherchiert | K26: Kantonales Gesetz (verbindlich) | L26: Kanton Uri | M26: https://rechtsbuch.ur.ch/app/de/texts_of_law/2.1201 | N26: geltende Fassung; Revision hängig (Synopse 2026) | O26: 2026-10-14 | P26: Rechtsrahmen für kommunale Entscheidungen | Q26: Referendum / Zuständigkeiten | R26: Gemeindeordnung konkret prüfen | S26: Qualitativ | T26: Noch nicht bewertet | U26: Mittel | V26: Geltende kantonale Detailgrundlage und Datenstand prüfen | W26: C3; Q1 | X26: Politische Tragfähigkeit | Y26: Dokument auswerten; Aktualität und Geltung prüfen | Z26: URL nach dokumentiertem Schema der amtlichen Rechtssammlung gebildet; Identität per Runner geprüft | AD26: Verifiziert | AE26: 200 | AG26: HTML | AH26: Bestätigt | AI26: Titel via LexWork-API (https://rechtsbuch.ur.ch/api/de/texts_of_law/2.1201); Schlüsselwörter 1/1 gefunden (Wahlen) | AJ26: Gesetz über die geheimen Wahlen, Abstimmungen und die Volksrechte | AK26: 2010, 2009 | AL26: Hoch (Erlassnummer) | AM26: 2026-10-14 13:53 | AN26: Öffentlich verfügbar und verifiziert | AO26: geltende Fassung; Revision hängig (Synopse 2026) | AP26: Belegt Existenz und Zugänglichkeit der Quelle; inhaltliche Aussagen erst nach Auswertung. | AQ26: Keine Einstufung: Kennzahlen/Befunde noch nicht ausgewertet; Schwellen der Bewertungslogik noch nicht validiert. | AR26: Nein | AS26: Kanton Uri | AT26: In Prüfung | AW26: 2026-10-14: Link ersetzt (vorher https://rechtsbuch.ur.ch/). Grund: Startseite der Rechtssammlung durch direkten Erlass ersetzt (WAVG, RB 2.1201).
A27: BL-C1-01 | B27: Kanton | C27: Schweiz | D27: Basel-Landschaft | E27: Alle | F27: C1 | G27: Gemeindefinanzen | H27: Statistik Basel-Landschaft: Gemeindefinanzen / Finanzausgleich | I27: Statistik | J27: Offizielle Quelle recherchiert | K27: Orientierung / Datengrundlage | L27: Kanton Basel-Landschaft | M27: https://statistik.bl.ch/web_portal/18_5 | N27: Zu prüfen | O27: 2026-10-14 | P27: Finanz- und Finanzausgleichsdaten nach Gemeinde | Q27: Finanzausgleich, Finanzkennzahlen | R27: Münchenstein herausfiltern | S27: Kanton × Grössenklasse | T27: Noch nicht bewertet | U27: Mittel | V27: Geltende kantonale Detailgrundlage und Datenstand prüfen | W27: A1; C1 | X27: Finanztragfähigkeit | Y27: Dokument auswerten; Aktualität und Geltung prüfen | Z27: Webrecherche 14.10.2026 | AD27: Verifiziert | AE27: 200 | AG27: HTML | AH27: Bestätigt | AI27: Schlüsselwörter 1/1 gefunden (Gemeindefinanzen); Ort/Zuständigkeit: Basel-Landschaft, Baselland | AJ27: Statistik Baselland | AK27: 2026, 2025, 2024, 2023, 2022, 2021 | AL27: Mittel (Webseite) | AM27: 2026-10-14 13:53 | AN27: Öffentlich verfügbar und verifiziert | AO27: Zu prüfen | AP27: Belegt Existenz und Zugänglichkeit der Quelle; inhaltliche Aussagen erst nach Auswertung. | AQ27: Keine Einstufung: Kennzahlen/Befunde noch nicht ausgewertet; Schwellen der Bewertungslogik noch nicht validiert. | AR27: Nein | AS27: Kanton Basel-Landschaft | AT27: In Prüfung
A28: BL-C1-02 | B28: Kanton | C28: Schweiz | D28: Basel-Landschaft | E28: Alle | F28: C1 | G28: Rechnungslegung | H28: Gemeindefinanzen BL: Rechnungslegung und Excel-Vorlagen | I28: Arbeitshilfe | J28: Offizielle Quelle recherchiert | K28: Orientierung / Datengrundlage | L28: Kanton Basel-Landschaft | M28: https://www.baselland.ch/politik-und-behorden/gemeinden/gemeindefinanzen/rechnungslegung-einwohnergemeinden/excel-vorlagen | N28: Zu prüfen | O28: 14.10.2026 | P28: HRM2-Struktur, Bilanz und Investitionsrechnung | Q28: Investitionen / Bilanz | R28: Jahresrechnung nach einheitlichem Raster auswerten | S28: Kanton × Grössenklasse | T28: Noch nicht bewertet | U28: Mittel | V28: Geltende kantonale Detailgrundlage und Datenstand prüfen | W28: C1 | X28: Vergleichbarkeit | Y28: Dokument auswerten; Aktualität und Geltung prüfen | Z28: Webrecherche 14.10.2026 | AD28: Nicht prüfbar | AE28: 403 | AH28: Offen | AI28: Zugriff verweigert/gedrosselt (HTTP 403); keine Umgehung versucht | AL28: Mittel (Webseite) | AM28: 2026-10-14 13:53 | AN28: Nicht zugänglich / nicht prüfbar | AO28: Zu prüfen | AP28: Belegt Existenz und Zugänglichkeit der Quelle; inhaltliche Aussagen erst nach Auswertung. | AQ28: Keine Einstufung: Kennzahlen/Befunde noch nicht ausgewertet; Schwellen der Bewertungslogik noch nicht validiert. | AR28: Nein | AS28: Kanton Basel-Landschaft | AT28: Offen | AU28: Automatisch nicht prüfbar – manuell im Browser prüfen
A29: BL-C1-03 | B29: Kanton | C29: Schweiz | D29: Basel-Landschaft | E29: Alle | F29: C1 | G29: Rechnungslegung Gemeinden | H29: Kanton BL: Gemeindefinanzen (Rechtsgrundlagen, Finanzausgleich, Rechnungslegung) | I29: Behördeninformation | J29: Webseite | K29: Information | L29: Kanton Basel-Landschaft, Finanz- und Kirchendirektion | M29: https://www.baselland.ch/politik-und-behorden/gemeinden/gemeindefinanzen | O29: 2026-10-14 | P29: Einstieg zu Finanzhandbuch, Rechtsgrundlagen und Finanzausgleich | S29: Kanton × Grössenklasse | T29: Noch nicht bewertet | U29: Mittel | Y29: Dokument auswerten; Aktualität und Geltung prüfen | Z29: Websuche 14.10.2026 (URL im Suchergebnis gefunden) | AD29: Nicht prüfbar | AE29: 403 | AH29: Offen | AI29: Zugriff verweigert/gedrosselt (HTTP 403); keine Umgehung versucht | AL29: Mittel (Webseite) | AM29: 2026-10-14 13:54 | AN29: Nicht zugänglich / nicht prüfbar | AP29: Belegt Existenz und Zugänglichkeit der Quelle; inhaltliche Aussagen erst nach Auswertung. | AQ29: Keine Einstufung: Kennzahlen/Befunde noch nicht ausgewertet; Schwellen der Bewertungslogik noch nicht validiert. | AR29: Nein | AS29: Kanton Basel-Landschaft, Finanz- und Kirchendirektion | AT29: Offen | AU29: Automatisch nicht prüfbar – manuell im Browser prüfen | AW29: 2026-10-14: neu aufgenommen
A30: BL-C1-05 | B30: Kanton | C30: Schweiz | D30: Basel-Landschaft | E30: Alle | F30: C1 | G30: Finanzstatistik Gemeinden | H30: Statistisches Amt BL: Webartikel Gemeindefinanzen 2023 (18.9.2024) | I30: Statistischer Bericht | J30: Webseite | K30: Information | L30: Statistisches Amt Basel-Landschaft | M30: https://www.baselland.ch/politik-und-behorden/direktionen/finanz-und-kirchendirektion/daten-statistik/abteilung-statistik/publikationen-und-statistiken/finanzen-und-steuern/webartikel-vom-18-09-2024-gemeindefinanzen-2023 | N30: 2023 | O30: 2026-10-14 | P30: Kantonaler Überblick Ergebnis/Eigenkapital der Gemeinden | S30: Kanton × Grössenklasse | T30: Noch nicht bewertet | U30: Mittel | Y30: Dokument auswerten; Aktualität und Geltung prüfen | Z30: Websuche 14.10.2026 (URL im Suchergebnis gefunden) | AD30: Nicht prüfbar | AE30: 403 | AH30: Offen | AI30: Zugriff verweigert/gedrosselt (HTTP 403); keine Umgehung versucht | AL30: Mittel (Webseite) | AM30: 2026-10-14 13:54 | AN30: Nicht zugänglich / nicht prüfbar | AO30: 2023 | AP30: Belegt Existenz und Zugänglichkeit der Quelle; inhaltliche Aussagen erst nach Auswertung. | AQ30: Keine Einstufung: Kennzahlen/Befunde noch nicht ausgewertet; Schwellen der Bewertungslogik noch nicht validiert. | AR30: Nein | AS30: Statistisches Amt Basel-Landschaft | AT30: Offen | AU30: Automatisch nicht prüfbar – manuell im Browser prüfen | AW30: 2026-10-14: neu aufgenommen
A31: BL-C1-06 | B31: Kanton | C31: Schweiz | D31: Basel-Landschaft | E31: Alle | F31: C1 | G31: Finanzausgleich | H31: Finanzausgleichsgesetz (FAG) Basel-Landschaft, SGS 185 | I31: Kantonales Gesetz | J31: Direktes Dokument | K31: Kantonales Recht (verbindlich) | L31: Kanton Basel-Landschaft | M31: https://bl.clex.ch/app/de/texts_of_law/185 | O31: 2026-10-14 | P31: Ressourcen- und Lastenausgleich; Münchenstein als Geber/Nehmer prüfen | S31: Kanton × Grössenklasse | T31: Noch nicht bewertet | U31: Hoch | Y31: Dokument auswerten; Aktualität und Geltung prüfen | Z31: URL nach dokumentiertem Schema der amtlichen Rechtssammlung gebildet; Identität per Runner geprüft | AD31: Verifiziert | AE31: 200 | AG31: HTML | AH31: Bestätigt | AI31: Titel via LexWork-API (https://bl.clex.ch/api/de/texts_of_law/185); Schlüsselwörter 1/1 gefunden (Finanzausgleich) | AJ31: Finanzausgleichsgesetz | AK31: 2023, 2009, 2010, 2024, 2025, 2026 | AL31: Hoch (Erlassnummer) | AM31: 2026-10-14 13:54 | AN31: Öffentlich verfügbar und verifiziert | AP31: Belegt Existenz und Zugänglichkeit der Quelle; inhaltliche Aussagen erst nach Auswertung. | AQ31: Keine Einstufung: Kennzahlen/Befunde noch nicht ausgewertet; Schwellen der Bewertungslogik noch nicht validiert. | AR31: Nein | AS31: Kanton Basel-Landschaft | AT31: In Prüfung | AW31: 2026-10-14: neu aufgenommen
A32: BL-C2-01 | B32: Kanton | C32: Schweiz | D32: Basel-Landschaft | E32: Alle | F32: C2 | G32: Geodaten | H32: Geoportal Basel-Landschaft | I32: Geodatenportal | J32: Offizielle Quelle recherchiert | K32: Orientierung / Datengrundlage | L32: Kanton Basel-Landschaft | M32: https://geoview.bl.ch/ | N32: Zu prüfen | O32: 2026-10-14 | P32: Parzellen- und Zoneninformationen; Eigentum gesondert nachweisen | Q32: ÖBA, Parzellenstruktur | R32: Luucy übernehmen; Eigentümerdaten abgleichen | S32: Kein Peer | T32: Noch nicht bewertet | U32: Mittel | V32: Geltende kantonale Detailgrundlage und Datenstand prüfen | W32: B; Q1 | X32: Bodenverfügbarkeit | Y32: Dokument auswerten; Aktualität und Geltung prüfen | Z32: Webrecherche 14.10.2026 | AD32: Verifiziert | AE32: 200 | AG32: HTML | AH32: Bestätigt | AI32: Schlüsselwörter 1/1 gefunden (GeoView); Ort/Zuständigkeit: BL, geoview | AJ32: GeoView BL | AK32: 2011, 2001 | AL32: Mittel (Startseite, kein Dokument) | AM32: 2026-10-14 13:53 | AN32: Öffentlich verfügbar und verifiziert | AO32: Zu prüfen | AP32: Belegt Existenz und Zugänglichkeit der Quelle; inhaltliche Aussagen erst nach Auswertung. | AQ32: Keine Einstufung: Kennzahlen/Befunde noch nicht ausgewertet; Schwellen der Bewertungslogik noch nicht validiert. | AR32: Nein | AS32: Kanton Basel-Landschaft | AT32: In Prüfung | AU32: Kartenportal (JavaScript); kein Eigentumsnachweis.
A33: BL-C2-02 | B33: Kanton | C33: Schweiz | D33: Basel-Landschaft | E33: Alle | F33: C2 | G33: Raumplanung / Baulandmobilisierung | H33: Raumplanungs- und Baugesetz (RBG) Basel-Landschaft, SGS 400 | I33: Kantonales Gesetz | J33: Direktes Dokument | K33: Kantonales Recht (verbindlich) | L33: Kanton Basel-Landschaft | M33: https://bl.clex.ch/app/de/texts_of_law/400 | N33: vom 8.1.1998; geltende Fassung | O33: 2026-10-14 | P33: Mehrwertabgabe, Quartierplanung, Mitwirkung § 7 RBG | S33: Kein Peer-Vergleich | T33: Noch nicht bewertet | U33: Hoch | W33: B; Q1 | Y33: Dokument auswerten; Aktualität und Geltung prüfen | Z33: Websuche 14.10.2026 (URL im Suchergebnis gefunden) | AA33: C5 | AD33: Verifiziert | AE33: 200 | AG33: HTML | AH33: Bestätigt | AI33: Titel via LexWork-API (https://bl.clex.ch/api/de/texts_of_law/400); Schlüsselwörter 1/1 gefunden (Raumplanungs) | AJ33: Raumplanungs- und Baugesetz | AK33: 2024, 2023 | AL33: Hoch (Erlassnummer) | AM33: 2026-10-14 13:54 | AN33: Öffentlich verfügbar und verifiziert | AO33: vom 8.1.1998; geltende Fassung | AP33: Belegt Existenz und Zugänglichkeit der Quelle; inhaltliche Aussagen erst nach Auswertung. | AQ33: Keine Einstufung: Kennzahlen/Befunde noch nicht ausgewertet; Schwellen der Bewertungslogik noch nicht validiert. | AR33: Nein | AS33: Kanton Basel-Landschaft | AT33: In Prüfung | AW33: 2026-10-14: neu aufgenommen
A34: BL-C3-01 | B34: Kanton | C34: Schweiz | D34: Basel-Landschaft | E34: Alle | F34: C3 | G34: Gemeinderecht | H34: Gemeindegesetz (GemG) Basel-Landschaft, SGS 180 | I34: Kantonales Gesetz | J34: Offizielle Quelle recherchiert | K34: Kantonales Gesetz (verbindlich) | L34: Kanton Basel-Landschaft | M34: https://bl.clex.ch/app/de/texts_of_law/180 | N34: vom 28.5.1970; geltende Fassung | O34: 2026-10-14 | P34: Gemeinderecht und Kooperationsinstrumente | Q34: Gemeindeordnung / Kooperation | R34: Relevante Normen konkret auswählen | S34: Qualitativ | T34: Noch nicht bewertet | U34: Mittel | V34: Geltende kantonale Detailgrundlage und Datenstand prüfen | W34: C4; C5 | X34: Trägerschaft | Y34: Dokument auswerten; Aktualität und Geltung prüfen | Z34: Websuche 14.10.2026 (URL im Suchergebnis gefunden) | AD34: Verifiziert | AE34: 200 | AG34: HTML | AH34: Bestätigt | AI34: Titel via LexWork-API (https://bl.clex.ch/api/de/texts_of_law/180); Schlüsselwörter 1/1 gefunden (Gemeinden) | AJ34: Gesetz über die Organisation und die Verwaltung der Gemeinden | AK34: 2026, 2008, 2004, 2005, 2009 | AL34: Hoch (Erlassnummer) | AM34: 2026-10-14 13:53 | AN34: Öffentlich verfügbar und verifiziert | AO34: vom 28.5.1970; geltende Fassung | AP34: Belegt Existenz und Zugänglichkeit der Quelle; inhaltliche Aussagen erst nach Auswertung. | AQ34: Keine Einstufung: Kennzahlen/Befunde noch nicht ausgewertet; Schwellen der Bewertungslogik noch nicht validiert. | AR34: Nein | AS34: Kanton Basel-Landschaft | AT34: In Prüfung | AW34: 2026-10-14: Link ersetzt (vorher https://bl.clex.ch/). Grund: Startseite der Gesetzessammlung durch direkten Erlass ersetzt (Gemeindegesetz SGS 180).
A35: BL-C3-02 | B35: Kanton | C35: Schweiz | D35: Basel-Landschaft | E35: Alle | F35: C3 | G35: Regionale Kooperation | H35: Medienmitteilung Kanton BL: Birsstadt erhält den Wakkerpreis (Verein Birsstadt, Raumkonzept Birsstadt 2035) | I35: Medienmitteilung | J35: Webseite | K35: Information | L35: Kanton Basel-Landschaft, Bau- und Umweltschutzdirektion | M35: https://www.baselland.ch/politik-und-behorden/direktionen/bau-und-umweltschutzdirektion/medienmitteilungen/ausgezeichnete-agglomeration-birsstadt-erhaelt-den-wakkerpreis | O35: 2026-10-14 | P35: Belegt interkommunale Kooperation Birsstadt (10 Gemeinden inkl. Münchenstein) | S35: Kein Peer-Vergleich | T35: Noch nicht bewertet | U35: Mittel | Y35: Dokument auswerten; Aktualität und Geltung prüfen | Z35: Websuche 14.10.2026 (URL im Suchergebnis gefunden) | AD35: Nicht prüfbar | AE35: 403 | AH35: Offen | AI35: Zugriff verweigert/gedrosselt (HTTP 403); keine Umgehung versucht | AL35: Mittel (Webseite) | AM35: 2026-10-14 13:54 | AN35: Nicht zugänglich / nicht prüfbar | AP35: Belegt Existenz und Zugänglichkeit der Quelle; inhaltliche Aussagen erst nach Auswertung. | AQ35: Keine Einstufung: Kennzahlen/Befunde noch nicht ausgewertet; Schwellen der Bewertungslogik noch nicht validiert. | AR35: Nein | AS35: Kanton Basel-Landschaft, Bau- und Umweltschutzdirektion | AT35: Offen | AU35: Automatisch nicht prüfbar – manuell im Browser prüfen | AW35: 2026-10-14: neu aufgenommen
A36: BL-C4-01 | B36: Kanton | C36: Schweiz | D36: Basel-Landschaft | E36: Alle | F36: C4 | G36: Verwaltung | H36: Kanton Basel-Landschaft: Gemeindefachstellen | I36: Behördenportal | J36: Offizielle Quelle recherchiert | K36: Orientierung / Datengrundlage | L36: Kanton Basel-Landschaft | M36: https://www.baselland.ch/politik-und-behorden/gemeinden | N36: Zu prüfen | O36: 14.10.2026 | P36: Fachliche Rahmenbedingungen für Gemeindeverwaltung | Q36: Organisation / Kompetenzen | R36: Kommunale Organisationsdokumente ergänzen | S36: Qualitativ | T36: Noch nicht bewertet | U36: Mittel | V36: Geltende kantonale Detailgrundlage und Datenstand prüfen | W36: Q6 | X36: Bestellerkompetenz | Y36: Dokument auswerten; Aktualität und Geltung prüfen | Z36: Webrecherche 14.10.2026 | AD36: Nicht prüfbar | AE36: 403 | AH36: Offen | AI36: Zugriff verweigert/gedrosselt (HTTP 403); keine Umgehung versucht | AL36: Mittel (Webseite) | AM36: 2026-10-14 13:53 | AN36: Nicht zugänglich / nicht prüfbar | AO36: Zu prüfen | AP36: Belegt Existenz und Zugänglichkeit der Quelle; inhaltliche Aussagen erst nach Auswertung. | AQ36: Keine Einstufung: Kennzahlen/Befunde noch nicht ausgewertet; Schwellen der Bewertungslogik noch nicht validiert. | AR36: Nein | AS36: Kanton Basel-Landschaft | AT36: Offen | AU36: Automatisch nicht prüfbar – manuell im Browser prüfen
A37: BL-C4-02 | B37: Kanton | C37: Schweiz | D37: Basel-Landschaft | E37: Alle | F37: C4 | G37: Beschaffung | H37: Verordnung zum Einführungsgesetz zur IVöB (Vo EG IVöB) Basel-Landschaft, SGS 420.11 | I37: Kantonale Verordnung | J37: Direktes Dokument | K37: Kantonales Recht (verbindlich) | L37: Kanton Basel-Landschaft | M37: https://bl.clex.ch/app/de/texts_of_law/420.11 | O37: 2026-10-14 | P37: Beschaffungsrecht für Gemeinden ab 1.1.2024 | S37: Kein Peer-Vergleich | T37: Noch nicht bewertet | U37: Hoch | Y37: Dokument auswerten; Aktualität und Geltung prüfen | Z37: URL nach dokumentiertem Schema der amtlichen Rechtssammlung gebildet; Identität per Runner geprüft | AD37: Verifiziert | AE37: 200 | AG37: HTML | AH37: Bestätigt | AI37: Titel via LexWork-API (https://bl.clex.ch/api/de/texts_of_law/420.11); Schlüsselwörter 1/1 gefunden (Beschaffung) | AJ37: Verordnung zum Einführungsgesetz zur Interkantonalen Vereinbarung über das öffentliche Beschaffungswesen | AK37: 2026, 2023, 2024, 2022 | AL37: Hoch (Erlassnummer) | AM37: 2026-10-14 13:54 | AN37: Öffentlich verfügbar und verifiziert | AP37: Belegt Existenz und Zugänglichkeit der Quelle; inhaltliche Aussagen erst nach Auswertung. | AQ37: Keine Einstufung: Kennzahlen/Befunde noch nicht ausgewertet; Schwellen der Bewertungslogik noch nicht validiert. | AR37: Nein | AS37: Kanton Basel-Landschaft | AT37: In Prüfung | AW37: 2026-10-14: neu aufgenommen
A38: BL-C5-01 | B38: Kanton | C38: Schweiz | D38: Basel-Landschaft | E38: Alle | F38: C5 | G38: Mitwirkung | H38: Gesetz über die politischen Rechte (GpR) Basel-Landschaft, SGS 120 | I38: Kantonales Gesetz | J38: Offizielle Quelle recherchiert | K38: Kantonales Gesetz (verbindlich) | L38: Kanton Basel-Landschaft | M38: https://bl.clex.ch/app/de/texts_of_law/120 | N38: vom 7.9.1981; geltende Fassung | O38: 2026-10-14 | P38: Rechtsrahmen von Gemeindeversammlung und Mitwirkung | Q38: Entscheidungswege | R38: Gemeindeordnung und Beschlüsse prüfen | S38: Qualitativ | T38: Noch nicht bewertet | U38: Mittel | V38: Geltende kantonale Detailgrundlage und Datenstand prüfen | W38: C3 | X38: Politische Machbarkeit | Y38: Dokument auswerten; Aktualität und Geltung prüfen | Z38: URL nach dokumentiertem Schema der amtlichen Rechtssammlung gebildet; Identität per Runner geprüft | AD38: Verifiziert | AE38: 200 | AG38: HTML | AH38: Bestätigt | AI38: Titel via LexWork-API (https://bl.clex.ch/api/de/texts_of_law/120); Schlüsselwörter 1/1 gefunden (politischen Rechte) | AJ38: Gesetz über die politischen Rechte | AK38: 2025, 2024, 2014, 2006 | AL38: Hoch (Erlassnummer) | AM38: 2026-10-14 13:53 | AN38: Öffentlich verfügbar und verifiziert | AO38: vom 7.9.1981; geltende Fassung | AP38: Belegt Existenz und Zugänglichkeit der Quelle; inhaltliche Aussagen erst nach Auswertung. | AQ38: Keine Einstufung: Kennzahlen/Befunde noch nicht ausgewertet; Schwellen der Bewertungslogik noch nicht validiert. | AR38: Nein | AS38: Kanton Basel-Landschaft | AT38: In Prüfung | AW38: 2026-10-14: Link ersetzt (vorher https://bl.clex.ch/). Grund: Startseite der Gesetzessammlung durch direkten Erlass ersetzt (GpR SGS 120).
A39: SG-C1-01 | B39: Kanton | C39: Schweiz | D39: St. Gallen | E39: Alle | F39: C1 | G39: Gemeindefinanzen | H39: Kanton St. Gallen, Amt für Gemeinden: Rechnungslegung (RMSG) / Gemeindefinanzen | I39: Behördeninformation | J39: Offizielle Quelle recherchiert | K39: Orientierung / Datengrundlage | L39: Kanton St. Gallen, Amt für Gemeinden | M39: https://www.sg.ch/politik-verwaltung/gemeinden/gemeindefinanzen/rechnungslegung--rmsg-.html | N39: Zu prüfen | O39: 2026-10-14 | P39: Finanzdaten als kantonaler Einstieg | Q39: Selbstfinanzierung, Verschuldung | R39: SG- und Wil-Werte mit kantonaler Rechnungslegung abgleichen | S39: Kanton × Grössenklasse | T39: Noch nicht bewertet | U39: Mittel | V39: Geltende kantonale Detailgrundlage und Datenstand prüfen | W39: A1; C1 | X39: Finanztragfähigkeit | Y39: Dokument auswerten; Aktualität und Geltung prüfen | Z39: Webrecherche 14.10.2026 | AD39: Verifiziert | AE39: 200 | AG39: HTML | AH39: Bestätigt | AI39: Schlüsselwörter 1/1 gefunden (Rechnungslegung); Ort/Zuständigkeit: St. Gallen, St.Gallen | AJ39: Rechnungslegung (RMSG) | sg.ch | Rechnungslegung (RMSG) | AK39: 2017, 2021, 2026, 2022, 2020, 2025 | AL39: Mittel (Webseite) | AM39: 2026-10-14 13:53 | AN39: Öffentlich verfügbar und verifiziert | AO39: Zu prüfen | AP39: Belegt Existenz und Zugänglichkeit der Quelle; inhaltliche Aussagen erst nach Auswertung. | AQ39: Keine Einstufung: Kennzahlen/Befunde noch nicht ausgewertet; Schwellen der Bewertungslogik noch nicht validiert. | AR39: Nein | AS39: Kanton St. Gallen, Amt für Gemeinden | AT39: In Prüfung | AW39: 2026-10-14: Link ersetzt (vorher https://www.efv.admin.ch/de/finanzstatistik-daten). Grund: Herausgeber «Kanton St. Gallen» passte nicht zum EFV-Bundeslink (Dublette zu CH-C1-01); durch kantonale Fundstelle ersetzt.
A40: SG-C1-02 | B40: Kanton | C40: Schweiz | D40: St. Gallen | E40: Alle | F40: C1 | G40: Finanzausgleich | H40: Finanzausgleichsgesetz St. Gallen, sGS 813.1 | I40: Kantonales Gesetz | J40: Direktes Dokument | K40: Kantonales Recht (verbindlich) | L40: Kanton St. Gallen | M40: https://www.gesetzessammlung.sg.ch/app/de/texts_of_law/813.1 | O40: 2026-10-14 | S40: Kanton × Grössenklasse | T40: Noch nicht bewertet | U40: Hoch | Y40: Dokument auswerten; Aktualität und Geltung prüfen | Z40: URL nach dokumentiertem Schema der amtlichen Rechtssammlung gebildet; Identität per Runner geprüft | AD40: Verifiziert | AE40: 200 | AG40: HTML | AH40: Bestätigt | AI40: Titel via LexWork-API (https://www.gesetzessammlung.sg.ch/api/de/texts_of_law/813.1); Schlüsselwörter 1/1 gefunden (Finanzausgleich) | AJ40: Finanzausgleichsgesetz | AK40: 2021, 2007, 2008, 2006, 2001 | AL40: Hoch (Erlassnummer) | AM40: 2026-10-14 13:56 | AN40: Öffentlich verfügbar und verifiziert | AP40: Belegt Existenz und Zugänglichkeit der Quelle; inhaltliche Aussagen erst nach Auswertung. | AQ40: Keine Einstufung: Kennzahlen/Befunde noch nicht ausgewertet; Schwellen der Bewertungslogik noch nicht validiert. | AR40: Nein | AS40: Kanton St. Gallen | AT40: In Prüfung | AW40: 2026-10-14: neu aufgenommen
A41: SG-C1-03 | B41: Kanton | C41: Schweiz | D41: St. Gallen | E41: Alle | F41: C1 | G41: Rechnungslegung Gemeinden | H41: Verordnung über den Finanzhaushalt der Gemeinden (FHGV) St. Gallen, sGS 151.53 | I41: Kantonale Verordnung | J41: Direktes Dokument | K41: Kantonales Recht (verbindlich) | L41: Kanton St. Gallen | M41: https://www.gesetzessammlung.sg.ch/app/de/texts_of_law/151.53 | O41: 2026-10-14 | S41: Kanton × Grössenklasse | T41: Noch nicht bewertet | U41: Hoch | Y41: Dokument auswerten; Aktualität und Geltung prüfen | Z41: URL nach dokumentiertem Schema der amtlichen Rechtssammlung gebildet; Identität per Runner geprüft | AD41: Verifiziert | AE41: 200 | AG41: HTML | AH41: Bestätigt | AI41: Titel via LexWork-API (https://www.gesetzessammlung.sg.ch/api/de/texts_of_law/151.53); Schlüsselwörter 1/1 gefunden (Finanzhaushalt) | AJ41: Verordnung über den Finanzhaushalt der Gemeinden | AK41: 2019, 2017, 2009 | AL41: Hoch (Erlassnummer) | AM41: 2026-10-14 13:56 | AN41: Öffentlich verfügbar und verifiziert | AP41: Belegt Existenz und Zugänglichkeit der Quelle; inhaltliche Aussagen erst nach Auswertung. | AQ41: Keine Einstufung: Kennzahlen/Befunde noch nicht ausgewertet; Schwellen der Bewertungslogik noch nicht validiert. | AR41: Nein | AS41: Kanton St. Gallen | AT41: In Prüfung | AW41: 2026-10-14: neu aufgenommen
A42: SG-C2-01 | B42: Kanton | C42: Schweiz | D42: St. Gallen | E42: Alle | F42: C2 | G42: Geodaten | H42: Geoportal Kanton St. Gallen / geoportal.ch | I42: Geodatenportal | J42: Offizielle Quelle recherchiert | K42: Orientierung / Datengrundlage | L42: Kanton St. Gallen | M42: https://www.geoportal.ch/ | N42: Zu prüfen | O42: 2026-10-14 | P42: Parzellen und Nutzungsplanung; Eigentum gesondert nachweisen | Q42: Parzellen / ÖBA | R42: Luucy-Layer verwenden | S42: Kein Peer | T42: Noch nicht bewertet | U42: Mittel | V42: Geltende kantonale Detailgrundlage und Datenstand prüfen | W42: B; Q1 | X42: Bodenpotenzial | Y42: Dokument auswerten; Aktualität und Geltung prüfen | Z42: Webrecherche 14.10.2026 | AD42: Verifiziert | AE42: 200 | AG42: HTML | AH42: Bestätigt | AI42: Schlüsselwörter 1/1 gefunden (geoportal) | AJ42: Geoportal | AL42: Mittel (Startseite, kein Dokument) | AM42: 2026-10-14 13:53 | AN42: Öffentlich verfügbar und verifiziert | AO42: Zu prüfen | AP42: Belegt Existenz und Zugänglichkeit der Quelle; inhaltliche Aussagen erst nach Auswertung. | AQ42: Keine Einstufung: Kennzahlen/Befunde noch nicht ausgewertet; Schwellen der Bewertungslogik noch nicht validiert. | AR42: Nein | AS42: Kanton St. Gallen | AT42: In Prüfung | AU42: Kartenportal (JavaScript); kein Eigentumsnachweis.
A43: SG-C2-02 | B43: Kanton | C43: Schweiz | D43: St. Gallen | E43: Alle | F43: C2 | G43: Arealentwicklung | H43: WILWEST: Grundstücksgeschäft Kanton St. Gallen (Verkauf an Kanton Thurgau) – Kantonsratsvorlage | I43: Botschaft / Beschluss | J43: Direktes Dokument | K43: Beschluss (Volksabstimmung 2026) | L43: Kanton St. Gallen | M43: https://www.ratsinfo.sg.ch//media/documents/published/signed/8b158b37-2fff-4d5d-b018-ef035f08732e.pdf | O43: 2026-10-14 | P43: Kantonales Grundeigentum im Entwicklungsgebiet WILWEST (nicht städtisches Eigentum) | S43: Kein Peer-Vergleich | T43: Noch nicht bewertet | U43: Mittel | W43: B | Y43: Dokument auswerten; Aktualität und Geltung prüfen | Z43: Websuche 14.10.2026 (URL im Suchergebnis gefunden) | AD43: Verifiziert | AE43: 200 | AG43: PDF | AH43: Bestätigt | AI43: Schlüsselwörter 1/1 gefunden (WILWEST); Ort/Zuständigkeit: Wil | AJ43: Kantonsrat St.Gallen 51.26.15 | AK43: 2026, 2022, 2023, 2025, 2011, 2021 | AL43: Mittel (CMS-Dokumentlink) | AM43: 2026-10-14 13:55 | AN43: Öffentlich verfügbar und verifiziert | AP43: Belegt Existenz und Zugänglichkeit der Quelle; inhaltliche Aussagen erst nach Auswertung. | AQ43: Keine Einstufung: Kennzahlen/Befunde noch nicht ausgewertet; Schwellen der Bewertungslogik noch nicht validiert. | AR43: Nein | AS43: Kanton St. Gallen | AT43: In Prüfung | AW43: 2026-10-14: neu aufgenommen
A44: SG-C2-03 | B44: Kanton | C44: Schweiz | D44: St. Gallen | E44: Alle | F44: C2 | G44: Raumplanung / Baulandmobilisierung | H44: Planungs- und Baugesetz (PBG) St. Gallen, sGS 731.1 | I44: Kantonales Gesetz | J44: Direktes Dokument | K44: Kantonales Recht (verbindlich) | L44: Kanton St. Gallen | M44: https://www.gesetzessammlung.sg.ch/app/de/texts_of_law/731.1 | O44: 2026-10-14 | P44: Ortsplanungsrevision bis 2027, Bauverpflichtung, Mehrwertabgabe | S44: Kein Peer-Vergleich | T44: Noch nicht bewertet | U44: Hoch | W44: B; Q1 | Y44: Dokument auswerten; Aktualität und Geltung prüfen | Z44: URL nach dokumentiertem Schema der amtlichen Rechtssammlung gebildet; Identität per Runner geprüft | AD44: Verifiziert | AE44: 200 | AG44: HTML | AH44: Bestätigt | AI44: Titel via LexWork-API (https://www.gesetzessammlung.sg.ch/api/de/texts_of_law/731.1); Schlüsselwörter 1/1 gefunden (Planungs) | AJ44: Planungs- und Baugesetz | AK44: 2026, 2016, 2017, 2027, 2015 | AL44: Hoch (Erlassnummer) | AM44: 2026-10-14 13:55 | AN44: Öffentlich verfügbar und verifiziert | AP44: Belegt Existenz und Zugänglichkeit der Quelle; inhaltliche Aussagen erst nach Auswertung. | AQ44: Keine Einstufung: Kennzahlen/Befunde noch nicht ausgewertet; Schwellen der Bewertungslogik noch nicht validiert. | AR44: Nein | AS44: Kanton St. Gallen | AT44: In Prüfung | AW44: 2026-10-14: neu aufgenommen
A45: SG-C3-01 | B45: Kanton | C45: Schweiz | D45: St. Gallen | E45: Alle | F45: C3 | G45: Gemeinderecht | H45: Gemeindegesetz (GG) St. Gallen, sGS 151.2 | I45: Kantonales Gesetz | J45: Offizielle Quelle recherchiert | K45: Kantonales Gesetz (verbindlich) | L45: Kanton St. Gallen | M45: https://www.gesetzessammlung.sg.ch/app/de/texts_of_law/151.2 | N45: vom 21.4.2009; geltende Fassung | O45: 2026-10-14 | P45: Gemeinderecht und öffentlich-rechtliche Kooperation | Q45: Zuständigkeiten / Trägerschaften | R45: Geltende Erlasse ermitteln | S45: Qualitativ | T45: Noch nicht bewertet | U45: Mittel | V45: Geltende kantonale Detailgrundlage und Datenstand prüfen | W45: C5; Q6 | X45: Governance | Y45: Dokument auswerten; Aktualität und Geltung prüfen | Z45: URL nach dokumentiertem Schema der amtlichen Rechtssammlung gebildet; Identität per Runner geprüft | AA45: C1 | AD45: Verifiziert | AE45: 200 | AG45: HTML | AH45: Bestätigt | AI45: Titel via LexWork-API (https://www.gesetzessammlung.sg.ch/api/de/texts_of_law/151.2); Schlüsselwörter 1/1 gefunden (Gemeindegesetz) | AJ45: Gemeindegesetz | AK45: 2009, 2026, 2010, 2025, 2018, 2008 | AL45: Hoch (Erlassnummer) | AM45: 2026-10-14 13:53 | AN45: Öffentlich verfügbar und verifiziert | AO45: vom 21.4.2009; geltende Fassung | AP45: Belegt Existenz und Zugänglichkeit der Quelle; inhaltliche Aussagen erst nach Auswertung. | AQ45: Keine Einstufung: Kennzahlen/Befunde noch nicht ausgewertet; Schwellen der Bewertungslogik noch nicht validiert. | AR45: Nein | AS45: Kanton St. Gallen | AT45: In Prüfung | AW45: 2026-10-14: Link ersetzt (vorher https://www.gesetzessammlung.sg.ch/). Grund: Startseite der Gesetzessammlung durch direkten Erlass ersetzt (Gemeindegesetz sGS 151.2).
A46: SG-C4-01 | B46: Kanton | C46: Schweiz | D46: St. Gallen | E46: Alle | F46: C4 | G46: Verwaltung | H46: Kanton St. Gallen: offizielles Behördenportal | I46: Behördenportal | J46: Offizielle Quelle recherchiert | K46: Orientierung / Datengrundlage | L46: Kanton St. Gallen | M46: https://www.sg.ch/ | N46: Zu prüfen | O46: 2026-10-14 | P46: Verwaltungs- und Gemeindeorganisation | Q46: Aufgaben / Kompetenzen | R46: Wil-Organisation ergänzen | S46: Qualitativ | T46: Noch nicht bewertet | U46: Mittel | V46: Geltende kantonale Detailgrundlage und Datenstand prüfen | W46: Q6; C3 | X46: Verwaltungskapazität | Y46: Dokument auswerten; Aktualität und Geltung prüfen | Z46: Webrecherche 14.10.2026 | AD46: Verifiziert | AE46: 200 | AG46: HTML | AH46: Bestätigt | AI46: Schlüsselwörter 1/1 gefunden (St.Gallen); Ort/Zuständigkeit: St. Gallen, St.Gallen | AJ46: Portal Kanton St.Gallen | sg.ch | Alles im Kanton St.Gallen finden | AK46: 2026, 2030, 2028 | AL46: Mittel (Startseite, kein Dokument) | AM46: 2026-10-14 13:53 | AN46: Öffentlich verfügbar und verifiziert | AO46: Zu prüfen | AP46: Belegt Existenz und Zugänglichkeit der Quelle; inhaltliche Aussagen erst nach Auswertung. | AQ46: Keine Einstufung: Kennzahlen/Befunde noch nicht ausgewertet; Schwellen der Bewertungslogik noch nicht validiert. | AR46: Nein | AS46: Kanton St. Gallen | AT46: In Prüfung
A47: SG-C4-02 | B47: Kanton | C47: Schweiz | D47: St. Gallen | E47: Alle | F47: C4 | G47: Beschaffung | H47: Einführungsgesetz zur IVöB St. Gallen, sGS 841.1 | I47: Kantonales Gesetz | J47: Direktes Dokument | K47: Kantonales Recht (verbindlich) | L47: Kanton St. Gallen | M47: https://www.gesetzessammlung.sg.ch/app/de/texts_of_law/841.1 | O47: 2026-10-14 | S47: Kein Peer-Vergleich | T47: Noch nicht bewertet | U47: Hoch | Y47: Dokument auswerten; Aktualität und Geltung prüfen | Z47: URL nach dokumentiertem Schema der amtlichen Rechtssammlung gebildet; Identität per Runner geprüft | AC47: https://www.sg.ch/recht/beschaffungswesen/neues_beschaffungsrecht_2023/ | AD47: Verifiziert | AE47: 200 | AG47: HTML | AH47: Bestätigt | AI47: Titel via LexWork-API (https://www.gesetzessammlung.sg.ch/api/de/texts_of_law/841.1); Schlüsselwörter 1/1 gefunden (Beschaffung) | AJ47: Einführungsgesetz zur Interkantonalen Vereinbarung über das öffentliche Beschaffungswesen aus dem Jahr 2019 | AK47: 2023, 2022, 2019, 2002, 2001 | AL47: Hoch (Erlassnummer) | AM47: 2026-10-14 13:56 | AN47: Öffentlich verfügbar und verifiziert | AP47: Belegt Existenz und Zugänglichkeit der Quelle; inhaltliche Aussagen erst nach Auswertung. | AQ47: Keine Einstufung: Kennzahlen/Befunde noch nicht ausgewertet; Schwellen der Bewertungslogik noch nicht validiert. | AR47: Nein | AS47: Kanton St. Gallen | AT47: In Prüfung | AW47: 2026-10-14: neu aufgenommen
A48: SG-C5-01 | B48: Kanton | C48: Schweiz | D48: St. Gallen | E48: Alle | F48: C5 | G48: Politische Rechte | H48: Gesetz über Referendum und Initiative (RIG) St. Gallen, sGS 125.1 | I48: Kantonales Gesetz | J48: Offizielle Quelle recherchiert | K48: Kantonales Gesetz (verbindlich) | L48: Kanton St. Gallen | M48: https://www.gesetzessammlung.sg.ch/app/de/texts_of_law/125.1 | N48: geltende Fassung | O48: 2026-10-14 | P48: Kommunale demokratische Verfahren | Q48: Legitimation / Referenden | R48: Gemeindeordnung und Ratsgeschäfte auswerten | S48: Qualitativ | T48: Noch nicht bewertet | U48: Mittel | V48: Geltende kantonale Detailgrundlage und Datenstand prüfen | W48: C3 | X48: Politische Machbarkeit | Y48: Dokument auswerten; Aktualität und Geltung prüfen | Z48: URL nach dokumentiertem Schema der amtlichen Rechtssammlung gebildet; Identität per Runner geprüft | AD48: Verifiziert | AE48: 200 | AG48: HTML | AH48: Bestätigt | AI48: Titel via LexWork-API (https://www.gesetzessammlung.sg.ch/api/de/texts_of_law/125.1); Schlüsselwörter 1/1 gefunden (Referendum) | AJ48: Gesetz über Referendum und Initiative | AK48: 2026, 2025, 2008 | AL48: Hoch (Erlassnummer) | AM48: 2026-10-14 13:53 | AN48: Öffentlich verfügbar und verifiziert | AO48: geltende Fassung | AP48: Belegt Existenz und Zugänglichkeit der Quelle; inhaltliche Aussagen erst nach Auswertung. | AQ48: Keine Einstufung: Kennzahlen/Befunde noch nicht ausgewertet; Schwellen der Bewertungslogik noch nicht validiert. | AR48: Nein | AS48: Kanton St. Gallen | AT48: In Prüfung | AW48: 2026-10-14: Link ersetzt (vorher https://www.gesetzessammlung.sg.ch/). Grund: Startseite der Gesetzessammlung durch direkten Erlass ersetzt (RIG sGS 125.1).
A49: SEE-C1-01 | B49: Gemeinde | C49: Schweiz | D49: Uri | E49: Seelisberg | F49: C1 | G49: Budget / Jahresrechnung | H49: Gemeindeversammlung Seelisberg: Budgets, Rechnungen und Protokolle | I49: Dokumentsammlung | J49: Offizielle Quelle recherchiert | K49: Orientierung / Datengrundlage | L49: Gemeinde Seelisberg | M49: https://www.seelisberg.ch/politik/gemeindeversammlung | N49: Zu prüfen | O49: 2026-10-14 | P49: Budget 2026 und Jahresrechnung 2024 über Versammlungsunterlagen | Q49: Selbstfinanzierungsgrad, Nettoinvestitionen, Nettoschuld | R49: Dokumente herunterladen und Kennzahlen berechnen | S49: Kanton × Grössenklasse | T49: Noch nicht bewertet | U49: Mittel | V49: Kennzahlen und Befunde noch extrahieren | W49: A1; C1 | X49: Finanztragfähigkeit | Y49: Dokument auswerten; Aktualität und Geltung prüfen | Z49: Webrecherche 14.10.2026 | AC49: https://www.seelisberg.ch/ | AD49: Verifiziert | AE49: 200 | AG49: HTML | AH49: Bestätigt | AI49: Schlüsselwörter 1/1 gefunden (Gemeindeversammlung); Ort/Zuständigkeit: Seelisberg | AJ49: Gemeinde Seelisberg | Einwohner-Service | Gemeindeversammlung | AK49: 2024, 2023, 2022, 2021, 2025, 2026 | AL49: Mittel (Webseite) | AM49: 2026-10-14 13:53 | AN49: Öffentlich verfügbar und verifiziert | AO49: Zu prüfen | AP49: Belegt Existenz und Zugänglichkeit der Quelle; inhaltliche Aussagen erst nach Auswertung. | AQ49: Keine Einstufung: Kennzahlen/Befunde noch nicht ausgewertet; Schwellen der Bewertungslogik noch nicht validiert. | AR49: Nein | AS49: Gemeindeverwaltung Seelisberg | AT49: In Prüfung | AU49: Direkte Dokumente: SEE-C1-02 bis SEE-C1-05. | AV49: SEE-C5-01
A50: SEE-C1-02 | B50: Gemeinde | C50: Schweiz | D50: Uri | E50: Seelisberg | F50: C1 | G50: Budget / Finanzplan | H50: Einladung Gemeindeversammlung November 2025: Traktanden und Botschaften (Budget 2026, Finanzplan 2027–2032, Leitbild) | I50: Botschaft / Vorlage | J50: Direktes Dokument | K50: Beschlussvorlage | L50: Gemeinde Seelisberg | M50: https://www.seelisberg.ch/files/pdf/Druckvorlage2_Original_Versammlung-Nov2025_Traktanden-und-Botschaften-gesamt.pdf | N50: Budget 2026; Finanzplan 2027–2032 | O50: 2026-10-14 | P50: Budget 2026, Nettoinvestitionen, Steuerfuss, Finanzplan; Grundlage C1 | Q50: Aufwand/Ertrag, Nettoinvestitionen, Steuerfuss | S50: Kanton × Grössenklasse | T50: Noch nicht bewertet | U50: Hoch | W50: A1; C1 | X50: Finanztragfähigkeit | Y50: Dokument auswerten; Aktualität und Geltung prüfen | Z50: Websuche 14.10.2026 (URL im Suchergebnis gefunden) | AA50: C5 | AC50: https://www.seelisberg.ch/politik/gemeindeversammlung | AD50: Verifiziert | AE50: 200 | AG50: PDF | AH50: Bestätigt | AI50: Schlüsselwörter 2/2 gefunden (Budget, 2026); Ort/Zuständigkeit: Seelisberg | AJ50: E I N L A D U N G Z U R G E M E I N D E V E R S A M M L U N G | AK50: 2026, 2025, 2024, 2027, 2032, 2020 | AL50: Mittel (CMS-Dokumentlink) | AM50: 2026-10-14 13:54 | AN50: Öffentlich verfügbar und verifiziert | AO50: Budget 2026; Finanzplan 2027–2032 | AP50: Belegt Existenz und Zugänglichkeit der Quelle; inhaltliche Aussagen erst nach Auswertung. Fundstellen im Dokument (automatisch): Steuerfuss: S. 5; Finanzplan: S. 1, 5; Nettoinvestition: S. 4, 5. | AQ50: Keine Einstufung: Kennzahlen/Befunde noch nicht ausgewertet; Schwellen der Bewertungslogik noch nicht validiert. | AR50: Nein | AS50: Gemeindeverwaltung Seelisberg | AT50: In Prüfung | AW50: 2026-10-14: neu aufgenommen
A51: SEE-C1-03 | B51: Gemeinde | C51: Schweiz | D51: Uri | E51: Seelisberg | F51: C1 | G51: Jahresrechnung | H51: Jahresrechnung 2024 der Einwohnergemeinde Seelisberg | I51: Jahresrechnung | J51: Direktes Dokument | K51: Beschlossene Jahresrechnung (GV 28.5.2025) | L51: Gemeinde Seelisberg | M51: https://www.seelisberg.ch/files/pdf/JR2024_Gde-Seelisberg.pdf | N51: 2024 | O51: 2026-10-14 | P51: Erfolgsrechnung, Investitionsrechnung, Bilanz 2024 | Q51: Selbstfinanzierungsgrad, Nettoinvestitionen, Nettoschuld | S51: Kanton × Grössenklasse | T51: Noch nicht bewertet | U51: Hoch | W51: A1; C1 | X51: Finanztragfähigkeit | Y51: Dokument auswerten; Aktualität und Geltung prüfen | Z51: Automatische Recherche GitHub Actions (Discovery), Fundstelle siehe Spalte Offizielle Fundstelle | AC51: https://www.seelisberg.ch/politik/budget-rechnung | AD51: Verifiziert | AE51: 200 | AG51: PDF | AH51: Bestätigt | AI51: Schlüsselwörter 2/2 gefunden (Rechnung, 2024); Ort/Zuständigkeit: Seelisberg | AJ51: GEMEINDE SEELISBERG | AK51: 2024, 2023, 2025, 2015 | AL51: Mittel (CMS-Dokumentlink) | AM51: 2026-10-14 13:54 | AN51: Öffentlich verfügbar und verifiziert | AO51: 2024 | AP51: Belegt Existenz und Zugänglichkeit der Quelle; inhaltliche Aussagen erst nach Auswertung. | AQ51: Keine Einstufung: Kennzahlen/Befunde noch nicht ausgewertet; Schwellen der Bewertungslogik noch nicht validiert. | AR51: Nein | AS51: Gemeindeverwaltung Seelisberg | AT51: In Prüfung | AU51: Jahresrechnung 2025 (GV 29.5.2026) auf der Fundstelle nicht als PDF gefunden. | AW51: 2026-10-14: neu aufgenommen
A52: SEE-C1-04 | B52: Gemeinde | C52: Schweiz | D52: Uri | E52: Seelisberg | F52: C1 | G52: Jahresrechnung | H52: Jahresrechnung 2023 der Einwohnergemeinde Seelisberg | I52: Jahresrechnung | J52: Direktes Dokument | K52: Beschlossene Jahresrechnung | L52: Gemeinde Seelisberg | M52: https://www.seelisberg.ch/files/pdf/Jahresrechnung_Gde-Seelisberg_2023.pdf | N52: 2023 | O52: 2026-10-14 | P52: Zeitreihe | S52: Kanton × Grössenklasse | T52: Noch nicht bewertet | U52: Hoch | Y52: Dokument auswerten; Aktualität und Geltung prüfen | Z52: Automatische Recherche GitHub Actions (Discovery), Fundstelle siehe Spalte Offizielle Fundstelle | AC52: https://www.seelisberg.ch/politik/budget-rechnung | AD52: Verifiziert | AE52: 200 | AG52: PDF | AH52: Bestätigt | AI52: Schlüsselwörter 2/2 gefunden (Rechnung, 2023); Ort/Zuständigkeit: Seelisberg | AJ52: GEMEINDE SEELISBERG | AK52: 2023, 2022, 2024, 2015 | AL52: Mittel (CMS-Dokumentlink) | AM52: 2026-10-14 13:54 | AN52: Öffentlich verfügbar und verifiziert | AO52: 2023 | AP52: Belegt Existenz und Zugänglichkeit der Quelle; inhaltliche Aussagen erst nach Auswertung. | AQ52: Keine Einstufung: Kennzahlen/Befunde noch nicht ausgewertet; Schwellen der Bewertungslogik noch nicht validiert. | AR52: Nein | AS52: Gemeindeverwaltung Seelisberg | AT52: In Prüfung | AW52: 2026-10-14: neu aufgenommen
A53: SEE-C1-05 | B53: Gemeinde | C53: Schweiz | D53: Uri | E53: Seelisberg | F53: C1 | G53: Budget | H53: Budget 2026 der Einwohnergemeinde Seelisberg (Erfolgsrechnung, Gesamtauflage) | I53: Budget | J53: Direktes Dokument | K53: Beschlossenes Budget (GV 28.11.2025) | L53: Gemeinde Seelisberg | M53: https://www.seelisberg.ch/files/pdf/Budget-ER-2026_Gesamtauflage_ohne-Bemerkungen_%C3%B6ffentlich.pdf | N53: 2026 | O53: 2026-10-14 | S53: Kanton × Grössenklasse | T53: Noch nicht bewertet | U53: Hoch | Y53: Dokument auswerten; Aktualität und Geltung prüfen | Z53: Automatische Recherche GitHub Actions (Discovery), Fundstelle siehe Spalte Offizielle Fundstelle | AC53: https://www.seelisberg.ch/politik/budget-rechnung | AD53: Verifiziert | AE53: 200 | AG53: PDF | AH53: Bestätigt | AI53: Schlüsselwörter 2/2 gefunden (Budget, 2026); Ort/Zuständigkeit: Seelisberg | AJ53: GEMEINDE SEELISBERG | AK53: 2026, 2025, 2024 | AL53: Mittel (CMS-Dokumentlink) | AM53: 2026-10-14 13:54 | AN53: Öffentlich verfügbar und verifiziert | AO53: 2026 | AP53: Belegt Existenz und Zugänglichkeit der Quelle; inhaltliche Aussagen erst nach Auswertung. | AQ53: Keine Einstufung: Kennzahlen/Befunde noch nicht ausgewertet; Schwellen der Bewertungslogik noch nicht validiert. | AR53: Nein | AS53: Gemeindeverwaltung Seelisberg | AT53: In Prüfung | AW53: 2026-10-14: neu aufgenommen
A54: SEE-C2-01 | B54: Gemeinde | C54: Schweiz | D54: Uri | E54: Seelisberg | F54: C2 | G54: Boden / Liegenschaften | H54: Teilrevision Nutzungsplanung und Quartiergestaltungsplanung «Sonnenberg» – Erläuterungsbericht nach Art. 47 RPV (öffentliche Auflage) | I54: Planungsbericht | J54: Direktes Dokument | K54: Planungsbericht (orientierend) | L54: Gemeinde Seelisberg | M54: https://www.seelisberg.ch/files/pdf/ERLUTE1.PDF | N54: Zu prüfen | O54: 2026-10-14 | P54: Planungsgrundlage für das Entwicklungsgebiet Sonnenberg. Kein Nachweis kommunalen Grundeigentums oder eines Baurechts: «Baurecht», «775» und «Erwerb» kommen im Dokumenttext nicht vor (automatische Volltextsuche). | Q54: Gemeindeeigentum, Baurechte, ÖBA | R54: Liegenschaftsverzeichnis bei Gemeinde anfragen | S54: Kein Peer | T54: Noch nicht bewertet | U54: Niedrig | V54: Konkrete kommunale Unterlagen / Datensatz nachfordern | W54: B; Q1 | X54: Bodenmobilisierung | Y54: Dokument auswerten; Aktualität und Geltung prüfen | Z54: Webrecherche 14.10.2026 | AC54: https://www.seelisberg.ch/ | AD54: Verifiziert | AE54: 200 | AG54: PDF | AH54: Bestätigt | AI54: Schlüsselwörter 2/2 gefunden (Sonnenberg, Nutzungsplanung); Ort/Zuständigkeit: Seelisberg | AJ54: Teilrevision N UP und QGP «Sonnenberg », Gemeinde Seelisberg | AK54: 2024, 2023, 2018 | AL54: Mittel (CMS-Dokumentlink) | AM54: 2026-10-14 13:53 | AN54: Öffentlich verfügbar und verifiziert | AO54: Zu prüfen | AP54: Belegt das Planungsverfahren Sonnenberg (Teilrevision NUP/QGP); belegt kein kommunales Grundeigentum. Fundstellen im Dokument (automatisch): Baurecht: nicht gefunden; 775: nicht gefunden; Erwerb: nicht gefunden; Halter: S. 2, 6, 8, 28, 32, 75, 76, 79, 85; Grundeigentümer: S. 32, 48, 70. | AQ54: Keine Einstufung: Kennzahlen/Befunde noch nicht ausgewertet; Schwellen der Bewertungslogik noch nicht validiert. | AR54: Ja | AS54: Gemeindeverwaltung Seelisberg | AT54: In Prüfung | AU54: Eine Suchmaschinen-Zusammenfassung nannte einen Erwerb von Parzelle 775 mit Baurecht – im Dokument nicht bestätigt, daher nicht übernommen. Ebenso unbestätigter Sekundärhinweis auf eine Projektbeteiligung der Halter AG: Belegstellen prüfen; allfällige Interessenbindung bei der Auswertung offenlegen. Kein Liegenschaftsverzeichnis öffentlich. | AW54: 2026-10-14: Link ersetzt (vorher https://www.seelisberg.ch/). Grund: Startseite durch direktes Dokument zu Grundeigentum/Baurecht ersetzt.
A55: SEE-C2-02 | B55: Gemeinde | C55: Schweiz | D55: Uri | E55: Seelisberg | F55: C2 | G55: Bau- und Zonenordnung | H55: Bau- und Zonenordnung Seelisberg (BZO) | I55: Kommunales Reglement | J55: Direktes Dokument | K55: Kommunales Recht (verbindlich) | L55: Gemeinde Seelisberg | M55: https://www.seelisberg.ch/files/pdf/Bau-und-Zonenordnung-Seelisberg.pdf | O55: 2026-10-14 | P55: Zonen und Bauvorschriften; Q-Bezug; kein Eigentumsnachweis | S55: Kein Peer-Vergleich | T55: Noch nicht bewertet | U55: Hoch | W55: B; Q1 | Y55: Dokument auswerten; Aktualität und Geltung prüfen | Z55: Websuche 14.10.2026 (URL im Suchergebnis gefunden) | AD55: Verifiziert | AE55: 200 | AG55: PDF | AH55: Bestätigt | AI55: Schlüsselwörter 1/1 gefunden (Zonenordnung); Ort/Zuständigkeit: Seelisberg | AJ55: GEMEINDE SEELISBERG | AK55: 2023, 2025, 2014, 2015, 2010, 2005 | AL55: Mittel (CMS-Dokumentlink) | AM55: 2026-10-14 13:54 | AN55: Öffentlich verfügbar und verifiziert | AP55: Belegt Existenz und Zugänglichkeit der Quelle; inhaltliche Aussagen erst nach Auswertung. | AQ55: Keine Einstufung: Kennzahlen/Befunde noch nicht ausgewertet; Schwellen der Bewertungslogik noch nicht validiert. | AR55: Ja | AS55: Gemeindeverwaltung Seelisberg | AT55: In Prüfung | AW55: 2026-10-14: neu aufgenommen
A56: SEE-C2-03 | B56: Gemeinde | C56: Schweiz | D56: Uri | E56: Seelisberg | F56: C2 | G56: Siedlungsentwicklung | H56: Siedlungsleitbild Seelisberg (Genehmigungsexemplar, 5.10.2022) | I56: Leitbild / Bericht | J56: Direktes Dokument | K56: Behördenverbindliche Planung | L56: Gemeinderat Seelisberg | M56: https://www.seelisberg.ch/files/pdf/8_20221005_Bericht_Siedlungsleitbild_Genehmigungsexemplar.pdf | N56: 2022 | O56: 2026-10-14 | P56: Strategische Entwicklungsgebiete (Sonnenberg, Chilendorf); Bodenpolitik-Absichten | S56: Kein Peer-Vergleich | T56: Noch nicht bewertet | U56: Hoch | W56: B | Y56: Dokument auswerten; Aktualität und Geltung prüfen | Z56: Websuche 14.10.2026 (URL im Suchergebnis gefunden) | AA56: C5 | AD56: Verifiziert | AE56: 200 | AG56: PDF | AH56: Bestätigt | AI56: Schlüsselwörter 1/1 gefunden (Siedlungsleitbild); Ort/Zuständigkeit: Seelisberg | AJ56: Seelisberg, Siedlungsleitbild | AK56: 2022, 2021, 2017, 2020, 2019, 2015 | AL56: Mittel (CMS-Dokumentlink) | AM56: 2026-10-14 13:54 | AN56: Öffentlich verfügbar und verifiziert | AO56: 2022 | AP56: Belegt Existenz und Zugänglichkeit der Quelle; inhaltliche Aussagen erst nach Auswertung. | AQ56: Keine Einstufung: Kennzahlen/Befunde noch nicht ausgewertet; Schwellen der Bewertungslogik noch nicht validiert. | AR56: Ja | AS56: Gemeindeverwaltung Seelisberg | AT56: In Prüfung | AW56: 2026-10-14: neu aufgenommen
A57: SEE-C2-04 | B57: Gemeinde | C57: Schweiz | D57: Uri | E57: Seelisberg | F57: C2 | G57: Nutzungsplanung | H57: Seelisberg: Teilrevision Nutzungsplanung – Erläuterungsbericht (26.5.2023) | I57: Planungsbericht | J57: Direktes Dokument | K57: Planungsbericht | L57: Gemeinde Seelisberg | M57: https://www.seelisberg.ch/files/pdf/20230526_Erl%C3%A4uterungsbericht.pdf | N57: 2023 | O57: 2026-10-14 | P57: Planerische Flächenverfügbarkeit (≠ Eigentum) | S57: Kein Peer-Vergleich | T57: Noch nicht bewertet | U57: Mittel | W57: B | Y57: Dokument auswerten; Aktualität und Geltung prüfen | Z57: Websuche 14.10.2026 (URL im Suchergebnis gefunden) | AD57: Verifiziert | AE57: 200 | AG57: PDF | AH57: Bestätigt | AI57: Schlüsselwörter 1/1 gefunden (Nutzungsplanung); Ort/Zuständigkeit: Seelisberg | AJ57: Seelisberg, Teilrevision Nutzungsplanung | AK57: 2021, 2022, 2017, 2023, 2019, 2014 | AL57: Mittel (CMS-Dokumentlink) | AM57: 2026-10-14 13:54 | AN57: Öffentlich verfügbar und verifiziert | AO57: 2023 | AP57: Belegt Existenz und Zugänglichkeit der Quelle; inhaltliche Aussagen erst nach Auswertung. | AQ57: Keine Einstufung: Kennzahlen/Befunde noch nicht ausgewertet; Schwellen der Bewertungslogik noch nicht validiert. | AR57: Ja | AS57: Gemeindeverwaltung Seelisberg | AT57: In Prüfung | AW57: 2026-10-14: neu aufgenommen
A58: SEE-C3-01 | B58: Gemeinde | C58: Schweiz | D58: Uri | E58: Seelisberg | F58: C3 | G58: Gemeindeorganisation | H58: Seelisberg: Behörden und Kommissionen | I58: Behördenübersicht | J58: Offizielle Quelle recherchiert | K58: Orientierung / Datengrundlage | L58: Gemeinde Seelisberg | M58: https://www.seelisberg.ch/politik/beh%C3%B6rden-kommissionen | N58: Zu prüfen | O58: 2026-10-14 | P58: Behördenstruktur, Räte und Kommissionen | Q58: Rollen, Zuständigkeiten, Kooperationen | R58: Akteurskarte und Entscheidungswege erstellen | S58: Qualitativ | T58: Noch nicht bewertet | U58: Mittel | V58: Kennzahlen und Befunde noch extrahieren | W58: C4; C5 | X58: Trägerschaft | Y58: Dokument auswerten; Aktualität und Geltung prüfen | Z58: Webrecherche 14.10.2026 | AD58: Verifiziert | AE58: 200 | AG58: HTML | AH58: Bestätigt | AI58: Schlüsselwörter 1/1 gefunden (Kommission); Ort/Zuständigkeit: Seelisberg | AJ58: Gemeinde Seelisberg | Einwohner-Service | Behörden und Kommissionen | AL58: Mittel (Webseite) | AM58: 2026-10-14 13:53 | AN58: Öffentlich verfügbar und verifiziert | AO58: Zu prüfen | AP58: Belegt Existenz und Zugänglichkeit der Quelle; inhaltliche Aussagen erst nach Auswertung. | AQ58: Keine Einstufung: Kennzahlen/Befunde noch nicht ausgewertet; Schwellen der Bewertungslogik noch nicht validiert. | AR58: Ja | AS58: Gemeindeverwaltung Seelisberg | AT58: In Prüfung | AV58: SEE-C4-01
A59: SEE-C3-02 | B59: Gemeinde | C59: Schweiz | D59: Uri | E59: Seelisberg | F59: C3 | G59: Gemeindeordnung | H59: Gemeindeordnung der Einwohnergemeinde Seelisberg | I59: Gemeindeordnung | J59: Direktes Dokument | K59: Kommunales Recht (verbindlich) | L59: Gemeinde Seelisberg | M59: https://www.seelisberg.ch/files/pdf/Gemeindeordnung.pdf | O59: 2026-10-14 | P59: Zuständigkeiten Gemeindeversammlung/Gemeinderat, Finanzkompetenzen, Zusammenarbeit | S59: Kein Peer-Vergleich | T59: Noch nicht bewertet | U59: Hoch | Y59: Dokument auswerten; Aktualität und Geltung prüfen | Z59: Automatische Recherche GitHub Actions (Discovery), Fundstelle siehe Spalte Offizielle Fundstelle | AA59: C1, C5 | AC59: https://www.seelisberg.ch/politik/rechtssammlung | AD59: Verifiziert | AE59: 200 | AG59: PDF | AH59: Bestätigt | AI59: Schlüsselwörter 1/1 gefunden (Gemeindeordnung); Ort/Zuständigkeit: Seelisberg | AJ59: GEMEINDE SEELISBERG | AK59: 2018, 2009 | AL59: Mittel (CMS-Dokumentlink) | AM59: 2026-10-14 13:54 | AN59: Öffentlich verfügbar und verifiziert | AP59: Belegt Existenz und Zugänglichkeit der Quelle; inhaltliche Aussagen erst nach Auswertung. Fundstellen im Dokument (automatisch): Zweckverband: nicht gefunden; Zusammenarbeit: nicht gefunden; Finanzbefugnis: nicht gefunden; Kredit: S. 9. | AQ59: Keine Einstufung: Kennzahlen/Befunde noch nicht ausgewertet; Schwellen der Bewertungslogik noch nicht validiert. | AR59: Ja | AS59: Gemeindeverwaltung Seelisberg | AT59: In Prüfung | AU59: Fassungsdatum im Dokument prüfen (zitiert als 27.11.2009). | AW59: 2026-10-14: neu aufgenommen
A60: SEE-C4-01 | B60: Gemeinde | C60: Schweiz | D60: Uri | E60: Seelisberg | F60: C4 | G60: Verwaltung | H60: Seelisberg: Behörden und Kommissionen | I60: Behördenübersicht | J60: Offizielle Quelle recherchiert | K60: Orientierung / Datengrundlage | L60: Gemeinde Seelisberg | M60: https://www.seelisberg.ch/politik/beh%C3%B6rden-kommissionen | N60: Zu prüfen | O60: 2026-10-14 | P60: Erste Übersicht zur kommunalen Aufgabenorganisation | Q60: Projektleitung, Personal, externe Mandate | R60: Personal- und Prozessangaben bei Gemeinde anfragen | S60: Qualitativ | T60: Noch nicht bewertet | U60: Mittel | V60: Kennzahlen und Befunde noch extrahieren | W60: Q6; C3 | X60: Verwaltungsfähigkeit | Y60: Dokument auswerten; Aktualität und Geltung prüfen | Z60: Webrecherche 14.10.2026 | AD60: Verifiziert | AE60: 200 | AG60: HTML | AH60: Bestätigt | AI60: Schlüsselwörter 1/1 gefunden (Kommission); Ort/Zuständigkeit: Seelisberg | AJ60: Gemeinde Seelisberg | Einwohner-Service | Behörden und Kommissionen | AL60: Mittel (Webseite) | AM60: 2026-10-14 13:53 | AN60: Öffentlich verfügbar und verifiziert | AO60: Zu prüfen | AP60: Belegt Existenz und Zugänglichkeit der Quelle; inhaltliche Aussagen erst nach Auswertung. | AQ60: Keine Einstufung: Kennzahlen/Befunde noch nicht ausgewertet; Schwellen der Bewertungslogik noch nicht validiert. | AR60: Ja | AS60: Gemeindeverwaltung Seelisberg | AT60: In Prüfung | AV60: SEE-C3-01
A61: SEE-C4-02 | B61: Gemeinde | C61: Schweiz | D61: Uri | E61: Seelisberg | F61: C4 | G61: Verwaltungsorganisation | H61: Gemeinde Seelisberg: Personal der Gemeindeverwaltung | I61: Webseite | J61: Webseite | K61: Information | L61: Gemeinde Seelisberg | M61: https://www.seelisberg.ch/personal | O61: 2026-10-14 | P61: Übersicht Verwaltungspersonal (Kapazitätsindikator, kein Kompetenznachweis) | S61: Kein Peer-Vergleich | T61: Noch nicht bewertet | U61: Mittel | Y61: Dokument auswerten; Aktualität und Geltung prüfen | Z61: Websuche 14.10.2026 (URL im Suchergebnis gefunden) | AD61: Verifiziert | AE61: 200 | AG61: HTML | AH61: Bestätigt | AI61: Schlüsselwörter 1/1 gefunden (Verwaltung); Ort/Zuständigkeit: Seelisberg | AJ61: Gemeinde Seelisberg | Einwohner-Service | Unsere Mitarbeitenden im Überblick | AL61: Mittel (Webseite) | AM61: 2026-10-14 13:54 | AN61: Öffentlich verfügbar und verifiziert | AP61: Belegt Existenz und Zugänglichkeit der Quelle; inhaltliche Aussagen erst nach Auswertung. | AQ61: Keine Einstufung: Kennzahlen/Befunde noch nicht ausgewertet; Schwellen der Bewertungslogik noch nicht validiert. | AR61: Ja | AS61: Gemeindeverwaltung Seelisberg | AT61: In Prüfung | AW61: 2026-10-14: neu aufgenommen
A62: SEE-C4-03 | B62: Gemeinde | C62: Schweiz | D62: Uri | E62: Seelisberg | F62: C4 | G62: Personal | H62: Verordnung über das Personal der Gemeinde Seelisberg | I62: Kommunale Verordnung | J62: Direktes Dokument | K62: Kommunales Recht (verbindlich) | L62: Gemeinde Seelisberg | M62: https://www.seelisberg.ch/files/pdf/Verordnung_%C3%BCber_das_Personal.pdf | O62: 2026-10-14 | P62: Anstellungsrahmen und Zuständigkeiten im Personalwesen (keine Aussage zu Kapazität) | S62: Kein Peer-Vergleich | T62: Noch nicht bewertet | U62: Hoch | Y62: Dokument auswerten; Aktualität und Geltung prüfen | Z62: Automatische Recherche GitHub Actions (Discovery), Fundstelle siehe Spalte Offizielle Fundstelle | AC62: https://www.seelisberg.ch/politik/rechtssammlung | AD62: Fehler | AE62: 404 | AH62: Offen | AI62: HTTP 404 | AL62: Mittel (CMS-Dokumentlink) | AM62: 2026-10-14 13:54 | AN62: Nicht zugänglich / nicht prüfbar | AP62: Belegt Existenz und Zugänglichkeit der Quelle; inhaltliche Aussagen erst nach Auswertung. | AQ62: Keine Einstufung: Kennzahlen/Befunde noch nicht ausgewertet; Schwellen der Bewertungslogik noch nicht validiert. | AR62: Ja | AS62: Gemeindeverwaltung Seelisberg | AT62: Offen | AU62: Link defekt – Ersatz recherchieren | AW62: 2026-10-14: neu aufgenommen
A63: SEE-C4-04 | B63: Gemeinde | C63: Schweiz | D63: Uri | E63: Seelisberg | F63: C4 | G63: Behördenorganisation | H63: Verordnung über das Verfahren in den Behörden der Gemeinde Seelisberg | I63: Kommunale Verordnung | J63: Direktes Dokument | K63: Kommunales Recht (verbindlich) | L63: Gemeinde Seelisberg | M63: https://www.seelisberg.ch/files/pdf/Verordnung_%C3%BCber_das_Verfahren_in_den_Beh%C3%B6rden.pdf | O63: 2026-10-14 | P63: Arbeitsweise und Beschlussfassung von Gemeinderat und Kommissionen | S63: Kein Peer-Vergleich | T63: Noch nicht bewertet | U63: Hoch | Y63: Dokument auswerten; Aktualität und Geltung prüfen | Z63: Automatische Recherche GitHub Actions (Discovery), Fundstelle siehe Spalte Offizielle Fundstelle | AA63: C3 | AC63: https://www.seelisberg.ch/politik/rechtssammlung | AD63: Fehler | AE63: 404 | AH63: Offen | AI63: HTTP 404 | AL63: Mittel (CMS-Dokumentlink) | AM63: 2026-10-14 13:54 | AN63: Nicht zugänglich / nicht prüfbar | AP63: Belegt Existenz und Zugänglichkeit der Quelle; inhaltliche Aussagen erst nach Auswertung. | AQ63: Keine Einstufung: Kennzahlen/Befunde noch nicht ausgewertet; Schwellen der Bewertungslogik noch nicht validiert. | AR63: Ja | AS63: Gemeindeverwaltung Seelisberg | AT63: Offen | AU63: Link defekt – Ersatz recherchieren | AW63: 2026-10-14: neu aufgenommen
A64: SEE-C5-01 | B64: Gemeinde | C64: Schweiz | D64: Uri | E64: Seelisberg | F64: C5 | G64: Politische Beschlüsse | H64: Seelisberg: Gemeindeversammlung und Beschlussprotokolle | I64: Protokollsammlung | J64: Offizielle Quelle recherchiert | K64: Orientierung / Datengrundlage | L64: Gemeinde Seelisberg | M64: https://www.seelisberg.ch/politik/gemeindeversammlung | N64: Zu prüfen | O64: 2026-10-14 | P64: Politische Zuständigkeiten; dokumentierte Ausgabenkompetenzen | Q64: Mitwirkung, Abstimmungen, Entscheidungsregeln | R64: Beschlüsse und Gemeindeordnung auswerten | S64: Qualitativ | T64: Noch nicht bewertet | U64: Mittel | V64: Kennzahlen und Befunde noch extrahieren | W64: C3; Q1 | X64: Legitimation | Y64: Dokument auswerten; Aktualität und Geltung prüfen | Z64: Webrecherche 14.10.2026 | AD64: Verifiziert | AE64: 200 | AG64: HTML | AH64: Bestätigt | AI64: Schlüsselwörter 1/1 gefunden (Gemeindeversammlung); Ort/Zuständigkeit: Seelisberg | AJ64: Gemeinde Seelisberg | Einwohner-Service | Gemeindeversammlung | AK64: 2024, 2023, 2022, 2021, 2025, 2026 | AL64: Mittel (Webseite) | AM64: 2026-10-14 13:53 | AN64: Öffentlich verfügbar und verifiziert | AO64: Zu prüfen | AP64: Belegt Existenz und Zugänglichkeit der Quelle; inhaltliche Aussagen erst nach Auswertung. | AQ64: Keine Einstufung: Kennzahlen/Befunde noch nicht ausgewertet; Schwellen der Bewertungslogik noch nicht validiert. | AR64: Nein | AS64: Gemeindeverwaltung Seelisberg | AT64: In Prüfung | AV64: SEE-C1-01
A65: SEE-C5-02 | B65: Gemeinde | C65: Schweiz | D65: Uri | E65: Seelisberg | F65: C5 | G65: Leitbild | H65: Gemeinde Seelisberg: Neues Leitbild der Gemeinde (2025) | I65: Leitbild / Mitteilung | J65: Webseite | K65: Politische Zielsetzung | L65: Gemeinde Seelisberg | M65: https://www.seelisberg.ch/news/neues-leitbild-der-gemeinde-seelisberg | N65: 2025 | O65: 2026-10-14 | P65: Mitwirkungsprozess (Workshop, Umfrage) und Themen; belegt keine Akzeptanz | S65: Kein Peer-Vergleich | T65: Noch nicht bewertet | U65: Mittel | Y65: Dokument auswerten; Aktualität und Geltung prüfen | Z65: Websuche 14.10.2026 (URL im Suchergebnis gefunden) | AC65: https://www.seelisberg.ch/ueber-seelisberg/leitbild | AD65: Verifiziert | AE65: 200 | AG65: HTML | AH65: Bestätigt | AI65: Schlüsselwörter 1/1 gefunden (Leitbild); Ort/Zuständigkeit: Seelisberg | AJ65: Gemeinde Seelisberg | Einwohner-Service | Leitbild der Gemeinde Seelisberg | AK65: 2011, 2025 | AL65: Mittel (Webseite) | AM65: 2026-10-14 13:54 | AN65: Öffentlich verfügbar und verifiziert | AO65: 2025 | AP65: Belegt Existenz und Zugänglichkeit der Quelle; inhaltliche Aussagen erst nach Auswertung. | AQ65: Keine Einstufung: Kennzahlen/Befunde noch nicht ausgewertet; Schwellen der Bewertungslogik noch nicht validiert. | AR65: Nein | AS65: Gemeindeverwaltung Seelisberg | AT65: In Prüfung | AW65: 2026-10-14: neu aufgenommen
A66: SEE-C5-03 | B66: Gemeinde | C66: Schweiz | D66: Uri | E66: Seelisberg | F66: C5 | G66: Beschlussprotokoll | H66: Beschlussprotokoll Gemeindeversammlung Seelisberg vom 24.11.2023 | I66: Protokoll | J66: Direktes Dokument | K66: Beschluss (verbindlich) | L66: Gemeinde Seelisberg | M66: https://www.seelisberg.ch/files/pdf/Beschlussprotokoll_GV_24.11.2023.pdf | N66: 2023 | O66: 2026-10-14 | P66: Dokumentierte Beschlüsse/Wahlen | S66: Kein Peer-Vergleich | T66: Noch nicht bewertet | U66: Hoch | Y66: Dokument auswerten; Aktualität und Geltung prüfen | Z66: Websuche 14.10.2026 (URL im Suchergebnis gefunden) | AC66: https://www.seelisberg.ch/politik/gemeindeversammlung | AD66: Verifiziert | AE66: 200 | AG66: PDF | AH66: Bestätigt | AI66: Schlüsselwörter 1/1 gefunden (Beschluss); Ort/Zuständigkeit: Seelisberg | AJ66: 'GEMEINDESEELISBERG | AK66: 2024, 2023 | AL66: Mittel (CMS-Dokumentlink) | AM66: 2026-10-14 13:54 | AN66: Öffentlich verfügbar und verifiziert | AO66: 2023 | AP66: Belegt Existenz und Zugänglichkeit der Quelle; inhaltliche Aussagen erst nach Auswertung. | AQ66: Keine Einstufung: Kennzahlen/Befunde noch nicht ausgewertet; Schwellen der Bewertungslogik noch nicht validiert. | AR66: Nein | AS66: Gemeindeverwaltung Seelisberg | AT66: In Prüfung | AU66: Neuere Protokolle (28.5.2025, 28.11.2025) auf der Fundstelle gelistet; direkter Link per Discovery suchen. | AW66: 2026-10-14: neu aufgenommen
A67: SEE-C5-04 | B67: Gemeinde | C67: Schweiz | D67: Uri | E67: Seelisberg | F67: C5 | G67: Beschlussprotokoll | H67: Beschlussprotokoll Gemeindeversammlung Seelisberg vom 28.11.2025 | I67: Protokoll | J67: Direktes Dokument | K67: Beschluss (verbindlich) | L67: Gemeinde Seelisberg | M67: https://www.seelisberg.ch/files/pdf/Beschlussprotokoll_GV_28.11.2025.pdf | N67: 2025 | O67: 2026-10-14 | P67: Beschlüsse Budget 2026, Leitbild, Verordnungen | S67: Kein Peer-Vergleich | T67: Noch nicht bewertet | U67: Hoch | Y67: Dokument auswerten; Aktualität und Geltung prüfen | Z67: Automatische Recherche GitHub Actions (Discovery), Fundstelle siehe Spalte Offizielle Fundstelle | AA67: C1 | AC67: https://www.seelisberg.ch/politik/gemeindeversammlung | AD67: Verifiziert | AE67: 200 | AG67: PDF | AH67: Bestätigt | AI67: Schlüsselwörter 1/1 gefunden (Beschluss); Ort/Zuständigkeit: Seelisberg | AJ67: (‚LHEIWDESLLLISBERG | AK67: 2024, 2025, 2026 | AL67: Mittel (CMS-Dokumentlink) | AM67: 2026-10-14 13:55 | AN67: Öffentlich verfügbar und verifiziert | AO67: 2025 | AP67: Belegt Existenz und Zugänglichkeit der Quelle; inhaltliche Aussagen erst nach Auswertung. | AQ67: Keine Einstufung: Kennzahlen/Befunde noch nicht ausgewertet; Schwellen der Bewertungslogik noch nicht validiert. | AR67: Nein | AS67: Gemeindeverwaltung Seelisberg | AT67: In Prüfung | AW67: 2026-10-14: neu aufgenommen
A68: SEE-C5-05 | B68: Gemeinde | C68: Schweiz | D68: Uri | E68: Seelisberg | F68: C5 | G68: Beschlussprotokoll | H68: Beschlussprotokoll Gemeindeversammlung Seelisberg vom 28.5.2025 | I68: Protokoll | J68: Direktes Dokument | K68: Beschluss (verbindlich) | L68: Gemeinde Seelisberg | M68: https://www.seelisberg.ch/files/pdf/Beschlussprotokoll-GV-Mai-2025.pdf | N68: 2025 | O68: 2026-10-14 | P68: Beschluss Jahresrechnung 2024 (44 Stimmberechtigte anwesend) | S68: Kein Peer-Vergleich | T68: Noch nicht bewertet | U68: Hoch | Y68: Dokument auswerten; Aktualität und Geltung prüfen | Z68: Automatische Recherche GitHub Actions (Discovery), Fundstelle siehe Spalte Offizielle Fundstelle | AA68: C1 | AC68: https://www.seelisberg.ch/politik/gemeindeversammlung | AD68: Verifiziert | AE68: 200 | AG68: PDF | AH68: Bestätigt | AI68: Schlüsselwörter 2/2 gefunden (Beschluss, 28. Mai 2025); Ort/Zuständigkeit: Seeusberg | AJ68: GEMEINDESEEUSBERG | AK68: 2024, 2025 | AL68: Mittel (CMS-Dokumentlink) | AM68: 2026-10-14 13:55 | AN68: Öffentlich verfügbar und verifiziert | AO68: 2025 | AP68: Belegt Existenz und Zugänglichkeit der Quelle; inhaltliche Aussagen erst nach Auswertung. | AQ68: Keine Einstufung: Kennzahlen/Befunde noch nicht ausgewertet; Schwellen der Bewertungslogik noch nicht validiert. | AR68: Nein | AS68: Gemeindeverwaltung Seelisberg | AT68: In Prüfung | AU68: Textextraktion liest den Kopf als «GEMEINDESEEUSBERG» (Schriftbild); Ortsabgleich toleriert diese Lesart. | AW68: 2026-10-14: neu aufgenommen
A69: SEE-C5-06 | B69: Gemeinde | C69: Schweiz | D69: Uri | E69: Seelisberg | F69: C5 | G69: Leitbild | H69: Leitbild Seelisberg 2025 (Dokument) | I69: Leitbild | J69: Direktes Dokument | K69: Politische Zielsetzung | L69: Gemeinde Seelisberg | M69: https://www.seelisberg.ch/files/pdf/ORIGINAL-Leitbild-Seelisberg-2025-f%C3%BCr-Webseite.pdf | N69: 2025 | O69: 2026-10-14 | P69: Strategische Ziele (Wohnen, Tourismus, Finanzen); belegt keine Akzeptanz | S69: Kein Peer-Vergleich | T69: Noch nicht bewertet | U69: Hoch | Y69: Dokument auswerten; Aktualität und Geltung prüfen | Z69: Automatische Recherche GitHub Actions (Discovery), Fundstelle siehe Spalte Offizielle Fundstelle | AC69: https://www.seelisberg.ch/ueber-seelisberg/leitbild | AD69: Verifiziert | AE69: 200 | AG69: PDF | AH69: Bestätigt | AI69: Schlüsselwörter 1/1 gefunden (Leitbild); Ort/Zuständigkeit: Seelisberg | AJ69: Leitbild Seelisberg.indd | AK69: 2025 | AL69: Mittel (CMS-Dokumentlink) | AM69: 2026-10-14 13:55 | AN69: Öffentlich verfügbar und verifiziert | AO69: 2025 | AP69: Belegt Existenz und Zugänglichkeit der Quelle; inhaltliche Aussagen erst nach Auswertung. | AQ69: Keine Einstufung: Kennzahlen/Befunde noch nicht ausgewertet; Schwellen der Bewertungslogik noch nicht validiert. | AR69: Nein | AS69: Gemeindeverwaltung Seelisberg | AT69: In Prüfung | AW69: 2026-10-14: neu aufgenommen
A70: SEE-C5-07 | B70: Gemeinde | C70: Schweiz | D70: Uri | E70: Seelisberg | F70: C5 | G70: Abstimmung | H70: Kommunale Abstimmung Seelisberg vom 8.3.2026 (Unterlage) | I70: Abstimmungsunterlage | J70: Direktes Dokument | K70: Information | L70: Gemeinde Seelisberg | M70: https://www.seelisberg.ch/files/pdf/kommunale-Abstimmung-Seelisberg_260308.pdf | N70: 2026 | O70: 2026-10-14 | P70: Kommunale Urnenentscheide (Legitimation) | S70: Kein Peer-Vergleich | T70: Noch nicht bewertet | U70: Mittel | Y70: Dokument auswerten; Aktualität und Geltung prüfen | Z70: Automatische Recherche GitHub Actions (Discovery), Fundstelle siehe Spalte Offizielle Fundstelle | AC70: https://www.seelisberg.ch/politik/abstimmungen-wahlen | AD70: Verifiziert | AE70: 200 | AG70: PDF | AH70: Bestätigt | AI70: Schlüsselwörter 1/1 gefunden (Abstimmung); Ort/Zuständigkeit: Seelisberg | AJ70: Seelisberg KANTON | AK70: 2026 | AL70: Mittel (CMS-Dokumentlink) | AM70: 2026-10-14 13:55 | AN70: Öffentlich verfügbar und verifiziert | AO70: 2026 | AP70: Belegt Existenz und Zugänglichkeit der Quelle; inhaltliche Aussagen erst nach Auswertung. | AQ70: Keine Einstufung: Kennzahlen/Befunde noch nicht ausgewertet; Schwellen der Bewertungslogik noch nicht validiert. | AR70: Nein | AS70: Gemeindeverwaltung Seelisberg | AT70: In Prüfung | AW70: 2026-10-14: neu aufgenommen
A71: SEE-C5-08 | B71: Gemeinde | C71: Schweiz | D71: Uri | E71: Seelisberg | F71: C5 | G71: Verfahren Gemeindeversammlung | H71: Verordnung über das Verfahren an der Gemeindeversammlung Seelisberg | I71: Kommunale Verordnung | J71: Direktes Dokument | K71: Kommunales Recht (verbindlich) | L71: Gemeinde Seelisberg | M71: https://www.seelisberg.ch/files/pdf/Verordnung_%C3%BCber_das_Verfahren_an_der_Gemeindeversammlung.pdf | O71: 2026-10-14 | P71: Entscheidungsverfahren, Antragsrechte der Stimmberechtigten | S71: Kein Peer-Vergleich | T71: Noch nicht bewertet | U71: Hoch | Y71: Dokument auswerten; Aktualität und Geltung prüfen | Z71: Automatische Recherche GitHub Actions (Discovery), Fundstelle siehe Spalte Offizielle Fundstelle | AC71: https://www.seelisberg.ch/politik/rechtssammlung | AD71: Verifiziert | AE71: 200 | AG71: PDF | AH71: Bestätigt | AI71: Schlüsselwörter 2/2 gefunden (Gemeindeversammlung, Verfahren); Ort/Zuständigkeit: Seelisberg | AJ71: GEMEINDE SEELISBERG | AK71: 2018 | AL71: Mittel (CMS-Dokumentlink) | AM71: 2026-10-14 13:54 | AN71: Öffentlich verfügbar und verifiziert | AP71: Belegt Existenz und Zugänglichkeit der Quelle; inhaltliche Aussagen erst nach Auswertung. | AQ71: Keine Einstufung: Kennzahlen/Befunde noch nicht ausgewertet; Schwellen der Bewertungslogik noch nicht validiert. | AR71: Nein | AS71: Gemeindeverwaltung Seelisberg | AT71: In Prüfung | AW71: 2026-10-14: neu aufgenommen
A72: MUE-C1-01 | B72: Gemeinde | C72: Schweiz | D72: Basel-Landschaft | E72: Münchenstein | F72: C1 | G72: Finanzplanung | H72: Aufgaben- und Finanzplan 2025–2029 Münchenstein | I72: Finanzplan | J72: Offizielle Quelle recherchiert | K72: Orientierung / Datengrundlage | L72: Gemeinde Münchenstein | M72: https://www.muenchenstein.ch/publikationen/523378 | N72: Zu prüfen | O72: 2026-10-14 | P72: Mehrjährige Finanz- und Aufgabenplanung | Q72: Investitionsprogramm, Finanzierungsbedarf | R72: Finanzplan und Jahresrechnung vergleichen | S72: Kanton × Grössenklasse | T72: Noch nicht bewertet | U72: Mittel | V72: Kennzahlen und Befunde noch extrahieren | W72: A1; C1 | X72: Investitionspfad | Y72: Dokument auswerten; Aktualität und Geltung prüfen | Z72: Webrecherche 14.10.2026 | AD72: Verifiziert | AE72: 200 | AG72: HTML | AH72: Bestätigt | AI72: Schlüsselwörter 1/1 gefunden (Finanzplan); Ort/Zuständigkeit: Münchenstein | AJ72: Münchenstein - Aufgaben- &amp; Finanzplan 2025-2029 | Kopfzeile | AK72: 2025, 2029, 2024, 2026 | AL72: Mittel (CMS-Dokumentlink) | AM72: 2026-10-14 13:53 | AN72: Öffentlich verfügbar und verifiziert | AO72: Zu prüfen | AP72: Belegt Existenz und Zugänglichkeit der Quelle; inhaltliche Aussagen erst nach Auswertung. | AQ72: Keine Einstufung: Kennzahlen/Befunde noch nicht ausgewertet; Schwellen der Bewertungslogik noch nicht validiert. | AR72: Nein | AS72: Gemeindeverwaltung Münchenstein | AT72: In Prüfung
A73: MUE-C1-02 | B73: Gemeinde | C73: Schweiz | D73: Basel-Landschaft | E73: Münchenstein | F73: C1 | G73: Jahresrechnung | H73: Bericht zur Jahresrechnung 2025 der Einwohnergemeinde Münchenstein | I73: Jahresrechnung | J73: Publikationsseite mit PDF | K73: Beschlossene Jahresrechnung (Gemeindeversammlung 15.6.2026) | L73: Gemeinde Münchenstein | M73: https://www.muenchenstein.ch/publikationen/621658 | N73: 2025 | O73: 2026-10-14 | P73: Einstieg zur Beschaffung Jahresrechnung 2025 und Budget 2026 | Q73: Selbstfinanzierung, Nettoinvestitionen | R73: Konkrete Publikation ermitteln | S73: Kanton × Grössenklasse | T73: Noch nicht bewertet | U73: Mittel | V73: Konkrete kommunale Unterlagen / Datensatz nachfordern | W73: C1 | X73: Finanztragfähigkeit | Y73: Dokument auswerten; Aktualität und Geltung prüfen | Z73: Webrecherche 14.10.2026 | AD73: Verifiziert | AE73: 200 | AG73: HTML | AH73: Bestätigt | AI73: Schlüsselwörter 1/1 gefunden (Jahresrechnung 2025); Ort/Zuständigkeit: Münchenstein | AJ73: Münchenstein - Bericht zur Jahresrechnung 2025 | Kopfzeile | AK73: 2025, 2026 | AL73: Mittel (CMS-Dokumentlink) | AM73: 2026-10-14 13:53 | AN73: Öffentlich verfügbar und verifiziert | AO73: 2025 | AP73: Belegt Existenz und Zugänglichkeit der Quelle; inhaltliche Aussagen erst nach Auswertung. | AQ73: Keine Einstufung: Kennzahlen/Befunde noch nicht ausgewertet; Schwellen der Bewertungslogik noch nicht validiert. | AR73: Nein | AS73: Gemeindeverwaltung Münchenstein | AT73: In Prüfung | AW73: 2026-10-14: Link ersetzt (vorher https://www.muenchenstein.ch/). Grund: Startseite durch Publikationsseite der Jahresrechnung 2025 ersetzt.
A74: MUE-C1-03 | B74: Gemeinde | C74: Schweiz | D74: Basel-Landschaft | E74: Münchenstein | F74: C1 | G74: Jahresrechnung | H74: Bericht zur Jahresrechnung 2024 der Einwohnergemeinde Münchenstein | I74: Jahresrechnung | J74: Publikationsseite mit PDF | K74: Beschlossene Jahresrechnung | L74: Gemeinde Münchenstein | M74: https://www.muenchenstein.ch/publikationen/556069 | N74: 2024 | O74: 2026-10-14 | P74: Ergebnis, Investitionen, Bilanz 2024 (Zeitreihe) | S74: Kanton × Grössenklasse | T74: Noch nicht bewertet | U74: Mittel | Y74: Dokument auswerten; Aktualität und Geltung prüfen | Z74: Websuche 14.10.2026 (URL im Suchergebnis gefunden) | AD74: Verifiziert | AE74: 200 | AG74: HTML | AH74: Bestätigt | AI74: Schlüsselwörter 1/1 gefunden (Jahresrechnung 2024); Ort/Zuständigkeit: Münchenstein | AJ74: Münchenstein - Bericht zur Jahresrechnung 2024 | Kopfzeile | AK74: 2024, 2025, 2026 | AL74: Mittel (CMS-Dokumentlink) | AM74: 2026-10-14 13:55 | AN74: Öffentlich verfügbar und verifiziert | AO74: 2024 | AP74: Belegt Existenz und Zugänglichkeit der Quelle; inhaltliche Aussagen erst nach Auswertung. | AQ74: Keine Einstufung: Kennzahlen/Befunde noch nicht ausgewertet; Schwellen der Bewertungslogik noch nicht validiert. | AR74: Nein | AS74: Gemeindeverwaltung Münchenstein | AT74: In Prüfung | AW74: 2026-10-14: neu aufgenommen
A75: MUE-C1-04 | B75: Gemeinde | C75: Schweiz | D75: Basel-Landschaft | E75: Münchenstein | F75: C1 | G75: Budget | H75: Budget 2025 der Einwohnergemeinde Münchenstein | I75: Budget | J75: Publikationsseite mit PDF | K75: Beschlossenes Budget | L75: Gemeinde Münchenstein | M75: https://www.muenchenstein.ch/publikationen/523381 | N75: 2025 | O75: 2026-10-14 | S75: Kanton × Grössenklasse | T75: Noch nicht bewertet | U75: Mittel | Y75: Dokument auswerten; Aktualität und Geltung prüfen | Z75: Websuche 14.10.2026 (URL im Suchergebnis gefunden) | AD75: Verifiziert | AE75: 200 | AG75: HTML | AH75: Bestätigt | AI75: Schlüsselwörter 1/1 gefunden (Budget 2025); Ort/Zuständigkeit: Münchenstein | AJ75: Münchenstein - Budget 2025 | Kopfzeile | AK75: 2025, 2024, 2026 | AL75: Mittel (CMS-Dokumentlink) | AM75: 2026-10-14 13:55 | AN75: Öffentlich verfügbar und verifiziert | AO75: 2025 | AP75: Belegt Existenz und Zugänglichkeit der Quelle; inhaltliche Aussagen erst nach Auswertung. | AQ75: Keine Einstufung: Kennzahlen/Befunde noch nicht ausgewertet; Schwellen der Bewertungslogik noch nicht validiert. | AR75: Nein | AS75: Gemeindeverwaltung Münchenstein | AT75: In Prüfung | AW75: 2026-10-14: neu aufgenommen
A76: MUE-C1-05 | B76: Gemeinde | C76: Schweiz | D76: Basel-Landschaft | E76: Münchenstein | F76: C1 | G76: Budget / Finanzplan | H76: Gemeindeversammlung 8.12.2025: Budgetbericht 2026 und Bericht zum Aufgaben- und Finanzplan 2026–2030 | I76: Sitzungsseite mit Unterlagen | J76: Sitzungsseite mit PDF | K76: Beschlussvorlage | L76: Gemeinde Münchenstein | M76: https://www.muenchenstein.ch/sitzung/5729137 | N76: 2026 / 2026–2030 | O76: 2026-10-14 | P76: Aktuellstes Budget und AFP inkl. Investitionsplanung | S76: Kanton × Grössenklasse | T76: Noch nicht bewertet | U76: Mittel | Y76: Dokument auswerten; Aktualität und Geltung prüfen | Z76: Websuche 14.10.2026 (URL im Suchergebnis gefunden) | AA76: C5 | AD76: Verifiziert | AE76: 200 | AG76: HTML | AH76: Bestätigt | AI76: Schlüsselwörter 2/2 gefunden (Budget, 2026); Ort/Zuständigkeit: Münchenstein | AJ76: Münchenstein - Gemeindeversammlung | Kopfzeile | AK76: 2026, 2025, 2030 | AL76: Mittel (Webseite) | AM76: 2026-10-14 13:55 | AN76: Öffentlich verfügbar und verifiziert | AO76: 2026 / 2026–2030 | AP76: Belegt Existenz und Zugänglichkeit der Quelle; inhaltliche Aussagen erst nach Auswertung. | AQ76: Keine Einstufung: Kennzahlen/Befunde noch nicht ausgewertet; Schwellen der Bewertungslogik noch nicht validiert. | AR76: Nein | AS76: Gemeindeverwaltung Münchenstein | AT76: In Prüfung | AW76: 2026-10-14: neu aufgenommen
A77: MUE-C1-06 | B77: Gemeinde | C77: Schweiz | D77: Basel-Landschaft | E77: Münchenstein | F77: C1 | G77: Finanzplanung | H77: Aufgaben- & Finanzplan der Einwohnergemeinde Münchenstein 2023–2027 | I77: Finanzplan | J77: Direktes Dokument | K77: Planungsinstrument (Kenntnisnahme) | L77: Gemeinde Münchenstein | M77: https://www.muenchenstein.ch/_docn/4130681/Bericht_Aufgaben__Finanzplan_2023-2027_publiziert.pdf | N77: 2023–2027 (historisch) | O77: 2026-10-14 | P77: Baurechtszinsen, Investitionen, Bilanzüberschuss-Prognose | S77: Kanton × Grössenklasse | T77: Noch nicht bewertet | U77: Hoch | Y77: Dokument auswerten; Aktualität und Geltung prüfen | Z77: Websuche 14.10.2026 (URL im Suchergebnis gefunden) | AD77: Verifiziert | AE77: 200 | AG77: PDF | AH77: Bestätigt | AI77: Schlüsselwörter 2/2 gefunden (Finanzplan, 2023); Ort/Zuständigkeit: Münchenstein | AJ77: untitled | AK77: 2023, 2022, 2027, 2021, 2020, 2025 | AL77: Mittel (CMS-Dokumentlink) | AM77: 2026-10-14 13:55 | AN77: Öffentlich verfügbar und verifiziert | AO77: 2023–2027 (historisch) | AP77: Belegt Existenz und Zugänglichkeit der Quelle; inhaltliche Aussagen erst nach Auswertung. Fundstellen im Dokument (automatisch): Baurechtszins: S. 14, 27, 35. | AQ77: Keine Einstufung: Kennzahlen/Befunde noch nicht ausgewertet; Schwellen der Bewertungslogik noch nicht validiert. | AR77: Nein | AS77: Gemeindeverwaltung Münchenstein | AT77: In Prüfung | AU77: Ältere Fassung; aktuelle AFP 2026–2030 siehe MUE-C1-05. | AW77: 2026-10-14: neu aufgenommen
A78: MUE-C2-01 | B78: Gemeinde | C78: Schweiz | D78: Basel-Landschaft | E78: Münchenstein | F78: C2 | G78: Boden / Liegenschaften | H78: Ratschlag Gemeindeversammlung 16.3.2015 (Landverkauf Parzelle 799; Grundsätze aktive Landpolitik / Baurecht) | I78: Ratschlag / Vorlage | J78: Direktes Dokument | K78: Beschlussvorlage (historisch) | L78: Gemeinde Münchenstein | M78: https://www.muenchenstein.ch/_docn/1059619/2015.03.16_Ratschlag_Homepage.pdf | N78: 2015 | O78: 2026-10-14 | P78: Dokumentiert Grundsätze der kommunalen Landpolitik (Verkauf vs. Baurecht); historische Grundlage | Q78: ÖBA, Grundstücke, Baurechte | R78: Liegenschaftsverzeichnis anfragen | S78: Kein Peer | T78: Noch nicht bewertet | U78: Mittel | V78: Konkrete kommunale Unterlagen / Datensatz nachfordern | W78: B; Q1 | X78: Bodenmobilisierung | Y78: Dokument auswerten; Aktualität und Geltung prüfen | Z78: Webrecherche 14.10.2026 | AD78: Verifiziert | AE78: 200 | AG78: PDF | AH78: Bestätigt | AI78: Schlüsselwörter 2/2 gefunden (Ratschlag, Baurecht); Ort/Zuständigkeit: Münchenstein | AJ78: Ratschlag | AK78: 2014, 2015, 2016, 2030, 2012, 2006 | AL78: Mittel (CMS-Dokumentlink) | AM78: 2026-10-14 13:53 | AN78: Öffentlich verfügbar und verifiziert | AO78: 2015 | AP78: Belegt Existenz und Zugänglichkeit der Quelle; inhaltliche Aussagen erst nach Auswertung. Fundstellen im Dokument (automatisch): Baurecht: S. 5, 15, 17, 18, 19, 20, 26, 27, 41; Landpolitik: S. 4, 5, 41. | AQ78: Keine Einstufung: Kennzahlen/Befunde noch nicht ausgewertet; Schwellen der Bewertungslogik noch nicht validiert. | AR78: Ja | AS78: Gemeindeverwaltung Münchenstein | AT78: In Prüfung | AU78: Historisches Dokument (2015); aktuelle Liegenschaftsstrategie nicht öffentlich gefunden. | AW78: 2026-10-14: Link ersetzt (vorher https://www.muenchenstein.ch/). Grund: Startseite durch direktes Dokument zur Landpolitik ersetzt.
A79: MUE-C2-02 | B79: Gemeinde | C79: Schweiz | D79: Basel-Landschaft | E79: Münchenstein | F79: C2 | G79: Zonenvorschriften / Mehrwertabgabe | H79: Zonenreglement Siedlung Münchenstein | I79: Kommunales Reglement | J79: Direktes Dokument | K79: Kommunales Recht (verbindlich) | L79: Gemeinde Münchenstein | M79: https://www.muenchenstein.ch/_docn/1199675/Zonenreglement_Siedlung.pdf | O79: 2026-10-14 | P79: Mehrwertabgabe und Zonenordnung; kein Eigentumsnachweis | S79: Kein Peer-Vergleich | T79: Noch nicht bewertet | U79: Hoch | W79: B; Q1 | Y79: Dokument auswerten; Aktualität und Geltung prüfen | Z79: Websuche 14.10.2026 (URL im Suchergebnis gefunden) | AC79: https://www.muenchenstein.ch/reglemente/10743 | AD79: Verifiziert | AE79: 200 | AG79: PDF | AH79: Bestätigt | AI79: Schlüsselwörter 1/1 gefunden (Zonenreglement); Ort/Zuständigkeit: Münchenstein | AJ79: 43026_Reg01_Beschlussfassung2 | AK79: 2000, 2016, 2003, 2004 | AL79: Mittel (CMS-Dokumentlink) | AM79: 2026-10-14 13:55 | AN79: Öffentlich verfügbar und verifiziert | AP79: Belegt Existenz und Zugänglichkeit der Quelle; inhaltliche Aussagen erst nach Auswertung. | AQ79: Keine Einstufung: Kennzahlen/Befunde noch nicht ausgewertet; Schwellen der Bewertungslogik noch nicht validiert. | AR79: Ja | AS79: Gemeindeverwaltung Münchenstein | AT79: In Prüfung | AW79: 2026-10-14: neu aufgenommen
A80: MUE-C2-03 | B80: Gemeinde | C80: Schweiz | D80: Basel-Landschaft | E80: Münchenstein | F80: C2 | G80: Liegenschaftsverkäufe / Baurecht | H80: Ratschlag Gemeindeversammlung 12.3.2018 (Baurechtszinsen, Liegenschaftsverkäufe) | I80: Ratschlag / Vorlage | J80: Direktes Dokument | K80: Beschlussvorlage (historisch) | L80: Gemeinde Münchenstein | M80: https://www.muenchenstein.ch/_docn/1591897/2018.03.12_Ratschlag_GzD.pdf | N80: 2018 | O80: 2026-10-14 | P80: Bedeutung von Baurechtszinsen und Landverkäufen für den Haushalt | S80: Kein Peer-Vergleich | T80: Noch nicht bewertet | U80: Mittel | Y80: Dokument auswerten; Aktualität und Geltung prüfen | Z80: Websuche 14.10.2026 (URL im Suchergebnis gefunden) | AA80: C1 | AD80: Verifiziert | AE80: 200 | AG80: PDF | AH80: Bestätigt | AI80: Schlüsselwörter 1/1 gefunden (Ratschlag); Ort/Zuständigkeit: Münchenstein | AJ80: 46670_1_Mstein_Ratschlag.indd | AK80: 2017, 2018, 2015, 2016, 2014, 2011 | AL80: Mittel (CMS-Dokumentlink) | AM80: 2026-10-14 13:55 | AN80: Öffentlich verfügbar und verifiziert | AO80: 2018 | AP80: Belegt Existenz und Zugänglichkeit der Quelle; inhaltliche Aussagen erst nach Auswertung. | AQ80: Keine Einstufung: Kennzahlen/Befunde noch nicht ausgewertet; Schwellen der Bewertungslogik noch nicht validiert. | AR80: Ja | AS80: Gemeindeverwaltung Münchenstein | AT80: In Prüfung | AW80: 2026-10-14: neu aufgenommen
A81: MUE-C3-01 | B81: Gemeinde | C81: Schweiz | D81: Basel-Landschaft | E81: Münchenstein | F81: C3 | G81: Governance | H81: Gemeindeordnung der Einwohnergemeinde Münchenstein (Stand 1.1.2013) | I81: Gemeindeordnung | J81: Direktes Dokument | K81: Kommunales Recht (verbindlich) | L81: Gemeinde Münchenstein | M81: https://www.muenchenstein.ch/_docn/2430218/20180713_Gemeindeordnung_Stand_01.01.2013_publiziert_sw.pdf | N81: vom 13.9.1999, Stand 1.1.2013 | O81: 2026-10-14 | P81: Behörden, Kooperationen und Projektorganisation recherchieren | Q81: Trägerschaften, Zweckverbände | R81: Organigramm und Kooperationsverträge anfragen | S81: Qualitativ | T81: Noch nicht bewertet | U81: Hoch | V81: Konkrete kommunale Unterlagen / Datensatz nachfordern | W81: C4; C5 | X81: Governance | Y81: Dokument auswerten; Aktualität und Geltung prüfen | Z81: Webrecherche 14.10.2026 | AA81: C5 | AC81: https://www.muenchenstein.ch/reglemente/7140 | AD81: Verifiziert | AE81: 200 | AG81: PDF | AH81: Bestätigt | AI81: Schlüsselwörter 2/2 gefunden (Gemeindeordnung, Gemeindekommission); Ort/Zuständigkeit: Münchenstein | AJ81: Rechtssammlung | AK81: 2013, 2011, 2008, 2000, 2014, 2012 | AL81: Mittel (CMS-Dokumentlink) | AM81: 2026-10-14 13:53 | AN81: Öffentlich verfügbar und verifiziert | AO81: vom 13.9.1999, Stand 1.1.2013 | AP81: Belegt Existenz und Zugänglichkeit der Quelle; inhaltliche Aussagen erst nach Auswertung. | AQ81: Keine Einstufung: Kennzahlen/Befunde noch nicht ausgewertet; Schwellen der Bewertungslogik noch nicht validiert. | AR81: Ja | AS81: Gemeindeverwaltung Münchenstein | AT81: In Prüfung | AU81: Prüfen, ob neuere Fassung existiert (Einwohnerrat-Diskussion). | AW81: 2026-10-14: Link ersetzt (vorher https://www.muenchenstein.ch/). Grund: Startseite durch Gemeindeordnung ersetzt.
A82: MUE-C3-02 | B82: Gemeinde | C82: Schweiz | D82: Basel-Landschaft | E82: Münchenstein | F82: C3 | G82: Leistungsvereinbarung / Kooperation | H82: Ratschlag Gemeindeversammlung 15.6.2026 (u. a. Leistungsvereinbarung Spitex Birseck, Jahresrechnung 2025) | I82: Ratschlag / Vorlage | J82: Direktes Dokument | K82: Beschlussvorlage | L82: Gemeinde Münchenstein | M82: https://www.muenchenstein.ch/_docn/6998503/Ratschlag_Gemeindeversammlung_Montag,_15._Juni_2026.pdf | N82: 2026 | O82: 2026-10-14 | P82: Interkommunale Leistungsvereinbarung und Kostenteiler | S82: Kein Peer-Vergleich | T82: Noch nicht bewertet | U82: Hoch | Y82: Dokument auswerten; Aktualität und Geltung prüfen | Z82: Websuche 14.10.2026 (URL im Suchergebnis gefunden) | AA82: C1, C5 | AD82: Verifiziert | AE82: 200 | AG82: PDF | AH82: Bestätigt | AI82: Schlüsselwörter 2/2 gefunden (Ratschlag, Spitex); Ort/Zuständigkeit: Münchenstein | AJ82: 2009/2 | AK82: 2025, 2026, 2024, 2027, 2009, 2028 | AL82: Mittel (CMS-Dokumentlink) | AM82: 2026-10-14 13:55 | AN82: Öffentlich verfügbar und verifiziert | AO82: 2026 | AP82: Belegt Existenz und Zugänglichkeit der Quelle; inhaltliche Aussagen erst nach Auswertung. | AQ82: Keine Einstufung: Kennzahlen/Befunde noch nicht ausgewertet; Schwellen der Bewertungslogik noch nicht validiert. | AR82: Ja | AS82: Gemeindeverwaltung Münchenstein | AT82: In Prüfung | AW82: 2026-10-14: neu aufgenommen
A83: MUE-C4-01 | B83: Gemeinde | C83: Schweiz | D83: Basel-Landschaft | E83: Münchenstein | F83: C4 | G83: Verwaltung | H83: Gemeinde Münchenstein: Organisation und Organigramm der Verwaltung | I83: Organigramm / Webseite | J83: Webseite | K83: Information | L83: Gemeinde Münchenstein | M83: https://www.muenchenstein.ch/organisationuorganigramm | N83: Zu prüfen | O83: 2026-10-14 | P83: Verwaltungsorganisation und Zuständigkeiten | Q83: Personal, Projekte, Prozesse | R83: Organigramm / Ressourcen abfragen | S83: Qualitativ | T83: Noch nicht bewertet | U83: Mittel | V83: Konkrete kommunale Unterlagen / Datensatz nachfordern | W83: Q6 | X83: Bestellerfähigkeit | Y83: Dokument auswerten; Aktualität und Geltung prüfen | Z83: Webrecherche 14.10.2026 | AD83: Verifiziert | AE83: 200 | AG83: HTML | AH83: Bestätigt | AI83: Schlüsselwörter 1/1 gefunden (Organigramm); Ort/Zuständigkeit: Münchenstein | AJ83: Münchenstein - Organisation Gemeinde Münchenstein | Kopfzeile | AK83: 2026 | AL83: Mittel (Webseite) | AM83: 2026-10-14 13:53 | AN83: Öffentlich verfügbar und verifiziert | AO83: Zu prüfen | AP83: Belegt Existenz und Zugänglichkeit der Quelle; inhaltliche Aussagen erst nach Auswertung. | AQ83: Keine Einstufung: Kennzahlen/Befunde noch nicht ausgewertet; Schwellen der Bewertungslogik noch nicht validiert. | AR83: Ja | AS83: Gemeindeverwaltung Münchenstein | AT83: In Prüfung | AW83: 2026-10-14: Link ersetzt (vorher https://www.muenchenstein.ch/). Grund: Startseite durch Organigrammseite ersetzt.
A84: MUE-C4-02 | B84: Gemeinde | C84: Schweiz | D84: Basel-Landschaft | E84: Münchenstein | F84: C4 | G84: Personal | H84: Personalreglement der Einwohnergemeinde Münchenstein (Genehmigungsfassung 23.6.2022) | I84: Kommunales Reglement | J84: Direktes Dokument | K84: Kommunales Recht (verbindlich) | L84: Gemeinde Münchenstein | M84: https://www.muenchenstein.ch/_docn/3794018/Bereinigtes_Personalreglement_Genehmigungsfassung_per_23._Juni_2022.pdf | N84: in Kraft 1.1.2023 | O84: 2026-10-14 | S84: Kein Peer-Vergleich | T84: Noch nicht bewertet | U84: Hoch | Y84: Dokument auswerten; Aktualität und Geltung prüfen | Z84: Websuche 14.10.2026 (URL im Suchergebnis gefunden) | AC84: https://www.muenchenstein.ch/reglemente/402889 | AD84: Verifiziert | AE84: 200 | AG84: PDF | AH84: Bestätigt | AI84: Schlüsselwörter 1/1 gefunden (Personalreglement); Ort/Zuständigkeit: Münchenstein | AJ84: Rechtssammlung | AK84: 2022, 2011, 2013 | AL84: Mittel (CMS-Dokumentlink) | AM84: 2026-10-14 13:55 | AN84: Öffentlich verfügbar und verifiziert | AO84: in Kraft 1.1.2023 | AP84: Belegt Existenz und Zugänglichkeit der Quelle; inhaltliche Aussagen erst nach Auswertung. | AQ84: Keine Einstufung: Kennzahlen/Befunde noch nicht ausgewertet; Schwellen der Bewertungslogik noch nicht validiert. | AR84: Ja | AS84: Gemeindeverwaltung Münchenstein | AT84: In Prüfung | AW84: 2026-10-14: neu aufgenommen
A85: MUE-C4-03 | B85: Gemeinde | C85: Schweiz | D85: Basel-Landschaft | E85: Münchenstein | F85: C4 | G85: Verwaltungsorganisation | H85: Verwaltungs- und Organisationsreglement der Einwohnergemeinde Münchenstein | I85: Kommunales Reglement | J85: Reglementsseite mit PDF | K85: Kommunales Recht (verbindlich) | L85: Gemeinde Münchenstein | M85: https://www.muenchenstein.ch/reglemente/7208 | N85: Stand 1.1.2000 | O85: 2026-10-14 | S85: Kein Peer-Vergleich | T85: Noch nicht bewertet | U85: Mittel | Y85: Dokument auswerten; Aktualität und Geltung prüfen | Z85: Websuche 14.10.2026 (URL im Suchergebnis gefunden) | AA85: C3 | AD85: Verifiziert | AE85: 200 | AG85: HTML | AH85: Bestätigt | AI85: Schlüsselwörter 1/1 gefunden (Organisationsreglement); Ort/Zuständigkeit: Münchenstein | AJ85: Münchenstein - Verwaltungs- und Organisationsreglement | Kopfzeile | AK85: 2000, 2026 | AL85: Mittel (Webseite) | AM85: 2026-10-14 13:55 | AN85: Öffentlich verfügbar und verifiziert | AO85: Stand 1.1.2000 | AP85: Belegt Existenz und Zugänglichkeit der Quelle; inhaltliche Aussagen erst nach Auswertung. | AQ85: Keine Einstufung: Kennzahlen/Befunde noch nicht ausgewertet; Schwellen der Bewertungslogik noch nicht validiert. | AR85: Ja | AS85: Gemeindeverwaltung Münchenstein | AT85: In Prüfung | AW85: 2026-10-14: neu aufgenommen
A86: MUE-C5-01 | B86: Gemeinde | C86: Schweiz | D86: Basel-Landschaft | E86: Münchenstein | F86: C5 | G86: Politik / Mitwirkung | H86: Legislaturziele 2024–2028 des Gemeinderats Münchenstein | I86: Legislaturprogramm | J86: Webseite | K86: Politische Zielsetzung (behördenverbindlich, nicht rechtsverbindlich) | L86: Gemeinde Münchenstein | M86: https://www.muenchenstein.ch/legislaturziele | N86: 2024–2028 | O86: 2026-10-14 | P86: Gemeindeversammlung und kommunale Beschlüsse | Q86: Beschlüsse, Mitwirkung, Interessen | R86: Protokolle und politische Geschäfte identifizieren | S86: Qualitativ | T86: Noch nicht bewertet | U86: Mittel | V86: Konkrete kommunale Unterlagen / Datensatz nachfordern | W86: C3 | X86: Legitimation | Y86: Dokument auswerten; Aktualität und Geltung prüfen | Z86: Webrecherche 14.10.2026 | AD86: Verifiziert | AE86: 200 | AG86: HTML | AH86: Bestätigt | AI86: Schlüsselwörter 1/1 gefunden (Legislatur); Ort/Zuständigkeit: Münchenstein | AJ86: Münchenstein - Legislaturziele 2024 bis 2028 | Kopfzeile | AK86: 2024, 2028, 2025, 2029, 2004, 2011 | AL86: Mittel (Webseite) | AM86: 2026-10-14 13:53 | AN86: Öffentlich verfügbar und verifiziert | AO86: 2024–2028 | AP86: Belegt Existenz und Zugänglichkeit der Quelle; inhaltliche Aussagen erst nach Auswertung. | AQ86: Keine Einstufung: Kennzahlen/Befunde noch nicht ausgewertet; Schwellen der Bewertungslogik noch nicht validiert. | AR86: Nein | AS86: Gemeindeverwaltung Münchenstein | AT86: In Prüfung | AW86: 2026-10-14: Link ersetzt (vorher https://www.muenchenstein.ch/). Grund: Startseite durch Legislaturziele ersetzt.
A87: MUE-C5-02 | B87: Gemeinde | C87: Schweiz | D87: Basel-Landschaft | E87: Münchenstein | F87: C5 | G87: Protokoll | H87: Protokoll Gemeindeversammlung Münchenstein 13.6.2024 | I87: Protokoll | J87: Direktes Dokument | K87: Beschluss (verbindlich) | L87: Gemeinde Münchenstein | M87: https://www.muenchenstein.ch/_docn/5478214/Protokoll_Gemeindeversammlung_13._Juni_2024_definitiv.pdf | N87: 2024 | O87: 2026-10-14 | P87: Beschlüsse, Stimmverhalten, Bericht Legislaturziele 2020–2024 | S87: Kein Peer-Vergleich | T87: Noch nicht bewertet | U87: Hoch | Y87: Dokument auswerten; Aktualität und Geltung prüfen | Z87: Websuche 14.10.2026 (URL im Suchergebnis gefunden) | AD87: Verifiziert | AE87: 200 | AG87: PDF | AH87: Bestätigt | AI87: Schlüsselwörter 2/2 gefunden (Protokoll, Gemeindeversammlung); Ort/Zuständigkeit: Münchenstein | AJ87: Protokoll Gemeindeversammlung 13. Juni 2024 | AK87: 2023, 2024, 2020, 2028, 2021, 2019 | AL87: Mittel (CMS-Dokumentlink) | AM87: 2026-10-14 13:55 | AN87: Öffentlich verfügbar und verifiziert | AO87: 2024 | AP87: Belegt Existenz und Zugänglichkeit der Quelle; inhaltliche Aussagen erst nach Auswertung. | AQ87: Keine Einstufung: Kennzahlen/Befunde noch nicht ausgewertet; Schwellen der Bewertungslogik noch nicht validiert. | AR87: Nein | AS87: Gemeindeverwaltung Münchenstein | AT87: In Prüfung | AW87: 2026-10-14: neu aufgenommen
A88: MUE-C5-03 | B88: Gemeinde | C88: Schweiz | D88: Basel-Landschaft | E88: Münchenstein | F88: C5 | G88: Beschlüsse | H88: Beschlüsse der Gemeindeversammlung vom 8.12.2025 (Budget 2026, AFP 2026–2030) | I88: Beschlussmitteilung | J88: Webseite | K88: Beschluss (verbindlich) | L88: Gemeinde Münchenstein | M88: https://www.muenchenstein.ch/politikinformationen/2666993 | N88: 2025 | O88: 2026-10-14 | P88: Beschlussstand, Teilnehmerzahl (Legitimationsindikator) | S88: Kein Peer-Vergleich | T88: Noch nicht bewertet | U88: Mittel | Y88: Dokument auswerten; Aktualität und Geltung prüfen | Z88: Websuche 14.10.2026 (URL im Suchergebnis gefunden) | AA88: C1 | AD88: Verifiziert | AE88: 200 | AG88: HTML | AH88: Bestätigt | AI88: Schlüsselwörter 2/2 gefunden (Gemeindeversammlung, Budget); Ort/Zuständigkeit: Münchenstein | AJ88: Münchenstein - Beschlüsse der Gemeindeversammlung vom 8. Dezember 2025 | Kopfzeile | AK88: 2025, 2026, 2030 | AL88: Mittel (Webseite) | AM88: 2026-10-14 13:55 | AN88: Öffentlich verfügbar und verifiziert | AO88: 2025 | AP88: Belegt Existenz und Zugänglichkeit der Quelle; inhaltliche Aussagen erst nach Auswertung. | AQ88: Keine Einstufung: Kennzahlen/Befunde noch nicht ausgewertet; Schwellen der Bewertungslogik noch nicht validiert. | AR88: Nein | AS88: Gemeindeverwaltung Münchenstein | AT88: In Prüfung | AW88: 2026-10-14: neu aufgenommen
A89: MUE-C5-04 | B89: Gemeinde | C89: Schweiz | D89: Basel-Landschaft | E89: Münchenstein | F89: C5 | G89: Mitwirkung | H89: Quartierplanung Spenglerpark – Mitwirkungsbericht (2019) | I89: Mitwirkungsbericht | J89: Direktes Dokument | K89: Bericht | L89: Gemeinde Münchenstein | M89: https://www.muenchenstein.ch/_docn/2359339/43037_Ber05_Mitwirkungsbericht_VerabschiedungGR_Unterschrieben_20190924_korr.pdf | N89: 2019 | O89: 2026-10-14 | P89: Mitwirkungspraxis und Einwendungen bei Arealentwicklung | S89: Kein Peer-Vergleich | T89: Noch nicht bewertet | U89: Hoch | Y89: Dokument auswerten; Aktualität und Geltung prüfen | Z89: Websuche 14.10.2026 (URL im Suchergebnis gefunden) | AA89: C2 | AD89: Verifiziert | AE89: 200 | AG89: PDF | AH89: Bestätigt | AI89: Schlüsselwörter 2/2 gefunden (Mitwirkung, Spenglerpark); Ort/Zuständigkeit: Münchenstein | AJ89: Quartierplanung "Bruggstrasse" | AK89: 2019, 2017 | AL89: Mittel (CMS-Dokumentlink) | AM89: 2026-10-14 13:55 | AN89: Öffentlich verfügbar und verifiziert | AO89: 2019 | AP89: Belegt Existenz und Zugänglichkeit der Quelle; inhaltliche Aussagen erst nach Auswertung. | AQ89: Keine Einstufung: Kennzahlen/Befunde noch nicht ausgewertet; Schwellen der Bewertungslogik noch nicht validiert. | AR89: Nein | AS89: Gemeindeverwaltung Münchenstein | AT89: In Prüfung | AW89: 2026-10-14: neu aufgenommen
A90: MUE-C5-05 | B90: Gemeinde | C90: Schweiz | D90: Basel-Landschaft | E90: Münchenstein | F90: C5 | G90: Politische Gremien | H90: Gemeindekommission Münchenstein (§ 88 GemG) | I90: Behördenseite | J90: Webseite | K90: Information | L90: Gemeinde Münchenstein | M90: https://www.muenchenstein.ch/behoerden/2838 | O90: 2026-10-14 | S90: Kein Peer-Vergleich | T90: Noch nicht bewertet | U90: Mittel | Y90: Dokument auswerten; Aktualität und Geltung prüfen | Z90: Websuche 14.10.2026 (URL im Suchergebnis gefunden) | AA90: C3 | AD90: Verifiziert | AE90: 200 | AG90: HTML | AH90: Bestätigt | AI90: Schlüsselwörter 1/1 gefunden (Gemeindekommission); Ort/Zuständigkeit: Münchenstein | AJ90: Münchenstein - Gemeindekommission | Kopfzeile | AK90: 2026 | AL90: Mittel (Webseite) | AM90: 2026-10-14 13:55 | AN90: Öffentlich verfügbar und verifiziert | AP90: Belegt Existenz und Zugänglichkeit der Quelle; inhaltliche Aussagen erst nach Auswertung. | AQ90: Keine Einstufung: Kennzahlen/Befunde noch nicht ausgewertet; Schwellen der Bewertungslogik noch nicht validiert. | AR90: Nein | AS90: Gemeindeverwaltung Münchenstein | AT90: In Prüfung | AW90: 2026-10-14: neu aufgenommen
A91: WIL-C1-01 | B91: Gemeinde | C91: Schweiz | D91: St. Gallen | E91: Wil | F91: C1 | G91: Finanzdaten | H91: Stadt Wil: Finanzen, Budgets, Jahresrechnungen und Finanzpläne | I91: Dokumentsammlung | J91: Offizielle Quelle recherchiert | K91: Orientierung / Datengrundlage | L91: Gemeinde Wil | M91: https://www.stadtwil.ch/topics/stadt-politik-und-recht/finanzen | N91: Zu prüfen | O91: 2026-10-14 | P91: Jahresrechnung 2025, Budget 2026, Finanz- und Investitionsplan 2026–2030 | Q91: Verschuldung, Selbstfinanzierung, Investitionsbedarf | R91: Zeitreihe und Planjahre auswerten | S91: Kanton × Grössenklasse | T91: Noch nicht bewertet | U91: Mittel | V91: Kennzahlen und Befunde noch extrahieren | W91: A1; C1 | X91: Finanztragfähigkeit | Y91: Dokument auswerten; Aktualität und Geltung prüfen | Z91: Webrecherche 14.10.2026 | AD91: Verifiziert | AE91: 200 (HEAD 405) | AG91: HTML | AH91: Bestätigt | AI91: Schlüsselwörter 1/1 gefunden (Finanzen); Ort/Zuständigkeit: Wil | AJ91: Finanzen | Finanzen | AK91: 2024, 2025, 2023, 2026, 2028, 2027 | AL91: Mittel (Webseite) | AM91: 2026-10-14 13:53 | AN91: Öffentlich verfügbar und verifiziert | AO91: Zu prüfen | AP91: Belegt Existenz und Zugänglichkeit der Quelle; inhaltliche Aussagen erst nach Auswertung. | AQ91: Keine Einstufung: Kennzahlen/Befunde noch nicht ausgewertet; Schwellen der Bewertungslogik noch nicht validiert. | AR91: Nein | AS91: Gemeindeverwaltung Wil | AT91: In Prüfung
A92: WIL-C1-02 | B92: Gemeinde | C92: Schweiz | D92: St. Gallen | E92: Wil | F92: C1 | G92: Jahresrechnung | H92: Jahresrechnung 2025 Stadt Wil: politisches Geschäft | I92: Geschäft mit Anlagen | J92: Offizielle Quelle recherchiert | K92: Orientierung / Datengrundlage | L92: Gemeinde Wil | M92: https://www.stadtwil.ch/political-business/28da2d58a16b4b85b0504eeaa7e396dc | N92: Zu prüfen | O92: 2026-10-14 | P92: Beschluss und Anlagen zur Jahresrechnung 2025 | Q92: Bilanz, Investitionsrechnung | R92: Anlagen herunterladen und Kennzahlen prüfen | S92: Kanton × Grössenklasse | T92: Noch nicht bewertet | U92: Mittel | V92: Kennzahlen und Befunde noch extrahieren | W92: C1 | X92: Finanzbasis | Y92: Dokument auswerten; Aktualität und Geltung prüfen | Z92: Webrecherche 14.10.2026 | AD92: Verifiziert | AE92: 200 (HEAD 405) | AG92: HTML | AH92: Bestätigt | AI92: Schlüsselwörter 1/1 gefunden (Jahresrechnung); Ort/Zuständigkeit: Wil | AJ92: Jahresrechnung 2025 Stadt Wil | Jahresrechnung 2025 Stadt Wil | AK92: 2024, 2025, 2026, 2023, 2028, 2027 | AL92: Mittel (Webseite) | AM92: 2026-10-14 13:53 | AN92: Öffentlich verfügbar und verifiziert | AO92: Zu prüfen | AP92: Belegt Existenz und Zugänglichkeit der Quelle; inhaltliche Aussagen erst nach Auswertung. | AQ92: Keine Einstufung: Kennzahlen/Befunde noch nicht ausgewertet; Schwellen der Bewertungslogik noch nicht validiert. | AR92: Nein | AS92: Gemeindeverwaltung Wil | AT92: In Prüfung
A93: WIL-C1-03 | B93: Gemeinde | C93: Schweiz | D93: St. Gallen | E93: Wil | F93: C1 | G93: Jahresrechnung | H93: Jahresrechnung 2023 der Stadt Wil | I93: Jahresrechnung | J93: Direktes Dokument | K93: Beschlossene Jahresrechnung | L93: Stadt Wil | M93: https://www.stadtwil.ch/storage/46c11db85e782dc122cd9a61cc291529509f659681277125f8b019bce5a31b9c | N93: 2023 | O93: 2026-10-14 | S93: Kanton × Grössenklasse | T93: Noch nicht bewertet | U93: Hoch | Y93: Dokument auswerten; Aktualität und Geltung prüfen | Z93: Automatische Recherche GitHub Actions (Discovery), Fundstelle siehe Spalte Offizielle Fundstelle | AC93: https://www.stadtwil.ch/topics/stadt-politik-und-recht/finanzen | AD93: Verifiziert | AE93: 200 | AG93: PDF | AH93: Bestätigt | AI93: Schlüsselwörter 2/2 gefunden (Rechnung, 2023); Ort/Zuständigkeit: Wil | AJ93: Rechnung 2023 - Kurzfassung | AK93: 2023, 2021, 2022, 2019, 2020, 2017 | AL93: Mittel (Webseite) | AM93: 2026-10-14 13:55 | AN93: Öffentlich verfügbar und verifiziert | AO93: 2023 | AP93: Belegt Existenz und Zugänglichkeit der Quelle; inhaltliche Aussagen erst nach Auswertung. | AQ93: Keine Einstufung: Kennzahlen/Befunde noch nicht ausgewertet; Schwellen der Bewertungslogik noch nicht validiert. | AR93: Nein | AS93: Gemeindeverwaltung Wil | AT93: In Prüfung | AU93: Frühere Adresse /_docn/5050942/… liefert HTTP 404 (CMS-Umstellung); Link über Finanzseite der Stadt ermittelt. | AW93: 2026-10-14: neu aufgenommen
A94: WIL-C1-04 | B94: Gemeinde | C94: Schweiz | D94: St. Gallen | E94: Wil | F94: C1 | G94: Jahresrechnung | H94: Jahresrechnung 2024 der Stadt Wil | I94: Jahresrechnung | J94: Direktes Dokument | K94: Beschlussvorlage | L94: Stadt Wil | M94: https://www.stadtwil.ch/storage/0f0d7ad95464bf91a72506e63d2aae1d5c18327f9bff4bf34b8400c36999b277 | N94: 2024 | O94: 2026-10-14 | S94: Kanton × Grössenklasse | T94: Noch nicht bewertet | U94: Hoch | Y94: Dokument auswerten; Aktualität und Geltung prüfen | Z94: Automatische Recherche GitHub Actions (Discovery), Fundstelle siehe Spalte Offizielle Fundstelle | AC94: https://www.stadtwil.ch/topics/stadt-politik-und-recht/finanzen | AD94: Verifiziert | AE94: 200 | AG94: PDF | AH94: Bestätigt | AI94: Schlüsselwörter 2/2 gefunden (Rechnung, 2024); Ort/Zuständigkeit: Wil | AJ94: Rechnung 2024 - Kurzfassung | AK94: 2024, 2021, 2023, 2018, 2019, 2022 | AL94: Mittel (Webseite) | AM94: 2026-10-14 13:55 | AN94: Öffentlich verfügbar und verifiziert | AO94: 2024 | AP94: Belegt Existenz und Zugänglichkeit der Quelle; inhaltliche Aussagen erst nach Auswertung. | AQ94: Keine Einstufung: Kennzahlen/Befunde noch nicht ausgewertet; Schwellen der Bewertungslogik noch nicht validiert. | AR94: Nein | AS94: Gemeindeverwaltung Wil | AT94: In Prüfung | AU94: Frühere Adresse /_doc/5592973 liefert HTTP 404 (CMS-Umstellung); Link über Finanzseite der Stadt ermittelt. | AW94: 2026-10-14: neu aufgenommen
A95: WIL-C1-05 | B95: Gemeinde | C95: Schweiz | D95: St. Gallen | E95: Wil | F95: C1 | G95: Jahresrechnung | H95: Rechnung 2025 Stadt Wil – Finanzbericht, Erfolgsrechnung, Bilanz, Anhang | I95: Jahresrechnung | J95: Direktes Dokument | K95: Beschlussvorlage | L95: Stadt Wil | M95: https://www.stadtwil.ch/storage/08902ff399818ccc0d53949607b2d0f6f8bf702c334e295d493c2fd842ba4079 | N95: 2025 | O95: 2026-10-14 | S95: Kanton × Grössenklasse | T95: Noch nicht bewertet | U95: Mittel | Y95: Dokument auswerten; Aktualität und Geltung prüfen | Z95: Websuche 14.10.2026 (URL im Suchergebnis gefunden) | AD95: Verifiziert | AE95: 200 | AG95: PDF | AH95: Bestätigt | AI95: Schlüsselwörter 2/2 gefunden (2025, Bilanz); Ort/Zuständigkeit: Wil | AJ95: Rechnung 2025 | AK95: 2025, 2024, 2022, 2023, 2026, 2019 | AL95: Mittel (Webseite) | AM95: 2026-10-14 13:55 | AN95: Öffentlich verfügbar und verifiziert | AO95: 2025 | AP95: Belegt Existenz und Zugänglichkeit der Quelle; inhaltliche Aussagen erst nach Auswertung. | AQ95: Keine Einstufung: Kennzahlen/Befunde noch nicht ausgewertet; Schwellen der Bewertungslogik noch nicht validiert. | AR95: Nein | AS95: Gemeindeverwaltung Wil | AT95: In Prüfung | AU95: Zuordnung der Hash-URL stammt aus Suchzusammenfassung; nur Inhaltsprüfung belegt Identität. | AW95: 2026-10-14: neu aufgenommen
A96: WIL-C1-06 | B96: Gemeinde | C96: Schweiz | D96: St. Gallen | E96: Wil | F96: C1 | G96: Finanzplanung | H96: Finanzplan 2026–2030 der Stadt Wil (Stadtrat 23.9.2025) | I96: Finanzplan | J96: Direktes Dokument | K96: Planungsinstrument | L96: Stadt Wil | M96: https://www.stadtwil.ch/storage/875d422378d72386aae96efa76356fbfa05e9a0e1e03f208fbbe599dea21021c | N96: 2026–2030 | O96: 2026-10-14 | S96: Kanton × Grössenklasse | T96: Noch nicht bewertet | U96: Hoch | Y96: Dokument auswerten; Aktualität und Geltung prüfen | Z96: Websuche 14.10.2026 (URL im Suchergebnis gefunden) | AC96: https://www.stadtwil.ch/topics/stadt-politik-und-recht/finanzen | AD96: Verifiziert | AE96: 200 | AG96: PDF | AH96: Bestätigt | AI96: Schlüsselwörter 2/2 gefunden (Finanzplan, 2030); Ort/Zuständigkeit: Wil | AJ96: Finanzplan 2026-2030 | AK96: 2026, 2030, 2025, 2027, 2028, 2029 | AL96: Mittel (Webseite) | AM96: 2026-10-14 13:55 | AN96: Öffentlich verfügbar und verifiziert | AO96: 2026–2030 | AP96: Belegt Existenz und Zugänglichkeit der Quelle; inhaltliche Aussagen erst nach Auswertung. | AQ96: Keine Einstufung: Kennzahlen/Befunde noch nicht ausgewertet; Schwellen der Bewertungslogik noch nicht validiert. | AR96: Nein | AS96: Gemeindeverwaltung Wil | AT96: In Prüfung | AW96: 2026-10-14: neu aufgenommen
A97: WIL-C1-07 | B97: Gemeinde | C97: Schweiz | D97: St. Gallen | E97: Wil | F97: C1 | G97: Investitionen | H97: Investitionsplan 2026–2030 der Stadt Wil | I97: Investitionsplan | J97: Direktes Dokument | K97: Planungsinstrument | L97: Stadt Wil | M97: https://www.stadtwil.ch/storage/c6097b5ae815fb81f14b4db7630b14d9452e3be1ae3cbddd9f8e28d9d0777c7f | N97: 2026–2030 | O97: 2026-10-14 | S97: Kanton × Grössenklasse | T97: Noch nicht bewertet | U97: Hoch | Y97: Dokument auswerten; Aktualität und Geltung prüfen | Z97: Automatische Recherche GitHub Actions (Discovery), Fundstelle siehe Spalte Offizielle Fundstelle | AC97: https://www.stadtwil.ch/topics/stadt-politik-und-recht/finanzen | AD97: Verifiziert | AE97: 200 | AG97: PDF | AH97: Bestätigt | AI97: Schlüsselwörter 2/2 gefunden (Investitionsplan, 2030); Ort/Zuständigkeit: Wil | AJ97: Investitionsplan 2026-2030 | AK97: 2024, 2026, 2030, 2025, 2023, 2027 | AL97: Mittel (Webseite) | AM97: 2026-10-14 13:55 | AN97: Öffentlich verfügbar und verifiziert | AO97: 2026–2030 | AP97: Belegt Existenz und Zugänglichkeit der Quelle; inhaltliche Aussagen erst nach Auswertung. | AQ97: Keine Einstufung: Kennzahlen/Befunde noch nicht ausgewertet; Schwellen der Bewertungslogik noch nicht validiert. | AR97: Nein | AS97: Gemeindeverwaltung Wil | AT97: In Prüfung | AW97: 2026-10-14: neu aufgenommen
A98: WIL-C1-08 | B98: Gemeinde | C98: Schweiz | D98: St. Gallen | E98: Wil | F98: C1 | G98: Budget | H98: Budget 2026 der Stadt Wil | I98: Budget | J98: Direktes Dokument | K98: Beschlussvorlage | L98: Stadt Wil | M98: https://www.stadtwil.ch/storage/2ecd9e697734cc2262543c9da23828c2b6ad0129cf1654fcfa47f21ba113bf8a | N98: 2026 | O98: 2026-10-14 | S98: Kanton × Grössenklasse | T98: Noch nicht bewertet | U98: Hoch | Y98: Dokument auswerten; Aktualität und Geltung prüfen | Z98: Automatische Recherche GitHub Actions (Discovery), Fundstelle siehe Spalte Offizielle Fundstelle | AC98: https://www.stadtwil.ch/topics/stadt-politik-und-recht/finanzen | AD98: Verifiziert | AE98: 200 | AG98: PDF | AH98: Bestätigt | AI98: Schlüsselwörter 2/2 gefunden (Budget, 2026); Ort/Zuständigkeit: Wil | AJ98: Budget 2026 | AK98: 2026, 2025, 2023, 2024, 2027, 2005 | AL98: Mittel (Webseite) | AM98: 2026-10-14 13:55 | AN98: Öffentlich verfügbar und verifiziert | AO98: 2026 | AP98: Belegt Existenz und Zugänglichkeit der Quelle; inhaltliche Aussagen erst nach Auswertung. | AQ98: Keine Einstufung: Kennzahlen/Befunde noch nicht ausgewertet; Schwellen der Bewertungslogik noch nicht validiert. | AR98: Nein | AS98: Gemeindeverwaltung Wil | AT98: In Prüfung | AU98: Steuerfuss-Referendum 2026 – Beschlussstand prüfen. | AW98: 2026-10-14: neu aufgenommen
A99: WIL-C1-09 | B99: Gemeinde | C99: Schweiz | D99: St. Gallen | E99: Wil | F99: C1 | G99: Beteiligungen / Rechnung | H99: Jahresrechnung 2025 Technische Betriebe Wil (TBW) – Bericht und Antrag | I99: Jahresrechnung Unternehmen | J99: Direktes Dokument | K99: Beschlussvorlage | L99: Stadt Wil / Technische Betriebe Wil | M99: https://www.stadtwil.ch/storage/9bf65acd52bfa75c91cc42760759e0ffc3a76d501e7d174c010444c290801cc2 | N99: 2025 | O99: 2026-10-14 | P99: Gewinnablieferung und Abgaben der TBW an die Stadt | S99: Kanton × Grössenklasse | T99: Noch nicht bewertet | U99: Mittel | Y99: Dokument auswerten; Aktualität und Geltung prüfen | Z99: Websuche 14.10.2026 (URL im Suchergebnis gefunden) | AA99: C3 | AD99: Verifiziert | AE99: 200 | AG99: PDF | AH99: Bestätigt | AI99: Schlüsselwörter 2/2 gefunden (Technische Betriebe, 2025); Ort/Zuständigkeit: Wil | AJ99: Marktgasse 58 | AK99: 2025, 2026, 2024, 2019 | AL99: Mittel (Webseite) | AM99: 2026-10-14 13:55 | AN99: Öffentlich verfügbar und verifiziert | AO99: 2025 | AP99: Belegt Existenz und Zugänglichkeit der Quelle; inhaltliche Aussagen erst nach Auswertung. | AQ99: Keine Einstufung: Kennzahlen/Befunde noch nicht ausgewertet; Schwellen der Bewertungslogik noch nicht validiert. | AR99: Nein | AS99: Gemeindeverwaltung Wil | AT99: In Prüfung | AW99: 2026-10-14: neu aufgenommen
A100: WIL-C1-10 | B100: Gemeinde | C100: Schweiz | D100: St. Gallen | E100: Wil | F100: C1 | G100: Budget | H100: Budget 2027 der Stadt Wil | I100: Budget | J100: Direktes Dokument | K100: Vorlage (Beschluss Stadtparlament ausstehend/prüfen) | L100: Stadt Wil | M100: https://www.stadtwil.ch/storage/86c954451190b5683f4cea602b5746ce096ff6338c9f35fbea68172b58f684d1 | N100: 2027 | O100: 2026-10-14 | P100: Aktuellster Planungsstand Erfolgsrechnung/Investitionen | S100: Kanton × Grössenklasse | T100: Noch nicht bewertet | U100: Hoch | Y100: Dokument auswerten; Aktualität und Geltung prüfen | Z100: Automatische Recherche GitHub Actions (Discovery), Fundstelle siehe Spalte Offizielle Fundstelle | AC100: https://www.stadtwil.ch/topics/stadt-politik-und-recht/finanzen | AD100: Verifiziert | AE100: 200 | AG100: PDF | AH100: Bestätigt | AI100: Schlüsselwörter 2/2 gefunden (Budget, 2027); Ort/Zuständigkeit: Wil | AJ100: Budget 2027 | AK100: 2027, 2026, 2030, 2025, 2024, 2023 | AL100: Mittel (Webseite) | AM100: 2026-10-14 13:55 | AN100: Öffentlich verfügbar und verifiziert | AO100: 2027 | AP100: Belegt Existenz und Zugänglichkeit der Quelle; inhaltliche Aussagen erst nach Auswertung. | AQ100: Keine Einstufung: Kennzahlen/Befunde noch nicht ausgewertet; Schwellen der Bewertungslogik noch nicht validiert. | AR100: Nein | AS100: Gemeindeverwaltung Wil | AT100: In Prüfung | AU100: Beschlussstand prüfen. | AW100: 2026-10-14: neu aufgenommen
...

Sheet Seelisberg
A1: ID | B1: Ebene | C1: Schweiz | D1: Kanton | E1: Gemeinde | F1: C-Dimension | G1: Themenfeld | H1: Dokument / Datengrundlage | I1: Dokumenttyp | J1: Dokumentstatus | K1: Rechts- / Verbindlichkeitsstatus | L1: Herausgeber / Zuständigkeit | M1: Link / Quelle | N1: Bezugsjahr / Stand | O1: Aktualität geprüft am | P1: Konkrete Aussage / Relevanz | Q1: Kennzahl / Prüfkriterium | R1: Erhebungs- / Bewertungsmethode | S1: Vergleichsmassstab | T1: Reifegrad / Tragfähigkeit | U1: Confidence | V1: Datenlücke / Gemeindeanfrage | W1: Verbindung A / B / Q | X1: Sprint-2-Verwendung | Y1: Prüfstatus / nächste Aktion | Z1: Herkunft / Nachweis | AA1: Weitere C-Dimensionen | AB1: Veröffentlichungsdatum | AC1: Offizielle Fundstelle | AD1: Linkstatus | AE1: HTTP-Status | AF1: Finale URL (nach Weiterleitung) | AG1: Dateityp | AH1: Inhaltsprüfung | AI1: Inhaltsprüfung – Nachweis | AJ1: Erkannter Dokumenttitel | AK1: Erkannte Jahresangaben | AL1: Linkstabilität | AM1: Letzte Linkprüfung | AN1: Quellenverfügbarkeit | AO1: Einheit / Bezugsjahr | AP1: Prüfnachweis (belegbare Aussage) | AQ1: Bewertungsbegründung | AR1: Gemeindeanfrage erforderlich | AS1: Zuständige Stelle | AT1: Bearbeitungsstatus | AU1: Recherchehinweis | AV1: Gleiche Quelle wie (ID) | AW1: Änderungsprotokoll | AX1: Abgleich mit Gesamtübersicht
A2: CH-C1-01 | B2: Bund | C2: Schweiz | D2: Alle | E2: Alle | F2: C1 | G2: Öffentliche Finanzstatistik | H2: Finanzstatistik: Daten der Eidgenössischen Finanzverwaltung | I2: Datenportal | J2: Offizielle Quelle recherchiert | K2: Orientierung / Datengrundlage | L2: Bund | M2: https://www.efv.admin.ch/de/finanzstatistik-daten | N2: Zu prüfen | O2: 2026-10-14 | P2: Harmonisierte Finanzstatistik als Kontext und methodische Vergleichsbasis | Q2: Finanzkennzahlen, Ausgaben, Einnahmen | R2: Zeitreihen und Aufgabenabgrenzung prüfen | S2: Kanton × Grössenklasse; Richtwerte | T2: Noch nicht bewertet | U2: Hoch | W2: A1/A2; C1 | X2: Finanziellen Spielraum und DYN-Korridor plausibilisieren | Y2: Dokument auswerten; Aktualität und Geltung prüfen | Z2: Offizielles Bundesportal; methodische Auswahl | AC2: https://www.efv.admin.ch/ | AD2: Verifiziert | AE2: 200 | AG2: HTML | AH2: Bestätigt | AI2: Schlüsselwörter 1/1 gefunden (Finanzstatistik) | AJ2: Übersicht über die Daten der Finanzstatistik | Übersicht über die Daten der Finanzstatistik | AK2: 2008, 2026, 2025, 2014 | AL2: Mittel (Webseite) | AM2: 2026-10-14 13:53 | AN2: Öffentlich verfügbar und verifiziert | AO2: Zu prüfen | AP2: Belegt Existenz und Zugänglichkeit der Quelle; inhaltliche Aussagen erst nach Auswertung. | AQ2: Keine Einstufung: Kennzahlen/Befunde noch nicht ausgewertet; Schwellen der Bewertungslogik noch nicht validiert. | AR2: Nein | AS2: Bund | AT2: In Prüfung | AX2: =IF(ISNA(MATCH($A2,'Gesamtübersicht'!$A:$A,0)),"ID fehlt in Gesamtübersicht",IF(AND(INDEX('Gesamtübersicht'!$H:$H,MATCH($A2,'Gesamtübersicht'!$A:$A,0))&""=$H2&"",INDEX('Gesamtübersicht'!$M:$M,MATCH($A2,'Gesamtübersicht'!$A:$A,0))&""=$M2&"",INDEX('Gesamtübersicht'!$AD:$AD,MATCH($A2,'Gesamtübersicht'!$A:$A,0))&""=$AD2&"",INDEX('Gesamtübersicht'!$AH:$AH,MATCH($A2,'Gesamtübersicht'!$A:$A,0))&""=$AH2&"",INDEX('Gesamtübersicht'!$T:$T,MATCH($A2,'Gesamtübersicht'!$A:$A,0))&""=$T2&""),"OK","Abweichung – Ansicht neu erzeugen"))
A3: CH-C1-02 | B3: Bund | C3: Schweiz | D3: Alle | E3: Alle | F3: C1 | G3: Rechnungslegung | H3: EFV: Methodik und Vergleichbarkeit der Finanzstatistik | I3: Methodik | J3: Offizielle Quelle recherchiert | K3: Orientierung / Datengrundlage | L3: Bund | M3: https://www.efv.admin.ch/de/was-ist-die-finanzstatistik | N3: Zu prüfen | O3: 2026-10-14 | P3: Kantonale Aufgabenverteilung begrenzt Vergleichbarkeit | Q3: HRM / Aufgabenabgrenzung | R3: Vergleichbarkeit explizit dokumentieren | S3: Kanton × Grössenklasse | T3: Noch nicht bewertet | U3: Hoch | W3: A1; C1 | X3: Vergleichsregeln absichern | Y3: Dokument auswerten; Aktualität und Geltung prüfen | Z3: Offizielles Bundesportal; methodische Auswahl | AD3: Verifiziert | AE3: 200 | AG3: HTML | AH3: Bestätigt | AI3: Schlüsselwörter 1/1 gefunden (Finanzstatistik) | AJ3: Was ist die Finanzstatistik? | Was ist die Finanzstatistik? | AK3: 2014, 2010, 2026, 2024, 2023, 2025 | AL3: Mittel (Webseite) | AM3: 2026-10-14 13:53 | AN3: Öffentlich verfügbar und verifiziert | AO3: Zu prüfen | AP3: Belegt Existenz und Zugänglichkeit der Quelle; inhaltliche Aussagen erst nach Auswertung. | AQ3: Keine Einstufung: Kennzahlen/Befunde noch nicht ausgewertet; Schwellen der Bewertungslogik noch nicht validiert. | AR3: Nein | AS3: Bund | AT3: In Prüfung | AX3: =IF(ISNA(MATCH($A3,'Gesamtübersicht'!$A:$A,0)),"ID fehlt in Gesamtübersicht",IF(AND(INDEX('Gesamtübersicht'!$H:$H,MATCH($A3,'Gesamtübersicht'!$A:$A,0))&""=$H3&"",INDEX('Gesamtübersicht'!$M:$M,MATCH($A3,'Gesamtübersicht'!$A:$A,0))&""=$M3&"",INDEX('Gesamtübersicht'!$AD:$AD,MATCH($A3,'Gesamtübersicht'!$A:$A,0))&""=$AD3&"",INDEX('Gesamtübersicht'!$AH:$AH,MATCH($A3,'Gesamtübersicht'!$A:$A,0))&""=$AH3&"",INDEX('Gesamtübersicht'!$T:$T,MATCH($A3,'Gesamtübersicht'!$A:$A,0))&""=$T3&""),"OK","Abweichung – Ansicht neu erzeugen"))
A4: CH-C1-03 | B4: Bund | C4: Schweiz | D4: Alle | E4: Alle | F4: C1 | G4: Finanzstatistik Methode | H4: EFV: Methoden der Finanzstatistik (FS-Modell, HRM2-Zuordnung) | I4: Methodik | J4: Webseite | K4: Methodische Grundlage | L4: Eidgenössische Finanzverwaltung (EFV) | M4: https://www.efv.admin.ch/de/methoden-finanzstatistik | O4: 2026-10-14 | P4: Definitionen der Kennzahlen und HRM2-Abbildung für Vergleichbarkeit | Q4: Kennzahlendefinitionen | S4: Kanton × Grössenklasse | T4: Noch nicht bewertet | U4: Hoch | W4: C1 | X4: Vergleichsregeln C1 | Y4: Dokument auswerten; Aktualität und Geltung prüfen | Z4: Automatische Recherche GitHub Actions (Discovery), Fundstelle siehe Spalte Offizielle Fundstelle | AC4: https://www.efv.admin.ch/de/finanzstatistik-daten | AD4: Verifiziert | AE4: 200 | AG4: HTML | AH4: Bestätigt | AI4: Schlüsselwörter 2/2 gefunden (Methode, Finanzstatistik) | AJ4: Methoden der Finanzstatistik | Methoden der Finanzstatistik | AK4: 2016, 2026, 2015, 2020, 2014, 2025 | AL4: Mittel (Webseite) | AM4: 2026-10-14 13:54 | AN4: Öffentlich verfügbar und verifiziert | AP4: Belegt Existenz und Zugänglichkeit der Quelle; inhaltliche Aussagen erst nach Auswertung. | AQ4: Keine Einstufung: Kennzahlen/Befunde noch nicht ausgewertet; Schwellen der Bewertungslogik noch nicht validiert. | AR4: Nein | AS4: Eidgenössische Finanzverwaltung (EFV) | AT4: In Prüfung | AU4: Früherer PDF-Link zum FS-Methodenband (efv.admin.ch/dam/…) liefert HTTP 502 (Website-Umbau); Methodenseite über EFV-Finanzstatistik ermittelt. | AW4: 2026-10-14: neu aufgenommen | AX4: =IF(ISNA(MATCH($A4,'Gesamtübersicht'!$A:$A,0)),"ID fehlt in Gesamtübersicht",IF(AND(INDEX('Gesamtübersicht'!$H:$H,MATCH($A4,'Gesamtübersicht'!$A:$A,0))&""=$H4&"",INDEX('Gesamtübersicht'!$M:$M,MATCH($A4,'Gesamtübersicht'!$A:$A,0))&""=$M4&"",INDEX('Gesamtübersicht'!$AD:$AD,MATCH($A4,'Gesamtübersicht'!$A:$A,0))&""=$AD4&"",INDEX('Gesamtübersicht'!$AH:$AH,MATCH($A4,'Gesamtübersicht'!$A:$A,0))&""=$AH4&"",INDEX('Gesamtübersicht'!$T:$T,MATCH($A4,'Gesamtübersicht'!$A:$A,0))&""=$T4&""),"OK","Abweichung – Ansicht neu erzeugen"))
A5: CH-C1-04 | B5: Bund | C5: Schweiz | D5: Alle | E5: Alle | F5: C1 | G5: Finanzdaten Gemeinden | H5: EFV: Detaillierte Daten FS- und GFS-Modell (Open Government Data) | I5: Datensatz | J5: Direktes Dokument | K5: Datengrundlage | L5: EFV / opendata.swiss | M5: https://opendata.swiss/en/dataset/detaillierte-daten-fs-und-gfs-modell-standardauswertungen | O5: 2026-10-14 | P5: Maschinenlesbare Finanzdaten für Peer-Vergleich | Q5: Einnahmen, Ausgaben, Schulden | S5: Kanton × Grössenklasse | T5: Noch nicht bewertet | U5: Mittel | Y5: Dokument auswerten; Aktualität und Geltung prüfen | Z5: Websuche 14.10.2026 (URL im Suchergebnis gefunden) | AD5: Verifiziert | AE5: 200 | AG5: HTML | AH5: Bestätigt | AI5: Schlüsselwörter 2/2 gefunden (FS, GFS) | AJ5: Detailed data FS and GFS model: Regular tables | opendata.swiss | Detailed data FS and GFS model: Regular tables | AK5: 2008, 2025, 2014, 2023 | AL5: Mittel (Webseite) | AM5: 2026-10-14 13:54 | AN5: Öffentlich verfügbar und verifiziert | AP5: Belegt Existenz und Zugänglichkeit der Quelle; inhaltliche Aussagen erst nach Auswertung. | AQ5: Keine Einstufung: Kennzahlen/Befunde noch nicht ausgewertet; Schwellen der Bewertungslogik noch nicht validiert. | AR5: Nein | AS5: EFV / opendata.swiss | AT5: In Prüfung | AW5: 2026-10-14: neu aufgenommen | AX5: =IF(ISNA(MATCH($A5,'Gesamtübersicht'!$A:$A,0)),"ID fehlt in Gesamtübersicht",IF(AND(INDEX('Gesamtübersicht'!$H:$H,MATCH($A5,'Gesamtübersicht'!$A:$A,0))&""=$H5&"",INDEX('Gesamtübersicht'!$M:$M,MATCH($A5,'Gesamtübersicht'!$A:$A,0))&""=$M5&"",INDEX('Gesamtübersicht'!$AD:$AD,MATCH($A5,'Gesamtübersicht'!$A:$A,0))&""=$AD5&"",INDEX('Gesamtübersicht'!$AH:$AH,MATCH($A5,'Gesamtübersicht'!$A:$A,0))&""=$AH5&"",INDEX('Gesamtübersicht'!$T:$T,MATCH($A5,'Gesamtübersicht'!$A:$A,0))&""=$T5&""),"OK","Abweichung – Ansicht neu erzeugen"))
A6: CH-C2-01 | B6: Bund | C6: Schweiz | D6: Alle | E6: Alle | F6: C2 | G6: Eigentumsrechte | H6: Schweizerisches Zivilgesetzbuch (ZGB) | I6: Bundesgesetz | J6: Offizielle Quelle recherchiert | K6: Bundesgesetz (verbindlich) | L6: Bund | M6: https://www.fedlex.admin.ch/eli/cc/24/233_245_233/de | N6: SR 210, geltende Fassung | O6: 2026-10-14 | P6: Eigentum, Dienstbarkeiten und Baurechte als rechtlicher Rahmen | Q6: Baurecht, Dienstbarkeit, Eigentum | R6: Grundbuch und Verträge gemeindespezifisch prüfen | S6: Kein Peer-Vergleich | T6: Noch nicht bewertet | U6: Hoch | W6: B; Q1 | X6: Bodenmobilisierung / Verfügung prüfen | Y6: Dokument auswerten; Aktualität und Geltung prüfen | Z6: Offizielles Bundesportal; methodische Auswahl | AD6: Verifiziert | AE6: 200 | AG6: HTML | AH6: Bestätigt | AI6: Titel via Fedlex-SPARQL (https://fedlex.data.admin.ch/eli/cc/24/233_245_233); Schlüsselwörter 1/1 gefunden (Zivilgesetzbuch) | AJ6: Schweizerisches Zivilgesetzbuch vom 10. Dezember 1907 (ZGB) | AL6: Hoch (ELI-Permalink) | AM6: 2026-10-14 13:53 | AN6: Öffentlich verfügbar und verifiziert | AO6: SR 210, geltende Fassung | AP6: Belegt Existenz und Zugänglichkeit der Quelle; inhaltliche Aussagen erst nach Auswertung. | AQ6: Keine Einstufung: Kennzahlen/Befunde noch nicht ausgewertet; Schwellen der Bewertungslogik noch nicht validiert. | AR6: Nein | AS6: Bund | AT6: In Prüfung | AX6: =IF(ISNA(MATCH($A6,'Gesamtübersicht'!$A:$A,0)),"ID fehlt in Gesamtübersicht",IF(AND(INDEX('Gesamtübersicht'!$H:$H,MATCH($A6,'Gesamtübersicht'!$A:$A,0))&""=$H6&"",INDEX('Gesamtübersicht'!$M:$M,MATCH($A6,'Gesamtübersicht'!$A:$A,0))&""=$M6&"",INDEX('Gesamtübersicht'!$AD:$AD,MATCH($A6,'Gesamtübersicht'!$A:$A,0))&""=$AD6&"",INDEX('Gesamtübersicht'!$AH:$AH,MATCH($A6,'Gesamtübersicht'!$A:$A,0))&""=$AH6&"",INDEX('Gesamtübersicht'!$T:$T,MATCH($A6,'Gesamtübersicht'!$A:$A,0))&""=$T6&""),"OK","Abweichung – Ansicht neu erzeugen"))
A7: CH-C2-02 | B7: Bund | C7: Schweiz | D7: Alle | E7: Alle | F7: C2 | G7: Raumplanung / Baulandmobilisierung | H7: Bundesgesetz über die Raumplanung (RPG), SR 700 | I7: Bundesgesetz | J7: Direktes Dokument | K7: Bundesgesetz (verbindlich) | L7: Bund | M7: https://www.fedlex.admin.ch/eli/cc/1979/1573_1573_1573/de | N7: SR 700, geltende Fassung | O7: 2026-10-14 | P7: Art. 15a RPG: Förderung der Verfügbarkeit von Bauland; Mehrwertausgleich Art. 5 | Q7: Bauverpflichtung, Mehrwertabgabe | S7: Kein Peer-Vergleich | T7: Noch nicht bewertet | U7: Hoch | W7: B; Q1 | Y7: Dokument auswerten; Aktualität und Geltung prüfen | Z7: ELI-Permalink Fedlex; Identität per Fedlex-SPARQL geprüft | AD7: Verifiziert | AE7: 200 | AG7: HTML | AH7: Bestätigt | AI7: Titel via Fedlex-SPARQL (https://fedlex.data.admin.ch/eli/cc/1979/1573_1573_1573); Schlüsselwörter 1/1 gefunden (Raumplanung) | AJ7: Bundesgesetz vom 22. Juni 1979 über die Raumplanung (Raumplanungsgesetz, RPG) (RPG) | AL7: Hoch (ELI-Permalink) | AM7: 2026-10-14 13:54 | AN7: Öffentlich verfügbar und verifiziert | AO7: SR 700, geltende Fassung | AP7: Belegt Existenz und Zugänglichkeit der Quelle; inhaltliche Aussagen erst nach Auswertung. | AQ7: Keine Einstufung: Kennzahlen/Befunde noch nicht ausgewertet; Schwellen der Bewertungslogik noch nicht validiert. | AR7: Nein | AS7: Bund | AT7: In Prüfung | AW7: 2026-10-14: neu aufgenommen | AX7: =IF(ISNA(MATCH($A7,'Gesamtübersicht'!$A:$A,0)),"ID fehlt in Gesamtübersicht",IF(AND(INDEX('Gesamtübersicht'!$H:$H,MATCH($A7,'Gesamtübersicht'!$A:$A,0))&""=$H7&"",INDEX('Gesamtübersicht'!$M:$M,MATCH($A7,'Gesamtübersicht'!$A:$A,0))&""=$M7&"",INDEX('Gesamtübersicht'!$AD:$AD,MATCH($A7,'Gesamtübersicht'!$A:$A,0))&""=$AD7&"",INDEX('Gesamtübersicht'!$AH:$AH,MATCH($A7,'Gesamtübersicht'!$A:$A,0))&""=$AH7&"",INDEX('Gesamtübersicht'!$T:$T,MATCH($A7,'Gesamtübersicht'!$A:$A,0))&""=$T7&""),"OK","Abweichung – Ansicht neu erzeugen"))
A8: CH-C3-01 | B8: Bund | C8: Schweiz | D8: Alle | E8: Alle | F8: C3 | G8: Interkommunale Zusammenarbeit | H8: Bundesverfassung der Schweizerischen Eidgenossenschaft | I8: Bundesverfassung | J8: Offizielle Quelle recherchiert | K8: Bundesverfassung (verbindlich) | L8: Bund | M8: https://www.fedlex.admin.ch/eli/cc/1999/404/de | N8: SR 101, geltende Fassung | O8: 2026-10-14 | P8: Grundlagen von Föderalismus und Gemeindeautonomie; Details kantonal | Q8: Zuständigkeits- und Kooperationsregeln | R8: Kantonale Gemeindeerlasse ergänzen | S8: Qualitative Reifegradskala | T8: Noch nicht bewertet | U8: Hoch | W8: Q6; C4 | X8: Trägerschaft und Kooperation beurteilen | Y8: Dokument auswerten; Aktualität und Geltung prüfen | Z8: Offizielles Bundesportal; methodische Auswahl | AA8: C5 | AD8: Verifiziert | AE8: 200 | AG8: HTML | AH8: Bestätigt | AI8: Titel via Fedlex-SPARQL (https://fedlex.data.admin.ch/eli/cc/1999/404); Schlüsselwörter 1/1 gefunden (Bundesverfassung) | AJ8: Bundesverfassung der Schweizerischen Eidgenossenschaft vom 18. April 1999 (BV) | AL8: Hoch (ELI-Permalink) | AM8: 2026-10-14 13:53 | AN8: Öffentlich verfügbar und verifiziert | AO8: SR 101, geltende Fassung | AP8: Belegt Existenz und Zugänglichkeit der Quelle; inhaltliche Aussagen erst nach Auswertung. | AQ8: Keine Einstufung: Kennzahlen/Befunde noch nicht ausgewertet; Schwellen der Bewertungslogik noch nicht validiert. | AR8: Nein | AS8: Bund | AT8: In Prüfung | AV8: CH-C5-01 | AX8: =IF(ISNA(MATCH($A8,'Gesamtübersicht'!$A:$A,0)),"ID fehlt in Gesamtübersicht",IF(AND(INDEX('Gesamtübersicht'!$H:$H,MATCH($A8,'Gesamtübersicht'!$A:$A,0))&""=$H8&"",INDEX('Gesamtübersicht'!$M:$M,MATCH($A8,'Gesamtübersicht'!$A:$A,0))&""=$M8&"",INDEX('Gesamtübersicht'!$AD:$AD,MATCH($A8,'Gesamtübersicht'!$A:$A,0))&""=$AD8&"",INDEX('Gesamtübersicht'!$AH:$AH,MATCH($A8,'Gesamtübersicht'!$A:$A,0))&""=$AH8&"",INDEX('Gesamtübersicht'!$T:$T,MATCH($A8,'Gesamtübersicht'!$A:$A,0))&""=$T8&""),"OK","Abweichung – Ansicht neu erzeugen"))
A9: CH-C4-01 | B9: Bund | C9: Schweiz | D9: Alle | E9: Alle | F9: C4 | G9: Öffentliche Beschaffung | H9: Bundesgesetz über das öffentliche Beschaffungswesen (BöB) | I9: Bundesgesetz | J9: Offizielle Quelle recherchiert | K9: Bundesgesetz (verbindlich für Bundesbeschaffungen; Gemeinden: IVöB/kantonales Recht) | L9: Bund | M9: https://www.fedlex.admin.ch/eli/cc/2020/126/de | N9: SR 172.056.1, geltende Fassung | O9: 2026-10-14 | P9: Beschaffungsrechtlicher Orientierungsrahmen; kommunale Geltung kantonal prüfen | Q9: Beschaffungsprozess, Zuständigkeit | R9: Kantonales Beschaffungsrecht vorrangig auf Geltung prüfen | S9: Qualitative Reifegradskala | T9: Noch nicht bewertet | U9: Hoch | W9: Q6; C3 | X9: Bestellerkompetenz / Umsetzungsorganisation | Y9: Dokument auswerten; Aktualität und Geltung prüfen | Z9: Offizielles Bundesportal; methodische Auswahl | AD9: Verifiziert | AE9: 200 | AG9: HTML | AH9: Bestätigt | AI9: Titel via Fedlex-SPARQL (https://fedlex.data.admin.ch/eli/cc/2020/126); Schlüsselwörter 1/1 gefunden (öffentliche Beschaffungswesen) | AJ9: Bundesgesetz vom 21. Juni 2019 über das öffentliche Beschaffungswesen (BöB) (BöB) | AK9: 2019 | AL9: Hoch (ELI-Permalink) | AM9: 2026-10-14 13:53 | AN9: Öffentlich verfügbar und verifiziert | AO9: SR 172.056.1, geltende Fassung | AP9: Belegt Existenz und Zugänglichkeit der Quelle; inhaltliche Aussagen erst nach Auswertung. | AQ9: Keine Einstufung: Kennzahlen/Befunde noch nicht ausgewertet; Schwellen der Bewertungslogik noch nicht validiert. | AR9: Nein | AS9: Bund | AT9: In Prüfung | AX9: =IF(ISNA(MATCH($A9,'Gesamtübersicht'!$A:$A,0)),"ID fehlt in Gesamtübersicht",IF(AND(INDEX('Gesamtübersicht'!$H:$H,MATCH($A9,'Gesamtübersicht'!$A:$A,0))&""=$H9&"",INDEX('Gesamtübersicht'!$M:$M,MATCH($A9,'Gesamtübersicht'!$A:$A,0))&""=$M9&"",INDEX('Gesamtübersicht'!$AD:$AD,MATCH($A9,'Gesamtübersicht'!$A:$A,0))&""=$AD9&"",INDEX('Gesamtübersicht'!$AH:$AH,MATCH($A9,'Gesamtübersicht'!$A:$A,0))&""=$AH9&"",INDEX('Gesamtübersicht'!$T:$T,MATCH($A9,'Gesamtübersicht'!$A:$A,0))&""=$T9&""),"OK","Abweichung – Ansicht neu erzeugen"))
A10: CH-C4-02 | B10: Bund | C10: Schweiz | D10: Alle | E10: Alle | F10: C4 | G10: Gemeindekennzahlen | H10: BFS: Regionalporträts – Kennzahlen aller Gemeinden (Datensatz) | I10: Datensatz | J10: Direktes Dokument | K10: Datengrundlage | L10: Bundesamt für Statistik (BFS) | M10: https://ckan.opendata.swiss/dataset/regionalportrats-2021-kennzahlen-aller-gemeinden | N10: 2021 (neuere Ausgabe prüfen) | O10: 2026-10-14 | P10: Strukturdaten (Einwohner, Fläche) zur Bildung der Grössenklassen | S10: Grössenklasse | T10: Noch nicht bewertet | U10: Mittel | Y10: Dokument auswerten; Aktualität und Geltung prüfen | Z10: Websuche 14.10.2026 (URL im Suchergebnis gefunden) | AA10: C1 | AD10: Verifiziert | AE10: 200 | AG10: HTML | AH10: Bestätigt | AI10: Schlüsselwörter 1/1 gefunden (Regionalporträts) | AJ10: Regional portraits 2021: key data of all communes - Dataset - opendata.swiss | Regional portraits 2021: key data of all communes | AK10: 2021, 2019, 2004 | AL10: Mittel (Webseite) | AM10: 2026-10-14 13:54 | AN10: Öffentlich verfügbar und verifiziert | AO10: 2021 (neuere Ausgabe prüfen) | AP10: Belegt Existenz und Zugänglichkeit der Quelle; inhaltliche Aussagen erst nach Auswertung. | AQ10: Keine Einstufung: Kennzahlen/Befunde noch nicht ausgewertet; Schwellen der Bewertungslogik noch nicht validiert. | AR10: Nein | AS10: Bundesamt für Statistik (BFS) | AT10: In Prüfung | AU10: Ausgabe 2021; aktuelle Ausgabe beim BFS prüfen. | AW10: 2026-10-14: neu aufgenommen | AX10: =IF(ISNA(MATCH($A10,'Gesamtübersicht'!$A:$A,0)),"ID fehlt in Gesamtübersicht",IF(AND(INDEX('Gesamtübersicht'!$H:$H,MATCH($A10,'Gesamtübersicht'!$A:$A,0))&""=$H10&"",INDEX('Gesamtübersicht'!$M:$M,MATCH($A10,'Gesamtübersicht'!$A:$A,0))&""=$M10&"",INDEX('Gesamtübersicht'!$AD:$AD,MATCH($A10,'Gesamtübersicht'!$A:$A,0))&""=$AD10&"",INDEX('Gesamtübersicht'!$AH:$AH,MATCH($A10,'Gesamtübersicht'!$A:$A,0))&""=$AH10&"",INDEX('Gesamtübersicht'!$T:$T,MATCH($A10,'Gesamtübersicht'!$A:$A,0))&""=$T10&""),"OK","Abweichung – Ansicht neu erzeugen"))
A11: CH-C5-01 | B11: Bund | C11: Schweiz | D11: Alle | E11: Alle | F11: C5 | G11: Politische Rechte | H11: Bundesverfassung der Schweizerischen Eidgenossenschaft | I11: Bundesverfassung | J11: Offizielle Quelle recherchiert | K11: Bundesverfassung (verbindlich) | L11: Bund | M11: https://www.fedlex.admin.ch/eli/cc/1999/404/de | N11: SR 101, geltende Fassung | O11: 2026-10-14 | P11: Demokratische Grundrechte und Beteiligung; konkrete kommunale Verfahren kantonal | Q11: Mitwirkung / Legitimation | R11: Kommunale und kantonale Bestimmungen ergänzen | S11: Qualitative Reifegradskala | T11: Noch nicht bewertet | U11: Hoch | W11: Q1; C3 | X11: Politische Machbarkeit | Y11: Dokument auswerten; Aktualität und Geltung prüfen | Z11: Offizielles Bundesportal; methodische Auswahl | AA11: C3 | AD11: Verifiziert | AE11: 200 | AG11: HTML | AH11: Bestätigt | AI11: Titel via Fedlex-SPARQL (https://fedlex.data.admin.ch/eli/cc/1999/404); Schlüsselwörter 1/1 gefunden (Bundesverfassung) | AJ11: Bundesverfassung der Schweizerischen Eidgenossenschaft vom 18. April 1999 (BV) | AL11: Hoch (ELI-Permalink) | AM11: 2026-10-14 13:53 | AN11: Öffentlich verfügbar und verifiziert | AO11: SR 101, geltende Fassung | AP11: Belegt Existenz und Zugänglichkeit der Quelle; inhaltliche Aussagen erst nach Auswertung. | AQ11: Keine Einstufung: Kennzahlen/Befunde noch nicht ausgewertet; Schwellen der Bewertungslogik noch nicht validiert. | AR11: Nein | AS11: Bund | AT11: In Prüfung | AU11: Gleiche Quelle wie CH-C3-01; bewusst doppelt geführt (Zuordnung C5 politische Rechte). | AV11: CH-C3-01 | AX11: =IF(ISNA(MATCH($A11,'Gesamtübersicht'!$A:$A,0)),"ID fehlt in Gesamtübersicht",IF(AND(INDEX('Gesamtübersicht'!$H:$H,MATCH($A11,'Gesamtübersicht'!$A:$A,0))&""=$H11&"",INDEX('Gesamtübersicht'!$M:$M,MATCH($A11,'Gesamtübersicht'!$A:$A,0))&""=$M11&"",INDEX('Gesamtübersicht'!$AD:$AD,MATCH($A11,'Gesamtübersicht'!$A:$A,0))&""=$AD11&"",INDEX('Gesamtübersicht'!$AH:$AH,MATCH($A11,'Gesamtübersicht'!$A:$A,0))&""=$AH11&"",INDEX('Gesamtübersicht'!$T:$T,MATCH($A11,'Gesamtübersicht'!$A:$A,0))&""=$T11&""),"OK","Abweichung – Ansicht neu erzeugen"))
A12: UR-C1-01 | B12: Kanton | C12: Schweiz | D12: Uri | E12: Alle | F12: C1 | G12: Finanzstatistik | H12: Gemeindefinanzstatistik Uri | I12: Statistik | J12: Offizielle Quelle recherchiert | K12: Orientierung / Datengrundlage | L12: Kanton Uri | M12: https://www.ur.ch/publikationen/6680 | N12: Zu prüfen | O12: 2026-10-14 | P12: Kennzahlen aller Urner Gemeinden | Q12: Selbstfinanzierung, Verschuldung, Investitionen | R12: Jahreswerte für Seelisberg extrahieren | S12: Kanton × Grössenklasse / Richtwerte | T12: Noch nicht bewertet | U12: Mittel | V12: Geltende kantonale Detailgrundlage und Datenstand prüfen | W12: A1; C1 | X12: Finanztragfähigkeit | Y12: Dokument auswerten; Aktualität und Geltung prüfen | Z12: Webrecherche 14.10.2026 | AD12: Verifiziert | AE12: 200 | AG12: HTML | AH12: Bestätigt | AI12: Schlüsselwörter 1/1 gefunden (Gemeindefinanzstatistik); Ort/Zuständigkeit: Uri | AJ12: Kanton Uri - Gemeindefinanzstatistik | Kontakt | AK12: 2023, 2025, 2026, 2024, 2022, 2021 | AL12: Mittel (CMS-Dokumentlink) | AM12: 2026-10-14 13:53 | AN12: Öffentlich verfügbar und verifiziert | AO12: Zu prüfen | AP12: Belegt Existenz und Zugänglichkeit der Quelle; inhaltliche Aussagen erst nach Auswertung. | AQ12: Keine Einstufung: Kennzahlen/Befunde noch nicht ausgewertet; Schwellen der Bewertungslogik noch nicht validiert. | AR12: Nein | AS12: Kanton Uri | AT12: In Prüfung | AX12: =IF(ISNA(MATCH($A12,'Gesamtübersicht'!$A:$A,0)),"ID fehlt in Gesamtübersicht",IF(AND(INDEX('Gesamtübersicht'!$H:$H,MATCH($A12,'Gesamtübersicht'!$A:$A,0))&""=$H12&"",INDEX('Gesamtübersicht'!$M:$M,MATCH($A12,'Gesamtübersicht'!$A:$A,0))&""=$M12&"",INDEX('Gesamtübersicht'!$AD:$AD,MATCH($A12,'Gesamtübersicht'!$A:$A,0))&""=$AD12&"",INDEX('Gesamtübersicht'!$AH:$AH,MATCH($A12,'Gesamtübersicht'!$A:$A,0))&""=$AH12&"",INDEX('Gesamtübersicht'!$T:$T,MATCH($A12,'Gesamtübersicht'!$A:$A,0))&""=$T12&""),"OK","Abweichung – Ansicht neu erzeugen"))
A13: UR-C1-02 | B13: Kanton | C13: Schweiz | D13: Uri | E13: Alle | F13: C1 | G13: Steuerkraft | H13: Steuerstatistiken Kanton Uri | I13: Statistik | J13: Offizielle Quelle recherchiert | K13: Orientierung / Datengrundlage | L13: Kanton Uri | M13: https://www.ur.ch/finanzen/1588 | N13: Zu prüfen | O13: 2026-10-14 | P13: Steuerbasis als Kontext zur Finanzkraft | Q13: Steuerbares Einkommen und Vermögen | R13: Lias-Daten übernehmen, nicht neu erheben | S13: Kanton × Grössenklasse | T13: Noch nicht bewertet | U13: Mittel | V13: Geltende kantonale Detailgrundlage und Datenstand prüfen | W13: A1/A2 | X13: DYN-Finanzkontext | Y13: Dokument auswerten; Aktualität und Geltung prüfen | Z13: Webrecherche 14.10.2026 | AD13: Verifiziert | AE13: 200 | AG13: HTML | AH13: Bestätigt | AI13: Schlüsselwörter 1/1 gefunden (Steuerstatistik); Ort/Zuständigkeit: Uri | AJ13: Kanton Uri - Steuerstatistiken | Kontakt | AK13: 2009, 2010, 2011, 2012, 2013, 2014 | AL13: Mittel (Webseite) | AM13: 2026-10-14 13:53 | AN13: Öffentlich verfügbar und verifiziert | AO13: Zu prüfen | AP13: Belegt Existenz und Zugänglichkeit der Quelle; inhaltliche Aussagen erst nach Auswertung. | AQ13: Keine Einstufung: Kennzahlen/Befunde noch nicht ausgewertet; Schwellen der Bewertungslogik noch nicht validiert. | AR13: Nein | AS13: Kanton Uri | AT13: In Prüfung | AX13: =IF(ISNA(MATCH($A13,'Gesamtübersicht'!$A:$A,0)),"ID fehlt in Gesamtübersicht",IF(AND(INDEX('Gesamtübersicht'!$H:$H,MATCH($A13,'Gesamtübersicht'!$A:$A,0))&""=$H13&"",INDEX('Gesamtübersicht'!$M:$M,MATCH($A13,'Gesamtübersicht'!$A:$A,0))&""=$M13&"",INDEX('Gesamtübersicht'!$AD:$AD,MATCH($A13,'Gesamtübersicht'!$A:$A,0))&""=$AD13&"",INDEX('Gesamtübersicht'!$AH:$AH,MATCH($A13,'Gesamtübersicht'!$A:$A,0))&""=$AH13&"",INDEX('Gesamtübersicht'!$T:$T,MATCH($A13,'Gesamtübersicht'!$A:$A,0))&""=$T13&""),"OK","Abweichung – Ansicht neu erzeugen"))
A14: UR-C1-03 | B14: Kanton | C14: Schweiz | D14: Uri | E14: Alle | F14: C1 | G14: Finanzkennzahlen Gemeinden | H14: Kennzahlen Einwohnergemeinden Uri 2025 (Finanzkontrolle) | I14: Statistik / Bericht | J14: Direktes Dokument | K14: Datengrundlage | L14: Kanton Uri, Finanzkontrolle | M14: https://www.ur.ch/_doc/451636 | N14: Rechnungsjahr 2025 (publ. 2026) | O14: 2026-10-14 | P14: Kennzahlen je Urner Gemeinde inkl. Seelisberg (Selbstfinanzierung, Kapitaldienst) | Q14: Selbstfinanzierungsanteil, Kapitaldienstanteil, Steuern/Kopf | S14: Kanton × Grössenklasse | T14: Noch nicht bewertet | U14: Hoch | W14: A1; C1 | X14: Finanztragfähigkeit Seelisberg im Kantonsvergleich | Y14: Dokument auswerten; Aktualität und Geltung prüfen | Z14: Websuche 14.10.2026 (URL im Suchergebnis gefunden) | AC14: https://www.ur.ch/publikationen/6680 | AD14: Weiterleitung | AE14: 200 | AF14: https://www.ur.ch/_docn/451636/Gemeindekennzahlen_2025_signiert.pdf | AG14: PDF | AH14: Bestätigt | AI14: Schlüsselwörter 2/2 gefunden (Kennzahlen, Seelisberg); Ort/Zuständigkeit: Uri | AJ14: Microsoft Word - Brief Versand Kennzahlen.docx | AK14: 2025, 2026, 2013, 2019, 2024 | AL14: Mittel (Webseite) | AM14: 2026-10-14 13:54 | AN14: Öffentlich verfügbar und verifiziert | AO14: Rechnungsjahr 2025 (publ. 2026) | AP14: Belegt Existenz und Zugänglichkeit der Quelle; inhaltliche Aussagen erst nach Auswertung. | AQ14: Keine Einstufung: Kennzahlen/Befunde noch nicht ausgewertet; Schwellen der Bewertungslogik noch nicht validiert. | AR14: Nein | AS14: Kanton Uri, Finanzkontrolle | AT14: In Prüfung | AW14: 2026-10-14: neu aufgenommen | AX14: =IF(ISNA(MATCH($A14,'Gesamtübersicht'!$A:$A,0)),"ID fehlt in Gesamtübersicht",IF(AND(INDEX('Gesamtübersicht'!$H:$H,MATCH($A14,'Gesamtübersicht'!$A:$A,0))&""=$H14&"",INDEX('Gesamtübersicht'!$M:$M,MATCH($A14,'Gesamtübersicht'!$A:$A,0))&""=$M14&"",INDEX('Gesamtübersicht'!$AD:$AD,MATCH($A14,'Gesamtübersicht'!$A:$A,0))&""=$AD14&"",INDEX('Gesamtübersicht'!$AH:$AH,MATCH($A14,'Gesamtübersicht'!$A:$A,0))&""=$AH14&"",INDEX('Gesamtübersicht'!$T:$T,MATCH($A14,'Gesamtübersicht'!$A:$A,0))&""=$T14&""),"OK","Abweichung – Ansicht neu erzeugen"))
A15: UR-C1-04 | B15: Kanton | C15: Schweiz | D15: Uri | E15: Alle | F15: C1 | G15: Finanzkennzahlen Gemeinden | H15: Kennzahlen Einwohnergemeinden Uri 2024 (Finanzkontrolle) | I15: Statistik / Bericht | J15: Direktes Dokument | K15: Datengrundlage | L15: Kanton Uri, Finanzkontrolle | M15: https://www.ur.ch/_doc/420775 | N15: Rechnungsjahr 2024 | O15: 2026-10-14 | P15: Vorjahreswerte für Zeitreihe | Q15: wie UR-C1-03 | S15: Kanton × Grössenklasse | T15: Noch nicht bewertet | U15: Hoch | Y15: Dokument auswerten; Aktualität und Geltung prüfen | Z15: Websuche 14.10.2026 (URL im Suchergebnis gefunden) | AC15: https://www.ur.ch/publikationen/6680 | AD15: Weiterleitung | AE15: 200 | AF15: https://www.ur.ch/_docn/420775/Gemeindekennzahlen_2024_signiert.pdf | AG15: PDF | AH15: Bestätigt | AI15: Schlüsselwörter 2/2 gefunden (Kennzahlen, Seelisberg); Ort/Zuständigkeit: Uri | AJ15: Gemeindekennzahlen 2024_final.xlsx | AK15: 2024, 2025, 2013, 2018 | AL15: Mittel (Webseite) | AM15: 2026-10-14 13:54 | AN15: Öffentlich verfügbar und verifiziert | AO15: Rechnungsjahr 2024 | AP15: Belegt Existenz und Zugänglichkeit der Quelle; inhaltliche Aussagen erst nach Auswertung. | AQ15: Keine Einstufung: Kennzahlen/Befunde noch nicht ausgewertet; Schwellen der Bewertungslogik noch nicht validiert. | AR15: Nein | AS15: Kanton Uri, Finanzkontrolle | AT15: In Prüfung | AW15: 2026-10-14: neu aufgenommen | AX15: =IF(ISNA(MATCH($A15,'Gesamtübersicht'!$A:$A,0)),"ID fehlt in Gesamtübersicht",IF(AND(INDEX('Gesamtübersicht'!$H:$H,MATCH($A15,'Gesamtübersicht'!$A:$A,0))&""=$H15&"",INDEX('Gesamtübersicht'!$M:$M,MATCH($A15,'Gesamtübersicht'!$A:$A,0))&""=$M15&"",INDEX('Gesamtübersicht'!$AD:$AD,MATCH($A15,'Gesamtübersicht'!$A:$A,0))&""=$AD15&"",INDEX('Gesamtübersicht'!$AH:$AH,MATCH($A15,'Gesamtübersicht'!$A:$A,0))&""=$AH15&"",INDEX('Gesamtübersicht'!$T:$T,MATCH($A15,'Gesamtübersicht'!$A:$A,0))&""=$T15&""),"OK","Abweichung – Ansicht neu erzeugen"))
A16: UR-C1-05 | B16: Kanton | C16: Schweiz | D16: Uri | E16: Alle | F16: C1 | G16: Rechnungslegung Gemeinden | H16: Reglement über das Rechnungswesen der Einwohnergemeinden (RRE), RB 3.2115 | I16: Kantonales Reglement | J16: Direktes Dokument | K16: Kantonales Recht (verbindlich) | L16: Regierungsrat Uri | M16: https://rechtsbuch.ur.ch/api/de/versions/776/pdf_file | N16: Version 776 (Stand prüfen) | O16: 2026-10-14 | P16: Rechtsgrundlage HRM2 und kantonale Finanzaufsicht über Gemeinden (Uri kennt kein separates FHGG) | S16: Kanton × Grössenklasse | T16: Noch nicht bewertet | U16: Hoch | Y16: Dokument auswerten; Aktualität und Geltung prüfen | Z16: Websuche 14.10.2026 (URL im Suchergebnis gefunden) | AC16: https://www.ur.ch/dienstleistungen/3150 | AD16: Verifiziert | AE16: 200 | AG16: PDF | AH16: Bestätigt | AI16: Schlüsselwörter 2/2 gefunden (Rechnungswesen, Einwohnergemeinden) | AJ16: 3.2115 - Reglement über das Rechnungswesen der Einwohnergemeinden | AK16: 2010, 2021, 2009, 2008 | AL16: Hoch (Erlassnummer) | AM16: 2026-10-14 13:54 | AN16: Öffentlich verfügbar und verifiziert | AO16: Version 776 (Stand prüfen) | AP16: Belegt Existenz und Zugänglichkeit der Quelle; inhaltliche Aussagen erst nach Auswertung. | AQ16: Keine Einstufung: Kennzahlen/Befunde noch nicht ausgewertet; Schwellen der Bewertungslogik noch nicht validiert. | AR16: Nein | AS16: Regierungsrat Uri | AT16: In Prüfung | AU16: Versions-PDF: prüfen, ob dies die geltende Fassung ist. | AW16: 2026-10-14: neu aufgenommen | AX16: =IF(ISNA(MATCH($A16,'Gesamtübersicht'!$A:$A,0)),"ID fehlt in Gesamtübersicht",IF(AND(INDEX('Gesamtübersicht'!$H:$H,MATCH($A16,'Gesamtübersicht'!$A:$A,0))&""=$H16&"",INDEX('Gesamtübersicht'!$M:$M,MATCH($A16,'Gesamtübersicht'!$A:$A,0))&""=$M16&"",INDEX('Gesamtübersicht'!$AD:$AD,MATCH($A16,'Gesamtübersicht'!$A:$A,0))&""=$AD16&"",INDEX('Gesamtübersicht'!$AH:$AH,MATCH($A16,'Gesamtübersicht'!$A:$A,0))&""=$AH16&"",INDEX('Gesamtübersicht'!$T:$T,MATCH($A16,'Gesamtübersicht'!$A:$A,0))&""=$T16&""),"OK","Abweichung – Ansicht neu erzeugen"))
A17: UR-C1-06 | B17: Kanton | C17: Schweiz | D17: Uri | E17: Alle | F17: C1 | G17: Finanzausgleich | H17: Gesetz über den Finanz- und Lastenausgleich zwischen dem Kanton und den Gemeinden (FiLaG), RB 3.2131 | I17: Kantonales Gesetz | J17: Direktes Dokument | K17: Kantonales Recht (verbindlich) | L17: Kanton Uri | M17: https://rechtsbuch.ur.ch/app/de/texts_of_law/3.2131 | N17: geltende Fassung | O17: 2026-10-14 | P17: Art. 22: Sonderbeitrag an Seelisberg (Abgeschiedenheit); Ressourcen- und Lastenausgleich | Q17: Ausgleichszahlungen | S17: Kanton × Grössenklasse | T17: Noch nicht bewertet | U17: Hoch | Y17: Dokument auswerten; Aktualität und Geltung prüfen | Z17: URL nach dokumentiertem Schema der amtlichen Rechtssammlung gebildet; Identität per Runner geprüft | AD17: Verifiziert | AE17: 200 | AG17: HTML | AH17: Bestätigt | AI17: Titel via LexWork-API (https://rechtsbuch.ur.ch/api/de/texts_of_law/3.2131); Schlüsselwörter 1/1 gefunden (Lastenausgleich) | AJ17: Gesetz über den Finanz- und Lastenausgleich zwischen dem Kanton und den Gemeinden | AK17: 2007, 2026, 2025, 2008 | AL17: Hoch (Erlassnummer) | AM17: 2026-10-14 13:54 | AN17: Öffentlich verfügbar und verifiziert | AO17: geltende Fassung | AP17: Belegt Existenz und Zugänglichkeit der Quelle; inhaltliche Aussagen erst nach Auswertung. | AQ17: Keine Einstufung: Kennzahlen/Befunde noch nicht ausgewertet; Schwellen der Bewertungslogik noch nicht validiert. | AR17: Nein | AS17: Kanton Uri | AT17: In Prüfung | AW17: 2026-10-14: neu aufgenommen | AX17: =IF(ISNA(MATCH($A17,'Gesamtübersicht'!$A:$A,0)),"ID fehlt in Gesamtübersicht",IF(AND(INDEX('Gesamtübersicht'!$H:$H,MATCH($A17,'Gesamtübersicht'!$A:$A,0))&""=$H17&"",INDEX('Gesamtübersicht'!$M:$M,MATCH($A17,'Gesamtübersicht'!$A:$A,0))&""=$M17&"",INDEX('Gesamtübersicht'!$AD:$AD,MATCH($A17,'Gesamtübersicht'!$A:$A,0))&""=$AD17&"",INDEX('Gesamtübersicht'!$AH:$AH,MATCH($A17,'Gesamtübersicht'!$A:$A,0))&""=$AH17&"",INDEX('Gesamtübersicht'!$T:$T,MATCH($A17,'Gesamtübersicht'!$A:$A,0))&""=$T17&""),"OK","Abweichung – Ansicht neu erzeugen"))
A18: UR-C1-07 | B18: Kanton | C18: Schweiz | D18: Uri | E18: Alle | F18: C1 | G18: Finanzausgleich | H18: Finanz- und Lastenausgleich (FiLa) 2025 – Berechnung je Gemeinde | I18: Berechnungstabelle | J18: Direktes Dokument | K18: Datengrundlage | L18: Kanton Uri, Finanzdirektion | M18: https://www.ur.ch/_docn/426685/Berechnung_FiLa_2025.pdf | N18: 2025 | O18: 2026-10-14 | P18: Höhe der Ausgleichszahlungen an Seelisberg | Q18: Ressourcenausgleich, Lastenausgleich CHF | S18: Kanton × Grössenklasse | T18: Noch nicht bewertet | U18: Hoch | Y18: Dokument auswerten; Aktualität und Geltung prüfen | Z18: Websuche 14.10.2026 (URL im Suchergebnis gefunden) | AD18: Verifiziert | AE18: 200 | AG18: PDF | AH18: Bestätigt | AI18: Schlüsselwörter 2/2 gefunden (2025, Seelisberg); Ort/Zuständigkeit: Uri | AJ18: FINANZDIREKTION Beilage 2 | AK18: 2025, 2024, 2023, 2021, 2015, 2008 | AL18: Mittel (CMS-Dokumentlink) | AM18: 2026-10-14 13:54 | AN18: Öffentlich verfügbar und verifiziert | AO18: 2025 | AP18: Belegt Existenz und Zugänglichkeit der Quelle; inhaltliche Aussagen erst nach Auswertung. | AQ18: Keine Einstufung: Kennzahlen/Befunde noch nicht ausgewertet; Schwellen der Bewertungslogik noch nicht validiert. | AR18: Nein | AS18: Kanton Uri, Finanzdirektion | AT18: In Prüfung | AW18: 2026-10-14: neu aufgenommen | AX18: =IF(ISNA(MATCH($A18,'Gesamtübersicht'!$A:$A,0)),"ID fehlt in Gesamtübersicht",IF(AND(INDEX('Gesamtübersicht'!$H:$H,MATCH($A18,'Gesamtübersicht'!$A:$A,0))&""=$H18&"",INDEX('Gesamtübersicht'!$M:$M,MATCH($A18,'Gesamtübersicht'!$A:$A,0))&""=$M18&"",INDEX('Gesamtübersicht'!$AD:$AD,MATCH($A18,'Gesamtübersicht'!$A:$A,0))&""=$AD18&"",INDEX('Gesamtübersicht'!$AH:$AH,MATCH($A18,'Gesamtübersicht'!$A:$A,0))&""=$AH18&"",INDEX('Gesamtübersicht'!$T:$T,MATCH($A18,'Gesamtübersicht'!$A:$A,0))&""=$T18&""),"OK","Abweichung – Ansicht neu erzeugen"))
A19: UR-C2-01 | B19: Kanton | C19: Schweiz | D19: Uri | E19: Alle | F19: C2 | G19: Geodaten / Eigentum | H19: Geoportal Uri: Liegenschaften und Nutzungsplanung | I19: Geodatenportal | J19: Offizielle Quelle recherchiert | K19: Orientierung / Datengrundlage | L19: Kanton Uri | M19: https://geo.ur.ch/ | N19: Zu prüfen | O19: 2026-10-14 | P19: Räumliche Parzellenstruktur; kein Nachweis kommunalen Eigentums | Q19: Parzellen, ÖBA-Zonen | R19: Luucy übernehmen, Eigentum separat belegen | S19: Kein Peer | T19: Noch nicht bewertet | U19: Mittel | V19: Geltende kantonale Detailgrundlage und Datenstand prüfen | W19: B; Q1 | X19: Bodenpotenzial | Y19: Dokument auswerten; Aktualität und Geltung prüfen | Z19: Webrecherche 14.10.2026 | AD19: Verifiziert | AE19: 200 | AG19: HTML | AH19: Bestätigt | AI19: Schlüsselwörter 1/1 gefunden (Geo); Ort/Zuständigkeit: geo.ur | AJ19: geo.ur | AL19: Mittel (Startseite, kein Dokument) | AM19: 2026-10-14 13:53 | AN19: Öffentlich verfügbar und verifiziert | AO19: Zu prüfen | AP19: Belegt Existenz und Zugänglichkeit der Quelle; inhaltliche Aussagen erst nach Auswertung. | AQ19: Keine Einstufung: Kennzahlen/Befunde noch nicht ausgewertet; Schwellen der Bewertungslogik noch nicht validiert. | AR19: Nein | AS19: Kanton Uri | AT19: In Prüfung | AU19: Kartenportal (JavaScript); Inhaltsprüfung nur eingeschränkt möglich. Kein Eigentumsnachweis. | AX19: =IF(ISNA(MATCH($A19,'Gesamtübersicht'!$A:$A,0)),"ID fehlt in Gesamtübersicht",IF(AND(INDEX('Gesamtübersicht'!$H:$H,MATCH($A19,'Gesamtübersicht'!$A:$A,0))&""=$H19&"",INDEX('Gesamtübersicht'!$M:$M,MATCH($A19,'Gesamtübersicht'!$A:$A,0))&""=$M19&"",INDEX('Gesamtübersicht'!$AD:$AD,MATCH($A19,'Gesamtübersicht'!$A:$A,0))&""=$AD19&"",INDEX('Gesamtübersicht'!$AH:$AH,MATCH($A19,'Gesamtübersicht'!$A:$A,0))&""=$AH19&"",INDEX('Gesamtübersicht'!$T:$T,MATCH($A19,'Gesamtübersicht'!$A:$A,0))&""=$T19&""),"OK","Abweichung – Ansicht neu erzeugen"))
A20: UR-C2-02 | B20: Kanton | C20: Schweiz | D20: Uri | E20: Alle | F20: C2 | G20: Raumplanung / Baulandmobilisierung | H20: Planungs- und Baugesetz (PBG) des Kantons Uri, RB 40.1111 | I20: Kantonales Gesetz | J20: Direktes Dokument | K20: Kantonales Recht (verbindlich) | L20: Kanton Uri | M20: https://rechtsbuch.ur.ch/app/de/texts_of_law/40.1111 | N20: geltende Fassung | O20: 2026-10-14 | P20: Bauverpflichtung/Baulandmobilisierung, Mehrwertausgleich | S20: Kein Peer-Vergleich | T20: Noch nicht bewertet | U20: Hoch | W20: B; Q1 | Y20: Dokument auswerten; Aktualität und Geltung prüfen | Z20: Websuche 14.10.2026 (URL im Suchergebnis gefunden) | AD20: Verifiziert | AE20: 200 | AG20: HTML | AH20: Bestätigt | AI20: Titel via LexWork-API (https://rechtsbuch.ur.ch/api/de/texts_of_law/40.1111); Schlüsselwörter 1/1 gefunden (Planungs) | AJ20: Planungs- und Baugesetz | AK20: 2010, 2022, 2012, 2021 | AL20: Hoch (Erlassnummer) | AM20: 2026-10-14 13:54 | AN20: Öffentlich verfügbar und verifiziert | AO20: geltende Fassung | AP20: Belegt Existenz und Zugänglichkeit der Quelle; inhaltliche Aussagen erst nach Auswertung. | AQ20: Keine Einstufung: Kennzahlen/Befunde noch nicht ausgewertet; Schwellen der Bewertungslogik noch nicht validiert. | AR20: Nein | AS20: Kanton Uri | AT20: In Prüfung | AW20: 2026-10-14: neu aufgenommen | AX20: =IF(ISNA(MATCH($A20,'Gesamtübersicht'!$A:$A,0)),"ID fehlt in Gesamtübersicht",IF(AND(INDEX('Gesamtübersicht'!$H:$H,MATCH($A20,'Gesamtübersicht'!$A:$A,0))&""=$H20&"",INDEX('Gesamtübersicht'!$M:$M,MATCH($A20,'Gesamtübersicht'!$A:$A,0))&""=$M20&"",INDEX('Gesamtübersicht'!$AD:$AD,MATCH($A20,'Gesamtübersicht'!$A:$A,0))&""=$AD20&"",INDEX('Gesamtübersicht'!$AH:$AH,MATCH($A20,'Gesamtübersicht'!$A:$A,0))&""=$AH20&"",INDEX('Gesamtübersicht'!$T:$T,MATCH($A20,'Gesamtübersicht'!$A:$A,0))&""=$T20&""),"OK","Abweichung – Ansicht neu erzeugen"))
A21: UR-C2-03 | B21: Kanton | C21: Schweiz | D21: Uri | E21: Alle | F21: C2 | G21: Bauland | H21: Kanton Uri: Baulanddatenbank (unbebaute Bauzonen, Raum+) | I21: Datenbank / Webseite | J21: Webseite | K21: Information | L21: Kanton Uri, Amt für Raumentwicklung | M21: https://www.ur.ch/dienstleistungen/4297 | O21: 2026-10-14 | P21: Unüberbaute Bauzonenreserven; kein Nachweis kommunalen Eigentums | S21: Kein Peer-Vergleich | T21: Noch nicht bewertet | U21: Mittel | Y21: Dokument auswerten; Aktualität und Geltung prüfen | Z21: Websuche 14.10.2026 (URL im Suchergebnis gefunden) | AD21: Verifiziert | AE21: 200 | AG21: HTML | AH21: Bestätigt | AI21: Schlüsselwörter 1/1 gefunden (Bauland); Ort/Zuständigkeit: Uri | AJ21: Kanton Uri - Baulanddatenbank | Kontakt | AK21: 2030, 2023, 2025, 2027, 2026 | AL21: Mittel (Webseite) | AM21: 2026-10-14 13:54 | AN21: Öffentlich verfügbar und verifiziert | AP21: Belegt Existenz und Zugänglichkeit der Quelle; inhaltliche Aussagen erst nach Auswertung. | AQ21: Keine Einstufung: Kennzahlen/Befunde noch nicht ausgewertet; Schwellen der Bewertungslogik noch nicht validiert. | AR21: Nein | AS21: Kanton Uri, Amt für Raumentwicklung | AT21: In Prüfung | AW21: 2026-10-14: neu aufgenommen | AX21: =IF(ISNA(MATCH($A21,'Gesamtübersicht'!$A:$A,0)),"ID fehlt in Gesamtübersicht",IF(AND(INDEX('Gesamtübersicht'!$H:$H,MATCH($A21,'Gesamtübersicht'!$A:$A,0))&""=$H21&"",INDEX('Gesamtübersicht'!$M:$M,MATCH($A21,'Gesamtübersicht'!$A:$A,0))&""=$M21&"",INDEX('Gesamtübersicht'!$AD:$AD,MATCH($A21,'Gesamtübersicht'!$A:$A,0))&""=$AD21&"",INDEX('Gesamtübersicht'!$AH:$AH,MATCH($A21,'Gesamtübersicht'!$A:$A,0))&""=$AH21&"",INDEX('Gesamtübersicht'!$T:$T,MATCH($A21,'Gesamtübersicht'!$A:$A,0))&""=$T21&""),"OK","Abweichung – Ansicht neu erzeugen"))
A22: UR-C3-01 | B22: Kanton | C22: Schweiz | D22: Uri | E22: Alle | F22: C3 | G22: Gemeinderecht | H22: Gemeindegesetz (GEG) des Kantons Uri, RB 1.1111 | I22: Kantonales Gesetz | J22: Offizielle Quelle recherchiert | K22: Kantonales Gesetz (verbindlich) | L22: Kanton Uri | M22: https://rechtsbuch.ur.ch/app/de/texts_of_law/1.1111 | N22: vom 21.5.2017; geltende Fassung | O22: 2026-10-14 | P22: Gemeinderechtliche Grundlagen und Zuständigkeiten recherchieren | Q22: Zuständigkeiten / Kooperation | R22: Konkrete Erlasse und geltende Fassung identifizieren | S22: Qualitativ | T22: Noch nicht bewertet | U22: Mittel | V22: Geltende kantonale Detailgrundlage und Datenstand prüfen | W22: Q6; C5 | X22: Governance | Y22: Dokument auswerten; Aktualität und Geltung prüfen | Z22: URL nach dokumentiertem Schema der amtlichen Rechtssammlung gebildet; Identität per Runner geprüft | AD22: Verifiziert | AE22: 200 | AG22: HTML | AH22: Bestätigt | AI22: Titel via LexWork-API (https://rechtsbuch.ur.ch/api/de/texts_of_law/1.1111); Schlüsselwörter 1/1 gefunden (Gemeindegesetz) | AJ22: Gemeindegesetz | AK22: 2017, 2026, 2025 | AL22: Hoch (Erlassnummer) | AM22: 2026-10-14 13:53 | AN22: Öffentlich verfügbar und verifiziert | AO22: vom 21.5.2017; geltende Fassung | AP22: Belegt Existenz und Zugänglichkeit der Quelle; inhaltliche Aussagen erst nach Auswertung. | AQ22: Keine Einstufung: Kennzahlen/Befunde noch nicht ausgewertet; Schwellen der Bewertungslogik noch nicht validiert. | AR22: Nein | AS22: Kanton Uri | AT22: In Prüfung | AW22: 2026-10-14: Link ersetzt (vorher https://rechtsbuch.ur.ch/). Grund: Startseite der Rechtssammlung durch direkten Erlass ersetzt (Gemeindegesetz, RB 1.1111). | AX22: =IF(ISNA(MATCH($A22,'Gesamtübersicht'!$A:$A,0)),"ID fehlt in Gesamtübersicht",IF(AND(INDEX('Gesamtübersicht'!$H:$H,MATCH($A22,'Gesamtübersicht'!$A:$A,0))&""=$H22&"",INDEX('Gesamtübersicht'!$M:$M,MATCH($A22,'Gesamtübersicht'!$A:$A,0))&""=$M22&"",INDEX('Gesamtübersicht'!$AD:$AD,MATCH($A22,'Gesamtübersicht'!$A:$A,0))&""=$AD22&"",INDEX('Gesamtübersicht'!$AH:$AH,MATCH($A22,'Gesamtübersicht'!$A:$A,0))&""=$AH22&"",INDEX('Gesamtübersicht'!$T:$T,MATCH($A22,'Gesamtübersicht'!$A:$A,0))&""=$T22&""),"OK","Abweichung – Ansicht neu erzeugen"))
A23: UR-C3-02 | B23: Kanton | C23: Schweiz | D23: Uri | E23: Alle | F23: C3 | G23: Kantonsverfassung | H23: Verfassung des Kantons Uri, RB 1.1101 | I23: Kantonsverfassung | J23: Direktes Dokument | K23: Kantonales Recht (verbindlich) | L23: Kanton Uri | M23: https://rechtsbuch.ur.ch/app/de/texts_of_law/1.1101 | N23: vom 28.10.1984; geltende Fassung | O23: 2026-10-14 | P23: Gemeindeautonomie; Art. 58 Finanzplanung der Gemeinden; Art. 110 Rechtsetzung Gemeinden | S23: Kein Peer-Vergleich | T23: Noch nicht bewertet | U23: Hoch | Y23: Dokument auswerten; Aktualität und Geltung prüfen | Z23: URL nach dokumentiertem Schema der amtlichen Rechtssammlung gebildet; Identität per Runner geprüft | AA23: C1, C5 | AD23: Verifiziert | AE23: 200 | AG23: HTML | AH23: Bestätigt | AI23: Titel via LexWork-API (https://rechtsbuch.ur.ch/api/de/texts_of_law/1.1101); Schlüsselwörter 1/1 gefunden (Verfassung) | AJ23: Verfassung des Kantons Uri | AK23: 2023, 2018 | AL23: Hoch (Erlassnummer) | AM23: 2026-10-14 13:54 | AN23: Öffentlich verfügbar und verifiziert | AO23: vom 28.10.1984; geltende Fassung | AP23: Belegt Existenz und Zugänglichkeit der Quelle; inhaltliche Aussagen erst nach Auswertung. | AQ23: Keine Einstufung: Kennzahlen/Befunde noch nicht ausgewertet; Schwellen der Bewertungslogik noch nicht validiert. | AR23: Nein | AS23: Kanton Uri | AT23: In Prüfung | AW23: 2026-10-14: neu aufgenommen | AX23: =IF(ISNA(MATCH($A23,'Gesamtübersicht'!$A:$A,0)),"ID fehlt in Gesamtübersicht",IF(AND(INDEX('Gesamtübersicht'!$H:$H,MATCH($A23,'Gesamtübersicht'!$A:$A,0))&""=$H23&"",INDEX('Gesamtübersicht'!$M:$M,MATCH($A23,'Gesamtübersicht'!$A:$A,0))&""=$M23&"",INDEX('Gesamtübersicht'!$AD:$AD,MATCH($A23,'Gesamtübersicht'!$A:$A,0))&""=$AD23&"",INDEX('Gesamtübersicht'!$AH:$AH,MATCH($A23,'Gesamtübersicht'!$A:$A,0))&""=$AH23&"",INDEX('Gesamtübersicht'!$T:$T,MATCH($A23,'Gesamtübersicht'!$A:$A,0))&""=$T23&""),"OK","Abweichung – Ansicht neu erzeugen"))
A24: UR-C4-01 | B24: Kanton | C24: Schweiz | D24: Uri | E24: Alle | F24: C4 | G24: Verwaltung | H24: Kanton Uri: Submissionsrecht (IVöB 2019, in Kraft seit 1.6.2023) | I24: Behördeninformation | J24: Offizielle Quelle recherchiert | K24: Information zu verbindlichem Recht | L24: Kanton Uri | M24: https://www.ur.ch/dienstleistungen/8444 | N24: Zu prüfen | O24: 2026-10-14 | P24: Rahmenbedingungen und interkommunale Aufgaben | Q24: Verwaltungsaufgaben / Organisation | R24: Gemeindespezifische Unterlagen ergänzen | S24: Qualitativ | T24: Noch nicht bewertet | U24: Mittel | V24: Geltende kantonale Detailgrundlage und Datenstand prüfen | W24: C3; Q6 | X24: Verwaltungskapazität | Y24: Dokument auswerten; Aktualität und Geltung prüfen | Z24: Webrecherche 14.10.2026 | AD24: Verifiziert | AE24: 200 | AG24: HTML | AH24: Bestätigt | AI24: Schlüsselwörter 1/1 gefunden (Submission); Ort/Zuständigkeit: Uri | AJ24: Kanton Uri - Submissionsrecht | Kontakt | AK24: 2023, 2030, 2025, 2027, 2026 | AL24: Mittel (Webseite) | AM24: 2026-10-14 13:53 | AN24: Öffentlich verfügbar und verifiziert | AO24: Zu prüfen | AP24: Belegt Existenz und Zugänglichkeit der Quelle; inhaltliche Aussagen erst nach Auswertung. | AQ24: Keine Einstufung: Kennzahlen/Befunde noch nicht ausgewertet; Schwellen der Bewertungslogik noch nicht validiert. | AR24: Nein | AS24: Kanton Uri | AT24: In Prüfung | AW24: 2026-10-14: Link ersetzt (vorher https://www.ur.ch/). Grund: Allgemeine Startseite ur.ch durch themenspezifische Seite zum Beschaffungsrecht ersetzt. | AX24: =IF(ISNA(MATCH($A24,'Gesamtübersicht'!$A:$A,0)),"ID fehlt in Gesamtübersicht",IF(AND(INDEX('Gesamtübersicht'!$H:$H,MATCH($A24,'Gesamtübersicht'!$A:$A,0))&""=$H24&"",INDEX('Gesamtübersicht'!$M:$M,MATCH($A24,'Gesamtübersicht'!$A:$A,0))&""=$M24&"",INDEX('Gesamtübersicht'!$AD:$AD,MATCH($A24,'Gesamtübersicht'!$A:$A,0))&""=$AD24&"",INDEX('Gesamtübersicht'!$AH:$AH,MATCH($A24,'Gesamtübersicht'!$A:$A,0))&""=$AH24&"",INDEX('Gesamtübersicht'!$T:$T,MATCH($A24,'Gesamtübersicht'!$A:$A,0))&""=$T24&""),"OK","Abweichung – Ansicht neu erzeugen"))
A25: UR-C4-02 | B25: Kanton | C25: Schweiz | D25: Uri | E25: Alle | F25: C4 | G25: Beschaffung | H25: Interkantonale Vereinbarung über das öffentliche Beschaffungswesen (IVöB 2019), RB 3.3111 | I25: Interkantonales Recht | J25: Direktes Dokument | K25: Interkantonales Recht (verbindlich) | L25: Kanton Uri | M25: https://rechtsbuch.ur.ch/app/de/texts_of_law/3.3111 | O25: 2026-10-14 | P25: Beschaffungsrecht für Gemeinden (Schwellenwerte, Verfahren) | S25: Kein Peer-Vergleich | T25: Noch nicht bewertet | U25: Hoch | Y25: Dokument auswerten; Aktualität und Geltung prüfen | Z25: URL nach dokumentiertem Schema der amtlichen Rechtssammlung gebildet; Identität per Runner geprüft | AD25: Verifiziert | AE25: 200 | AG25: HTML | AH25: Bestätigt | AI25: Titel via LexWork-API (https://rechtsbuch.ur.ch/api/de/texts_of_law/3.3111); Schlüsselwörter 1/1 gefunden (Beschaffungswesen) | AJ25: Interkantonale Vereinbarung über das öffentliche Beschaffungswesen | AK25: 2023, 2019 | AL25: Hoch (Erlassnummer) | AM25: 2026-10-14 13:54 | AN25: Öffentlich verfügbar und verifiziert | AP25: Belegt Existenz und Zugänglichkeit der Quelle; inhaltliche Aussagen erst nach Auswertung. | AQ25: Keine Einstufung: Kennzahlen/Befunde noch nicht ausgewertet; Schwellen der Bewertungslogik noch nicht validiert. | AR25: Nein | AS25: Kanton Uri | AT25: In Prüfung | AW25: 2026-10-14: neu aufgenommen | AX25: =IF(ISNA(MATCH($A25,'Gesamtübersicht'!$A:$A,0)),"ID fehlt in Gesamtübersicht",IF(AND(INDEX('Gesamtübersicht'!$H:$H,MATCH($A25,'Gesamtübersicht'!$A:$A,0))&""=$H25&"",INDEX('Gesamtübersicht'!$M:$M,MATCH($A25,'Gesamtübersicht'!$A:$A,0))&""=$M25&"",INDEX('Gesamtübersicht'!$AD:$AD,MATCH($A25,'Gesamtübersicht'!$A:$A,0))&""=$AD25&"",INDEX('Gesamtübersicht'!$AH:$AH,MATCH($A25,'Gesamtübersicht'!$A:$A,0))&""=$AH25&"",INDEX('Gesamtübersicht'!$T:$T,MATCH($A25,'Gesamtübersicht'!$A:$A,0))&""=$T25&""),"OK","Abweichung – Ansicht neu erzeugen"))
A26: UR-C5-01 | B26: Kanton | C26: Schweiz | D26: Uri | E26: Alle | F26: C5 | G26: Politische Rechte | H26: Gesetz über die geheimen Wahlen, Abstimmungen und die Volksrechte (WAVG), RB 2.1201 | I26: Kantonales Gesetz | J26: Offizielle Quelle recherchiert | K26: Kantonales Gesetz (verbindlich) | L26: Kanton Uri | M26: https://rechtsbuch.ur.ch/app/de/texts_of_law/2.1201 | N26: geltende Fassung; Revision hängig (Synopse 2026) | O26: 2026-10-14 | P26: Rechtsrahmen für kommunale Entscheidungen | Q26: Referendum / Zuständigkeiten | R26: Gemeindeordnung konkret prüfen | S26: Qualitativ | T26: Noch nicht bewertet | U26: Mittel | V26: Geltende kantonale Detailgrundlage und Datenstand prüfen | W26: C3; Q1 | X26: Politische Tragfähigkeit | Y26: Dokument auswerten; Aktualität und Geltung prüfen | Z26: URL nach dokumentiertem Schema der amtlichen Rechtssammlung gebildet; Identität per Runner geprüft | AD26: Verifiziert | AE26: 200 | AG26: HTML | AH26: Bestätigt | AI26: Titel via LexWork-API (https://rechtsbuch.ur.ch/api/de/texts_of_law/2.1201); Schlüsselwörter 1/1 gefunden (Wahlen) | AJ26: Gesetz über die geheimen Wahlen, Abstimmungen und die Volksrechte | AK26: 2010, 2009 | AL26: Hoch (Erlassnummer) | AM26: 2026-10-14 13:53 | AN26: Öffentlich verfügbar und verifiziert | AO26: geltende Fassung; Revision hängig (Synopse 2026) | AP26: Belegt Existenz und Zugänglichkeit der Quelle; inhaltliche Aussagen erst nach Auswertung. | AQ26: Keine Einstufung: Kennzahlen/Befunde noch nicht ausgewertet; Schwellen der Bewertungslogik noch nicht validiert. | AR26: Nein | AS26: Kanton Uri | AT26: In Prüfung | AW26: 2026-10-14: Link ersetzt (vorher https://rechtsbuch.ur.ch/). Grund: Startseite der Rechtssammlung durch direkten Erlass ersetzt (WAVG, RB 2.1201). | AX26: =IF(ISNA(MATCH($A26,'Gesamtübersicht'!$A:$A,0)),"ID fehlt in Gesamtübersicht",IF(AND(INDEX('Gesamtübersicht'!$H:$H,MATCH($A26,'Gesamtübersicht'!$A:$A,0))&""=$H26&"",INDEX('Gesamtübersicht'!$M:$M,MATCH($A26,'Gesamtübersicht'!$A:$A,0))&""=$M26&"",INDEX('Gesamtübersicht'!$AD:$AD,MATCH($A26,'Gesamtübersicht'!$A:$A,0))&""=$AD26&"",INDEX('Gesamtübersicht'!$AH:$AH,MATCH($A26,'Gesamtübersicht'!$A:$A,0))&""=$AH26&"",INDEX('Gesamtübersicht'!$T:$T,MATCH($A26,'Gesamtübersicht'!$A:$A,0))&""=$T26&""),"OK","Abweichung – Ansicht neu erzeugen"))
