Workbook

Sheet Anleitung
A1: Kanton St.Gallen
A2: Amt für Gemeinden und Bürgerrecht
A5: Berechnung Finanzausgleichsbeiträge 2025
A7: In dieser Datei werden die Finanzausgleichsbeiträge für das Jahr 2025 berechnet.
A9: In den grünen Laschen werden die Berechnungen vorgenommen. Diese Laschen sind ausschliesslich für den internen Gebrauch!
A13: Die drei blauen Laschen werden für die Auszahlungen der Finanzausgleichsbeiträge benötigt!
A17: Die roten Laschen dienen als Informationszweck für die Gemeinden. Diese Informationen werden regelmässig auf der Homepage aufgeschaltet! Bei der Aufschaltungsdatei sind die nicht relevanten Laschen auszublenden!

Sheet Ressourcenausgleich Basis
A1: Kanton St.Gallen
A2: Amt für Gemeinden und Bürgerrecht
A5: Ressourcenausgleich 2025
B7: Eingabefelder
C8: Total | D8: St.Gallen | E8: Wittenbach | F8: Häggenschwil | G8: Muolen | H8: Mörschwil | I8: Goldach | J8: Steinach | K8: Berg | L8: Tübach | M8: Untereggen | N8: Eggersriet | O8: Rorschacherberg | P8: Rorschach | Q8: Thal | R8: Rheineck | S8: St.Margrethen | T8: Au | U8: Berneck | V8: Balgach | W8: Diepoldsau | X8: Widnau | Y8: Rebstein | Z8: Marbach | AA8: Altstätten | AB8: Eichberg | AC8: Oberriet | AD8: Rüthi | AE8: Sennwald | AF8: Gams | AG8: Grabs | AH8: Buchs | AI8: Sevelen | AJ8: Wartau | AK8: Sargans | AL8: Vilters-Wangs | AM8: Bad Ragaz | AN8: Pfäfers | AO8: Mels | AP8: Flums | AQ8: Walenstadt | AR8: Quarten | AS8: Amden | AT8: Weesen | AU8: Schänis | AV8: Benken | AW8: Kaltbrunn | AX8: Gommiswald | AY8: Uznach | AZ8: Schmerikon | BA8: Rapperswil-Jona | BB8: Eschenbach | BC8: Wildhaus-Alt St.Johann | BD8: Nesslau | BE8: Ebnat-Kappel | BF8: Wattwil | BG8: Lichtensteig | BH8: Neckertal | BI8: Bütschwil-Ganterschwil | BJ8: Lütisburg | BK8: Mosnang | BL8: Kirchberg | BM8: Jonschwil | BN8: Oberuzwil | BO8: Uzwil | BP8: Flawil | BQ8: Degersheim | BR8: Wil | BS8: Zuzwil | BT8: Oberbüren | BU8: Niederbüren | BV8: Niederhelfenschwil | BW8: Gossau | BX8: Andwil | BY8: Waldkirch | BZ8: Gaiserwald | CB8: Quelle
A10: 1.) | B10: Steuerdaten 2023
A12: 1.1) | B12: Einkommens-/Vermögenssteuer
B13: Steuerfuss | C13: =C19/C17 -> 1.112714 | D13: 1.41 | E13: 1.28 | F13: 1.15 | G13: 1.23 | H13: 0.7 | I13: 0.91 | J13: 1.15 | K13: 1.26 | L13: 0.79 | M13: 1.19 | N13: 1.2 | O13: 0.93 | P13: 1.29 | Q13: 0.89 | R13: 1.13 | S13: 1.02 | T13: 0.89 | U13: 0.95 | V13: 0.61 | W13: 0.81 | X13: 0.76 | Y13: 1.01 | Z13: 1.07 | AA13: 1.19 | AB13: 1.04 | AC13: 0.99 | AD13: 1.15 | AE13: 0.75 | AF13: 1.18 | AG13: 1 | AH13: 1.18 | AI13: 1.1 | AJ13: 1.5 | AK13: 1.34 | AL13: 1.25 | AM13: 0.92 | AN13: 1.39 | AO13: 1.33 | AP13: 1.25 | AQ13: 1.15 | AR13: 1.07 | AS13: 1.12 | AT13: 1.15 | AU13: 1.25 | AV13: 1.19 | AW13: 1.06 | AX13: 1.08 | AY13: 1.12 | AZ13: 1.13 | BA13: 0.74 | BB13: 1.19 | BC13: 1.23 | BD13: 1.19 | BE13: 1.39 | BF13: 1.32 | BG13: 1.29 | BH13: 1.2 | BI13: 1.19 | BJ13: 1.15 | BK13: 1.29 | BL13: 1.2 | BM13: 1.17 | BN13: 1.17 | BO13: 1.27 | BP13: 1.27 | BQ13: 1.47 | BR13: 1.18 | BS13: 0.77 | BT13: 1 | BU13: 1.26 | BV13: 1.04 | BW13: 1.16 | BX13: 1.13 | BY13: 1.22 | BZ13: 1.03 | CB13: KStA
B15: Einfache Steuer Brutto | C15: =SUM(D15:BZ15) -> 1.267089e+09 | D15: 1.878166e+08 | E15: 19800001 | F15: 3126213 | G15: 2605174.8 | H15: 16744495 | I15: 24193019 | J15: 8384764.4 | K15: 3327004.4 | L15: 4561605.8 | M15: 2609380.8 | N15: 6425305.4 | O15: 20342881 | P15: 16012558 | Q15: 18465006 | R15: 6306940.7 | S15: 10248394 | T15: 20051683 | U15: 11390924 | V15: 18393452 | W15: 16185528 | X15: 24895132 | Y15: 10961179 | Z15: 5096520.3 | AA15: 27029609 | AB15: 3271931.3 | AC15: 19802617 | AD15: 4950818.8 | AE15: 14017525 | AF15: 7586630.2 | AG15: 16004291 | AH15: 31352464 | AI15: 10808520 | AJ15: 9876472.9 | AK15: 13758486 | AL15: 10393897 | AM15: 17547839 | AN15: 2756717 | AO15: 19190243 | AP15: 9892271.9 | AQ15: 13391133 | AR15: 7140130.6 | AS15: 5763960.2 | AT15: 5462877.5 | AU15: 7406962.8 | AV15: 5964295.8 | AW15: 10976752 | AX15: 15742683 | AY15: 14803214 | AZ15: 11293157 | BA15: 1.1355965e+08 | BB15: 23481192 | BC15: 5988472.4 | BD15: 7296659.2 | BE15: 8768260.8 | BF15: 16387597 | BG15: 4352460 | BH15: 10787747 | BI15: 9756532.2 | BJ15: 2948677.8 | BK15: 5148594.8 | BL15: 18629148 | BM15: 8856549 | BN15: 14911780 | BO15: 28559272 | BP15: 20549757 | BQ15: 6572747.3 | BR15: 65759635 | BS15: 17929962 | BT15: 11158375 | BU15: 3591048.9 | BV15: 7211398.2 | BW15: 41718111 | BX15: 5771636 | BY15: 7534001 | BZ15: 25730486 | CB15: KStA
B16: Abschreibungen | C16: =SUM(D16:BZ16) -> 3942852.1 | D16: 318598.67 | E16: 140790.54 | F16: -1770.1011 | G16: 18856.697 | H16: 1867.4827 | I16: 138776.9 | J16: 17573.546 | K16: -2025.2424 | L16: 163.27149 | M16: 431.53156 | N16: -4980.1646 | O16: 53317.985 | P16: 125665.7 | Q16: 24735.072 | R16: 19026.874 | S16: 113909.42 | T16: 143052.88 | U16: 28924.602 | V16: 36849.399 | W16: -20634.456 | X16: 354026.17 | Y16: 112129.22 | Z16: 15553.522 | AA16: 138859.94 | AB16: 21235.847 | AC16: 21487.378 | AD16: 36530.545 | AE16: 22861.57 | AF16: 12050.883 | AG16: 56217.182 | AH16: 82844.695 | AI16: -18010.612 | AJ16: 57498.277 | AK16: 44219.183 | AL16: 11818.521 | AM16: 62484.553 | AN16: 14326.347 | AO16: 12044.242 | AP16: 21525.99 | AQ16: -42704.048 | AR16: 55030.792 | AS16: 4293.1551 | AT16: 29848.971 | AU16: -7111.9984 | AV16: 44221.639 | AW16: 25065.182 | AX16: 53970.632 | AY16: 66331.2 | AZ16: 2468.6273 | BA16: 269955.62 | BB16: 26147.741 | BC16: 46891.341 | BD16: 10665.127 | BE16: 36743.062 | BF16: 198054.63 | BG16: 8578.5273 | BH16: 117743.62 | BI16: 50548.78 | BJ16: -4337.9978 | BK16: -3134.1263 | BL16: 36582.52 | BM16: 20123.296 | BN16: 33063.79 | BO16: 134062.7 | BP16: -4501.656 | BQ16: 26535.518 | BR16: 352652.73 | BS16: 11292.781 | BT16: -5290.3104 | BU16: -3070.0514 | BV16: 3059.5127 | BW16: 8766.8556 | BX16: 19928.853 | BY16: 12235.964 | BZ16: 75305.1 | CB16: KStA
B17: Einfache Steuer Netto | C17: =SUM(D17:BZ17) -> 1.2631462e+09 | D17: =D15-D16 -> 1.87498e+08 | E17: =E15-E16 -> 19659210 | F17: =F15-F16 -> 3127983.2 | G17: =G15-G16 -> 2586318.1 | H17: =H15-H16 -> 16742628 | I17: =I15-I16 -> 24054242 | J17: =J15-J16 -> 8367190.9 | K17: =K15-K16 -> 3329029.7 | ... BZ17: =BZ15-BZ16 -> 25655181
B19: Effektiver Nettoertrag | C19: =SUM(D19:BZ19) -> 1.4055204e+09 | D19: =D17*D13 -> 2.6437218e+08 | E19: =E17*E13 -> 25163789 | F19: =F17*F13 -> 3597180.6 | G19: =G17*G13 -> 3181171.3 | H19: =H17*H13 -> 11719839 | I19: =I17*I13 -> 21889360 | J19: =J17*J13 -> 9622269.5 | K19: =K17*K13 -> 4194577.4 | ... BZ19: =BZ17*BZ13 -> 26424836
B21: Standardisierter Ertrag | C21: =C17*$C13 -> 1.4055204e+09 | D21: =D17*$C13 -> 2.0863164e+08 | E21: =E17*$C13 -> 21875078 | F21: =F17*$C13 -> 3480550.6 | G21: =G17*$C13 -> 2877832.3 | H21: =H17*$C13 -> 18629756 | I21: =I17*$C13 -> 26765491 | J21: =J17*$C13 -> 9310290.2 | ... BZ21: =BZ17*$C13 -> 28546878
A23: 1.2) | B23: Quellensteuer
B24: Bruttoertrag | C24: =SUM(D24:BZ24) -> 82950711 | D24: 18214414 | E24: 767948.5 | F24: 128214.6 | G24: 85545.55 | H24: 137404.45 | I24: 1024789.2 | J24: 711553.25 | K24: 46262.6 | L24: 88988.15 | M24: 39011.85 | N24: 79487.4 | O24: 717111.65 | P24: 2809546.4 | Q24: 1727923.3 | R24: 564122.2 | S24: 2725295.1 | T24: 3547114.6 | U24: 817150.1 | V24: 2483401.5 | W24: 2534747.4 | X24: 1848314.3 | Y24: 878233.9 | Z24: 255185.1 | AA24: 3218999.4 | AB24: 129489.8 | AC24: 2041284.5 | AD24: 585796.1 | AE24: 3004467.5 | AF24: 423932.1 | AG24: 1539153.2 | AH24: 3638836.4 | AI24: 1041571.8 | AJ24: 864215.4 | AK24: 954139.2 | AL24: 411306.5 | AM24: 1328461.2 | AN24: 268129.1 | AO24: 680631 | AP24: 525359.3 | AQ24: 500568.1 | AR24: 272907.5 | AS24: 48104.95 | AT24: 69418.3 | AU24: 350006.5 | AV24: 204220.55 | AW24: 305058.85 | AX24: 307735.85 | AY24: 836155.1 | AZ24: 379688.5 | BA24: 2671301.4 | BB24: 772740.4 | BC24: 376945.95 | BD24: 149964.1 | BE24: 212955.25 | BF24: 654324.2 | BG24: 257966.5 | BH24: 323213.55 | BI24: 397504.25 | BJ24: 112673.9 | BK24: 89681.3 | BL24: 1388914.3 | BM24: 348502.7 | BN24: 464482.9 | BO24: 1756378 | BP24: 926999.55 | BQ24: 314616.95 | BR24: 2715752.7 | BS24: 216475.5 | BT24: 300449.8 | BU24: 86070.4 | BV24: 97882.2 | BW24: 1533549.8 | BX24: 78972.85 | BY24: 192967.45 | BZ24: 348022.85 | CB24: KStA
B25: Abschreibungen | C25: =SUM(D25:BZ25) -> 545968.24 | D25: 113012.77 | E25: 712.25 | F25: 806.85 | G25: 18.3 | H25: -5.7 | I25: 4411.75 | J25: 275.8 | K25: 24.5 | L25: 5517.8 | M25: 0.2 | N25: 8.8 | O25: 9514.75 | P25: 60608.29 | Q25: 19625.85 | R25: 3064.05 | S25: 35321.5 | T25: 43660.9 | U25: 32.8 | V25: 1227.85 | W25: 1575.9 | X25: 10444.52 | Y25: 5697.07 | Z25: 5957.5 | AA25: 11615.95 | AB25: 1033.37 | AC25: 6641.35 | AD25: 1703.65 | AE25: 1418.4 | AF25: 624.05 | AG25: 5697.64 | AH25: -4113.36 | AI25: 8664.1 | AJ25: 5504.14 | AK25: 56.56 | AL25: 1085.2 | AM25: 90.85 | AN25: 14.1 | AO25: 83.56 | AP25: 577.25 | AQ25: 1255.1 | AR25: 426.72 | AS25: 15.2 | AT25: 49.2 | AU25: 2745.55 | AV25: 12257.5 | AW25: 1177.45 | AX25: 1161.45 | AY25: 6586.53 | AZ25: 969.1 | BA25: 17614.35 | BB25: 6435.15 | BC25: 6915.9 | BD25: 17.95 | BE25: -2482.75 | BF25: 5522.66 | BG25: 2228.15 | BH25: 2255.35 | BI25: 57.35 | BJ25: 2222.8 | BK25: -1.75 | BL25: 470.7 | BM25: 1599.7 | BN25: 5544.15 | BO25: 38653.5 | BP25: 12374.4 | BQ25: 5760.4 | BR25: 36568.15 | BS25: 1784.87 | BT25: 758.8 | BU25: 0.15 | BV25: 6.6 | BW25: 11392.55 | BX25: 0.7 | BY25: 24.2 | BZ25: 1389.3 | CB25: KStA
B26: Nettoertrag (standardisierter Ertrag) | C26: =SUM(D26:BZ26) -> 82404742 | D26: =D24-D25 -> 18101401 | E26: =E24-E25 -> 767236.25 | F26: =F24-F25 -> 127407.75 | G26: =G24-G25 -> 85527.25 | H26: =H24-H25 -> 137410.15 | I26: =I24-I25 -> 1020377.4 | J26: =J24-J25 -> 711277.45 | K26: =K24-K25 -> 46238.1 | ... BZ26: =BZ24-BZ25 -> 346633.55
A28: 1.3) | B28: Gewinn- und Kapitalsteuer
B29: Bruttoertrag | C29: =SUM(D29:BZ29) -> 1.9263074e+08 | D29: 46167167 | E29: 1799044.9 | F29: 86881.1 | G29: 82643.4 | H29: 933177.85 | I29: 4440128.5 | J29: 763591.25 | K29: 66774.5 | L29: 430521.5 | M29: 66295.05 | N29: 147587.8 | O29: 1292065.9 | P29: 3598272.9 | Q29: 2409781.5 | R29: 781763.65 | S29: 2415120.8 | T29: 3138606.5 | U29: 1327749.9 | V29: 6295768.5 | W29: 2532743.5 | X29: 5899597.7 | Y29: 1413486.8 | Z29: 309224.1 | AA29: 4023815.7 | AB29: 35581.35 | AC29: 2926196 | AD29: 869261.95 | AE29: 5815538 | AF29: 506444.2 | AG29: 1106448.6 | AH29: 8026595.8 | AI29: 649779.5 | AJ29: 1008695.5 | AK29: 1256394.3 | AL29: 1444471.1 | AM29: 1558893.1 | AN29: 81645.3 | AO29: 1647552.3 | AP29: 939580.95 | AQ29: 650040.1 | AR29: 339327.95 | AS29: 201455.65 | AT29: 161260.6 | AU29: 495522.55 | AV29: 549249 | AW29: 594883.15 | AX29: 549447.25 | AY29: 2308572 | AZ29: 1534688.9 | BA29: 20844124 | BB29: 1850937.8 | BC29: 266542.05 | BD29: 461028.05 | BE29: 1327700.8 | BF29: 2042882.2 | BG29: 335054.7 | BH29: 387567.05 | BI29: 1114184.6 | BJ29: 112486.85 | BK29: 322178.65 | BL29: 2066831.1 | BM29: 1109957.6 | BN29: 875257.6 | BO29: 3483388 | BP29: 2298281.9 | BQ29: 1732285 | BR29: 14473712 | BS29: 946673.8 | BT29: 2490776.7 | BU29: 76828.7 | BV29: 244459.65 | BW29: 6679776.8 | BX29: 257005.15 | BY29: 615399.65 | BZ29: 536085.4 | CB29: KStA
B30: Abschreibungen | C30: =SUM(D30:BZ30) -> 1363211 | D30: 446047.4 | E30: 1946.75 | F30: 52.45 | G30: 34.05 | H30: 1588.85 | I30: 17672.95 | J30: 284.25 | K30: 18.4 | L30: 77.45 | M30: 66.85 | N30: 107.55 | O30: 3120.65 | P30: 53032.75 | Q30: 9801.65 | R30: 3309.15 | S30: 8914.55 | T30: 153523.25 | U30: 1606.55 | V30: 17431.5 | W30: 15099.4 | X30: 35451.85 | Y30: 1264 | Z30: 3218.6 | AA30: 8893.65 | AB30: 2399.95 | AC30: 78856.55 | AD30: 1114.85 | AE30: 7934 | AF30: 345.55 | AG30: 5538.55 | AH30: 52374 | AI30: 13049.25 | AJ30: 3191.75 | AK30: 2634.1 | AL30: 1761.3 | AM30: 2029.2 | AN30: 1332 | AO30: 7139.35 | AP30: 369.8 | AQ30: 1095.35 | AR30: 874.5 | AS30: 4443.65 | AT30: 99.7 | AU30: 452.15 | AV30: 36027.8 | AW30: 13637.15 | AX30: 1395.6 | AY30: 107881.75 | AZ30: 406.85 | BA30: 15212.7 | BB30: 1783.8 | BC30: 1820.25 | BD30: 3900.55 | BE30: 4557.75 | BF30: 8477.65 | BG30: 364.95 | BH30: 38426.75 | BI30: 3435.05 | BJ30: 200.1 | BK30: 64.6 | BL30: 1288.7 | BM30: 4975.5 | BN30: 23782.55 | BO30: 4109.85 | BP30: 14552.7 | BQ30: 846.7 | BR30: 70024.3 | BS30: 2060.95 | BT30: 2112.6 | BU30: 80.6 | BV30: 90 | BW30: 31296.65 | BX30: 38.1 | BY30: 251.4 | BZ30: 507.05 | CB30: KStA
B31: pauschale Steueranrechnung | C31: =SUM(D31:BZ31) -> 672651.9 | D31: 12611.6 | E31: 1395.15 | F31: 0 | G31: 0 | H31: 6989 | I31: 0 | J31: 0 | K31: 0 | L31: 0 | M31: 0 | N31: 0 | O31: 0 | P31: 179.65 | Q31: 0 | R31: 0 | S31: 0 | T31: 0 | U31: 452.35 | V31: 549965.4 | W31: 0 | X31: 5623.7 | Y31: 0 | Z31: 0 | AA31: 0 | AB31: 0 | AC31: 0 | AD31: 0 | AE31: 0 | AF31: 0 | AG31: 0 | AH31: 0 | AI31: 0 | AJ31: 0 | AK31: 0 | AL31: 0 | AM31: 0 | AN31: 0 | AO31: 0 | AP31: 0 | AQ31: 0 | AR31: 0 | AS31: 0 | AT31: 0 | AU31: 0 | AV31: 0 | AW31: 0 | AX31: 0 | AY31: 0 | AZ31: 0 | BA31: 79731.3 | BB31: 0 | BC31: 0 | BD31: 0 | BE31: 0 | BF31: 0 | BG31: 0 | BH31: 0 | BI31: 0 | BJ31: 0 | BK31: 0 | BL31: 0 | BM31: 0 | BN31: 0 | BO31: 0 | BP31: 14861.45 | BQ31: 0 | BR31: 0 | BS31: 0 | BT31: 0 | BU31: 0 | BV31: 0 | BW31: 842.3 | BX31: 0 | BY31: 0 | BZ31: 0 | CB31: KStA
B32: Nettoertrag (standardisierter Ertrag) | C32: =SUM(D32:BZ32) -> 1.9059488e+08 | D32: =D29-D30-D31 -> 45708508 | E32: =E29-E30-E31 -> 1795703 | F32: =F29-F30-F31 -> 86828.65 | G32: =G29-G30-G31 -> 82609.35 | H32: =H29-H30-H31 -> 924600 | I32: =I29-I30-I31 -> 4422455.6 | J32: =J29-J30-J31 -> 763307 | K32: =K29-K30-K31 -> 66756.1 | ... BZ32: =BZ29-BZ30-BZ31 -> 535578.35
A34: 1.4) | B34: Grundsteuer (ord. Satz)
B35: Steuersatz in ‰ | C35: =C39/C41 -> 0.68623685 | D35: 0.8 | E35: 0.8 | F35: 0.8 | G35: 0.8 | H35: 0.2 | I35: 0.4 | J35: 0.6 | K35: 0.3 | L35: 0.2 | M35: 0.8 | N35: 0.8 | O35: 0.8 | P35: 0.8 | Q35: 0.4 | R35: 0.8 | S35: 0.8 | T35: 0.4 | U35: 0.8 | V35: 0.5 | W35: 0.5 | X35: 0.8 | Y35: 0.7 | Z35: 0.8 | AA35: 0.8 | AB35: 0.8 | AC35: 0.8 | AD35: 0.8 | AE35: 0.8 | AF35: 0.8 | AG35: 0.8 | AH35: 0.7 | AI35: 0.8 | AJ35: 0.7 | AK35: 0.8 | AL35: 0.8 | AM35: 0.8 | AN35: 0.8 | AO35: 0.8 | AP35: 0.8 | AQ35: 0.8 | AR35: 0.8 | AS35: 0.8 | AT35: 0.8 | AU35: 0.8 | AV35: 0.8 | AW35: 0.8 | AX35: 0.8 | AY35: 0.8 | AZ35: 0.8 | BA35: 0.3 | BB35: 0.8 | BC35: 0.8 | BD35: 0.8 | BE35: 0.8 | BF35: 0.8 | BG35: 0.8 | BH35: 0.8 | BI35: 0.6 | BJ35: 0.8 | BK35: 0.5 | BL35: 0.8 | BM35: 0.6 | BN35: 0.8 | BO35: 0.6 | BP35: 0.8 | BQ35: 0.8 | BR35: 0.6 | BS35: 0.4 | BT35: 0.3 | BU35: 0.8 | BV35: 0.4 | BW35: 0.6 | BX35: 0.6 | BY35: 0.8 | BZ35: 0.8 | CB35: KStA/Gemeinden
B37: Bruttoertrag | C37: =SUM(D37:BZ37) -> 1.0333655e+08 | D37: 19085491 | E37: 1832609.4 | F37: 298303.1 | G37: 242743.95 | H37: 278485.6 | I37: 1090729.9 | J37: 655906 | K37: 80593.85 | L37: 110781 | M37: 230643.9 | N37: 475693.65 | O37: 1690738.8 | P37: 1855456.6 | Q37: 893512.1 | R37: 684173.95 | S37: 1428215.1 | T37: 952514.3 | U37: 987760.22 | V37: 832481.75 | W37: 1025995.5 | X37: 2586124 | Y37: 819382.92 | Z37: 443822.7 | AA37: 2639182.5 | AB37: 327266.56 | AC37: 2099310.2 | AD37: 568730.22 | AE37: 1562053.3 | AF37: 725417.45 | AG37: 1470721.6 | AH37: 2648500 | AI37: 1045815.8 | AJ37: 940561.5 | AK37: 1304820.8 | AL37: 1126258.1 | AM37: 1798957.3 | AN37: 439520.47 | AO37: 2107271.2 | AP37: 1304555.7 | AQ37: 1235368.2 | AR37: 1014942.4 | AS37: 556772.7 | AT37: 447628 | AU37: 776963.62 | AV37: 607312 | AW37: 935317.05 | AX37: 1387082.1 | AY37: 1499702.5 | AZ37: 983601.43 | BA37: 3165806 | BB37: 2279946.6 | BC37: 880430.65 | BD37: 694711.45 | BE37: 963323.25 | BF37: 1671666.6 | BG37: 356900.85 | BH37: 1035841.1 | BI37: 725891.95 | BJ37: 287068.19 | BK37: 309526.68 | BL37: 1959128.9 | BM37: 772391 | BN37: 1263500.6 | BO37: 2078386.1 | BP37: 1836111.8 | BQ37: 700362.8 | BR37: 4235361.2 | BS37: 644060.4 | BT37: 426151.55 | BU37: 320542.64 | BV37: 331262.15 | BW37: 3200069 | BX37: 331204.72 | BY37: 739523.04 | BZ37: 1991584.1 | CB37: Gemeinden
B38: Erlasse/Verluste | C38: =SUM(D38:BZ38) -> 2871.4 | D38: 0 | E38: 0 | F38: 0 | G38: 0 | H38: 0 | I38: 0 | J38: 0 | K38: 0 | L38: 0 | M38: 0 | N38: 0 | O38: 0 | P38: 0 | Q38: 0 | R38: 0 | S38: 0 | T38: 0 | U38: 0 | V38: 10.7 | W38: 0 | X38: 0 | Y38: 0 | Z38: 0 | AA38: 0 | AB38: 0 | AC38: 311.15 | AD38: 0 | AE38: 0 | AF38: 0 | AG38: 0 | AH38: 0 | AI38: 0 | AJ38: 0 | AK38: 0 | AL38: 0 | AM38: 0 | AN38: 0 | AO38: 0 | AP38: 0.23 | AQ38: -8.4 | AR38: 0 | AS38: 0 | AT38: 0 | AU38: 0 | AV38: 0 | AW38: 0 | AX38: 0 | AY38: 0 | AZ38: 0.95 | BA38: 0 | BB38: 0 | BC38: 0 | BD38: 1.5 | BE38: 0 | BF38: 0 | BG38: 0 | BH38: 0 | BI38: 0 | BJ38: 0 | BK38: 41.19 | BL38: 108.03 | BM38: 0 | BN38: 0 | BO38: 1823 | BP38: 583.05 | BQ38: 0 | BR38: 0 | BS38: 0 | BT38: 0 | BU38: 0 | BV38: 0 | BW38: 0 | BX38: 0 | BY38: 0 | BZ38: 0 | CB38: Gemeinden
B39: Nettoertrag | C39: =SUM(D39:BZ39) -> 1.0333367e+08 | D39: =D37-D38 -> 19085491 | E39: =E37-E38 -> 1832609.4 | F39: =F37-F38 -> 298303.1 | G39: =G37-G38 -> 242743.95 | H39: =H37-H38 -> 278485.6 | I39: =I37-I38 -> 1090729.9 | J39: =J37-J38 -> 655906 | K39: =K37-K38 -> 80593.85 | ... BZ39: =BZ37-BZ38 -> 1991584.1
B41: Ertrag bei Satz von 1‰ | C41: =SUM(D41:BZ41) -> 1.5058019e+08 | D41: =D39/D35 -> 23856863 | E41: =E39/E35 -> 2290761.8 | F41: =F39/F35 -> 372878.87 | G41: =G39/G35 -> 303429.94 | H41: =H39/H35 -> 1392428 | I41: =I39/I35 -> 2726824.7 | J41: =J39/J35 -> 1093176.7 | K41: =K39/K35 -> 268646.17 | ... BZ41: =BZ39/BZ35 -> 2489480.2
B43: Standardisierter Ertrag | C43: =C41*$C35 -> 1.0333367e+08 | D43: =D41*$C35 -> 16371459 | E43: =E41*$C35 -> 1572005.2 | F43: =F41*$C35 -> 255883.23 | G43: =G41*$C35 -> 208224.81 | H43: =H41*$C35 -> 955535.41 | I43: =I41*$C35 -> 1871247.6 | J43: =J41*$C35 -> 750178.12 | ... BZ43: =BZ41*$C35 -> 1708373.1
A45: 1.5) | B45: Grundsteuer (Spezialsatz)
B46: Bruttoertrag | C46: =SUM(D46:BZ46) -> 1630051.2 | D46: 339501.63 | E46: 31977.08 | F46: 3326.5 | G46: 2921.6 | H46: 10930.4 | I46: 16285.84 | J46: 14374 | K46: 1878.3 | L46: 0 | M46: 2843.15 | N46: 6184.3 | O46: 17053.2 | P46: 37120.6 | Q46: 23900.5 | R46: 12555.95 | S46: 13203.52 | T46: 29035.09 | U46: 7458.6 | V46: 11143.4 | W46: 21788.44 | X46: 20549.95 | Y46: 7968.2 | Z46: 3863.04 | AA46: 42924.98 | AB46: 2200 | AC46: 25820.27 | AD46: 4020.62 | AE46: 27408.15 | AF46: 7667.8 | AG46: 44157.05 | AH46: 33433 | AI46: 9619.2 | AJ46: 11965.55 | AK46: 12319.75 | AL46: 9797.75 | AM46: 11665.5 | AN46: 25600.94 | AO46: 27212.95 | AP46: 11985.38 | AQ46: 11991.8 | AR46: 184.2 | AS46: 5690.15 | AT46: 6231 | AU46: 6864.64 | AV46: 6029 | AW46: 8935.25 | AX46: 11471 | AY46: 25841.94 | AZ46: 13783.6 | BA46: 105516.6 | BB46: 22402.69 | BC46: 8108.2 | BD46: 19866.85 | BE46: 14631.22 | BF46: 30194.25 | BG46: 4183.55 | BH46: 22689.6 | BI46: 17348.7 | BJ46: 919.57 | BK46: 10660.26 | BL46: 30306.66 | BM46: 8419 | BN46: 15453.7 | BO46: 32753.2 | BP46: 27197.45 | BQ46: 12695.25 | BR46: 102501.85 | BS46: 8751.25 | BT46: 10761.95 | BU46: 1268.4 | BV46: 8016.65 | BW46: 32040 | BX46: 5595.4 | BY46: 12916.96 | BZ46: 24167.25 | CB46: Gemeinden
B47: Erlasse/Verluste | C47: =SUM(D47:BZ47) -> 12.11 | D47: 0 | E47: 0 | F47: 0 | G47: 0 | H47: 0 | I47: 0 | J47: 0.2 | K47: 0 | L47: 0 | M47: 0 | N47: 0 | O47: 0 | P47: 0 | Q47: 0 | R47: 0 | S47: 0 | T47: 0 | U47: 0 | V47: 0 | W47: 0 | X47: 0 | Y47: 0 | Z47: 0 | AA47: 0 | AB47: 0 | AC47: 0 | AD47: 0 | AE47: 0 | AF47: 0 | AG47: 0 | AH47: 0 | AI47: 0 | AJ47: 0 | AK47: 0 | AL47: 0 | AM47: 0 | AN47: 0 | AO47: 0 | AP47: 0 | AQ47: 0 | AR47: 0 | AS47: 0 | AT47: 0 | AU47: 0 | AV47: 0 | AW47: 0 | AX47: 0 | AY47: 0 | AZ47: 0 | BA47: 0 | BB47: 0 | BC47: 0 | BD47: 0 | BE47: 0 | BF47: 0 | BG47: 0 | BH47: 0 | BI47: 0 | BJ47: 0 | BK47: 0 | BL47: 11.71 | BM47: 0 | BN47: 0 | BO47: 0 | BP47: 0 | BQ47: 0 | BR47: 0 | BS47: 0 | BT47: 0 | BU47: 0 | BV47: 0 | BW47: 0 | BX47: 0.2 | BY47: 0 | BZ47: 0 | CB47: Gemeinden
B48: Nettoertrag (standardisierter Ertrag) | C48: =SUM(D48:BZ48) -> 1630039.1 | D48: =D46-D47 -> 339501.63 | E48: =E46-E47 -> 31977.08 | F48: =F46-F47 -> 3326.5 | G48: =G46-G47 -> 2921.6 | H48: =H46-H47 -> 10930.4 | I48: =I46-I47 -> 16285.84 | J48: =J46-J47 -> 14373.8 | K48: =K46-K47 -> 1878.3 | ... BZ48: =BZ46-BZ47 -> 24167.25
A50: 1.6) | B50: Handänderungssteuer
B51: Bruttoertrag | C51: =SUM(D51:BZ51) -> 59811726 | D51: 10387286 | E51: 912441.64 | F51: 185351.85 | G51: 86210.44 | H51: 600536.95 | I51: 930406 | J51: 234393 | K51: 29776 | L51: 60475 | M51: 78724.75 | N51: 341357.5 | O51: 1437093.7 | P51: 1368530.9 | Q51: 1308723.4 | R51: 208071.5 | S51: 1126899.8 | T51: 862486.84 | U51: 535210.24 | V51: 533677.95 | W51: 398843.6 | X51: 968996.8 | Y51: 468125.79 | Z51: 166423.67 | AA51: 1265992.4 | AB51: 161970 | AC51: 497524.99 | AD51: 325591.33 | AE51: 865209.3 | AF51: 367587.8 | AG51: 597556.45 | AH51: 1624695 | AI51: 284900.7 | AJ51: 824728.9 | AK51: 740033.5 | AL51: 399609 | AM51: 1042034.8 | AN51: 121047.9 | AO51: 1493596.9 | AP51: 831892.61 | AQ51: 327902.03 | AR51: 447439.4 | AS51: 270893.85 | AT51: 152915 | AU51: 553171.2 | AV51: 367129.1 | AW51: 304323.8 | AX51: 761999.5 | AY51: 425033.39 | AZ51: 136149.95 | BA51: 3326250.7 | BB51: 1308917.5 | BC51: 291165.4 | BD51: 270517.48 | BE51: 571905.85 | BF51: 1153720.9 | BG51: 220128.65 | BH51: 433491.3 | BI51: 701451.25 | BJ51: 193302.71 | BK51: 204503.55 | BL51: 1398569.2 | BM51: 319742 | BN51: 745478.55 | BO51: 1577461.6 | BP51: 496148 | BQ51: 252982.75 | BR51: 2834887.4 | BS51: 671883.3 | BT51: 718516.3 | BU51: 113448.67 | BV51: 442705.15 | BW51: 1926176 | BX51: 133294.62 | BY51: 198180.18 | BZ51: 885924.09 | CB51: Gemeinden
B52: Erlasse/Verluste | C52: =SUM(D52:BZ52) -> 0 | D52: 0 | E52: 0 | F52: 0 | G52: 0 | H52: 0 | I52: 0 | J52: 0 | K52: 0 | L52: 0 | M52: 0 | N52: 0 | O52: 0 | P52: 0 | Q52: 0 | R52: 0 | S52: 0 | T52: 0 | U52: 0 | V52: 0 | W52: 0 | X52: 0 | Y52: 0 | Z52: 0 | AA52: 0 | AB52: 0 | AC52: 0 | AD52: 0 | AE52: 0 | AF52: 0 | AG52: 0 | AH52: 0 | AI52: 0 | AJ52: 0 | AK52: 0 | AL52: 0 | AM52: 0 | AN52: 0 | AO52: 0 | AP52: 0 | AQ52: 0 | AR52: 0 | AS52: 0 | AT52: 0 | AU52: 0 | AV52: 0 | AW52: 0 | AX52: 0 | AY52: 0 | AZ52: 0 | BA52: 0 | BB52: 0 | BC52: 0 | BD52: 0 | BE52: 0 | BF52: 0 | BG52: 0 | BH52: 0 | BI52: 0 | BJ52: 0 | BK52: 0 | BL52: 0 | BM52: 0 | BN52: 0 | BO52: 0 | BP52: 0 | BQ52: 0 | BR52: 0 | BS52: 0 | BT52: 0 | BU52: 0 | BV52: 0 | BW52: 0 | BX52: 0 | BY52: 0 | BZ52: 0 | CB52: Gemeinden
B53: Nettoertrag (standardisierter Ertrag) | C53: =SUM(D53:BZ53) -> 59811726 | D53: =D51-D52 -> 10387286 | E53: =E51-E52 -> 912441.64 | F53: =F51-F52 -> 185351.85 | G53: =G51-G52 -> 86210.44 | H53: =H51-H52 -> 600536.95 | I53: =I51-I52 -> 930406 | J53: =J51-J52 -> 234393 | K53: =K51-K52 -> 29776 | ... BZ53: =BZ51-BZ52 -> 885924.09
A55: 1.7) | B55: Grundstückgewinnsteuer
B56: Bruttoertrag | C56: =SUM(D56:BZ56) -> 93028694 | D56: 14503679 | E56: 2194477.7 | F56: 206264.6 | G56: 304945.25 | H56: 1345683.6 | I56: 1325581.4 | J56: 378262.05 | K56: 118967.6 | L56: 288846 | M56: 132502.9 | N56: 680006.85 | O56: 974320.15 | P56: 566986.8 | Q56: 1346172 | R56: 512265.8 | S56: 1549933.8 | T56: 962845.6 | U56: 1081536.1 | V56: 1171300.6 | W56: 854594.35 | X56: 1749470.3 | Y56: 334138.65 | Z56: 392702.9 | AA56: 1854608.9 | AB56: 329099.65 | AC56: 1775127.9 | AD56: 1039953.4 | AE56: 807322.65 | AF56: 756713.75 | AG56: 1302279.4 | AH56: 1460649.6 | AI56: 520668.05 | AJ56: 715527.15 | AK56: 1335660.9 | AL56: 893285.2 | AM56: 2160312.5 | AN56: 48691.9 | AO56: 1190608.1 | AP56: 1167545.2 | AQ56: 747369 | AR56: 588733.55 | AS56: 569198.75 | AT56: 310365.15 | AU56: 616133.8 | AV56: 634761.55 | AW56: 513879.6 | AX56: 1195158.4 | AY56: 635047.95 | AZ56: 414650.8 | BA56: 9785081.9 | BB56: 1860856.6 | BC56: 751230.15 | BD56: 586253.5 | BE56: 840518.8 | BF56: 1345998.8 | BG56: 627217.6 | BH56: 579351 | BI56: 1135127.1 | BJ56: 182921.35 | BK56: 459970.9 | BL56: 1389210.1 | BM56: 550889.65 | BN56: 1252614.2 | BO56: 1794937.2 | BP56: 1306155.1 | BQ56: 244665.4 | BR56: 3419985.5 | BS56: 1289067.2 | BT56: 1428421.4 | BU56: 122269.65 | BV56: 511258.8 | BW56: 3049380.1 | BX56: 199617.2 | BY56: 608478.9 | BZ56: 1148378.6 | CB56: KStA
B57: Abschreibungen | C57: =SUM(D57:BZ57) -> 3924.45 | D57: 68.8 | E57: 43.75 | F57: 8.75 | G57: 1.55 | H57: 0 | I57: 18.05 | J57: 5.6 | K57: 0 | L57: 0 | M57: 2.5 | N57: 0.15 | O57: 4.15 | P57: 10.75 | Q57: 16.6 | R57: 0.3 | S57: 20.65 | T57: 33.3 | U57: 19.2 | V57: 2.95 | W57: 0 | X57: 15.9 | Y57: 6.4 | Z57: 16.8 | AA57: 11.05 | AB57: 0.05 | AC57: 2.05 | AD57: 3.95 | AE57: 2.9 | AF57: 21.05 | AG57: 19.4 | AH57: 5.4 | AI57: 0 | AJ57: 25.15 | AK57: 41.6 | AL57: 14.5 | AM57: 0 | AN57: 0 | AO57: 40.65 | AP57: 30.4 | AQ57: 9.45 | AR57: -31.95 | AS57: 269.3 | AT57: 2.9 | AU57: 5.55 | AV57: 0 | AW57: 0 | AX57: 3.2 | AY57: 4.2 | AZ57: 0 | BA57: 4.2 | BB57: 1918.35 | BC57: 0 | BD57: 2.1 | BE57: 5.5 | BF57: 6 | BG57: 17.2 | BH57: 4.3 | BI57: 27 | BJ57: 17.55 | BK57: 4.35 | BL57: 11.5 | BM57: 16.6 | BN57: 3.7 | BO57: 25.45 | BP57: 0 | BQ57: 0 | BR57: 18.65 | BS57: 22.2 | BT57: 89.8 | BU57: 0 | BV57: 1.65 | BW57: 906.65 | BX57: 15.2 | BY57: 0 | BZ57: 29.55 | CB57: KStA
B58: Nettoertrag (standardisierter Ertrag) | C58: =SUM(D58:BZ58) -> 93024770 | D58: =D56-D57 -> 14503610 | E58: =E56-E57 -> 2194434 | F58: =F56-F57 -> 206255.85 | G58: =G56-G57 -> 304943.7 | H58: =H56-H57 -> 1345683.6 | I58: =I56-I57 -> 1325563.3 | J58: =J56-J57 -> 378256.45 | K58: =K56-K57 -> 118967.6 | ... BZ58: =BZ56-BZ57 -> 1148349.1
A61: 2.) | B61: Steuerdaten 2022
A63: 2.1) | B63: Einkommens-/Vermögenssteuer
B64: Steuerfuss | C64: =C70/C68 -> 1.1243039 | D64: 1.41 | E64: 1.33 | F64: 1.15 | G64: 1.25 | H64: 0.7 | I64: 0.91 | J64: 1.15 | K64: 1.34 | L64: 0.79 | M64: 1.19 | N64: 1.25 | O64: 0.93 | P64: 1.29 | Q64: 0.89 | R64: 1.19 | S64: 1.04 | T64: 0.87 | U64: 0.95 | V64: 0.64 | W64: 0.81 | X64: 0.76 | Y64: 1.01 | Z64: 1.12 | AA64: 1.19 | AB64: 1.09 | AC64: 1.02 | AD64: 1.19 | AE64: 0.83 | AF64: 1.25 | AG64: 1 | AH64: 1.18 | AI64: 1.1 | AJ64: 1.55 | AK64: 1.39 | AL64: 1.29 | AM64: 0.92 | AN64: 1.42 | AO64: 1.33 | AP64: 1.3 | AQ64: 1.15 | AR64: 1.07 | AS64: 1.15 | AT64: 1.15 | AU64: 1.25 | AV64: 1.24 | AW64: 1.06 | AX64: 1.13 | AY64: 1.18 | AZ64: 1.16 | BA64: 0.74 | BB64: 1.21 | BC64: 1.23 | BD64: 1.19 | BE64: 1.39 | BF64: 1.32 | BG64: 1.33 | BH64: 1.3261832 | BI64: 1.19 | BJ64: 1.15 | BK64: 1.33 | BL64: 1.2 | BM64: 1.22 | BN64: 1.22 | BO64: 1.27 | BP64: 1.27 | BQ64: 1.5 | BR64: 1.18 | BS64: 0.77 | BT64: 1 | BU64: 1.26 | BV64: 1.09 | BW64: 1.16 | BX64: 1.18 | BY64: 1.22 | BZ64: 1.03 | CB64: KStA
B66: Einfache Steuer Brutto | C66: =SUM(D66:BZ66) -> 1.1902545e+09 | D66: 1.7793726e+08 | E66: 19316359 | F66: 2933025.9 | G66: 2420969.8 | H66: 18105400 | I66: 23000531 | J66: 7780504.7 | K66: 2622808.5 | L66: 5025347.2 | M66: 2562245.6 | N66: 5659882.1 | O66: 19553052 | P66: 15100952 | Q66: 17747608 | R66: 6117031.9 | S66: 9520282.7 | T66: 18585672 | U66: 10825368 | V66: 15928230 | W66: 15193209 | X66: 23014444 | Y66: 10989106 | Z66: 4653961.5 | AA66: 25188028 | AB66: 3113333 | AC66: 18854452 | AD66: 4536071.3 | AE66: 12879518 | AF66: 7264568.5 | AG66: 14869549 | AH66: 27897186 | AI66: 10186535 | AJ66: 9041280.2 | AK66: 12780475 | AL66: 9825335.1 | AM66: 16195523 | AN66: 2766584.7 | AO66: 17729054 | AP66: 9324708.2 | AQ66: 13199966 | AR66: 6804481.9 | AS66: 5438087.6 | AT66: 4911445.3 | AU66: 7006002.8 | AV66: 5760742.5 | AW66: 10048842 | AX66: 14524568 | AY66: 13877854 | AZ66: 10488854 | BA66: 1.0499052e+08 | BB66: 21794544 | BC66: 5699928 | BD66: 6675111.7 | BE66: 8961300.7 | BF66: 15740198 | BG66: 4083591.8 | BH66: 9688061.6 | BI66: 9179914.6 | BJ66: 2831819 | BK66: 4950854.4 | BL66: 17377483 | BM66: 8309001.3 | BN66: 13311682 | BO66: 25627360 | BP66: 19299356 | BQ66: 6611803.1 | BR66: 60066862 | BS66: 15740229 | BT66: 10446313 | BU66: 3261879.3 | BV66: 7303242.5 | BW66: 42135075 | BX66: 5251622.5 | BY66: 7779613.2 | BZ66: 24030824 | CB66: KStA
B67: Abschreibungen | C67: =SUM(D67:BZ67) -> 4194886.4 | D67: 784665.07 | E67: 177504.88 | F67: 3292.8569 | G67: 60.356522 | H67: -2026.8601 | I67: 99746.034 | J67: 45261.083 | K67: -2194.9439 | L67: -602.32891 | M67: -1038.4613 | N67: 455.87352 | O67: 22118.951 | P67: 211127.86 | Q67: 4199.2223 | R67: 37717.674 | S67: 173511.2 | T67: 167590.67 | U67: 11276.134 | V67: 36009.38 | W67: 64550.812 | X67: 66181.529 | Y67: 15146.811 | Z67: -7540.3174 | AA67: 148876.96 | AB67: 20580.127 | AC67: 28097.364 | AD67: 13601.951 | AE67: 50945.173 | AF67: 8716.83 | AG67: -4631.9654 | AH67: 95185.363 | AI67: 6756.6477 | AJ67: 31112.267 | AK67: 66508.613 | AL67: 39752.475 | AM67: 72283.144 | AN67: 7057.6596 | AO67: 49240.385 | AP67: 23906.046 | AQ67: 13734.739 | AR67: 40463.108 | AS67: 10069.887 | AT67: 641.32946 | AU67: -9372.8401 | AV67: 12952.014 | AW67: 38804.248 | AX67: 47066.889 | AY67: 226463.96 | AZ67: 11135.924 | BA67: 121917.33 | BB67: 63100.596 | BC67: 33764.398 | BD67: 13507.768 | BE67: 70521.99 | BF67: 155687.65 | BG67: 27794.726 | BH67: -24304.334 | BI67: 62770.077 | BJ67: -909.26838 | BK67: 8191.3814 | BL67: 94063.291 | BM67: 16892.237 | BN67: 29313.409 | BO67: 91406.516 | BP67: 56273.476 | BQ67: 44965.211 | BR67: 263472.55 | BS67: 13696.147 | BT67: 3309.6218 | BU67: 9512.4146 | BV67: -8342.7419 | BW67: 67695.052 | BX67: 18918.015 | BY67: -3799.1462 | BZ67: 8506.2186 | CB67: KStA
B68: Einfache Steuer Netto | C68: =SUM(D68:BZ68) -> 1.1860596e+09 | D68: =D66-D67 -> 1.7715259e+08 | E68: =E66-E67 -> 19138854 | F68: =F66-F67 -> 2929733 | G68: =G66-G67 -> 2420909.4 | H68: =H66-H67 -> 18107427 | I68: =I66-I67 -> 22900785 | J68: =J66-J67 -> 7735243.6 | K68: =K66-K67 -> 2625003.5 | ... BZ68: =BZ66-BZ67 -> 24022318
B70: Effektiver Nettoertrag | C70: =SUM(D70:BZ70) -> 1.3334915e+09 | D70: =D68*D64 -> 2.4978516e+08 | E70: =E68*E64 -> 25454676 | F70: =F68*F64 -> 3369192.9 | G70: =G68*G64 -> 3026136.8 | H70: =H68*H64 -> 12675199 | I70: =I68*I64 -> 20839714 | J70: =J68*J64 -> 8895530.1 | K70: =K68*K64 -> 3517504.6 | ... BZ70: =BZ68*BZ64 -> 24742988
B72: Standardisierter Ertrag | C72: =C68*$C64 -> 1.3334915e+09 | D72: =D68*$C64 -> 1.9917336e+08 | E72: =E68*$C64 -> 21517889 | F72: =F68*$C64 -> 3293910.4 | G72: =G68*$C64 -> 2721838 | H72: =H68*$C64 -> 20358252 | I72: =I68*$C64 -> 25747443 | J72: =J68*$C64 -> 8696764.9 | ... BZ72: =BZ68*$C64 -> 27008387
A74: 2.2) | B74: Quellensteuer
B75: Bruttoertrag | C75: =SUM(D75:BZ75) -> 71317459 | D75: 14919528 | E75: 597347.75 | F75: 80213.25 | G75: 63747.2 | H75: 121360.15 | I75: 797640.8 | J75: 612707.05 | K75: 52401.2 | L75: 59729.65 | M75: 22835.5 | N75: 50262.75 | O75: 579956.65 | P75: 2261526.2 | Q75: 1455152.5 | R75: 512132.9 | S75: 2349119.1 | T75: 2516161.4 | U75: 783239.7 | V75: 2319574.3 | W75: 1985428.8 | X75: 3206540.7 | Y75: 730926.5 | Z75: 234289 | AA75: 2818813.9 | AB75: 121408.4 | AC75: 1904305.9 | AD75: 496487.25 | AE75: 3066458.7 | AF75: 397864.65 | AG75: 1419930.7 | AH75: 3068758.1 | AI75: 985607.3 | AJ75: 751908.2 | AK75: 904449 | AL75: 340461.95 | AM75: 1081748.8 | AN75: 289160.55 | AO75: 529206.1 | AP75: 494450.25 | AQ75: 474693.9 | AR75: 256021.1 | AS75: 58217.1 | AT75: 52570 | AU75: 217897 | AV75: 187175.25 | AW75: 276029.6 | AX75: 260768.85 | AY75: 662984.45 | AZ75: 315810.95 | BA75: 2342977.1 | BB75: 646846.65 | BC75: 278191.2 | BD75: 97707.4 | BE75: 191505.8 | BF75: 462016.2 | BG75: 146883 | BH75: 266683.4 | BI75: 325994.25 | BJ75: 116559.7 | BK75: 68831.8 | BL75: 1507231.9 | BM75: 245644.2 | BN75: 447804.7 | BO75: 1282262 | BP75: 700144.1 | BQ75: 252974.65 | BR75: 1856859.8 | BS75: 131518.05 | BT75: 309879.7 | BU75: 83566.55 | BV75: 89027.15 | BW75: 1202780.5 | BX75: 47585.9 | BY75: 163757.7 | BZ75: 307216.45 | CB75: KStA
B76: Abschreibungen | C76: =SUM(D76:BZ76) -> 761087.46 | D76: -73370.65 | E76: 9576.35 | F76: 11.1 | G76: 2.3 | H76: 7 | I76: 3715.8 | J76: 6143.8 | K76: 59.35 | L76: 411.7 | M76: 329.35 | N76: 5.55 | O76: 6004.95 | P76: 42564 | Q76: 376208.3 | R76: 766.1 | S76: 15832.5 | T76: 3482.65 | U76: 3937.2 | V76: 11399.6 | W76: 103614.07 | X76: 14174.15 | Y76: 4638.15 | Z76: 266.95 | AA76: 24016.9 | AB76: 23.3 | AC76: 19116.75 | AD76: 130.75 | AE76: 175.73 | AF76: 445.7 | AG76: 15.35 | AH76: 2411.9 | AI76: 1820.95 | AJ76: 788.95 | AK76: 5713.25 | AL76: -1448.1 | AM76: 33.35 | AN76: 17.4 | AO76: 1946.64 | AP76: 9402.2 | AQ76: 2770.8 | AR76: 2228 | AS76: 9.45 | AT76: 1132.4 | AU76: 8601.75 | AV76: 2660.3 | AW76: 8777.75 | AX76: 2376.05 | AY76: 18457.8 | AZ76: 836.65 | BA76: 18555.21 | BB76: 6816.5 | BC76: 1994.55 | BD76: 60.55 | BE76: 5142.55 | BF76: 5271.15 | BG76: 1140.7 | BH76: 1082.75 | BI76: 1843.2 | BJ76: 84.35 | BK76: 29.4 | BL76: 4016.65 | BM76: 125.15 | BN76: 10024.41 | BO76: 21332.8 | BP76: 6834.1 | BQ76: 1736.45 | BR76: 24271.55 | BS76: 555.1 | BT76: 6.45 | BU76: 2.75 | BV76: 11.2 | BW76: 7073.65 | BX76: 1.95 | BY76: 27.2 | BZ76: 804.9 | CB76: KStA
B77: Nettoertrag (standardisierter Ertrag) | C77: =SUM(D77:BZ77) -> 70556371 | D77: =D75-D76 -> 14992899 | E77: =E75-E76 -> 587771.4 | F77: =F75-F76 -> 80202.15 | G77: =G75-G76 -> 63744.9 | H77: =H75-H76 -> 121353.15 | I77: =I75-I76 -> 793925 | J77: =J75-J76 -> 606563.25 | K77: =K75-K76 -> 52341.85 | ... BZ77: =BZ75-BZ76 -> 306411.55
A79: 2.3) | B79: Gewinn- und Kapitalsteuer
B80: Bruttoertrag | C80: =SUM(D80:BZ80) -> 1.967179e+08 | D80: 51735525 | E80: 1851968.4 | F80: 138171.5 | G80: 107636 | H80: 937616.45 | I80: 5306127.8 | J80: 1096776.9 | K80: 66285.85 | L80: 487484.45 | M80: 81745.9 | N80: 106422 | O80: 1048801.6 | P80: 3604196.6 | Q80: 3399078.5 | R80: 754921.95 | S80: 2793731.9 | T80: 3266857.7 | U80: 1726777 | V80: 4729751.2 | W80: 3187098.6 | X80: 6593302 | Y80: 1940500.1 | Z80: 381835.3 | AA80: 3799419.8 | AB80: 77993.35 | AC80: 2535108.9 | AD80: 944845.4 | AE80: 6784566.8 | AF80: 682283.75 | AG80: 1070730.3 | AH80: 6391030.7 | AI80: 756074.7 | AJ80: 691339.45 | AK80: 1492299.6 | AL80: 1228620.8 | AM80: 1405062 | AN80: 88777.35 | AO80: 1926303.6 | AP80: 741810.85 | AQ80: 571153.2 | AR80: 234880.85 | AS80: 174353.7 | AT80: 180956.15 | AU80: 340099.25 | AV80: 539788.85 | AW80: 690339.25 | AX80: 487951.4 | AY80: 1945282.9 | AZ80: 919927.8 | BA80: 22943117 | BB80: 1745788.6 | BC80: 377764.05 | BD80: 483117.85 | BE80: 969370.6 | BF80: 1606542.5 | BG80: 145877.35 | BH80: 491282.1 | BI80: 970655.8 | BJ80: 280261.45 | BK80: 225082.4 | BL80: 2408078.1 | BM80: 1017018.9 | BN80: 876571 | BO80: 2742450.6 | BP80: 2381284 | BQ80: 2101239.5 | BR80: 11594660 | BS80: 887816.6 | BT80: 2004708.7 | BU80: 137635.7 | BV80: 265896.5 | BW80: 6273689.3 | BX80: 279807.55 | BY80: 527744.45 | BZ80: 936826.4 | CB80: KStA
B81: Abschreibungen | C81: =SUM(D81:BZ81) -> 1744133.5 | D81: 725118.65 | E81: 5951.7 | F81: 286.5 | G81: 5295.75 | H81: 4218.85 | I81: 12783.6 | J81: 553.45 | K81: 23.35 | L81: 75.8 | M81: 63.55 | N81: 33.75 | O81: 19313 | P81: 53369.8 | Q81: 199682.45 | R81: 7691.25 | S81: 33957.05 | T81: 23015 | U81: 1266 | V81: 40625 | W81: 10140.95 | X81: 10731.95 | Y81: 559.1 | Z81: 500.7 | AA81: 11795.9 | AB81: 23.35 | AC81: 8264.1 | AD81: 222.3 | AE81: 185.55 | AF81: 250.05 | AG81: 878.95 | AH81: 333340.05 | AI81: 4694.2 | AJ81: 989.1 | AK81: 6478.1 | AL81: 95.1 | AM81: 8745.1 | AN81: 15.6 | AO81: 8501.5 | AP81: 1956.25 | AQ81: 1636.75 | AR81: 77.9 | AS81: 60.9 | AT81: 1115.95 | AU81: 160.35 | AV81: 790.35 | AW81: 6516.85 | AX81: 18797.75 | AY81: 8568.2 | AZ81: 1253.25 | BA81: 22091.85 | BB81: 29980.1 | BC81: 2700.65 | BD81: 170.7 | BE81: 120.25 | BF81: 4737.35 | BG81: 2691.6 | BH81: 4756.5 | BI81: 10904 | BJ81: 627 | BK81: 59.25 | BL81: 1260.35 | BM81: 4167.75 | BN81: 5104 | BO81: 8924.7 | BP81: 1179.7 | BQ81: 1872.7 | BR81: 34827.95 | BS81: 324.7 | BT81: 6373.75 | BU81: 9084.55 | BV81: 35.35 | BW81: 3819.2 | BX81: -27.9 | BY81: 1504.9 | BZ81: 6171.85 | CB81: KStA
B82: pauschale Steueranrechnung | C82: =SUM(D82:BZ82) -> 276894.85 | D82: 34901.05 | E82: 99.35 | F82: 0 | G82: 0 | H82: 40467.15 | I82: 0 | J82: 0 | K82: 0 | L82: 0 | M82: 0 | N82: 0 | O82: 0 | P82: 0 | Q82: 695.35 | R82: 0 | S82: 0 | T82: 71129.9 | U82: 0 | V82: 2195.5 | W82: 0 | X82: 30011.75 | Y82: 0 | Z82: 0 | AA82: 7504.05 | AB82: 0 | AC82: 0 | AD82: 0 | AE82: 30470.2 | AF82: 0 | AG82: 0 | AH82: 1675.25 | AI82: 12480.6 | AJ82: 0 | AK82: 0 | AL82: 0 | AM82: 0 | AN82: 0 | AO82: 0 | AP82: 0 | AQ82: 0 | AR82: 0 | AS82: 0 | AT82: 0 | AU82: 0 | AV82: 0 | AW82: 0 | AX82: 0 | AY82: 0 | AZ82: 0 | BA82: 38161.65 | BB82: 0 | BC82: 0 | BD82: 0 | BE82: 0 | BF82: 867.3 | BG82: 0 | BH82: 0 | BI82: 0 | BJ82: 0 | BK82: 0 | BL82: 0 | BM82: 0 | BN82: 0 | BO82: 0 | BP82: 6235.75 | BQ82: 0 | BR82: 0 | BS82: 0 | BT82: 0 | BU82: 0 | BV82: 0 | BW82: 0 | BY82: 0 | BZ82: 0
B83: Nettoertrag (standardisierter Ertrag) | C83: =SUM(D83:BZ83) -> 1.9469687e+08 | D83: =D80-D81-D82 -> 50975506 | E83: =E80-E81-E82 -> 1845917.4 | F83: =F80-F81-F82 -> 137885 | G83: =G80-G81-G82 -> 102340.25 | H83: =H80-H81-H82 -> 892930.45 | I83: =I80-I81-I82 -> 5293344.2 | J83: =J80-J81-J82 -> 1096223.5 | K83: =K80-K81-K82 -> 66262.5 | ... BZ83: =BZ80-BZ81-BZ82 -> 930654.55
A85: 2.4) | B85: Grundsteuer (ord. Satz)
B86: Steuersatz in ‰ | C86: =C90/C92 -> 0.69112917 | D86: 0.8 | E86: 0.8 | F86: 0.8 | G86: 0.8 | H86: 0.2 | I86: 0.4 | J86: 0.6 | K86: 0.3 | L86: 0.2 | M86: 0.8 | N86: 0.8 | O86: 0.8 | P86: 0.8 | Q86: 0.4 | R86: 0.8 | S86: 0.8 | T86: 0.4 | U86: 0.8 | V86: 0.6 | W86: 0.6 | X86: 0.8 | Y86: 0.8 | Z86: 0.8 | AA86: 0.8 | AB86: 0.8 | AC86: 0.8 | AD86: 0.8 | AE86: 0.8 | AF86: 0.8 | AG86: 0.8 | AH86: 0.7 | AI86: 0.8 | AJ86: 0.7 | AK86: 0.8 | AL86: 0.8 | AM86: 0.8 | AN86: 0.8 | AO86: 0.8 | AP86: 0.8 | AQ86: 0.8 | AR86: 0.8 | AS86: 0.8 | AT86: 0.8 | AU86: 0.8 | AV86: 0.8 | AW86: 0.8 | AX86: 0.8 | AY86: 0.8 | AZ86: 0.8 | BA86: 0.3 | BB86: 0.8 | BC86: 0.8 | BD86: 0.8 | BE86: 0.8 | BF86: 0.8 | BG86: 0.8 | BH86: 0.8 | BI86: 0.8 | BJ86: 0.8 | BK86: 0.5 | BL86: 0.8 | BM86: 0.6 | BN86: 0.8 | BO86: 0.6 | BP86: 0.8 | BQ86: 0.8 | BR86: 0.6 | BS86: 0.4 | BT86: 0.3 | BU86: 0.8 | BV86: 0.4 | BW86: 0.6 | BX86: 0.6 | BY86: 0.8 | BZ86: 0.8 | CB86: KStA/Gemeinden
B88: Bruttoertrag | C88: =SUM(D88:BZ88) -> 1.0026633e+08 | D88: 18512651 | E88: 1780474 | F88: 283322.3 | G88: 234635.38 | H88: 267882.25 | I88: 1053279.6 | J88: 637408.6 | K88: 76910.55 | L88: 107284.6 | M88: 219593.6 | N88: 457627.45 | O88: 1630432.4 | P88: 1816702 | Q88: 857414.43 | R88: 669667.95 | S88: 1353130.4 | T88: 917110.62 | U88: 955143 | V88: 975038.09 | W88: 1191402 | X88: 2521156.3 | Y88: 899418 | Z88: 431941.52 | AA88: 2539434.4 | AB88: 313713.41 | AC88: 2026651.4 | AD88: 549140.4 | AE88: 1487998.5 | AF88: 690442.75 | AG88: 1403538.6 | AH88: 2515904.3 | AI88: 1022565.8 | AJ88: 916765.95 | AK88: 1263953.4 | AL88: 1083238 | AM88: 1730249 | AN88: 431544.8 | AO88: 1994656.1 | AP88: 1254850.6 | AQ88: 1203982.3 | AR88: 969530.65 | AS88: 544183.1 | AT88: 437241.32 | AU88: 740692.8 | AV88: 586055.1 | AW88: 906937.35 | AX88: 1320913.8 | AY88: 1420098.9 | AZ88: 937118.27 | BA88: 3065693.4 | BB88: 2193019.7 | BC88: 848078.5 | BD88: 662278.25 | BE88: 941286.15 | BF88: 1557349.9 | BG88: 333814.01 | BH88: 1009730.7 | BI88: 915781.15 | BJ88: 274007.03 | BK88: 290884.69 | BL88: 1904333.7 | BM88: 725284.06 | BN88: 1220383.4 | BO88: 1975669.2 | BP88: 1770076.1 | BQ88: 679757.75 | BR88: 4068564.4 | BS88: 608470.15 | BT88: 411485.5 | BU88: 313732.21 | BV88: 319433.25 | BW88: 3080687.6 | BX88: 315900.27 | BY88: 722950.09 | BZ88: 1916648 | CB88: Gemeinden
B89: Erlasse/Verluste | C89: =SUM(D89:BZ89) -> 16646.19 | D89: 0 | E89: 0 | F89: 0 | G89: 0 | H89: 0 | I89: 0 | J89: 0 | K89: 0 | L89: 0 | M89: 0 | N89: 36 | O89: 0 | P89: 0 | Q89: 205.18 | R89: 0 | S89: 5716.35 | T89: 0 | U89: 0 | V89: 0 | W89: 1.3 | X89: 0 | Y89: 0 | Z89: 0 | AA89: 1103.34 | AB89: 0 | AC89: 0 | AD89: 0 | AE89: 0 | AF89: 0 | AG89: 0 | AH89: 6 | AI89: 0 | AJ89: 0 | AK89: 0 | AL89: 0 | AM89: 0 | AN89: 0 | AO89: 0 | AP89: 0.95 | AQ89: 2.25 | AR89: 0 | AS89: 0 | AT89: 0 | AU89: 0 | AV89: 0 | AW89: 0 | AX89: 0 | AY89: 0 | AZ89: 0 | BA89: 0 | BB89: 196.15 | BC89: 6416.8 | BD89: 2.6 | BE89: 0 | BF89: 0 | BG89: 0 | BH89: 0 | BI89: 0 | BJ89: 20.8 | BK89: 36.06 | BL89: 383.96 | BM89: 0 | BN89: 0 | BO89: 2279.8 | BP89: 238.55 | BQ89: 0 | BR89: 0 | BS89: 0 | BT89: 0.1 | BU89: 0 | BV89: 0 | BW89: 0 | BX89: 0 | BY89: 0 | BZ89: 0 | CB89: Gemeinden
B90: Nettoertrag | C90: =SUM(D90:BZ90) -> 1.0024968e+08 | D90: =D88-D89 -> 18512651 | E90: =E88-E89 -> 1780474 | F90: =F88-F89 -> 283322.3 | G90: =G88-G89 -> 234635.38 | H90: =H88-H89 -> 267882.25 | I90: =I88-I89 -> 1053279.6 | J90: =J88-J89 -> 637408.6 | K90: =K88-K89 -> 76910.55 | ... BZ90: =BZ88-BZ89 -> 1916648
B92: Ertrag bei Satz von 1‰ | C92: =SUM(D92:BZ92) -> 1.4505202e+08 | D92: =D90/D86 -> 23140814 | E92: =E90/E86 -> 2225592.5 | F92: =F90/F86 -> 354152.87 | G92: =G90/G86 -> 293294.22 | H92: =H90/H86 -> 1339411.2 | I92: =I90/I86 -> 2633198.9 | J92: =J90/J86 -> 1062347.7 | K92: =K90/K86 -> 256368.5 | ... BZ92: =BZ90/BZ86 -> 2395810
B94: Standardisierter Ertrag | C94: =C92*$C86 -> 1.0024968e+08 | D94: =D92*$C86 -> 15993292 | E94: =E92*$C86 -> 1538171.9 | F94: =F92*$C86 -> 244765.38 | G94: =G92*$C86 -> 202704.2 | H94: =H92*$C86 -> 925706.19 | I94: =I92*$C86 -> 1819880.6 | J94: =J92*$C86 -> 734219.46 | ... BZ94: =BZ92*$C86 -> 1655814.2
A96: 2.5) | B96: Grundsteuer (Spezialsatz)
B97: Bruttoertrag | C97: =SUM(D97:BZ97) -> 1616929.5 | D97: 341027 | E97: 31901.68 | F97: 3311.7 | G97: 2931.7 | H97: 10902.2 | I97: 16205.84 | J97: 11989.2 | K97: 1878.3 | L97: 0 | M97: 2746.55 | N97: 6172.45 | O97: 16555.62 | P97: 38852.2 | Q97: 21580.7 | R97: 12147.95 | S97: 12664.89 | T97: 28948.69 | U97: 7523 | V97: 11090.66 | W97: 19959.3 | X97: 16613.75 | Y97: 7913 | Z97: 3799.01 | AA97: 42771.94 | AB97: 2056.04 | AC97: 25533.35 | AD97: 4008.77 | AE97: 27407.35 | AF97: 7632.6 | AG97: 43384.85 | AH97: 34305 | AI97: 6301.4 | AJ97: 12029.15 | AK97: 12230.15 | AL97: 9732 | AM97: 11666 | AN97: 25556.94 | AO97: 27293.85 | AP97: 11505.78 | AQ97: 11991.8 | AR97: 184.2 | AS97: 5677.95 | AT97: 6184.17 | AU97: 6822.64 | AV97: 5899.6 | AW97: 8853.45 | AX97: 10893.05 | AY97: 26791.88 | AZ97: 13657.6 | BA97: 104845.2 | BB97: 23051.66 | BC97: 8106.2 | BD97: 19773.55 | BE97: 14735.22 | BF97: 33792.5 | BG97: 4306.35 | BH97: 22577.9 | BI97: 17110.9 | BJ97: 3108 | BK97: 10078.24 | BL97: 30393.92 | BM97: 8183.93 | BN97: 13801.55 | BO97: 32491 | BP97: 28138 | BQ97: 12760.25 | BR97: 101700.02 | BS97: 8815.05 | BT97: 9826.65 | BU97: 1268.4 | BV97: 7994.3 | BW97: 30836.34 | BX97: 5595.46 | BY97: 12626.06 | BZ97: 23926 | CB97: Gemeinden
B98: Erlasse/Verluste | C98: =SUM(D98:BZ98) -> 11.92 | D98: 0 | E98: 0 | F98: 0 | G98: 0 | H98: 0 | I98: 0 | J98: 0 | K98: 0 | L98: 0 | M98: 0 | N98: 0 | O98: 0 | P98: 0 | Q98: 0 | R98: 0 | S98: 0 | T98: 0 | U98: 0 | V98: 0 | W98: 0 | X98: 0 | Y98: 0 | Z98: 0 | AA98: 0 | AB98: 0 | AC98: 0 | AD98: 0.2 | AE98: 0 | AF98: 0 | AG98: 0 | AH98: 0 | AI98: 0 | AJ98: 0 | AK98: 0 | AL98: 0 | AM98: 0 | AN98: 0 | AO98: 0 | AP98: 0 | AQ98: 0 | AR98: 0 | AS98: 0 | AT98: 0 | AU98: 0 | AV98: 0 | AW98: 0 | AX98: 0 | AY98: 0 | AZ98: 0 | BA98: 0 | BB98: 0 | BC98: 0 | BD98: 0 | BE98: 0 | BF98: 0 | BG98: 0 | BH98: 0 | BI98: 0 | BJ98: 0 | BK98: 0 | BL98: 11.72 | BM98: 0 | BN98: 0 | BO98: 0 | BP98: 0 | BQ98: 0 | BR98: 0 | BS98: 0 | BT98: 0 | BU98: 0 | BV98: 0 | BW98: 0 | BX98: 0 | BY98: 0 | BZ98: 0 | CB98: Gemeinden
B99: Nettoertrag (standardisierter Ertrag) | C99: =SUM(D99:BZ99) -> 1616917.6 | D99: =D97-D98 -> 341027 | E99: =E97-E98 -> 31901.68 | F99: =F97-F98 -> 3311.7 | G99: =G97-G98 -> 2931.7 | H99: =H97-H98 -> 10902.2 | I99: =I97-I98 -> 16205.84 | J99: =J97-J98 -> 11989.2 | K99: =K97-K98 -> 1878.3 | ... BZ99: =BZ97-BZ98 -> 23926
A101: 2.6) | B101: Handänderungssteuer
B102: Bruttoertrag | C102: =SUM(D102:BZ102) -> 66697906 | D102: 10747088 | E102: 1043078.8 | F102: 130609.25 | G102: 63419.6 | H102: 657110.5 | I102: 818506.56 | J102: 484469.95 | K102: 280086.4 | L102: 150547.85 | M102: 39640.45 | N102: 211831.45 | O102: 1764100.9 | P102: 1232195.5 | Q102: 822027.05 | R102: 427526.35 | S102: 1058235.5 | T102: 1472775 | U102: 465984 | V102: 496769.45 | W102: 1047267.6 | X102: 1137544.2 | Y102: 534555 | Z102: 150512.47 | AA102: 1221347.1 | AB102: 152245.79 | AC102: 868191.49 | AD102: 208144.87 | AE102: 592568.85 | AF102: 314155.95 | AG102: 662938.8 | AH102: 1532879.6 | AI102: 712353.9 | AJ102: 676079.2 | AK102: 753282.7 | AL102: 507399 | AM102: 788651 | AN102: 118401.31 | AO102: 1046843.5 | AP102: 890717.45 | AQ102: 365733.64 | AR102: 357911.3 | AS102: 319816.8 | AT102: 238631.68 | AU102: 417986.07 | AV102: 242948.85 | AW102: 585988.7 | AX102: 1062006.2 | AY102: 1534595.2 | AZ102: 481626.92 | BA102: 3963250.2 | BB102: 1392136.7 | BC102: 399077.45 | BD102: 438589.81 | BE102: 477269.77 | BF102: 1364961.9 | BG102: 525157.8 | BH102: 578932.35 | BI102: 324153.05 | BJ102: 132032.98 | BK102: 143051.35 | BL102: 735867.75 | BM102: 578276.04 | BN102: 598875.3 | BO102: 1884720.9 | BP102: 1106897.9 | BQ102: 501559.2 | BR102: 3832501.4 | BS102: 864370.7 | BT102: 818061 | BU102: 84187.08 | BV102: 228669.6 | BW102: 2111197.4 | BX102: 328055.43 | BY102: 321128.2 | BZ102: 1075597 | CB102: Gemeinden
B103: Erlasse/Verluste | C103: =SUM(D103:BZ103) -> 0 | D103: 0 | E103: 0 | F103: 0 | G103: 0 | H103: 0 | I103: 0 | J103: 0 | K103: 0 | L103: 0 | M103: 0 | N103: 0 | O103: 0 | P103: 0 | Q103: 0 | R103: 0 | S103: 0 | T103: 0 | U103: 0 | V103: 0 | W103: 0 | X103: 0 | Y103: 0 | Z103: 0 | AA103: 0 | AB103: 0 | AC103: 0 | AD103: 0 | AE103: 0 | AF103: 0 | AG103: 0 | AH103: 0 | AI103: 0 | AJ103: 0 | AK103: 0 | AL103: 0 | AM103: 0 | AN103: 0 | AO103: 0 | AP103: 0 | AQ103: 0 | AR103: 0 | AS103: 0 | AT103: 0 | AU103: 0 | AV103: 0 | AW103: 0 | AX103: 0 | AY103: 0 | AZ103: 0 | BA103: 0 | BB103: 0 | BC103: 0 | BD103: 0 | BE103: 0 | BF103: 0 | BG103: 0 | BH103: 0 | BI103: 0 | BJ103: 0 | BK103: 0 | BL103: 0 | BM103: 0 | BN103: 0 | BO103: 0 | BP103: 0 | BQ103: 0 | BR103: 0 | BS103: 0 | BT103: 0 | BU103: 0 | BV103: 0 | BW103: 0 | BX103: 0 | BY103: 0 | BZ103: 0 | CB103: Gemeinden
B104: Nettoertrag (standardisierter Ertrag) | C104: =SUM(D104:BZ104) -> 66697906 | D104: =D102-D103 -> 10747088 | E104: =E102-E103 -> 1043078.8 | F104: =F102-F103 -> 130609.25 | G104: =G102-G103 -> 63419.6 | H104: =H102-H103 -> 657110.5 | I104: =I102-I103 -> 818506.56 | J104: =J102-J103 -> 484469.95 | K104: =K102-K103 -> 280086.4 | ... BZ104: =BZ102-BZ103 -> 1075597
A106: 2.7) | B106: Grundstückgewinnsteuer
B107: Bruttoertrag | C107: =SUM(D107:BZ107) -> 1.0440682e+08 | D107: 16851787 | E107: 2081416.8 | F107: 280270.9 | G107: 170378.35 | H107: 1891906.2 | I107: 1188319.6 | J107: 376225.7 | K107: 301232.35 | L107: 217145.65 | M107: -44848.15 | N107: 155263.05 | O107: 1116246.4 | P107: 2711163.6 | Q107: 799833.3 | R107: 836199.7 | S107: 1978241.6 | T107: 1757086.4 | U107: 694071.65 | V107: 1212217.9 | W107: 1297422.1 | X107: 2099683.1 | Y107: 998789.55 | Z107: 290842.85 | AA107: 2547396 | AB107: 238412.05 | AC107: 1804698.4 | AD107: 273054.35 | AE107: 1346923.3 | AF107: 695833.7 | AG107: 1563625.2 | AH107: 3098474.9 | AI107: 883678.3 | AJ107: 998782.55 | AK107: 1401788.1 | AL107: 708206 | AM107: 1480239.9 | AN107: 176567.6 | AO107: 763483.75 | AP107: 1447153.4 | AQ107: 482699.7 | AR107: 786436.5 | AS107: 846769.6 | AT107: 308881 | AU107: 471269.75 | AV107: 763926.35 | AW107: 480151.15 | AX107: 1947710.7 | AY107: 1637513.2 | AZ107: 335644.85 | BA107: 9175916.8 | BB107: 1414357.9 | BC107: 475110.95 | BD107: 450220.9 | BE107: 849752.35 | BF107: 2206604.4 | BG107: 247702 | BH107: 897912.75 | BI107: 897180.45 | BJ107: 177912.05 | BK107: 121733.7 | BL107: 2960802.2 | BM107: 449204.65 | BN107: 824094.2 | BO107: 2453118.8 | BP107: 1528981.1 | BQ107: 570195.4 | BR107: 3511591.1 | BS107: 1269487.6 | BT107: 836992.15 | BU107: 277014.35 | BV107: 196839.2 | BW107: 2893917.7 | BX107: 286068.3 | BY107: 685947.45 | BZ107: 1997945.8 | CB107: KStA
B108: Abschreibungen | C108: =SUM(D108:BZ108) -> 21810.15 | D108: 50.55 | E108: 23.5 | F108: 0 | G108: 0 | H108: 6.45 | I108: 0 | J108: 0 | K108: 0 | L108: 0 | M108: 0 | N108: 1.4 | O108: 23.85 | P108: 0.45 | Q108: 15.15 | R108: 26.8 | S108: 17.45 | T108: 16.7 | U108: 15.3 | V108: 0.15 | W108: 0.3 | X108: 12.55 | Y108: 12 | Z108: 0 | AA108: 14.8 | AB108: 8.35 | AC108: 14.5 | AD108: 10.75 | AE108: 14.25 | AF108: 12.55 | AG108: 27.1 | AH108: 41.9 | AI108: 5.65 | AJ108: 69.7 | AK108: 5.95 | AL108: 32.45 | AM108: 23.2 | AN108: 13.5 | AO108: 26.1 | AP108: 9.05 | AQ108: 24.95 | AR108: 14399.1 | AS108: 6.4 | AT108: 17.2 | AU108: 1.7 | AV108: 14.45 | AW108: 3.15 | AX108: 6.8 | AY108: 0 | AZ108: 2939.15 | BA108: 43.5 | BB108: 22.55 | BC108: 0.2 | BD108: 9.35 | BE108: 24.95 | BF108: 7.05 | BG108: 3.65 | BH108: 20.1 | BI108: 12 | BJ108: 9 | BK108: 6.4 | BL108: 4.35 | BM108: 0 | BN108: 0.4 | BO108: 17.85 | BP108: 3557.55 | BQ108: 1.55 | BR108: 30.5 | BS108: 4.55 | BT108: 0.7 | BU108: 3.7 | BV108: 11 | BW108: 22.7 | BX108: 0 | BY108: 11.75 | BZ108: 19.5 | CB108: KStA
B109: Nettoertrag (standardisierter Ertrag) | C109: =SUM(D109:BZ109) -> 1.0438501e+08 | D109: =D107-D108 -> 16851736 | E109: =E107-E108 -> 2081393.2 | F109: =F107-F108 -> 280270.9 | G109: =G107-G108 -> 170378.35 | H109: =H107-H108 -> 1891899.8 | I109: =I107-I108 -> 1188319.6 | J109: =J107-J108 -> 376225.7 | K109: =K107-K108 -> 301232.35 | ... BZ109: =BZ107-BZ108 -> 1997926.2
A112: 3.) | B112: Berechnung der technischen Steuerkraft
A114: 3.1) | B114: Technische Steuerkraft 2023
B115: Einkommens-/Vermögenssteuer | C115: =C21 -> 1.4055204e+09 | D115: =D21 -> 2.0863164e+08 | E115: =E21 -> 21875078 | F115: =F21 -> 3480550.6 | G115: =G21 -> 2877832.3 | H115: =H21 -> 18629756 | I115: =I21 -> 26765491 | J115: =J21 -> 9310290.2 | ... BZ115: =BZ21 -> 28546878
B116: Quellensteuer | C116: =C26 -> 82404742 | D116: =D26 -> 18101401 | E116: =E26 -> 767236.25 | F116: =F26 -> 127407.75 | G116: =G26 -> 85527.25 | H116: =H26 -> 137410.15 | I116: =I26 -> 1020377.4 | J116: =J26 -> 711277.45 | ... BZ116: =BZ26 -> 346633.55
B117: Gewinn- und Kapitalsteuer | C117: =C32 -> 1.9059488e+08 | D117: =D32 -> 45708508 | E117: =E32 -> 1795703 | F117: =F32 -> 86828.65 | G117: =G32 -> 82609.35 | H117: =H32 -> 924600 | I117: =I32 -> 4422455.6 | J117: =J32 -> 763307 | ... BZ117: =BZ32 -> 535578.35
B118: Grundsteuer (ord. Satz) | C118: =C43 -> 1.0333367e+08 | D118: =D43 -> 16371459 | E118: =E43 -> 1572005.2 | F118: =F43 -> 255883.23 | G118: =G43 -> 208224.81 | H118: =H43 -> 955535.41 | I118: =I43 -> 1871247.6 | J118: =J43 -> 750178.12 | ... BZ118: =BZ43 -> 1708373.1
B119: Grundsteuer (Spezialsatz) | C119: =C48 -> 1630039.1 | D119: =D48 -> 339501.63 | E119: =E48 -> 31977.08 | F119: =F48 -> 3326.5 | G119: =G48 -> 2921.6 | H119: =H48 -> 10930.4 | I119: =I48 -> 16285.84 | J119: =J48 -> 14373.8 | ... BZ119: =BZ48 -> 24167.25
B120: Handänderungssteuer | C120: =C53 -> 59811726 | D120: =D53 -> 10387286 | E120: =E53 -> 912441.64 | F120: =F53 -> 185351.85 | G120: =G53 -> 86210.44 | H120: =H53 -> 600536.95 | I120: =I53 -> 930406 | J120: =J53 -> 234393 | ... BZ120: =BZ53 -> 885924.09
B121: Grundstückgewinnsteuer | C121: =C58 -> 93024770 | D121: =D58 -> 14503610 | E121: =E58 -> 2194434 | F121: =F58 -> 206255.85 | G121: =G58 -> 304943.7 | H121: =H58 -> 1345683.6 | I121: =I58 -> 1325563.3 | J121: =J58 -> 378256.45 | ... BZ121: =BZ58 -> 1148349.1
B122: Total | C122: =SUM(C115:C121) -> 1.9363202e+09 | D122: =SUM(D115:D121) -> 3.1404341e+08 | E122: =SUM(E115:E121) -> 29148875 | F122: =SUM(F115:F121) -> 4345604.4 | G122: =SUM(G115:G121) -> 3648269.5 | H122: =SUM(H115:H121) -> 22604452 | I122: =SUM(I115:I121) -> 36351827 | J122: =SUM(J115:J121) -> 12162076 | ... BZ122: =SUM(BZ115:BZ121) -> 33195904
B124: Einwohnerzahl per 31.12. | C124: =SUM(D124:BZ124) -> 535114 | D124: 78213 | E124: 10026 | F124: 1431 | G124: 1257 | H124: 3662 | I124: 9709 | J124: 3580 | K124: 1012 | L124: 1594 | M124: 1027 | N124: 2475 | O124: 7685 | P124: 9955 | Q124: 7097 | R124: 3516 | S124: 6558 | T124: 8481 | U124: 3989 | V124: 5139 | W124: 6928 | X124: 10337 | Y124: 5051 | Z124: 2118 | AA124: 12456 | AB124: 1571 | AC124: 9291 | AD124: 2542 | AE124: 6269 | AF124: 3711 | AG124: 7402 | AH124: 13931 | AI124: 5392 | AJ124: 5496 | AK124: 6522 | AL124: 5057 | AM124: 6835 | AN124: 1601 | AO124: 9538 | AP124: 5347 | AQ124: 5852 | AR124: 3085 | AS124: 1906 | AT124: 1871 | AU124: 4154 | AV124: 3035 | AW124: 5084 | AX124: 5657 | AY124: 7014 | AZ124: 4162 | BA124: 28640 | BB124: 10169 | BC124: 2618 | BD124: 3833 | BE124: 5092 | BF124: 9161 | BG124: 2079 | BH124: 6437 | BI124: 5202 | BJ124: 1645 | BK124: 2969 | BL124: 9755 | BM124: 4023 | BN124: 6674 | BO124: 14279 | BP124: 10631 | BQ124: 4132 | BR124: 24980 | BS124: 5026 | BT124: 4660 | BU124: 1497 | BV124: 3256 | BW124: 18454 | BX124: 2128 | BY124: 3544 | BZ124: 8609 | CB124: Bundesamt für Statistik
B126: Technische Steuerkraft pro Einwohner | C126: =C122/C124 -> 3618.5191 | D126: =D122/D124 -> 4015.2329 | E126: =E122/E124 -> 2907.3284 | F126: =F122/F124 -> 3036.7606 | G126: =G122/G124 -> 2902.3623 | H126: =H122/H124 -> 6172.7068 | I126: =I122/I124 -> 3744.1371 | J126: =J122/J124 -> 3397.2279 | ... BZ126: =BZ122/BZ124 -> 3855.9535
A128: 3.2) | B128: Technische Steuerkraft 2022
B129: Einkommens-/Vermögenssteuer | C129: =C72 -> 1.3334915e+09 | D129: =D72 -> 1.9917336e+08 | E129: =E72 -> 21517889 | F129: =F72 -> 3293910.4 | G129: =G72 -> 2721838 | H129: =H72 -> 20358252 | I129: =I72 -> 25747443 | J129: =J72 -> 8696764.9 | ... BZ129: =BZ72 -> 27008387
B130: Quellensteuer | C130: =C77 -> 70556371 | D130: =D77 -> 14992899 | E130: =E77 -> 587771.4 | F130: =F77 -> 80202.15 | G130: =G77 -> 63744.9 | H130: =H77 -> 121353.15 | I130: =I77 -> 793925 | J130: =J77 -> 606563.25 | ... BZ130: =BZ77 -> 306411.55
B131: Gewinn- und Kapitalsteuer | C131: =C83 -> 1.9469687e+08 | D131: =D83 -> 50975506 | E131: =E83 -> 1845917.4 | F131: =F83 -> 137885 | G131: =G83 -> 102340.25 | H131: =H83 -> 892930.45 | I131: =I83 -> 5293344.2 | J131: =J83 -> 1096223.5 | ... BZ131: =BZ83 -> 930654.55
B132: Grundsteuer (ord. Satz) | C132: =C94 -> 1.0024968e+08 | D132: =D94 -> 15993292 | E132: =E94 -> 1538171.9 | F132: =F94 -> 244765.38 | G132: =G94 -> 202704.2 | H132: =H94 -> 925706.19 | I132: =I94 -> 1819880.6 | J132: =J94 -> 734219.46 | ... BZ132: =BZ94 -> 1655814.2
B133: Grundsteuer (Spezialsatz) | C133: =C99 -> 1616917.6 | D133: =D99 -> 341027 | E133: =E99 -> 31901.68 | F133: =F99 -> 3311.7 | G133: =G99 -> 2931.7 | H133: =H99 -> 10902.2 | I133: =I99 -> 16205.84 | J133: =J99 -> 11989.2 | ... BZ133: =BZ99 -> 23926
B134: Handänderungssteuer | C134: =C104 -> 66697906 | D134: =D104 -> 10747088 | E134: =E104 -> 1043078.8 | F134: =F104 -> 130609.25 | G134: =G104 -> 63419.6 | H134: =H104 -> 657110.5 | I134: =I104 -> 818506.56 | J134: =J104 -> 484469.95 | ... BZ134: =BZ104 -> 1075597
B135: Grundstückgewinnsteuer | C135: =C109 -> 1.0438501e+08 | D135: =D109 -> 16851736 | E135: =E109 -> 2081393.2 | F135: =F109 -> 280270.9 | G135: =G109 -> 170378.35 | H135: =H109 -> 1891899.8 | I135: =I109 -> 1188319.6 | J135: =J109 -> 376225.7 | ... BZ135: =BZ109 -> 1997926.2
B136: Total | C136: =SUM(C129:C135) -> 1.8716942e+09 | D136: =SUM(D129:D135) -> 3.0907491e+08 | E136: =SUM(E129:E135) -> 28646124 | F136: =SUM(F129:F135) -> 4170954.7 | G136: =SUM(G129:G135) -> 3327357 | H136: =SUM(H129:H135) -> 24858154 | I136: =SUM(I129:I135) -> 35677624 | J136: =SUM(J129:J135) -> 12006456 | ... BZ136: =SUM(BZ129:BZ135) -> 32998717
B138: Einwohnerzahl per 31.12. | C138: =SUM(D138:BZ138) -> 525967 | D138: 76931 | E138: 9914 | F138: 1393 | G138: 1253 | H138: 3619 | I138: 9562 | J138: 3583 | K138: 988 | L138: 1587 | M138: 1026 | N138: 2364 | O138: 7620 | P138: 9777 | Q138: 6914 | R138: 3481 | S138: 6249 | T138: 8252 | U138: 3963 | V138: 5067 | W138: 6889 | X138: 10178 | Y138: 4906 | Z138: 2137 | AA138: 12278 | AB138: 1556 | AC138: 9180 | AD138: 2472 | AE138: 6101 | AF138: 3606 | AG138: 7302 | AH138: 13605 | AI138: 5279 | AJ138: 5395 | AK138: 6443 | AL138: 5015 | AM138: 6663 | AN138: 1563 | AO138: 9311 | AP138: 5211 | AQ138: 5763 | AR138: 3000 | AS138: 1847 | AT138: 1845 | AU138: 4021 | AV138: 3018 | AW138: 5051 | AX138: 5564 | AY138: 6850 | AZ138: 4110 | BA138: 28252 | BB138: 9996 | BC138: 2612 | BD138: 3733 | BE138: 4979 | BF138: 8954 | BG138: 1980 | BH138: 6324 | BI138: 5163 | BJ138: 1619 | BK138: 2920 | BL138: 9632 | BM138: 3961 | BN138: 6536 | BO138: 13831 | BP138: 10446 | BQ138: 4081 | BR138: 24541 | BS138: 4997 | BT138: 4588 | BU138: 1527 | BV138: 3201 | BW138: 18226 | BX138: 2115 | BY138: 3528 | BZ138: 8523 | CB138: Bundesamt für Statistik
B140: Technische Steuerkraft pro Einwohner | C140: =C136/C138 -> 3558.5773 | D140: =D136/D138 -> 4017.56 | E140: =E136/E138 -> 2889.4618 | F140: =F136/F138 -> 2994.2245 | G140: =G136/G138 -> 2655.5124 | H140: =H136/H138 -> 6868.7908 | I140: =I136/I138 -> 3731.1885 | J140: =J136/J138 -> 3350.9506 | ... BZ140: =BZ136/BZ138 -> 3871.7255
...

Sheet SL Weite Basis
A1: Kanton St.Gallen
A2: Amt für Gemeinden und Bürgerrecht
A5: Sonderlastenausgleich Weite 2025
B7: Eingabefelder
C8: Total | D8: St.Gallen | E8: Wittenbach | F8: Häggenschwil | G8: Muolen | H8: Mörschwil | I8: Goldach | J8: Steinach | K8: Berg | L8: Tübach | M8: Untereggen | N8: Eggersriet | O8: Rorschacherberg | P8: Rorschach | Q8: Thal | R8: Rheineck | S8: St.Margrethen | T8: Au | U8: Berneck | V8: Balgach | W8: Diepoldsau | X8: Widnau | Y8: Rebstein | Z8: Marbach | AA8: Altstätten | AB8: Eichberg | AC8: Oberriet | AD8: Rüthi | AE8: Sennwald | AF8: Gams | AG8: Grabs | AH8: Buchs | AI8: Sevelen | AJ8: Wartau | AK8: Sargans | AL8: Vilters-Wangs | AM8: Bad Ragaz | AN8: Pfäfers | AO8: Mels | AP8: Flums | AQ8: Walenstadt | AR8: Quarten | AS8: Amden | AT8: Weesen | AU8: Schänis | AV8: Benken | AW8: Kaltbrunn | AX8: Gommiswald | AY8: Uznach | AZ8: Schmerikon | BA8: Rapperswil-Jona | BB8: Eschenbach | BC8: Wildhaus-Alt St.Johann | BD8: Nesslau | BE8: Ebnat-Kappel | BF8: Wattwil | BG8: Lichtensteig | BH8: Neckertal | BI8: Bütschwil-Ganterschwil | BJ8: Lütisburg | BK8: Mosnang | BL8: Kirchberg | BM8: Jonschwil | BN8: Oberuzwil | BO8: Uzwil | BP8: Flawil | BQ8: Degersheim | BR8: Wil | BS8: Zuzwil | BT8: Oberbüren | BU8: Niederbüren | BV8: Niederhelfenschwil | BW8: Gossau | BX8: Andwil | BY8: Waldkirch | BZ8: Gaiserwald | CB8: Quelle
A10: 1.) | B10: Allgemeine Daten
B12: ='Ressourcenausgleich Basis'!B124 -> Einwohnerzahl per 31.12. | C12: ='Ressourcenausgleich Basis'!C124 -> 535114 | D12: ='Ressourcenausgleich Basis'!D124 -> 78213 | E12: ='Ressourcenausgleich Basis'!E124 -> 10026 | F12: ='Ressourcenausgleich Basis'!F124 -> 1431 | G12: ='Ressourcenausgleich Basis'!G124 -> 1257 | H12: ='Ressourcenausgleich Basis'!H124 -> 3662 | I12: ='Ressourcenausgleich Basis'!I124 -> 9709 | ... BZ12: ='Ressourcenausgleich Basis'!BZ124 -> 8609
A15: 2.) | B15: Berechnung Sonderlastenausgleich Weite
A17: 2.1) | B17: Länge des Strassennetzes
B19: gewichtete Strassenlänge in km per 31.12. | C19: =SUM(D19:BZ19) -> 125235.24 | D19: 10066.292 | E19: 1310.8918 | F19: 701.577 | G19: 855.182 | H19: 993.2544 | I19: 1249.827 | J19: 576.485 | K19: 284.222 | L19: 205.687 | M19: 519.8956 | N19: 874.2578 | O19: 1160.425 | P19: 1124.358 | Q19: 1427.3 | R19: 572.782 | S19: 1020.14 | T19: 1055.805 | U19: 847.8914 | V19: 783.923 | W19: 1172.627 | X19: 1314.211 | Y19: 764.733 | Z19: 687.784 | AA19: 4106.595 | AB19: 602.717 | AC19: 3379.2274 | AD19: 883.492 | AE19: 1941.105 | AF19: 1311.427 | AG19: 2734.0092 | AH19: 1653.93 | AI19: 1478.321 | AJ19: 1564.5064 | AK19: 958.037 | AL19: 1439.271 | AM19: 1158.3412 | AN19: 1859.6064 | AO19: 3085.0162 | AP19: 2034.2468 | AQ19: 1313.409 | AR19: 968.56 | AS19: 1535.6024 | AT19: 299.946 | AU19: 1259.112 | AV19: 953.002 | AW19: 971.197 | AX19: 1370.6226 | AY19: 894.218 | AZ19: 540.465 | BA19: 2652.419 | BB19: 3400.0128 | BC19: 2075.4826 | BD19: 2633.0698 | BE19: 2441.4366 | BF19: 3280.3196 | BG19: 355.9052 | BH19: 5094.0272 | BI19: 1871.1374 | BJ19: 923.506 | BK19: 2291.0282 | BL19: 4033.4392 | BM19: 1015.3124 | BN19: 1281.5226 | BO19: 2407.979 | BP19: 2009.1152 | BQ19: 1492.3382 | BR19: 3299.3842 | BS19: 872.811 | BT19: 1695.6946 | BU19: 842.759 | BV19: 1286.016 | BW19: 3461.2002 | BX19: 654.5826 | BY19: 2371.4128 | BZ19: 1627.7938 | CB19: BD
B20: gewichtete Strassenlänge in km pro Einwohner | D20: =D19/D12 -> 0.12870357 | E20: =E19/E12 -> 0.13074923 | F20: =F19/F12 -> 0.49027044 | G20: =G19/G12 -> 0.68033572 | H20: =H19/H12 -> 0.27123277 | I20: =I19/I12 -> 0.12872871 | J20: =J19/J12 -> 0.16102933 | K20: =K19/K12 -> 0.28085178 | ... BZ20: =BZ19/BZ12 -> 0.18908047
B21: Pauschalbeitrag je gewichtetem Kilometer | C21: 1166 | CB21: FAG
B22: Beitrag je Einwohner | D22: =D20*$C21 -> 150.06836 | E22: =E20*$C21 -> 152.4536 | F22: =F20*$C21 -> 571.65533 | G22: =G20*$C21 -> 793.27145 | H22: =H20*$C21 -> 316.25741 | I22: =I20*$C21 -> 150.09767 | J22: =J20*$C21 -> 187.7602 | K22: =K20*$C21 -> 327.47317 | ... BZ22: =BZ20*$C21 -> 220.46783
B24: Sonderlast total | D24: =D12*D22 -> 11737297 | E24: =E12*E22 -> 1528499.8 | F24: =F12*F22 -> 818038.78 | G24: =G12*G22 -> 997142.21 | H24: =H12*H22 -> 1158134.6 | I24: =I12*I22 -> 1457298.3 | J24: =J12*J22 -> 672181.51 | K24: =K12*K22 -> 331402.85 | ... BZ24: =BZ12*BZ22 -> 1898007.6
A26: 2.2) | B26: Wohnbevölkerung mit Wohnsitz über 800 Metern über Meer
B28: Einwohner über 800m per 31.12. | C28: =SUM(D28:BZ28) -> 21712 | D28: 1750 | E28: 0 | F28: 1 | G28: 0 | H28: 0 | I28: 0 | J28: 0 | K28: 0 | L28: 0 | M28: 0 | N28: 2224 | O28: 0 | P28: 0 | Q28: 0 | R28: 0 | S28: 0 | T28: 0 | U28: 0 | V28: 0 | W28: 0 | X28: 0 | Y28: 0 | Z28: 0 | AA28: 131 | AB28: 0 | AC28: 3 | AD28: 0 | AE28: 1 | AF28: 58 | AG28: 171 | AH28: 15 | AI28: 70 | AJ28: 37 | AK28: 0 | AL28: 17 | AM28: 11 | AN28: 1508 | AO28: 266 | AP28: 658 | AQ28: 148 | AR28: 135 | AS28: 1478 | AT28: 14 | AU28: 9 | AV28: 0 | AW28: 21 | AX28: 253 | AY28: 0 | AZ28: 0 | BA28: 0 | BB28: 742 | BC28: 2618 | BD28: 1609 | BE28: 463 | BF28: 726 | BG28: 4 | BH28: 3073 | BI28: 27 | BJ28: 59 | BK28: 307 | BL28: 120 | BM28: 0 | BN28: 0 | BO28: 0 | BP28: 0 | BQ28: 2838 | BR28: 0 | BS28: 0 | BT28: 0 | BU28: 0 | BV28: 0 | BW28: 0 | BX28: 3 | BY28: 111 | BZ28: 33 | CB28: BD
B29: Anteil an Gesamtbevölkerung | D29: =D28/D12 -> 0.022374797 | E29: =E28/E12 -> 0 | F29: =F28/F12 -> 0.00069881202 | G29: =G28/G12 -> 0 | H29: =H28/H12 -> 0 | I29: =I28/I12 -> 0 | J29: =J28/J12 -> 0 | K29: =K28/K12 -> 0 | ... BZ29: =BZ28/BZ12 -> 0.0038331978
B30: Pauschalbeitrag je Einwohner | C30: 134 | CB30: FAG
B31: Beitrag je Einwohner | D31: =D29*$C30 -> 2.9982228 | E31: =E29*$C30 -> 0 | F31: =F29*$C30 -> 0.093640811 | G31: =G29*$C30 -> 0 | H31: =H29*$C30 -> 0 | I31: =I29*$C30 -> 0 | J31: =J29*$C30 -> 0 | K31: =K29*$C30 -> 0 | ... BZ31: =BZ29*$C30 -> 0.51364851
B33: Sonderlast total | D33: =D31*D12 -> 234500 | E33: =E31*E12 -> 0 | F33: =F31*F12 -> 134 | G33: =G31*G12 -> 0 | H33: =H31*H12 -> 0 | I33: =I31*I12 -> 0 | J33: =J31*J12 -> 0 | K33: =K31*K12 -> 0 | ... BZ33: =BZ31*BZ12 -> 4422
A35: 2.3) | B35: Streuung des Siedlungsgebiets
B37: Streuung des Siedlungsgebiets per 31.12. | C37: =SUM(D37:BZ37) -> 89559.804 | D37: 5635.265 | E37: 0 | F37: 0 | G37: 0 | H37: 1416.3457 | I37: 0 | J37: 0 | K37: 0 | L37: 0 | M37: 0 | N37: 3386.469 | O37: 0 | P37: 0 | Q37: 0 | R37: 0 | S37: 0 | T37: 0 | U37: 0 | V37: 0 | W37: 0 | X37: 0 | Y37: 0 | Z37: 0 | AA37: 0 | AB37: 1303.7378 | AC37: 4634.3461 | AD37: 0 | AE37: 6275.212 | AF37: 0 | AG37: 0 | AH37: 0 | AI37: 0 | AJ37: 2878.4221 | AK37: 0 | AL37: 0 | AM37: 0 | AN37: 10487.398 | AO37: 0 | AP37: 0 | AQ37: 2706.927 | AR37: 3227.3218 | AS37: 0 | AT37: 0 | AU37: 0 | AV37: 0 | AW37: 0 | AX37: 4689.7287 | AY37: 0 | AZ37: 0 | BA37: 4402.5641 | BB37: 6359.2101 | BC37: 3817.8607 | BD37: 0 | BE37: 0 | BF37: 0 | BG37: 0 | BH37: 9280.882 | BI37: 0 | BJ37: 1621.8872 | BK37: 0 | BL37: 4971.8542 | BM37: 0 | BN37: 0 | BO37: 0 | BP37: 0 | BQ37: 0 | BR37: 0 | BS37: 0 | BT37: 4118.8784 | BU37: 0 | BV37: 2216.7633 | BW37: 0 | BX37: 0 | BY37: 3701.677 | BZ37: 2427.0541 | CB37: BD
B38: Pauschalbeitrag je Einwohner | C38: 0.008 | CB38: FAG
B39: Beitrag je Einwohner | D39: =D37*$C38 -> 45.08212 | E39: =E37*$C38 -> 0 | F39: =F37*$C38 -> 0 | G39: =G37*$C38 -> 0 | H39: =H37*$C38 -> 11.330765 | I39: =I37*$C38 -> 0 | J39: =J37*$C38 -> 0 | K39: =K37*$C38 -> 0 | ... BZ39: =BZ37*$C38 -> 19.416433
B41: Sonderlast total | D41: =D39*D12 -> 3526007.9 | E41: =E39*E12 -> 0 | F41: =F39*F12 -> 0 | G41: =G39*G12 -> 0 | H41: =H39*H12 -> 41493.263 | I41: =I39*I12 -> 0 | J41: =J39*J12 -> 0 | K41: =K39*K12 -> 0 | ... BZ41: =BZ39*BZ12 -> 167156.07
A43: 2.4) | B43: geringe Einwohnerdichte
B45: Gemeindefläche in ha per 31.12. | C45: =SUM(D45:BZ45) -> 198379.11 | D45: 3937.9027 | E45: 1219.8863 | F45: 907.13576 | G45: 1032.6048 | H45: 983.80483 | I45: 493.55439 | J45: 475.64582 | K45: 375.5481 | L45: 198.92533 | M45: 713.53101 | N45: 890.26861 | O45: 739.52706 | P45: 230.66874 | Q45: 1061.3525 | R45: 220.4941 | S45: 686.86051 | T45: 465.38316 | U45: 562.10794 | V45: 652.02473 | W45: 1124.5537 | X45: 421.82522 | Y45: 439.35968 | Z45: 438.05007 | AA45: 3946.2257 | AB45: 543.72095 | AC45: 3460.2139 | AD45: 933.35056 | AE45: 4156.4203 | AF45: 2227.3426 | AG45: 5464.7331 | AH45: 1595.008 | AI45: 3032.6793 | AJ45: 4175.1626 | AK45: 946.38909 | AL45: 3271.6752 | AM45: 2539.5592 | AN45: 12846.14 | AO45: 13910.56 | AP45: 7515.4821 | AQ45: 4884.1079 | AR45: 7321.0384 | AS45: 4761.8226 | AT45: 574.88233 | AU45: 3990.4293 | AV45: 1649.5495 | AW45: 1864.1369 | AX45: 3358.5925 | AY45: 753.53892 | AZ45: 597.65725 | BA45: 3136.8576 | BB45: 5489.1676 | BC45: 8752.84 | BD45: 9270.1651 | BE45: 4354.5887 | BF45: 5117.5465 | BG45: 282.00813 | BH45: 8184.0326 | BI45: 2183.3848 | BJ45: 1409.6043 | BK45: 5051.0875 | BL45: 4253.973 | BM45: 1099.4986 | BN45: 1407.6019 | BO45: 1449.5028 | BP45: 1146.9009 | BQ45: 1447.7431 | BR45: 2081.6392 | BS45: 896.73393 | BT45: 1773.1319 | BU45: 1583.6607 | BV45: 1637.1642 | BW45: 2750.6228 | BX45: 630.62275 | BY45: 3134.3092 | BZ45: 1263.2849 | CB45: BD
B46: Gemeindefläche je Einwohner | D46: =D45/D12 -> 0.050348443 | E46: =E45/E12 -> 0.12167228 | F46: =F45/F12 -> 0.63391737 | G46: =G45/G12 -> 0.82148356 | H46: =H45/H12 -> 0.26865233 | I46: =I45/I12 -> 0.05083473 | J46: =J45/J12 -> 0.13286196 | K46: =K45/K12 -> 0.37109496 | ... BZ46: =BZ45/BZ12 -> 0.14674002
B47: Pauschalbeitrag je ha je Einwohner | C47: 29 | CB47: FAG
B48: Beitrag je Einwohner | D48: =D46*$C47 -> 1.4601048 | E48: =E46*$C47 -> 3.528496 | F48: =F46*$C47 -> 18.383604 | G48: =G46*$C47 -> 23.823023 | H48: =H46*$C47 -> 7.7909176 | I48: =I46*$C47 -> 1.4742072 | J48: =J46*$C47 -> 3.8529969 | K48: =K46*$C47 -> 10.761754 | ... BZ48: =BZ46*$C47 -> 4.2554607
B50: Sonderlast total | D50: =D48*D12 -> 114199.18 | E50: =E48*E12 -> 35376.701 | F50: =F48*F12 -> 26306.937 | G50: =G48*G12 -> 29945.54 | H50: =H48*H12 -> 28530.34 | I50: =I48*I12 -> 14313.077 | J50: =J48*J12 -> 13793.729 | K50: =K48*K12 -> 10890.895 | ... BZ50: =BZ48*BZ12 -> 36635.261
A52: 2.5) | B52: Korrekturwert
B54: Korrekturwert je Einwohner für mittlere Belastung | C54: 320 | CB54: FAG
B56: Minderlast total | D56: =D12*$C54*-1 -> -25028160 | E56: =E12*$C54*-1 -> -3208320 | F56: =F12*$C54*-1 -> -457920 | G56: =G12*$C54*-1 -> -402240 | H56: =H12*$C54*-1 -> -1171840 | I56: =I12*$C54*-1 -> -3106880 | J56: =J12*$C54*-1 -> -1145600 | K56: =K12*$C54*-1 -> -323840 | ... BZ56: =BZ12*$C54*-1 -> -2754880
A58: 2.6) | B58: Sonderlastenausgleich Weite (vor allfälliger Kürzung) | D58: =IF((D24+D33+D41+D50+D56)<0,0,D24+D33+D41+D50+D56) -> 0 | E58: =IF((E24+E33+E41+E50+E56)<0,0,E24+E33+E41+E50+E56) -> 0 | F58: =IF((F24+F33+F41+F50+F56)<0,0,F24+F33+F41+F50+F56) -> 386559.72 | G58: =IF((G24+G33+G41+G50+G56)<0,0,G24+G33+G41+G50+G56) -> 624847.75 | H58: =IF((H24+H33+H41+H50+H56)<0,0,H24+H33+H41+H50+H56) -> 56318.234 | I58: =IF((I24+I33+I41+I50+I56)<0,0,I24+I33+I41+I50+I56) -> 0 | J58: =IF((J24+J33+J41+J50+J56)<0,0,J24+J33+J41+J50+J56) -> 0 | K58: =IF((K24+K33+K41+K50+K56)<0,0,K24+K33+K41+K50+K56) -> 18453.747 | ... BZ58: =IF((BZ24+BZ33+BZ41+BZ50+BZ56)<0,0,BZ24+BZ33+BZ41+BZ50+BZ56) -> 0
A60: 2.7) | B60: Kürzung infolge hoher technischer Steuerkraft
B62: Technische Steuerkraft in % zum kantonalen Durchschnitt | D62: ='Ressourcenausgleich Basis'!D144 -> 1.119226 | E62: ='Ressourcenausgleich Basis'!E144 -> 0.80767902 | F62: ='Ressourcenausgleich Basis'!F144 -> 0.84030989 | G62: ='Ressourcenausgleich Basis'!G144 -> 0.77439043 | H62: ='Ressourcenausgleich Basis'!H144 -> 1.8170994 | I62: ='Ressourcenausgleich Basis'!I144 -> 1.0415529 | J62: ='Ressourcenausgleich Basis'!J144 -> 0.94023797 | K62: ='Ressourcenausgleich Basis'!K144 -> 1.1118426 | ... BZ62: ='Ressourcenausgleich Basis'!BZ144 -> 1.0767138
B64: Kürzungsfaktor in % | D64: =IF(D62<100%,0%,IF(D62>120%,100%,(-100%+D62)/20*100)) -> 0.59613 | E64: =IF(E62<100%,0%,IF(E62>120%,100%,(-100%+E62)/20*100)) -> 0 | F64: =IF(F62<100%,0%,IF(F62>120%,100%,(-100%+F62)/20*100)) -> 0 | G64: =IF(G62<100%,0%,IF(G62>120%,100%,(-100%+G62)/20*100)) -> 0 | H64: =IF(H62<100%,0%,IF(H62>120%,100%,(-100%+H62)/20*100)) -> 1 | I64: =IF(I62<100%,0%,IF(I62>120%,100%,(-100%+I62)/20*100)) -> 0.20776451 | J64: =IF(J62<100%,0%,IF(J62>120%,100%,(-100%+J62)/20*100)) -> 0 | K64: =IF(K62<100%,0%,IF(K62>120%,100%,(-100%+K62)/20*100)) -> 0.559213 | ... BZ64: =IF(BZ62<100%,0%,IF(BZ62>120%,100%,(-100%+BZ62)/20*100)) -> 0.3835692
B65: Kürzung in Fr. | D65: =D58*-D64 -> 0 | E65: =E58*-E64 -> 0 | F65: =F58*-F64 -> 0 | G65: =G58*-G64 -> 0 | H65: =H58*-H64 -> -56318.234 | I65: =I58*-I64 -> 0 | J65: =J58*-J64 -> 0 | K65: =K58*-K64 -> -10319.575 | ... BZ65: =BZ58*-BZ64 -> 0
A68: 3.) | B68: Zusammenfassung
B70: Sonderlastenausgleich Weite (vor allfälliger Kürzung) | C70: =SUM(D70:BZ70) -> 37941178 | D70: =D58 -> 0 | E70: =E58 -> 0 | F70: =F58 -> 386559.72 | G70: =G58 -> 624847.75 | H70: =H58 -> 56318.234 | I70: =I58 -> 0 | J70: =J58 -> 0 | K70: =K58 -> 18453.747 | ... BZ70: =BZ58 -> 0
B72: Kürzung infolge hoher technischer Steuerkraft | C72: =SUM(D72:BZ72) -> -2388643.7 | D72: =D65 -> 0 | E72: =E65 -> 0 | F72: =F65 -> 0 | G72: =G65 -> 0 | H72: =H65 -> -56318.234 | I72: =I65 -> 0 | J72: =J65 -> 0 | K72: =K65 -> -10319.575 | ... BZ72: =BZ65 -> 0
B74: Beitrag Sonderlastenausgleich Weite | C74: =SUM(D74:BZ74) -> 35552500 | D74: =ROUND(D70+D72,-2) -> 0 | E74: =ROUND(E70+E72,-2) -> 0 | F74: =ROUND(F70+F72,-2) -> 386600 | G74: =ROUND(G70+G72,-2) -> 624800 | H74: =ROUND(H70+H72,-2) -> 0 | I74: =ROUND(I70+I72,-2) -> 0 | J74: =ROUND(J70+J72,-2) -> 0 | K74: =ROUND(K70+K72,-2) -> 8100 | ... BZ74: =ROUND(BZ70+BZ72,-2) -> 0

Sheet SL Schule Basis
A1: Kanton St.Gallen
A2: Amt für Gemeinden und Bürgerrecht
A5: Sonderlastenausgleich Schule 2025 | D5: Vorgenommene Korrekturen für Nachkalkulation!
B7: Eingabefelder
C8: Total | D8: St.Gallen | E8: Wittenbach | F8: Häggenschwil | G8: Muolen | H8: Mörschwil | I8: Goldach | J8: Steinach | K8: Berg | L8: Tübach | M8: Untereggen | N8: Eggersriet | O8: Rorschacherberg | P8: Rorschach | Q8: Thal | R8: Rheineck | S8: St.Margrethen | T8: Au | U8: Berneck | V8: Balgach | W8: Diepoldsau | X8: Widnau | Y8: Rebstein | Z8: Marbach | AA8: Altstätten | AB8: Eichberg | AC8: Oberriet | AD8: Rüthi | AE8: Sennwald | AF8: Gams | AG8: Grabs | AH8: Buchs | AI8: Sevelen | AJ8: Wartau | AK8: Sargans | AL8: Vilters-Wangs | AM8: Bad Ragaz | AN8: Pfäfers | AO8: Mels | AP8: Flums | AQ8: Walenstadt | AR8: Quarten | AS8: Amden | AT8: Weesen | AU8: Schänis | AV8: Benken | AW8: Kaltbrunn | AX8: Gommiswald | AY8: Uznach | AZ8: Schmerikon | BA8: Rapperswil-Jona | BB8: Eschenbach | BC8: Wildhaus-Alt St.Johann | BD8: Nesslau | BE8: Ebnat-Kappel | BF8: Wattwil | BG8: Lichtensteig | BH8: Neckertal | BI8: Bütschwil-Ganterschwil | BJ8: Lütisburg | BK8: Mosnang | BL8: Kirchberg | BM8: Jonschwil | BN8: Oberuzwil | BO8: Uzwil | BP8: Flawil | BQ8: Degersheim | BR8: Wil | BS8: Zuzwil | BT8: Oberbüren | BU8: Niederbüren | BV8: Niederhelfenschwil | BW8: Gossau | BX8: Andwil | BY8: Waldkirch | BZ8: Gaiserwald | CB8: Quelle
A10: 1.) | B10: Allgemeine Daten
B12: ='Ressourcenausgleich Basis'!B124 -> Einwohnerzahl per 31.12. | C12: ='Ressourcenausgleich Basis'!C124 -> 535114 | D12: ='Ressourcenausgleich Basis'!D124 -> 78213 | E12: ='Ressourcenausgleich Basis'!E124 -> 10026 | F12: ='Ressourcenausgleich Basis'!F124 -> 1431 | G12: ='Ressourcenausgleich Basis'!G124 -> 1257 | H12: ='Ressourcenausgleich Basis'!H124 -> 3662 | I12: ='Ressourcenausgleich Basis'!I124 -> 9709 | ... BZ12: ='Ressourcenausgleich Basis'!BZ124 -> 8609
B14: Schülerzahlen Volksschule per 31.12.2023 | C14: =SUM(D14:BZ14) -> 60379 | D14: 7466 | E14: 1157 | F14: 210 | G14: 153 | H14: 420 | I14: 1045 | J14: 369 | K14: 124 | L14: 231 | M14: 136 | N14: 311 | O14: 763 | P14: 946 | Q14: 731 | R14: 324 | S14: 752 | T14: 901 | U14: 466 | V14: 588 | W14: 818 | X14: 1173 | Y14: 506 | Z14: 229 | AA14: 1384 | AB14: 191 | AC14: 1131 | AD14: 344 | AE14: 613 | AF14: 491 | AG14: 903 | AH14: 1616 | AI14: 685 | AJ14: 718 | AK14: 793 | AL14: 589 | AM14: 698 | AN14: 186 | AO14: 1147 | AP14: 664 | AQ14: 688 | AR14: 313 | AS14: 171 | AT14: 181 | AU14: 582 | AV14: 393 | AW14: 604 | AX14: 581 | AY14: 853 | AZ14: 441 | BA14: 2968 | BB14: 1206 | BC14: 319 | BD14: 417 | BE14: 564 | BF14: 1034 | BG14: 197 | BH14: 835 | BI14: 681 | BJ14: 234 | BK14: 420 | BL14: 1298 | BM14: 537 | BN14: 860 | BO14: 1744 | BP14: 1277 | BQ14: 558 | BR14: 2744 | BS14: 563 | BT14: 558 | BU14: 217 | BV14: 459 | BW14: 2065 | BX14: 298 | BY14: 530 | BZ14: 1017 | CB14: BLD
B15: Schülerzahlen Sonderschule per 31.12.2023 | C15: =SUM(D15:BZ15) -> 1583 | D15: 219 | E15: 42 | F15: 2 | G15: 3 | H15: 8 | I15: 32 | J15: 10 | K15: 1 | L15: 2 | M15: 5 | N15: 13 | O15: 32 | P15: 47 | Q15: 13 | R15: 12 | S15: 22 | T15: 28 | U15: 10 | V15: 10 | W15: 13 | X15: 38 | Y15: 24 | Z15: 4 | AA15: 39 | AB15: 2 | AC15: 25 | AD15: 5 | AE15: 9 | AF15: 5 | AG15: 21 | AH15: 46 | AI15: 17 | AJ15: 14 | AK15: 19 | AL15: 11 | AM15: 18 | AN15: 3 | AO15: 28 | AP15: 13 | AQ15: 16 | AR15: 1 | AS15: 3 | AT15: 4 | AU15: 13 | AV15: 12 | AW15: 10 | AX15: 11 | AY15: 35 | AZ15: 10 | BA15: 63 | BB15: 31 | BC15: 0 | BD15: 12 | BE15: 22 | BF15: 46 | BG15: 12 | BH15: 29 | BI15: 21 | BJ15: 6 | BK15: 5 | BL15: 37 | BM15: 6 | BN15: 26 | BO15: 43 | BP15: 43 | BQ15: 10 | BR15: 82 | BS15: 14 | BT15: 8 | BU15: 2 | BV15: 5 | BW15: 45 | BX15: 3 | BY15: 5 | BZ15: 27 | CB15: BLD
B17: Nettoaufwand Schulrat in Einheitsgemeinden (Funktion 0121) | C17: =SUM(D17:BZ17) -> 6056128.4 | D17: 26415.95 | E17: 15160 | F17: 47814.75 | G17: 29394.2 | H17: 0 | I17: 156205 | J17: 79802.65 | K17: 70229.25 | L17: 29928 | M17: 50949.11 | N17: 77894.8 | O17: 261485.15 | P17: 249309.45 | Q17: 75871.07 | R17: 109590.15 | S17: 142707.25 | T17: 0 | U17: 115564.1 | V17: 0 | W17: 249430.9 | X17: 336027.05 | Y17: 0 | Z17: 0 | AA17: 0 | AB17: 0 | AC17: 0 | AD17: 19939.2 | AE17: 149071.3 | AF17: 152488.48 | AG17: 54651.1 | AH17: 125182 | AI17: 143787.1 | AJ17: 114955.45 | AK17: 113756.7 | AL17: 83437.19 | AM17: 145649.61 | AN17: 43079.45 | AO17: 173573.95 | AP17: 102806.68 | AQ17: 16751.35 | AR17: 116178.6 | AS17: 0 | AT17: 0 | AU17: 0 | AV17: 74938.55 | AW17: 6858.6 | AX17: 0 | AY17: 0 | AZ17: 0 | BA17: 98605 | BB17: 43123.5 | BC17: 49582.17 | BD17: 31603.15 | BE17: 129850 | BF17: 0 | BG17: 59249.45 | BH17: 6071.65 | BI17: 137622.35 | BJ17: 0 | BK17: 111421.25 | BL17: 131797.2 | BM17: 110114.3 | BN17: 69710.05 | BO17: 45072.5 | BP17: 266518.24 | BQ17: 98895.25 | BR17: 36364.6 | BS17: 96290.15 | BT17: 0 | BU17: 0 | BV17: 35057.35 | BW17: 321412.1 | BX17: 0 | BY17: 169745.83 | BZ17: 247138.15 | CB17: GFS
B18: Nettoaufwand Obligatorische Schule (Funktion 21) | C18: =SUM(D18:BZ18) -> 1.1954987e+09 | D18: 1.6479301e+08 | E18: 22153097 | F18: 3868385.5 | G18: 3149919.8 | H18: 8937112.8 | I18: 19532274 | J18: 7451553.4 | K18: 2559988.5 | L18: 3897994.2 | M18: 2730834.2 | N18: 5930382.2 | O18: 15778317 | P18: 21124538 | Q18: 14716465 | R18: 6067391.9 | S18: 13286184 | T18: 18030766 | U18: 8959580.4 | V18: 10332333 | W18: 14634824 | X18: 19418440 | Y18: 10676102 | Z18: 4868991 | AA18: 26895536 | AB18: 3613717.9 | AC18: 22184318 | AD18: 6330471.7 | AE18: 12131719 | AF18: 8986756.5 | AG18: 17073004 | AH18: 29202052 | AI18: 13161143 | AJ18: 13315056 | AK18: 14248350 | AL18: 11752890 | AM18: 13007285 | AN18: 4577235.7 | AO18: 20559907 | AP18: 11380075 | AQ18: 11975123 | AR18: 5581747.5 | AS18: 3851683.2 | AT18: 3933518 | AU18: 8948826.5 | AV18: 7533931.9 | AW18: 10947302 | AX18: 12678046 | AY18: 16322011 | AZ18: 9234890.4 | BA18: 64971345 | BB18: 23788559 | BC18: 6042872.2 | BD18: 8069592.6 | BE18: 13366358 | BF18: 17961728 | BG18: 3786616 | BH18: 17505607 | BI18: 12802283 | BJ18: 4885962.8 | BK18: 8608225.6 | BL18: 27680949 | BM18: 11415024 | BN18: 17851847 | BO18: 29670026 | BP18: 25007218 | BQ18: 9829828.7 | BR18: 56050109 | BS18: 11798940 | BT18: 11879645 | BU18: 4788722.2 | BV18: 9168570.1 | BW18: 38844774 | BX18: 5590125 | BY18: 10303068 | BZ18: 21505665 | CB18: GFS
B19: Nettoaufwand Schulgesundheitsdienst in EHG (Funktion 433) | C19: =SUM(D19:BZ19) -> 3910715.7 | D19: 1736001.8 | E19: 37046.45 | F19: 8034.2 | G19: 4431 | H19: 0 | I19: 65020.2 | J19: 17787.1 | K19: 3219.15 | L19: 9316.95 | M19: 7034.7 | N19: 10007.15 | O19: 36218.55 | P19: 30945.4 | Q19: 38767.82 | R19: 15065.7 | S19: 22894 | T19: 0 | U19: 15080.95 | V19: 0 | W19: 36917.3 | X19: 48998.24 | Y19: 0 | Z19: 0 | AA19: 0 | AB19: 0 | AC19: 0 | AD19: 8746.49 | AE19: 30642.5 | AF19: 23538.05 | AG19: 54799.66 | AH19: 86784.1 | AI19: 28854.55 | AJ19: 29927.85 | AK19: 28771.25 | AL19: 31745.6 | AM19: 33557.25 | AN19: 9012.77 | AO19: 27877.65 | AP19: 37114.05 | AQ19: 38674.95 | AR19: 29732.6 | AS19: 0 | AT19: 0 | AU19: 38837.3 | AV19: 17110.9 | AW19: 33778.2 | AX19: 22098.3 | AY19: 45322.1 | AZ19: 26285.8 | BA19: 161101.41 | BB19: 65967.85 | BC19: 16169.8 | BD19: 32979.44 | BE19: 32234.25 | BF19: 0 | BG19: 7729.8 | BH19: 21442 | BI19: 22486.71 | BJ19: 0 | BK19: 27404.15 | BL19: 66930.35 | BM19: 26132.45 | BN19: 23515.69 | BO19: 66877.14 | BP19: 53979.25 | BQ19: 11534.25 | BR19: 231893.2 | BS19: 31065.85 | BT19: 0 | BU19: 0 | BV19: 18957.3 | BW19: 88327.06 | BX19: 0 | BY19: 24569.88 | BZ19: 53419.3 | CB19: GFS
B20: Total | C20: =SUM(C17:C19) -> 1.2054656e+09 | D20: =SUM(D17:D19) -> 1.6655543e+08 | E20: =SUM(E17:E19) -> 22205303 | F20: =SUM(F17:F19) -> 3924234.5 | G20: =SUM(G17:G19) -> 3183745 | H20: =SUM(H17:H19) -> 8937112.8 | I20: =SUM(I17:I19) -> 19753499 | J20: =SUM(J17:J19) -> 7549143.2 | ... BZ20: =SUM(BZ17:BZ19) -> 21806223
B22: Kantonaler Durchschnitt Kosten je Schüler | C22: =C20/C14 -> 19964.981
A25: 2.) | B25: Berechnung Sonderlastenausgleich Schule
A27: 2.1) | B27: Sonder-/Minderlasten Volksschule
B29: Beitragssatz Volksschule bei überdurchschnittlicher Belastung | C29: 0.65
B30: Beitragssatz Volksschule bei unterdurchschnittlicher Belastung | C30: 0.2
B31: Volksschüler je Einwohner | C31: =C14/C12 -> 0.1128339 | D31: =D14/D12 -> 0.095457277 | E31: =E14/E12 -> 0.11539996 | F31: =F14/F12 -> 0.14675052 | G31: =G14/G12 -> 0.12171838 | H31: =H14/H12 -> 0.11469143 | I31: =I14/I12 -> 0.10763209 | J31: =J14/J12 -> 0.10307263 | ... BZ31: =BZ14/BZ12 -> 0.11813219
B32: BLD-Sozialindex per 31.12. | D32: 1.11 | E32: 1.06 | F32: 0.83 | G32: 0.84 | H32: 0.81 | I32: 0.99 | J32: 0.97 | K32: 0.85 | L32: 0.83 | M32: 0.8 | N32: 0.85 | O32: 1 | P32: 1.2 | Q32: 0.94 | R32: 1.04 | S32: 1.11 | T32: 1.02 | U32: 0.88 | V32: 0.89 | W32: 0.91 | X32: 0.94 | Y32: 1.03 | Z32: 0.88 | AA32: 0.98 | AB32: 0.87 | AC32: 0.91 | AD32: 0.92 | AE32: 0.94 | AF32: 0.9 | AG32: 0.92 | AH32: 1.03 | AI32: 1.05 | AJ32: 0.98 | AK32: 0.95 | AL32: 0.89 | AM32: 0.93 | AN32: 0.86 | AO32: 0.92 | AP32: 0.96 | AQ32: 0.92 | AR32: 0.87 | AS32: 0.83 | AT32: 0.93 | AU32: 0.92 | AV32: 0.87 | AW32: 0.93 | AX32: 0.9 | AY32: 1.01 | AZ32: 0.98 | BA32: 0.92 | BB32: 0.9 | BC32: 0.86 | BD32: 0.95 | BE32: 0.99 | BF32: 1.05 | BG32: 1.05 | BH32: 0.97 | BI32: 0.96 | BJ32: 0.91 | BK32: 0.86 | BL32: 1.02 | BM32: 0.88 | BN32: 0.94 | BO32: 1.01 | BP32: 1.03 | BQ32: 0.97 | BR32: 1.09 | BS32: 0.86 | BT32: 0.87 | BU32: 0.8 | BV32: 0.83 | BW32: 0.94 | BX32: 0.85 | BY32: 0.85 | BZ32: 0.92 | CB32: Fachstelle für Statistik
B33: reduzierter BLD-Sozialindex per 31.12. | D33: =1+(D32-1)*0.15 -> 1.0165 | E33: =1+(E32-1)*0.15 -> 1.009 | F33: =1+(F32-1)*0.15 -> 0.9745 | G33: =1+(G32-1)*0.15 -> 0.976 | H33: =1+(H32-1)*0.15 -> 0.9715 | I33: =1+(I32-1)*0.15 -> 0.9985 | J33: =1+(J32-1)*0.15 -> 0.9955 | K33: =1+(K32-1)*0.15 -> 0.9775 | ... BZ33: =1+(BZ32-1)*0.15 -> 0.988
B35: Sonder-/Minderlasten Volksschule (vor allfälliger Kürzung) | D35: =IF(D31*D33>$C31,(D31*D33-$C31)*D12*$C22*$C29,(D31*D33-$C31)*D12*$C22*$C30) -> -4934899.6 | E35: =IF(E31*E33>$C31,(E31*E33-$C31)*E12*$C22*$C29,(E31*E33-$C31)*E12*$C22*$C30) -> 469001.4 | F35: =IF(F31*F33>$C31,(F31*F33-$C31)*F12*$C22*$C29,(F31*F33-$C31)*F12*$C22*$C30) -> 560353.07 | G35: =IF(G31*G33>$C31,(G31*G33-$C31)*G12*$C22*$C29,(G31*G33-$C31)*G12*$C22*$C30) -> 97274.605 | H35: =IF(H31*H33>$C31,(H31*H33-$C31)*H12*$C22*$C29,(H31*H33-$C31)*H12*$C22*$C30) -> -20634.785 | I35: =IF(I31*I33>$C31,(I31*I33-$C31)*I12*$C22*$C29,(I31*I33-$C31)*I12*$C22*$C30) -> -207922.67 | J35: =IF(J31*J33>$C31,(J31*J33-$C31)*J12*$C22*$C29,(J31*J33-$C31)*J12*$C22*$C30) -> -146167.08 | K35: =IF(K31*K33>$C31,(K31*K33-$C31)*K12*$C22*$C29,(K31*K33-$C31)*K12*$C22*$C30) -> 91127.361 | ... BZ35: =IF(BZ31*BZ33>$C31,(BZ31*BZ33-$C31)*BZ12*$C22*$C29,(BZ31*BZ33-$C31)*BZ12*$C22*$C30) -> 433555.85
A37: 2.2) | B37: Sonderlasten Sonderschule
B39: Pauschalbeitrag je Schüler in der Sonderschule | C39: 11000
B40: Beitragssatz Sonderschule | C40: 0.65
B41: Sonderschüler je Einwohner | C41: =C15/C12 -> 0.0029582481 | D41: =D15/D12 -> 0.002800046 | E41: =E15/E12 -> 0.0041891083 | F41: =F15/F12 -> 0.001397624 | G41: =G15/G12 -> 0.0023866348 | H41: =H15/H12 -> 0.0021845986 | I41: =I15/I12 -> 0.003295911 | J41: =J15/J12 -> 0.0027932961 | ... BZ41: =BZ15/BZ12 -> 0.0031362528
B43: Sonderlasten Sonderschule (vor allfälliger Kürzung) | D43: =IF(D41>$C41,(D41-$C41)*D12*$C39*$C40,0) -> 0 | E43: =IF(E41>$C41,(E41-$C41)*E12*$C39*$C40,0) -> 88235.319 | F43: =IF(F41>$C41,(F41-$C41)*F12*$C39*$C40,0) -> 0 | G43: =IF(G41>$C41,(G41-$C41)*G12*$C39*$C40,0) -> 0 | H43: =IF(H41>$C41,(H41-$C41)*H12*$C39*$C40,0) -> 0 | I43: =IF(I41>$C41,(I41-$C41)*I12*$C39*$C40,0) -> 23440.336 | J43: =IF(J41>$C41,(J41-$C41)*J12*$C39*$C40,0) -> 0 | K43: =IF(K41>$C41,(K41-$C41)*K12*$C39*$C40,0) -> 0 | ... BZ43: =IF(BZ41>$C41,(BZ41-$C41)*BZ12*$C39*$C40,0) -> 10956.958
A45: 2.3) | B45: Sonderlastenausgleich Schule (vor allfälliger Kürzung) | D45: =IF(D35+D43<0,0,D35+D43) -> 0 | E45: =IF(E35+E43<0,0,E35+E43) -> 557236.71 | F45: =IF(F35+F43<0,0,F35+F43) -> 560353.07 | G45: =IF(G35+G43<0,0,G35+G43) -> 97274.605 | H45: =IF(H35+H43<0,0,H35+H43) -> 0 | I45: =IF(I35+I43<0,0,I35+I43) -> 0 | J45: =IF(J35+J43<0,0,J35+J43) -> 0 | K45: =IF(K35+K43<0,0,K35+K43) -> 91127.361 | ... BZ45: =IF(BZ35+BZ43<0,0,BZ35+BZ43) -> 444512.81
A47: 2.4) | B47: Kürzung infolge hoher technischer Steuerkraft
B49: Technische Steuerkraft in % zum kantonalen Durchschnitt | D49: ='Ressourcenausgleich Basis'!D144 -> 1.119226 | E49: ='Ressourcenausgleich Basis'!E144 -> 0.80767902 | F49: ='Ressourcenausgleich Basis'!F144 -> 0.84030989 | G49: ='Ressourcenausgleich Basis'!G144 -> 0.77439043 | H49: ='Ressourcenausgleich Basis'!H144 -> 1.8170994 | I49: ='Ressourcenausgleich Basis'!I144 -> 1.0415529 | J49: ='Ressourcenausgleich Basis'!J144 -> 0.94023797 | K49: ='Ressourcenausgleich Basis'!K144 -> 1.1118426 | ... BZ49: ='Ressourcenausgleich Basis'!BZ144 -> 1.0767138
B51: Kürzungsfaktor in % | D51: =IF(D49<100%,0%,IF(D49>120%,100%,(-100%+D49)/20*100)) -> 0.59613 | E51: =IF(E49<100%,0%,IF(E49>120%,100%,(-100%+E49)/20*100)) -> 0 | F51: =IF(F49<100%,0%,IF(F49>120%,100%,(-100%+F49)/20*100)) -> 0 | G51: =IF(G49<100%,0%,IF(G49>120%,100%,(-100%+G49)/20*100)) -> 0 | H51: =IF(H49<100%,0%,IF(H49>120%,100%,(-100%+H49)/20*100)) -> 1 | I51: =IF(I49<100%,0%,IF(I49>120%,100%,(-100%+I49)/20*100)) -> 0.20776451 | J51: =IF(J49<100%,0%,IF(J49>120%,100%,(-100%+J49)/20*100)) -> 0 | K51: =IF(K49<100%,0%,IF(K49>120%,100%,(-100%+K49)/20*100)) -> 0.559213 | ... BZ51: =IF(BZ49<100%,0%,IF(BZ49>120%,100%,(-100%+BZ49)/20*100)) -> 0.3835692
B52: Kürzung in Fr. | D52: =D45*-D51 -> 0 | E52: =E45*-E51 -> 0 | F52: =F45*-F51 -> 0 | G52: =G45*-G51 -> 0 | H52: =H45*-H51 -> 0 | I52: =I45*-I51 -> 0 | J52: =J45*-J51 -> 0 | K52: =K45*-K51 -> -50959.605 | ... BZ52: =BZ45*-BZ51 -> -170501.42
A55: 3.) | B55: Zusammenfassung
B57: Sonder-/Minderlasten Volksschule | C57: =SUM(D57:BZ57) -> 22242517 | D57: =D35 -> -4934899.6 | E57: =E35 -> 469001.4 | F57: =F35 -> 560353.07 | G57: =G35 -> 97274.605 | H57: =H35 -> -20634.785 | I57: =I35 -> -207922.67 | J57: =J35 -> -146167.08 | K57: =K35 -> 91127.361 | ... BZ57: =BZ35 -> 433555.85
B58: Sonderlasten Sonderschule | C58: =SUM(D58:BZ58) -> 1329536.9 | D58: =D43 -> 0 | E58: =E43 -> 88235.319 | F58: =F43 -> 0 | G58: =G43 -> 0 | H58: =H43 -> 0 | I58: =I43 -> 23440.336 | J58: =J43 -> 0 | K58: =K43 -> 0 | ... BZ58: =BZ43 -> 10956.958
B60: Sonderlastenausgleich Schule (vor allfälliger Kürzung) | C60: =SUM(D60:BZ60) -> 34029883 | D60: =D45 -> 0 | E60: =E45 -> 557236.71 | F60: =F45 -> 560353.07 | G60: =G45 -> 97274.605 | H60: =H45 -> 0 | I60: =I45 -> 0 | J60: =J45 -> 0 | K60: =K45 -> 91127.361 | ... BZ60: =BZ45 -> 444512.81
B62: Kürzung infolge hoher technischer Steuerkraft | C62: =SUM(D62:BZ62) -> -974984.31 | D62: =D52 -> 0 | E62: =E52 -> 0 | F62: =F52 -> 0 | G62: =G52 -> 0 | H62: =H52 -> 0 | I62: =I52 -> 0 | J62: =J52 -> 0 | K62: =K52 -> -50959.605 | ... BZ62: =BZ52 -> -170501.42
B64: Beitrag Sonderlastenausgleich Schule | C64: =SUM(D64:BZ64) -> 33054900 | D64: =ROUND(D60+D62,-2) -> 0 | E64: =ROUND(E60+E62,-2) -> 557200 | F64: =ROUND(F60+F62,-2) -> 560400 | G64: =ROUND(G60+G62,-2) -> 97300 | H64: =ROUND(H60+H62,-2) -> 0 | I64: =ROUND(I60+I62,-2) -> 0 | J64: =ROUND(J60+J62,-2) -> 0 | K64: =ROUND(K60+K62,-2) -> 40200 | ... BZ64: =ROUND(BZ60+BZ62,-2) -> 274000

Sheet SL Sozio Basis
A1: Kanton St.Gallen
A2: Amt für Gemeinden und Bürgerrecht
A5: Soziodemographischer Sonderlastenausgleich 2025 | E5: Vorgenommene Korrekturen für Nachkalkulation!
B7: Eingabefelder
C8: Total | D8: St.Gallen | E8: Wittenbach | F8: Häggenschwil | G8: Muolen | H8: Mörschwil | I8: Goldach | J8: Steinach | K8: Berg | L8: Tübach | M8: Untereggen | N8: Eggersriet | O8: Rorschacherberg | P8: Rorschach | Q8: Thal | R8: Rheineck | S8: St.Margrethen | T8: Au | U8: Berneck | V8: Balgach | W8: Diepoldsau | X8: Widnau | Y8: Rebstein | Z8: Marbach | AA8: Altstätten | AB8: Eichberg | AC8: Oberriet | AD8: Rüthi | AE8: Sennwald | AF8: Gams | AG8: Grabs | AH8: Buchs | AI8: Sevelen | AJ8: Wartau | AK8: Sargans | AL8: Vilters-Wangs | AM8: Bad Ragaz | AN8: Pfäfers | AO8: Mels | AP8: Flums | AQ8: Walenstadt | AR8: Quarten | AS8: Amden | AT8: Weesen | AU8: Schänis | AV8: Benken | AW8: Kaltbrunn | AX8: Gommiswald | AY8: Uznach | AZ8: Schmerikon | BA8: Rapperswil-Jona | BB8: Eschenbach | BC8: Wildhaus-Alt St.Johann | BD8: Nesslau | BE8: Ebnat-Kappel | BF8: Wattwil | BG8: Lichtensteig | BH8: Neckertal | BI8: Bütschwil-Ganterschwil | BJ8: Lütisburg | BK8: Mosnang | BL8: Kirchberg | BM8: Jonschwil | BN8: Oberuzwil | BO8: Uzwil | BP8: Flawil | BQ8: Degersheim | BR8: Wil | BS8: Zuzwil | BT8: Oberbüren | BU8: Niederbüren | BV8: Niederhelfenschwil | BW8: Gossau | BX8: Andwil | BY8: Waldkirch | BZ8: Gaiserwald | CB8: Quelle
A10: 1.) | B10: Allgemeine Daten
B12: ='Ressourcenausgleich Basis'!B124 -> Einwohnerzahl per 31.12. | C12: ='Ressourcenausgleich Basis'!C124 -> 535114 | D12: ='Ressourcenausgleich Basis'!D124 -> 78213 | E12: ='Ressourcenausgleich Basis'!E124 -> 10026 | F12: ='Ressourcenausgleich Basis'!F124 -> 1431 | G12: ='Ressourcenausgleich Basis'!G124 -> 1257 | H12: ='Ressourcenausgleich Basis'!H124 -> 3662 | I12: ='Ressourcenausgleich Basis'!I124 -> 9709 | ... BZ12: ='Ressourcenausgleich Basis'!BZ124 -> 8609
A15: 2.) | B15: Berechnung Soziodemographischer Sonderlastenausgleich
A17: 2.1) | B17: Sonderlasten Familie und Jugend
B19: Beitragssatz bei überdurchschnittlicher Belastung | C19: 0.6
B20: Beitragssatz bei unterdurchschnittlicher Belastung | C20: 0
B22: Nettoaufwand Familie und Jugend (Funktion 54) | C22: =SUM(D22:BZ22) -> 72059794 | D22: 21771194 | E22: 1802506.7 | F22: 94269.85 | G22: 60989.52 | H22: 174296.1 | I22: 911808 | J22: 392428 | K22: 5021.7 | L22: 98350 | M22: 85416.4 | N22: 142109.92 | O22: 1034327.2 | P22: 2627215.5 | Q22: 444079.79 | R22: 269492.88 | S22: 1744712.7 | T22: 771676.82 | U22: 365825.92 | V22: 451561.69 | W22: 634045.75 | X22: 1280808.7 | Y22: 705632.25 | Z22: -1469.51 | AA22: 1141359.3 | AB22: 77708 | AC22: 177954.79 | AD22: 352191.47 | AE22: 379166.15 | AF22: 297749.6 | AG22: 661217.06 | AH22: 1430178 | AI22: 763414.43 | AJ22: 712635.14 | AK22: 376715.57 | AL22: 203391.25 | AM22: 387621.99 | AN22: 64997.8 | AO22: 1184427.8 | AP22: 389988.89 | AQ22: 604537.61 | AR22: 86200.15 | AS22: 20277 | AT22: 78443 | AU22: 363608.5 | AV22: 189520.95 | AW22: 842148.48 | AX22: 162382.51 | AY22: 808830.71 | AZ22: 411379.45 | BA22: 4663945.6 | BB22: 1114584.4 | BC22: 44881.21 | BD22: 345686.59 | BE22: 738303.64 | BF22: 1247792.7 | BG22: 253555.61 | BH22: 555947.85 | BI22: 288101.2 | BJ22: 339376.8 | BK22: 44011.6 | BL22: 949453.1 | BM22: 371258 | BN22: 539853.8 | BO22: 1035116.9 | BP22: 1534198.6 | BQ22: 649485.62 | BR22: 4710020.2 | BS22: 103414.92 | BT22: 202640.99 | BU22: 66.15 | BV22: 44926.47 | BW22: 2591019.6 | BX22: 50369.72 | BY22: 539342.96 | BZ22: 1068093.8 | CB22: GFS
B23: Nettoaufwand Familie und Jugend pro Einwohner | C23: =C22/C12 -> 134.66251 | D23: =D22/D12 -> 278.35774 | E23: =E22/E12 -> 179.78324 | F23: =F22/F12 -> 65.876904 | G23: =G22/G12 -> 48.519905 | H23: =H22/H12 -> 47.595877 | I23: =I22/I12 -> 93.913688 | J23: =J22/J12 -> 109.61676 | ... BZ23: =BZ22/BZ12 -> 124.06711
B25: Sonderlasten Familie und Jugend | C25: =SUM(D25:BZ25) -> 10062792 | D25: =IF(D23-$C23>0,(D23-$C23)*D12*$C19,(D23-$C23)*D12*$C20) -> 6743301.1 | E25: =IF(E23-$C23>0,(E23-$C23)*E12*$C19,(E23-$C23)*E12*$C20) -> 271428.26 | F25: =IF(F23-$C23>0,(F23-$C23)*F12*$C19,(F23-$C23)*F12*$C20) -> 0 | G25: =IF(G23-$C23>0,(G23-$C23)*G12*$C19,(G23-$C23)*G12*$C20) -> 0 | H25: =IF(H23-$C23>0,(H23-$C23)*H12*$C19,(H23-$C23)*H12*$C20) -> 0 | I25: =IF(I23-$C23>0,(I23-$C23)*I12*$C19,(I23-$C23)*I12*$C20) -> 0 | J25: =IF(J23-$C23>0,(J23-$C23)*J12*$C19,(J23-$C23)*J12*$C20) -> 0 | K25: =IF(K23-$C23>0,(K23-$C23)*K12*$C19,(K23-$C23)*K12*$C20) -> 0 | ... BZ25: =IF(BZ23-$C23>0,(BZ23-$C23)*BZ12*$C19,(BZ23-$C23)*BZ12*$C20) -> 0
A28: 2.2) | B28: Sonder-/Minderlasten Sozialhilfe
B30: Beitragssatz bei überdurchschnittlicher Belastung | C30: 0.6
B31: Beitragssatz bei unterdurchschnittlicher Belastung | C31: 0.2
B33: Nettoaufwand Finanzielle Sozialhilfe (Funktion 572) | C33: =SUM(D33:BZ33) -> 63432251 | D33: 21649705 | E33: 1674131.6 | F33: 88381.75 | G33: 98794.3 | H33: 52666.15 | I33: 525430 | J33: 309808 | K33: 0 | L33: 13903 | M33: 100893.35 | N33: 8625.05 | O33: 1298450.1 | P33: 1201616.1 | Q33: 324197.1 | R33: 831767.52 | S33: 461720.31 | T33: 1132770.8 | U33: 183700.11 | V33: -59035.45 | W33: 156147.38 | X33: 258973.54 | Y33: 214685.33 | Z33: 175258.02 | AA33: 735352.31 | AB33: 135147 | AC33: -87876.45 | AD33: 75908.3 | AE33: 430160.27 | AF33: 50432.75 | AG33: 469516.51 | AH33: 1194268 | AI33: 590519.61 | AJ33: 512049 | AK33: 497985.1 | AL33: 116539.85 | AM33: 334915.6 | AN33: 114665.36 | AO33: 383983.25 | AP33: 294421.13 | AQ33: 74135.48 | AR33: 136260.05 | AS33: 59817.5 | AT33: -68471 | AU33: 388641.37 | AV33: 368269.86 | AW33: 693942.98 | AX33: 222851.88 | AY33: 298290.48 | AZ33: 531005.38 | BA33: 3899133.5 | BB33: 574037.87 | BC33: 15201.97 | BD33: 278950.17 | BE33: 666021.94 | BF33: 1031510.9 | BG33: 109932.75 | BH33: 823900.16 | BI33: 496318.57 | BJ33: 93580.6 | BK33: 152268.11 | BL33: 2092587.5 | BM33: 219532 | BN33: 423119.85 | BO33: 1277741 | BP33: 2104758.8 | BQ33: 434193.55 | BR33: 5678103.6 | BS33: 278665.6 | BT33: 187427.6 | BU33: 9516.84 | BV33: 211300.4 | BW33: 1673321.1 | BX33: 70748.95 | BY33: 326945.77 | BZ33: 1048110.8 | CB33: GFS
B34: Nettoaufwand Finanzielle Sozialhilfe pro Einwohner | C34: =C33/C12 -> 118.5397 | D34: =D33/D12 -> 276.80443 | E34: =E33/E12 -> 166.97902 | F34: =F33/F12 -> 61.762229 | G34: =G33/G12 -> 78.595306 | H34: =H33/H12 -> 14.3818 | I34: =I33/I12 -> 54.117829 | J34: =J33/J12 -> 86.538547 | ... BZ34: =BZ33/BZ12 -> 121.74594
B36: Sonder-/Minderlasten Sozialhilfe | C36: =SUM(D36:BZ36) -> 7642281.4 | D36: =IF(D34-$C34>0,(D34-$C34)*D12*$C30,(D34-$C34)*D12*$C31) -> 7427015.9 | E36: =IF(E34-$C34>0,(E34-$C34)*E12*$C30,(E34-$C34)*E12*$C31) -> 291391.57 | F36: =IF(F34-$C34>0,(F34-$C34)*F12*$C30,(F34-$C34)*F12*$C31) -> -16249.711 | G36: =IF(G34-$C34>0,(G34-$C34)*G12*$C30,(G34-$C34)*G12*$C31) -> -10042.019 | H36: =IF(H34-$C34>0,(H34-$C34)*H12*$C30,(H34-$C34)*H12*$C31) -> -76285.243 | I36: =IF(I34-$C34>0,(I34-$C34)*I12*$C30,(I34-$C34)*I12*$C31) -> -125094.38 | J36: =IF(J34-$C34>0,(J34-$C34)*J12*$C30,(J34-$C34)*J12*$C31) -> -22912.822 | K36: =IF(K34-$C34>0,(K34-$C34)*K12*$C30,(K34-$C34)*K12*$C31) -> -23992.434 | ... BZ36: =IF(BZ34-$C34>0,(BZ34-$C34)*BZ12*$C30,(BZ34-$C34)*BZ12*$C31) -> 16561.554
A39: 2.3) | B39: Sonder-/Minderlasten Stationäre Pflege
B41: Beitragssatz bei überdurchschnittlicher Belastung | C41: 0.6
B42: Beitragssatz bei unterdurchschnittlicher Belastung | C42: 0.2
B44: Nettoaufwand Stationäre Pflege | C44: =SUM(D44:BZ44) -> 1.1522372e+08 | D44: 21229161 | E44: 2309180.1 | F44: 259026.05 | G44: 110200.95 | H44: 776135.25 | I44: 3282274.2 | J44: 622696.1 | K44: 278034.1 | L44: 304533 | M44: 177729.15 | N44: 375751.75 | O44: 1438868.2 | P44: 2440704.5 | Q44: 1073409.6 | R44: 849853.1 | S44: 1221404.9 | T44: 1659313 | U44: 814853.55 | V44: 687597.25 | W44: 962063.3 | X44: 1432349.6 | Y44: 1366736.2 | Z44: 324362.15 | AA44: 2580739 | AB44: 193206.95 | AC44: 1200066.2 | AD44: 340805 | AE44: 778917.55 | AF44: 480202.85 | AG44: 1365354.4 | AH44: 2594782.8 | AI44: 926205.85 | AJ44: 1048915.1 | AK44: 1280075.8 | AL44: 741133.15 | AM44: 1193529.5 | AN44: 570448.2 | AO44: 1730664.8 | AP44: 1083664.2 | AQ44: 1429594.6 | AR44: 842519.85 | AS44: 365847.6 | AT44: 398697.85 | AU44: 1123311.5 | AV44: 587198.15 | AW44: 668866.5 | AX44: 804404.8 | AY44: 1298549.9 | AZ44: 896832.1 | BA44: 5891530 | BB44: 1762034.8 | BC44: 610025.8 | BD44: 1041222.6 | BE44: 1461554.8 | BF44: 2678912.7 | BG44: 513724.65 | BH44: 1268775 | BI44: 1207282.1 | BJ44: 223721.15 | BK44: 660297.05 | BL44: 2478520.4 | BM44: 752132.8 | BN44: 1449612.3 | BO44: 3101702.7 | BP44: 2337543.1 | BQ44: 1492512.7 | BR44: 6888235.7 | BS44: 730672.9 | BT44: 641328.8 | BU44: 103911.5 | BV44: 551692.25 | BW44: 3972005.4 | BX44: 257661.65 | BY44: 823698.25 | BZ44: 1802637.9 | CB44: DfIF
B45: Nettoaufwand Stationäre Pflege pro Einwohner | C45: =C44/C12 -> 215.32556 | D45: =D44/D12 -> 271.42753 | E45: =E44/E12 -> 230.31918 | F45: =F44/F12 -> 181.01052 | G45: =G44/G12 -> 87.669809 | H45: =H44/H12 -> 211.943 | I45: =I44/I12 -> 338.06511 | J45: =J44/J12 -> 173.93746 | ... BZ45: =BZ44/BZ12 -> 209.38993
B47: Sonder-/Minderlasten Stationäre Pflege | C47: =SUM(D47:BZ47) -> 4563466.9 | D47: =IF(D45-$C45>0,(D45-$C45)*D12*$C41,(D45-$C45)*D12*$C42) -> 2632742 | E47: =IF(E45-$C45>0,(E45-$C45)*E12*$C41,(E45-$C45)*E12*$C42) -> 90195.605 | F47: =IF(F45-$C45>0,(F45-$C45)*F12*$C41,(F45-$C45)*F12*$C42) -> -9820.9646 | G47: =IF(G45-$C45>0,(G45-$C45)*G12*$C41,(G45-$C45)*G12*$C42) -> -32092.655 | H47: =IF(H45-$C45>0,(H45-$C45)*H12*$C41,(H45-$C45)*H12*$C42) -> -2477.3884 | I47: =IF(I45-$C45>0,(I45-$C45)*I12*$C41,(I45-$C45)*I12*$C42) -> 715007.02 | J47: =IF(J45-$C45>0,(J45-$C45)*J12*$C41,(J45-$C45)*J12*$C42) -> -29633.879 | K47: =IF(K45-$C45>0,(K45-$C45)*K12*$C41,(K45-$C45)*K12*$C42) -> 36074.781 | ... BZ47: =IF(BZ45-$C45>0,(BZ45-$C45)*BZ12*$C41,(BZ45-$C45)*BZ12*$C42) -> -10219.965
A50: 3.) | B50: Zusammenfassung
B52: Sonderlasten Familie und Jugend | C52: =SUM(D52:BZ52) -> 10062792 | D52: =D25 -> 6743301.1 | E52: =E25 -> 271428.26 | F52: =F25 -> 0 | G52: =G25 -> 0 | H52: =H25 -> 0 | I52: =I25 -> 0 | J52: =J25 -> 0 | K52: =K25 -> 0 | ... BZ52: =BZ25 -> 0
B53: Sonder-/Minderlasten Sozialhilfe | C53: =SUM(D53:BZ53) -> 7642281.4 | D53: =D36 -> 7427015.9 | E53: =E36 -> 291391.57 | F53: =F36 -> -16249.711 | G53: =G36 -> -10042.019 | H53: =H36 -> -76285.243 | I53: =I36 -> -125094.38 | J53: =J36 -> -22912.822 | K53: =K36 -> -23992.434 | ... BZ53: =BZ36 -> 16561.554
B54: Sonder-/Minderlasten Stationäre Pflege | C54: =SUM(D54:BZ54) -> 4563466.9 | D54: =D47 -> 2632742 | E54: =E47 -> 90195.605 | F54: =F47 -> -9820.9646 | G54: =G47 -> -32092.655 | H54: =H47 -> -2477.3884 | I54: =I47 -> 715007.02 | J54: =J47 -> -29633.879 | K54: =K47 -> 36074.781 | ... BZ54: =BZ47 -> -10219.965
B56: Beitrag Soziodemographischer Sonderlastenausgleich | C56: =SUM(D56:BZ56) -> 27275800 | D56: =ROUND(IF((D52+D53+D54)<0,0,(D52+D53+D54)),-2) -> 16803100 | E56: =ROUND(IF((E52+E53+E54)<0,0,(E52+E53+E54)),-2) -> 653000 | F56: =ROUND(IF((F52+F53+F54)<0,0,(F52+F53+F54)),-2) -> 0 | G56: =ROUND(IF((G52+G53+G54)<0,0,(G52+G53+G54)),-2) -> 0 | H56: =ROUND(IF((H52+H53+H54)<0,0,(H52+H53+H54)),-2) -> 0 | I56: =ROUND(IF((I52+I53+I54)<0,0,(I52+I53+I54)),-2) -> 589900 | J56: =ROUND(IF((J52+J53+J54)<0,0,(J52+J53+J54)),-2) -> 0 | K56: =ROUND(IF((K52+K53+K54)<0,0,(K52+K53+K54)),-2) -> 12100 | ... BZ56: =ROUND(IF((BZ52+BZ53+BZ54)<0,0,(BZ52+BZ53+BZ54)),-2) -> 6300

Sheet SL Stadt SG Basis
A1: Kanton St.Gallen
A2: Amt für Gemeinden und Bürgerrecht
A5: Sonderlastenausgleich Stadt St.Gallen 2025
B7: Eingabefelder
C8: St.Gallen
A10: 1.) | B10: Berechnung SL Stadt St.Gallen
B12: Ausgleichsbeitrag gemäss Art. 25 Abs. 1 FAG | C12: 10000000
B13: zusätzlicher Ausgleichsbeitrag gemäss Art. 25 Abs. 2 FAG | C13: 6000000
B15: Indexstand Juni 2007 (Basis) | C15: 101.7 | D15: (Dezember 2005 = 100)
B16: Indexstand Juni 2024 | C16: 110.2
B18: Beitrag Sonderlastenausgleich Stadt St.Gallen | C18: =ROUND((C12+C13)/C15*C16,-2) -> 17337300

Sheet Total
A1: Kanton St.Gallen
A2: Amt für Gemeinden und Bürgerrecht
A5: Finanzausgleich 2025 / definitive Beiträge
H6: gemäss Nachkalkulation!
A7: Nr. | B7: Gemeinde | C7: Ressourcen-ausgleich | D7: Sonderlasten-ausgleich Weite | E7: Sonderlasten-ausgleich Schule | F7: Soziodemogra-phischer Sonder-lastenausgleich | G7: Sonderlasten-ausgleich Stadt St.Gallen | H7: Total (neu) | J7: Ressourcen-ausgleich | K7: Sonderlasten-ausgleich Weite | L7: Sonderlasten-ausgleich Schule | M7: Soziodemogra-phischer Sonder-lastenausgleich | N7: Sonderlasten-ausgleich Stadt St.Gallen | O7: Total (bisher)
A8: 1 | B8: St.Gallen | C8: =HLOOKUP(B8,'Ressourcenausgleich Basis'!$C$8:$BZ$151,144,FALSE) -> 0 | D8: =HLOOKUP(B8,'SL Weite Basis'!$C$8:$BZ$74,67,FALSE) -> 0 | E8: =HLOOKUP(B8,'SL Schule Basis'!$C$8:$BZ$64,57,FALSE) -> 0 | F8: =HLOOKUP(B8,'SL Sozio Basis'!$C$8:$BZ$56,49,FALSE) -> 16803100 | G8: ='SL Stadt SG Basis'!C18 -> 17337300 | H8: =SUM(C8:G8) -> 34140400 | J8: 0 | K8: 0 | L8: 0 | M8: 16762800 | N8: 17337300 | O8: 34100100
A9: 2 | B9: Wittenbach | C9: =HLOOKUP(B9,'Ressourcenausgleich Basis'!$C$8:$BZ$151,144,FALSE) -> 5419100 | D9: =HLOOKUP(B9,'SL Weite Basis'!$C$8:$BZ$74,67,FALSE) -> 0 | E9: =HLOOKUP(B9,'SL Schule Basis'!$C$8:$BZ$64,57,FALSE) -> 557200 | F9: =HLOOKUP(B9,'SL Sozio Basis'!$C$8:$BZ$56,49,FALSE) -> 653000 | G9: 0 | H9: =SUM(C9:G9) -> 6629300 | J9: 5419100 | K9: 0 | L9: 557200 | M9: 647900 | N9: 0 | O9: 6624200
A10: 3 | B10: Häggenschwil | C10: =HLOOKUP(B10,'Ressourcenausgleich Basis'!$C$8:$BZ$151,144,FALSE) -> 598300 | D10: =HLOOKUP(B10,'SL Weite Basis'!$C$8:$BZ$74,67,FALSE) -> 386600 | E10: =HLOOKUP(B10,'SL Schule Basis'!$C$8:$BZ$64,57,FALSE) -> 560400 | F10: =HLOOKUP(B10,'SL Sozio Basis'!$C$8:$BZ$56,49,FALSE) -> 0 | G10: 0 | H10: =SUM(C10:G10) -> 1545300 | J10: 598300 | K10: 386600 | L10: 560300 | M10: 0 | N10: 0 | O10: 1545200
A11: 4 | B11: Muolen | C11: =HLOOKUP(B11,'Ressourcenausgleich Basis'!$C$8:$BZ$151,144,FALSE) -> 834600 | D11: =HLOOKUP(B11,'SL Weite Basis'!$C$8:$BZ$74,67,FALSE) -> 624800 | E11: =HLOOKUP(B11,'SL Schule Basis'!$C$8:$BZ$64,57,FALSE) -> 97300 | F11: =HLOOKUP(B11,'SL Sozio Basis'!$C$8:$BZ$56,49,FALSE) -> 0 | G11: 0 | H11: =SUM(C11:G11) -> 1556700 | J11: 834600 | K11: 624800 | L11: 97300 | M11: 0 | N11: 0 | O11: 1556700
A12: 5 | B12: Mörschwil | C12: =HLOOKUP(B12,'Ressourcenausgleich Basis'!$C$8:$BZ$151,144,FALSE) -> 0 | D12: =HLOOKUP(B12,'SL Weite Basis'!$C$8:$BZ$74,67,FALSE) -> 0 | E12: =HLOOKUP(B12,'SL Schule Basis'!$C$8:$BZ$64,57,FALSE) -> 0 | F12: =HLOOKUP(B12,'SL Sozio Basis'!$C$8:$BZ$56,49,FALSE) -> 0 | G12: 0 | H12: =SUM(C12:G12) -> 0 | J12: 0 | K12: 0 | L12: 0 | M12: 0 | N12: 0 | O12: 0
A13: 6 | B13: Goldach | C13: =HLOOKUP(B13,'Ressourcenausgleich Basis'!$C$8:$BZ$151,144,FALSE) -> 0 | D13: =HLOOKUP(B13,'SL Weite Basis'!$C$8:$BZ$74,67,FALSE) -> 0 | E13: =HLOOKUP(B13,'SL Schule Basis'!$C$8:$BZ$64,57,FALSE) -> 0 | F13: =HLOOKUP(B13,'SL Sozio Basis'!$C$8:$BZ$56,49,FALSE) -> 589900 | G13: 0 | H13: =SUM(C13:G13) -> 589900 | J13: 0 | K13: 0 | L13: 0 | M13: 588500 | N13: 0 | O13: 588500
A14: 7 | B14: Steinach | C14: =HLOOKUP(B14,'Ressourcenausgleich Basis'!$C$8:$BZ$151,144,FALSE) -> 254100 | D14: =HLOOKUP(B14,'SL Weite Basis'!$C$8:$BZ$74,67,FALSE) -> 0 | E14: =HLOOKUP(B14,'SL Schule Basis'!$C$8:$BZ$64,57,FALSE) -> 0 | F14: =HLOOKUP(B14,'SL Sozio Basis'!$C$8:$BZ$56,49,FALSE) -> 0 | G14: 0 | H14: =SUM(C14:G14) -> 254100 | J14: 254100 | K14: 0 | L14: 0 | M14: 0 | N14: 0 | O14: 254100
A15: 8 | B15: Berg | C15: =HLOOKUP(B15,'Ressourcenausgleich Basis'!$C$8:$BZ$151,144,FALSE) -> 0 | D15: =HLOOKUP(B15,'SL Weite Basis'!$C$8:$BZ$74,67,FALSE) -> 8100 | E15: =HLOOKUP(B15,'SL Schule Basis'!$C$8:$BZ$64,57,FALSE) -> 40200 | F15: =HLOOKUP(B15,'SL Sozio Basis'!$C$8:$BZ$56,49,FALSE) -> 12100 | G15: 0 | H15: =SUM(C15:G15) -> 60400 | J15: 0 | K15: 8100 | L15: 40200 | M15: 11900 | N15: 0 | O15: 60200
A16: 9 | B16: Tübach | C16: =HLOOKUP(B16,'Ressourcenausgleich Basis'!$C$8:$BZ$151,144,FALSE) -> 0 | D16: =HLOOKUP(B16,'SL Weite Basis'!$C$8:$BZ$74,67,FALSE) -> 0 | E16: =HLOOKUP(B16,'SL Schule Basis'!$C$8:$BZ$64,57,FALSE) -> 113700 | F16: =HLOOKUP(B16,'SL Sozio Basis'!$C$8:$BZ$56,49,FALSE) -> 0 | G16: 0 | H16: =SUM(C16:G16) -> 113700 | J16: 0 | K16: 0 | L16: 113700 | M16: 0 | N16: 0 | O16: 113700
A17: 10 | B17: Untereggen | C17: =HLOOKUP(B17,'Ressourcenausgleich Basis'!$C$8:$BZ$151,144,FALSE) -> 239500 | D17: =HLOOKUP(B17,'SL Weite Basis'!$C$8:$BZ$74,67,FALSE) -> 298300 | E17: =HLOOKUP(B17,'SL Schule Basis'!$C$8:$BZ$64,57,FALSE) -> 222200 | F17: =HLOOKUP(B17,'SL Sozio Basis'!$C$8:$BZ$56,49,FALSE) -> 0 | G17: 0 | H17: =SUM(C17:G17) -> 760000 | J17: 239500 | K17: 298300 | L17: 222200 | M17: 0 | N17: 0 | O17: 760000
A18: 11 | B18: Eggersriet | C18: =HLOOKUP(B18,'Ressourcenausgleich Basis'!$C$8:$BZ$151,144,FALSE) -> 288800 | D18: =HLOOKUP(B18,'SL Weite Basis'!$C$8:$BZ$74,67,FALSE) -> 618300 | E18: =HLOOKUP(B18,'SL Schule Basis'!$C$8:$BZ$64,57,FALSE) -> 361600 | F18: =HLOOKUP(B18,'SL Sozio Basis'!$C$8:$BZ$56,49,FALSE) -> 0 | G18: 0 | H18: =SUM(C18:G18) -> 1268700 | J18: 288800 | K18: 618300 | L18: 361600 | M18: 0 | N18: 0 | O18: 1268700
A19: 12 | B19: Rorschacherberg | C19: =HLOOKUP(B19,'Ressourcenausgleich Basis'!$C$8:$BZ$151,144,FALSE) -> 0 | D19: =HLOOKUP(B19,'SL Weite Basis'!$C$8:$BZ$74,67,FALSE) -> 0 | E19: =HLOOKUP(B19,'SL Schule Basis'!$C$8:$BZ$64,57,FALSE) -> 0 | F19: =HLOOKUP(B19,'SL Sozio Basis'!$C$8:$BZ$56,49,FALSE) -> 189300 | G19: 0 | H19: =SUM(C19:G19) -> 189300 | J19: 0 | K19: 0 | L19: 0 | M19: 185900 | N19: 0 | O19: 185900
A20: 13 | B20: Rorschach | C20: =HLOOKUP(B20,'Ressourcenausgleich Basis'!$C$8:$BZ$151,144,FALSE) -> 6129000 | D20: =HLOOKUP(B20,'SL Weite Basis'!$C$8:$BZ$74,67,FALSE) -> 0 | E20: =HLOOKUP(B20,'SL Schule Basis'!$C$8:$BZ$64,57,FALSE) -> 0 | F20: =HLOOKUP(B20,'SL Sozio Basis'!$C$8:$BZ$56,49,FALSE) -> 963200 | G20: 0 | H20: =SUM(C20:G20) -> 7092200 | J20: 6129000 | K20: 0 | L20: 0 | M20: 958100 | N20: 0 | O20: 7087100
... A82: 90 | B82: Gaiserwald | C82: =HLOOKUP(B82,'Ressourcenausgleich Basis'!$C$8:$BZ$151,144,FALSE) -> 0 | D82: =HLOOKUP(B82,'SL Weite Basis'!$C$8:$BZ$74,67,FALSE) -> 0 | E82: =HLOOKUP(B82,'SL Schule Basis'!$C$8:$BZ$64,57,FALSE) -> 274000 | F82: =HLOOKUP(B82,'SL Sozio Basis'!$C$8:$BZ$56,49,FALSE) -> 6300 | G82: 0 | H82: =SUM(C82:G82) -> 280300 | J82: 0 | K82: 0 | L82: 274000 | M82: 2500 | N82: 0 | O82: 276500
B83: Total | C83: =SUM(C8:C82) -> 121067800 | D83: =SUM(D8:D82) -> 35552500 | E83: =SUM(E8:E82) -> 33054900 | F83: =SUM(F8:F82) -> 27275800 | G83: =SUM(G8:G82) -> 17337300 | H83: =SUM(H8:H82) -> 234288300 | J83: =SUM(J8:J82) -> 121067800 | K83: =SUM(K8:K82) -> 35552500 | L83: =SUM(L8:L82) -> 33052100 | M83: =SUM(M8:M82) -> 27227800 | N83: =SUM(N8:N82) -> 17337300 | O83: =SUM(O8:O82) -> 234237500

Sheet Auszahlungen
A1: Kanton St.Gallen | J1: Kanton St.Gallen | S1: Kanton St.Gallen | AB1: Kanton St.Gallen
A2: Amt für Gemeinden und Bürgerrecht | D2: Formeln wurden für Nachkalkulation aus der Tabelle entfernt! | J2: Amt für Gemeinden und Bürgerrecht | M2: Formeln wurden für Nachkalkulation aus der Tabelle entfernt! | S2: Amt für Gemeinden und Bürgerrecht | V2: Formeln wurden für Nachkalkulation aus der Tabelle entfernt! | AB2: Amt für Gemeinden und Bürgerrecht
A5: Finanzausgleich 2025 / Auszahlung 1. Rate März | J5: Finanzausgleich 2025 / Auszahlung 2. Rate Juni | S5: Finanzausgleich 2025 / Auszahlung 3. Rate September | AB5: Finanzausgleich 2025 / Auszahlung 4. Rate Dezember
A7: Nr. | B7: Gemeinde | C7: Ressourcen-ausgleich | D7: Sonderlasten-ausgleich Weite | E7: Sonderlasten-ausgleich Schule | F7: Soziodemogra-phischer Sonder-lastenausgleich | G7: Sonderlasten-ausgleich Stadt St.Gallen | H7: Total | J7: Nr. | K7: Gemeinde | L7: Ressourcen-ausgleich | M7: Sonderlasten-ausgleich Weite | N7: Sonderlasten-ausgleich Schule | O7: Soziodemogra-phischer Sonder-lastenausgleich | P7: Sonderlasten-ausgleich Stadt St.Gallen | Q7: Total | S7: Nr. | T7: Gemeinde | U7: Ressourcen-ausgleich | V7: Sonderlasten-ausgleich Weite | W7: Sonderlasten-ausgleich Schule | X7: Soziodemogra-phischer Sonder-lastenausgleich | Y7: Sonderlasten-ausgleich Stadt St.Gallen | Z7: Total | AB7: Nr. | AC7: Gemeinde | AD7: Ressourcen-ausgleich | AE7: Sonderlasten-ausgleich Weite | AF7: Sonderlasten-ausgleich Schule | AG7: Soziodemogra-phischer Sonder-lastenausgleich | AH7: Sonderlasten-ausgleich Stadt St.Gallen | AI7: Total
A8: 1 | B8: St.Gallen | C8: 0 | D8: 0 | E8: 0 | F8: 4190700 | G8: 4334300 | H8: =SUM(C8:G8) -> 8525000 | J8: 1 | K8: St.Gallen | L8: 0 | M8: 0 | N8: 0 | O8: 4190700 | P8: 4334300 | Q8: =SUM(L8:P8) -> 8525000 | S8: 1 | T8: St.Gallen | U8: 0 | V8: 0 | W8: 0 | X8: 4190700 | Y8: 4334300 | Z8: =SUM(U8:Y8) -> 8525000 | AB8: 1 | AC8: St.Gallen | AD8: =Total!C8-Auszahlungen!C8-Auszahlungen!L8-Auszahlungen!U8 -> 0 | AE8: =Total!D8-Auszahlungen!D8-Auszahlungen!M8-Auszahlungen!V8 -> 0 | AF8: =Total!E8-Auszahlungen!E8-Auszahlungen!N8-Auszahlungen!W8 -> 0 | AG8: =Total!F8-Auszahlungen!F8-Auszahlungen!O8-Auszahlungen!X8 -> 4231000 | AH8: =Total!G8-Auszahlungen!G8-Auszahlungen!P8-Auszahlungen!Y8 -> 4334400 | AI8: =SUM(AD8:AH8) -> 8565400
A9: 2 | B9: Wittenbach | C9: 1354800 | D9: 0 | E9: 139300 | F9: 162000 | G9: 0 | H9: =SUM(C9:G9) -> 1656100 | J9: 2 | K9: Wittenbach | L9: 1354800 | M9: 0 | N9: 139300 | O9: 162000 | P9: 0 | Q9: =SUM(L9:P9) -> 1656100 | S9: 2 | T9: Wittenbach | U9: 1354800 | V9: 0 | W9: 139300 | X9: 162000 | Y9: 0 | Z9: =SUM(U9:Y9) -> 1656100 | AB9: 2 | AC9: Wittenbach | AD9: =Total!C9-Auszahlungen!C9-Auszahlungen!L9-Auszahlungen!U9 -> 1354700 | AE9: =Total!D9-Auszahlungen!D9-Auszahlungen!M9-Auszahlungen!V9 -> 0 | AF9: =Total!E9-Auszahlungen!E9-Auszahlungen!N9-Auszahlungen!W9 -> 139300 | AG9: =Total!F9-Auszahlungen!F9-Auszahlungen!O9-Auszahlungen!X9 -> 167000 | AH9: =Total!G9-Auszahlungen!G9-Auszahlungen!P9-Auszahlungen!Y9 -> 0 | AI9: =SUM(AD9:AH9) -> 1661000
A10: 3 | B10: Häggenschwil | C10: 149600 | D10: 96700 | E10: 140100 | F10: 0 | G10: 0 | H10: =SUM(C10:G10) -> 386400 | J10: 3 | K10: Häggenschwil | L10: 149600 | M10: 96700 | N10: 140100 | O10: 0 | P10: 0 | Q10: =SUM(L10:P10) -> 386400 | S10: 3 | T10: Häggenschwil | U10: 149600 | V10: 96700 | W10: 140100 | X10: 0 | Y10: 0 | Z10: =SUM(U10:Y10) -> 386400 | AB10: 3 | AC10: Häggenschwil | AD10: =Total!C10-Auszahlungen!C10-Auszahlungen!L10-Auszahlungen!U10 -> 149500 | AE10: =Total!D10-Auszahlungen!D10-Auszahlungen!M10-Auszahlungen!V10 -> 96500 | AF10: =Total!E10-Auszahlungen!E10-Auszahlungen!N10-Auszahlungen!W10 -> 140100 | AG10: =Total!F10-Auszahlungen!F10-Auszahlungen!O10-Auszahlungen!X10 -> 0 | AH10: =Total!G10-Auszahlungen!G10-Auszahlungen!P10-Auszahlungen!Y10 -> 0 | AI10: =SUM(AD10:AH10) -> 386100
A11: 4 | B11: Muolen | C11: 208700 | D11: 156200 | E11: 24300 | F11: 0 | G11: 0 | H11: =SUM(C11:G11) -> 389200 | J11: 4 | K11: Muolen | L11: 208700 | M11: 156200 | N11: 24300 | O11: 0 | P11: 0 | Q11: =SUM(L11:P11) -> 389200 | S11: 4 | T11: Muolen | U11: 208700 | V11: 156200 | W11: 24300 | X11: 0 | Y11: 0 | Z11: =SUM(U11:Y11) -> 389200 | AB11: 4 | AC11: Muolen | AD11: =Total!C11-Auszahlungen!C11-Auszahlungen!L11-Auszahlungen!U11 -> 208500 | AE11: =Total!D11-Auszahlungen!D11-Auszahlungen!M11-Auszahlungen!V11 -> 156200 | AF11: =Total!E11-Auszahlungen!E11-Auszahlungen!N11-Auszahlungen!W11 -> 24400 | AG11: =Total!F11-Auszahlungen!F11-Auszahlungen!O11-Auszahlungen!X11 -> 0 | AH11: =Total!G11-Auszahlungen!G11-Auszahlungen!P11-Auszahlungen!Y11 -> 0 | AI11: =SUM(AD11:AH11) -> 389100
A12: 5 | B12: Mörschwil | C12: 0 | D12: 0 | E12: 0 | F12: 0 | G12: 0 | H12: =SUM(C12:G12) -> 0 | J12: 5 | K12: Mörschwil | L12: 0 | M12: 0 | N12: 0 | O12: 0 | P12: 0 | Q12: =SUM(L12:P12) -> 0 | S12: 5 | T12: Mörschwil | U12: 0 | V12: 0 | W12: 0 | X12: 0 | Y12: 0 | Z12: =SUM(U12:Y12) -> 0 | AB12: 5 | AC12: Mörschwil | AD12: =Total!C12-Auszahlungen!C12-Auszahlungen!L12-Auszahlungen!U12 -> 0 | AE12: =Total!D12-Auszahlungen!D12-Auszahlungen!M12-Auszahlungen!V12 -> 0 | AF12: =Total!E12-Auszahlungen!E12-Auszahlungen!N12-Auszahlungen!W12 -> 0 | AG12: =Total!F12-Auszahlungen!F12-Auszahlungen!O12-Auszahlungen!X12 -> 0 | AH12: =Total!G12-Auszahlungen!G12-Auszahlungen!P12-Auszahlungen!Y12 -> 0 | AI12: =SUM(AD12:AH12) -> 0
A13: 6 | B13: Goldach | C13: 0 | D13: 0 | E13: 0 | F13: 147100 | G13: 0 | H13: =SUM(C13:G13) -> 147100 | J13: 6 | K13: Goldach | L13: 0 | M13: 0 | N13: 0 | O13: 147100 | P13: 0 | Q13: =SUM(L13:P13) -> 147100 | S13: 6 | T13: Goldach | U13: 0 | V13: 0 | W13: 0 | X13: 147100 | Y13: 0 | Z13: =SUM(U13:Y13) -> 147100 | AB13: 6 | AC13: Goldach | AD13: =Total!C13-Auszahlungen!C13-Auszahlungen!L13-Auszahlungen!U13 -> 0 | AE13: =Total!D13-Auszahlungen!D13-Auszahlungen!M13-Auszahlungen!V13 -> 0 | AF13: =Total!E13-Auszahlungen!E13-Auszahlungen!N13-Auszahlungen!W13 -> 0 | AG13: =Total!F13-Auszahlungen!F13-Auszahlungen!O13-Auszahlungen!X13 -> 148600 | AH13: =Total!G13-Auszahlungen!G13-Auszahlungen!P13-Auszahlungen!Y13 -> 0 | AI13: =SUM(AD13:AH13) -> 148600
A14: 7 | B14: Steinach | C14: 63500 | D14: 0 | E14: 0 | F14: 0 | G14: 0 | H14: =SUM(C14:G14) -> 63500 | J14: 7 | K14: Steinach | L14: 63500 | M14: 0 | N14: 0 | O14: 0 | P14: 0 | Q14: =SUM(L14:P14) -> 63500 | S14: 7 | T14: Steinach | U14: 63500 | V14: 0 | W14: 0 | X14: 0 | Y14: 0 | Z14: =SUM(U14:Y14) -> 63500 | AB14: 7 | AC14: Steinach | AD14: =Total!C14-Auszahlungen!C14-Auszahlungen!L14-Auszahlungen!U14 -> 63600 | AE14: =Total!D14-Auszahlungen!D14-Auszahlungen!M14-Auszahlungen!V14 -> 0 | AF14: =Total!E14-Auszahlungen!E14-Auszahlungen!N14-Auszahlungen!W14 -> 0 | AG14: =Total!F14-Auszahlungen!F14-Auszahlungen!O14-Auszahlungen!X14 -> 0 | AH14: =Total!G14-Auszahlungen!G14-Auszahlungen!P14-Auszahlungen!Y14 -> 0 | AI14: =SUM(AD14:AH14) -> 63600
A15: 8 | B15: Berg | C15: 0 | D15: 2000 | E15: 10100 | F15: 3000 | G15: 0 | H15: =SUM(C15:G15) -> 15100 | J15: 8 | K15: Berg | L15: 0 | M15: 2000 | N15: 10100 | O15: 3000 | P15: 0 | Q15: =SUM(L15:P15) -> 15100 | S15: 8 | T15: Berg | U15: 0 | V15: 2000 | W15: 10100 | X15: 3000 | Y15: 0 | Z15: =SUM(U15:Y15) -> 15100 | AB15: 8 | AC15: Berg | AD15: =Total!C15-Auszahlungen!C15-Auszahlungen!L15-Auszahlungen!U15 -> 0 | AE15: =Total!D15-Auszahlungen!D15-Auszahlungen!M15-Auszahlungen!V15 -> 2100 | AF15: =Total!E15-Auszahlungen!E15-Auszahlungen!N15-Auszahlungen!W15 -> 9900 | AG15: =Total!F15-Auszahlungen!F15-Auszahlungen!O15-Auszahlungen!X15 -> 3100 | AH15: =Total!G15-Auszahlungen!G15-Auszahlungen!P15-Auszahlungen!Y15 -> 0 | AI15: =SUM(AD15:AH15) -> 15100
A16: 9 | B16: Tübach | C16: 0 | D16: 0 | E16: 28400 | F16: 0 | G16: 0 | H16: =SUM(C16:G16) -> 28400 | J16: 9 | K16: Tübach | L16: 0 | M16: 0 | N16: 28400 | O16: 0 | P16: 0 | Q16: =SUM(L16:P16) -> 28400 | S16: 9 | T16: Tübach | U16: 0 | V16: 0 | W16: 28400 | X16: 0 | Y16: 0 | Z16: =SUM(U16:Y16) -> 28400 | AB16: 9 | AC16: Tübach | AD16: =Total!C16-Auszahlungen!C16-Auszahlungen!L16-Auszahlungen!U16 -> 0 | AE16: =Total!D16-Auszahlungen!D16-Auszahlungen!M16-Auszahlungen!V16 -> 0 | AF16: =Total!E16-Auszahlungen!E16-Auszahlungen!N16-Auszahlungen!W16 -> 28500 | AG16: =Total!F16-Auszahlungen!F16-Auszahlungen!O16-Auszahlungen!X16 -> 0 | AH16: =Total!G16-Auszahlungen!G16-Auszahlungen!P16-Auszahlungen!Y16 -> 0 | AI16: =SUM(AD16:AH16) -> 28500
A17: 10 | B17: Untereggen | C17: 59900 | D17: 74600 | E17: 55600 | F17: 0 | G17: 0 | H17: =SUM(C17:G17) -> 190100 | J17: 10 | K17: Untereggen | L17: 59900 | M17: 74600 | N17: 55600 | O17: 0 | P17: 0 | Q17: =SUM(L17:P17) -> 190100 | S17: 10 | T17: Untereggen | U17: 59900 | V17: 74600 | W17: 55600 | X17: 0 | Y17: 0 | Z17: =SUM(U17:Y17) -> 190100 | AB17: 10 | AC17: Untereggen | AD17: =Total!C17-Auszahlungen!C17-Auszahlungen!L17-Auszahlungen!U17 -> 59800 | AE17: =Total!D17-Auszahlungen!D17-Auszahlungen!M17-Auszahlungen!V17 -> 74500 | AF17: =Total!E17-Auszahlungen!E17-Auszahlungen!N17-Auszahlungen!W17 -> 55400 | AG17: =Total!F17-Auszahlungen!F17-Auszahlungen!O17-Auszahlungen!X17 -> 0 | AH17: =Total!G17-Auszahlungen!G17-Auszahlungen!P17-Auszahlungen!Y17 -> 0 | AI17: =SUM(AD17:AH17) -> 189700
A18: 11 | B18: Eggersriet | C18: 72200 | D18: 154600 | E18: 90400 | F18: 0 | G18: 0 | H18: =SUM(C18:G18) -> 317200 | J18: 11 | K18: Eggersriet | L18: 72200 | M18: 154600 | N18: 90400 | O18: 0 | P18: 0 | Q18: =SUM(L18:P18) -> 317200 | S18: 11 | T18: Eggersriet | U18: 72200 | V18: 154600 | W18: 90400 | X18: 0 | Y18: 0 | Z18: =SUM(U18:Y18) -> 317200 | AB18: 11 | AC18: Eggersriet | AD18: =Total!C18-Auszahlungen!C18-Auszahlungen!L18-Auszahlungen!U18 -> 72200 | AE18: =Total!D18-Auszahlungen!D18-Auszahlungen!M18-Auszahlungen!V18 -> 154500 | AF18: =Total!E18-Auszahlungen!E18-Auszahlungen!N18-Auszahlungen!W18 -> 90400 | AG18: =Total!F18-Auszahlungen!F18-Auszahlungen!O18-Auszahlungen!X18 -> 0 | AH18: =Total!G18-Auszahlungen!G18-Auszahlungen!P18-Auszahlungen!Y18 -> 0 | AI18: =SUM(AD18:AH18) -> 317100
A19: 12 | B19: Rorschacherberg | C19: 0 | D19: 0 | E19: 0 | F19: 46500 | G19: 0 | H19: =SUM(C19:G19) -> 46500 | J19: 12 | K19: Rorschacherberg | L19: 0 | M19: 0 | N19: 0 | O19: 46500 | P19: 0 | Q19: =SUM(L19:P19) -> 46500 | S19: 12 | T19: Rorschacherberg | U19: 0 | V19: 0 | W19: 0 | X19: 46500 | Y19: 0 | Z19: =SUM(U19:Y19) -> 46500 | AB19: 12 | AC19: Rorschacherberg | AD19: =Total!C19-Auszahlungen!C19-Auszahlungen!L19-Auszahlungen!U19 -> 0 | AE19: =Total!D19-Auszahlungen!D19-Auszahlungen!M19-Auszahlungen!V19 -> 0 | AF19: =Total!E19-Auszahlungen!E19-Auszahlungen!N19-Auszahlungen!W19 -> 0 | AG19: =Total!F19-Auszahlungen!F19-Auszahlungen!O19-Auszahlungen!X19 -> 49800 | AH19: =Total!G19-Auszahlungen!G19-Auszahlungen!P19-Auszahlungen!Y19 -> 0 | AI19: =SUM(AD19:AH19) -> 49800
... A82: 90 | B82: Gaiserwald | C82: 0 | D82: 0 | E82: 68500 | F82: 600 | G82: 0 | H82: =SUM(C82:G82) -> 69100 | J82: 90 | K82: Gaiserwald | L82: 0 | M82: 0 | N82: 68500 | O82: 600 | P82: 0 | Q82: =SUM(L82:P82) -> 69100 | S82: 90 | T82: Gaiserwald | U82: 0 | V82: 0 | W82: 68500 | X82: 600 | Y82: 0 | Z82: =SUM(U82:Y82) -> 69100 | AB82: 90 | AC82: Gaiserwald | AD82: =Total!C82-Auszahlungen!C82-Auszahlungen!L82-Auszahlungen!U82 -> 0 | AE82: =Total!D82-Auszahlungen!D82-Auszahlungen!M82-Auszahlungen!V82 -> 0 | AF82: =Total!E82-Auszahlungen!E82-Auszahlungen!N82-Auszahlungen!W82 -> 68500 | AG82: =Total!F82-Auszahlungen!F82-Auszahlungen!O82-Auszahlungen!X82 -> 4500 | AH82: =Total!G82-Auszahlungen!G82-Auszahlungen!P82-Auszahlungen!Y82 -> 0 | AI82: =SUM(AD82:AH82) -> 73000
B83: Total | C83: =SUM(C8:C82) -> 30267800 | D83: =SUM(D8:D82) -> 8888600 | E83: =SUM(E8:E82) -> 8263200 | F83: =SUM(F8:F82) -> 6807600 | G83: =SUM(G8:G82) -> 4334300 | H83: =SUM(H8:H82) -> 58561500 | K83: Total | L83: =SUM(L8:L82) -> 30267800 | M83: =SUM(M8:M82) -> 8888600 | N83: =SUM(N8:N82) -> 8263200 | O83: =SUM(O8:O82) -> 6807600 | P83: =SUM(P8:P82) -> 4334300 | Q83: =SUM(Q8:Q82) -> 58561500 | T83: Total | U83: =SUM(U8:U82) -> 30267800 | V83: =SUM(V8:V82) -> 8888600 | W83: =SUM(W8:W82) -> 8263200 | X83: =SUM(X8:X82) -> 6762900 | Y83: =SUM(Y8:Y82) -> 4334300 | Z83: =SUM(Z8:Z82) -> 58516800 | AC83: Total | AD83: =SUM(AD8:AD82) -> 30264400 | AE83: =SUM(AE8:AE82) -> 8886700 | AF83: =SUM(AF8:AF82) -> 8265300 | AG83: =SUM(AG8:AG82) -> 6897700 | AH83: =SUM(AH8:AH82) -> 4334400 | AI83: =SUM(AI8:AI82) -> 58648500
B84: Kontierung | C84: Soll 3700001000.347200 | D84: Soll 3700001000.347211 | E84: Soll 3700001000.347212 | F84: Soll 3700001000.347214 | G84: Soll 3700001000.347213 | K84: Kontierung | L84: Soll 3700001000.347200 | M84: Soll 3700001000.347211 | N84: Soll 3700001000.347212 | O84: Soll 3700001000.347214 | P84: Soll 3700001000.347213 | T84: Kontierung | U84: Soll 3700001000.347200 | V84: Soll 3700001000.347211 | W84: Soll 3700001000.347212 | X84: Soll 3700001000.347214 | Y84: Soll 3700001000.347213 | AC84: Kontierung | AD84: Soll 3700001000.347200 | AE84: Soll 3700001000.347211 | AF84: Soll 3700001000.347212 | AG84: Soll 3700001000.347214 | AH84: Soll 3700001000.347213

Sheet Kreditorenbelege
A1: Kanton St.Gallen | I1: Kanton St.Gallen | Q1: Kanton St.Gallen | Y1: Kanton St.Gallen
A2: Amt für Gemeinden und Bürgerrecht | I2: Amt für Gemeinden und Bürgerrecht | Q2: Amt für Gemeinden und Bürgerrecht | Y2: Amt für Gemeinden und Bürgerrecht
A5: Finanzausgleich 2025 | I5: Finanzausgleich 2025 | Q5: Finanzausgleich 2025 | Y5: Finanzausgleich 2025
A6: Kreditorenbeleg 1. Rate März | I6: Kreditorenbeleg 2. Rate Juni | Q6: Kreditorenbeleg 3. Rate September | Y6: Kreditorenbeleg 4. Rate Dezember
A8: Nr. | B8: Gemeinde | C8: Kreditor | D8: Btyp | E8: IBAN | F8: Total Auszahlung 15. März 2025 | I8: Nr. | J8: Gemeinde | K8: Kreditor | L8: Btyp | M8: IBAN | N8: Total Auszahlung 15. Juni 2025 | Q8: Nr. | R8: Gemeinde | S8: Kreditor | T8: Btyp | U8: IBAN | V8: Total Auszahlung 15. September 2025 | Y8: Nr. | Z8: Gemeinde | AA8: Kreditor | AB8: Btyp | AC8: IBAN | AD8: Total Auszahlung 15. Dezember 2025
A9: 1 | B9: St.Gallen | C9: =IF(F9=0,"","G"&A9) -> G1 | D9: 0001 | E9: CH65 0078 1011 6000 0040 5 | F9: =Auszahlungen!H8 -> 8525000 | I9: 1 | J9: St.Gallen | K9: =IF(N9=0,"","G"&I9) -> G1 | L9: 0001 | M9: CH65 0078 1011 6000 0040 5 | N9: =Auszahlungen!Q8 -> 8525000 | Q9: 1 | R9: St.Gallen | S9: =IF(V9=0,"","G"&Q9) -> G1 | T9: 0001 | U9: CH65 0078 1011 6000 0040 5 | V9: =Auszahlungen!Z8 -> 8525000 | Y9: 1 | Z9: St.Gallen | AA9: =IF(AD9=0,"","G"&Y9) -> G1 | AB9: 0001 | AC9: CH65 0078 1011 6000 0040 5 | AD9: =Auszahlungen!AI8 -> 8565400
A10: 2 | B10: Wittenbach | C10: =IF(F10=0,"","G"&A10) -> G2 | D10: 0001 | E10: CH87 0900 0000 9000 0619 3 | F10: =Auszahlungen!H9 -> 1656100 | I10: 2 | J10: Wittenbach | K10: =IF(N10=0,"","G"&I10) -> G2 | L10: 0001 | M10: CH87 0900 0000 9000 0619 3 | N10: =Auszahlungen!Q9 -> 1656100 | Q10: 2 | R10: Wittenbach | S10: =IF(V10=0,"","G"&Q10) -> G2 | T10: 0001 | U10: CH87 0900 0000 9000 0619 3 | V10: =Auszahlungen!Z9 -> 1656100 | Y10: 2 | Z10: Wittenbach | AA10: =IF(AD10=0,"","G"&Y10) -> G2 | AB10: 0001 | AC10: CH87 0900 0000 9000 0619 3 | AD10: =Auszahlungen!AI9 -> 1661000
A11: 3 | B11: Häggenschwil | C11: =IF(F11=0,"","G"&A11) -> G3 | D11: 0001 | E11: CH89 0900 0000 9000 0305 3 | F11: =Auszahlungen!H10 -> 386400 | I11: 3 | J11: Häggenschwil | K11: =IF(N11=0,"","G"&I11) -> G3 | L11: 0001 | M11: CH89 0900 0000 9000 0305 3 | N11: =Auszahlungen!Q10 -> 386400 | Q11: 3 | R11: Häggenschwil | S11: =IF(V11=0,"","G"&Q11) -> G3 | T11: 0001 | U11: CH89 0900 0000 9000 0305 3 | V11: =Auszahlungen!Z10 -> 386400 | Y11: 3 | Z11: Häggenschwil | AA11: =IF(AD11=0,"","G"&Y11) -> G3 | AB11: 0001 | AC11: CH89 0900 0000 9000 0305 3 | AD11: =Auszahlungen!AI10 -> 386100
A12: 4 | B12: Muolen | C12: =IF(F12=0,"","G"&A12) -> G4 | D12: 0002 | E12: CH70 0900 0000 9000 4704 5 | F12: =Auszahlungen!H11 -> 389200 | I12: 4 | J12: Muolen | K12: =IF(N12=0,"","G"&I12) -> G4 | L12: 0002 | M12: CH70 0900 0000 9000 4704 5 | N12: =Auszahlungen!Q11 -> 389200 | Q12: 4 | R12: Muolen | S12: =IF(V12=0,"","G"&Q12) -> G4 | T12: 0002 | U12: CH70 0900 0000 9000 4704 5 | V12: =Auszahlungen!Z11 -> 389200 | Y12: 4 | Z12: Muolen | AA12: =IF(AD12=0,"","G"&Y12) -> G4 | AB12: 0002 | AC12: CH70 0900 0000 9000 4704 5 | AD12: =Auszahlungen!AI11 -> 389100
A13: 5 | B13: Mörschwil | C13: =IF(F13=0,"","G"&A13) | D13: 0001 | E13: CH20 8128 4000 0010 0230 1 | F13: =Auszahlungen!H12 -> 0 | I13: 5 | J13: Mörschwil | K13: =IF(N13=0,"","G"&I13) | L13: 0001 | M13: CH20 8128 4000 0010 0230 1 | N13: =Auszahlungen!Q12 -> 0 | Q13: 5 | R13: Mörschwil | S13: =IF(V13=0,"","G"&Q13) | T13: 0001 | U13: CH20 8128 4000 0010 0230 1 | V13: =Auszahlungen!Z12 -> 0 | Y13: 5 | Z13: Mörschwil | AA13: =IF(AD13=0,"","G"&Y13) | AB13: 0001 | AC13: CH20 8128 4000 0010 0230 1 | AD13: =Auszahlungen!AI12 -> 0
A14: 6 | B14: Goldach | C14: =IF(F14=0,"","G"&A14) -> G6 | D14: 0004 | E14: CH06 0900 0000 9000 0910 6 | F14: =Auszahlungen!H13 -> 147100 | I14: 6 | J14: Goldach | K14: =IF(N14=0,"","G"&I14) -> G6 | L14: 0005 | M14: CH06 0900 0000 9000 0910 6 | N14: =Auszahlungen!Q13 -> 147100 | Q14: 6 | R14: Goldach | S14: =IF(V14=0,"","G"&Q14) -> G6 | T14: 0005 | U14: CH06 0900 0000 9000 0910 6 | V14: =Auszahlungen!Z13 -> 147100 | Y14: 6 | Z14: Goldach | AA14: =IF(AD14=0,"","G"&Y14) -> G6 | AB14: 0005 | AC14: CH06 0900 0000 9000 0910 6 | AD14: =Auszahlungen!AI13 -> 148600
A15: 7 | B15: Steinach | C15: =IF(F15=0,"","G"&A15) -> G7 | D15: 0001 | E15: CH87 8130 7000 0011 3060 4 | F15: =Auszahlungen!H14 -> 63500 | I15: 7 | J15: Steinach | K15: =IF(N15=0,"","G"&I15) -> G7 | L15: 0001 | M15: CH87 8130 7000 0011 3060 4 | N15: =Auszahlungen!Q14 -> 63500 | Q15: 7 | R15: Steinach | S15: =IF(V15=0,"","G"&Q15) -> G7 | T15: 0001 | U15: CH87 8130 7000 0011 3060 4 | V15: =Auszahlungen!Z14 -> 63500 | Y15: 7 | Z15: Steinach | AA15: =IF(AD15=0,"","G"&Y15) -> G7 | AB15: 0001 | AC15: CH87 8130 7000 0011 3060 4 | AD15: =Auszahlungen!AI14 -> 63600
A16: 8 | B16: Berg | C16: =IF(F16=0,"","G"&A16) -> G8 | D16: 0001 | E16: CH76 0900 0000 9000 8127 5 | F16: =Auszahlungen!H15 -> 15100 | I16: 8 | J16: Berg | K16: =IF(N16=0,"","G"&I16) -> G8 | L16: 0001 | M16: CH76 0900 0000 9000 8127 5 | N16: =Auszahlungen!Q15 -> 15100 | Q16: 8 | R16: Berg | S16: =IF(V16=0,"","G"&Q16) -> G8 | T16: 0001 | U16: CH76 0900 0000 9000 8127 5 | V16: =Auszahlungen!Z15 -> 15100 | Y16: 8 | Z16: Berg | AA16: =IF(AD16=0,"","G"&Y16) -> G8 | AB16: 0001 | AC16: CH76 0900 0000 9000 8127 5 | AD16: =Auszahlungen!AI15 -> 15100
A17: 9 | B17: Tübach | C17: =IF(F17=0,"","G"&A17) -> G9 | D17: 0002 | E17: CH12 0900 0000 9000 0987 1 | F17: =Auszahlungen!H16 -> 28400 | I17: 9 | J17: Tübach | K17: =IF(N17=0,"","G"&I17) -> G9 | L17: 0002 | M17: CH12 0900 0000 9000 0987 1 | N17: =Auszahlungen!Q16 -> 28400 | Q17: 9 | R17: Tübach | S17: =IF(V17=0,"","G"&Q17) -> G9 | T17: 0002 | U17: CH12 0900 0000 9000 0987 1 | V17: =Auszahlungen!Z16 -> 28400 | Y17: 9 | Z17: Tübach | AA17: =IF(AD17=0,"","G"&Y17) -> G9 | AB17: 0002 | AC17: CH12 0900 0000 9000 0987 1 | AD17: =Auszahlungen!AI16 -> 28500
A18: 10 | B18: Untereggen | C18: =IF(F18=0,"","G"&A18) -> G10 | D18: 0001 | E18: CH55 0900 0000 9001 0396 3 | F18: =Auszahlungen!H17 -> 190100 | I18: 10 | J18: Untereggen | K18: =IF(N18=0,"","G"&I18) -> G10 | L18: 0001 | M18: CH55 0900 0000 9001 0396 3 | N18: =Auszahlungen!Q17 -> 190100 | Q18: 10 | R18: Untereggen | S18: =IF(V18=0,"","G"&Q18) -> G10 | T18: 0001 | U18: CH55 0900 0000 9001 0396 3 | V18: =Auszahlungen!Z17 -> 190100 | Y18: 10 | Z18: Untereggen | AA18: =IF(AD18=0,"","G"&Y18) -> G10 | AB18: 0001 | AC18: CH55 0900 0000 9001 0396 3 | AD18: =Auszahlungen!AI17 -> 189700
A19: 11 | B19: Eggersriet | C19: =IF(F19=0,"","G"&A19) -> G11 | D19: 0001 | E19: CH04 0900 0000 9000 5288 9 | F19: =Auszahlungen!H18 -> 317200 | I19: 11 | J19: Eggersriet | K19: =IF(N19=0,"","G"&I19) -> G11 | L19: 0001 | M19: CH04 0900 0000 9000 5288 9 | N19: =Auszahlungen!Q18 -> 317200 | Q19: 11 | R19: Eggersriet | S19: =IF(V19=0,"","G"&Q19) -> G11 | T19: 0001 | U19: CH04 0900 0000 9000 5288 9 | V19: =Auszahlungen!Z18 -> 317200 | Y19: 11 | Z19: Eggersriet | AA19: =IF(AD19=0,"","G"&Y19) -> G11 | AB19: 0001 | AC19: CH04 0900 0000 9000 5288 9 | AD19: =Auszahlungen!AI18 -> 317100
A20: 12 | B20: Rorschacherberg | C20: =IF(F20=0,"","G"&A20) -> G12 | D20: 0001 | E20: CH55 0900 0000 9000 0492 6 | F20: =Auszahlungen!H19 -> 46500 | I20: 12 | J20: Rorschacherberg | K20: =IF(N20=0,"","G"&I20) -> G12 | L20: 0001 | M20: CH55 0900 0000 9000 0492 6 | N20: =Auszahlungen!Q19 -> 46500 | Q20: 12 | R20: Rorschacherberg | S20: =IF(V20=0,"","G"&Q20) -> G12 | T20: 0001 | U20: CH55 0900 0000 9000 0492 6 | V20: =Auszahlungen!Z19 -> 46500 | Y20: 12 | Z20: Rorschacherberg | AA20: =IF(AD20=0,"","G"&Y20) -> G12 | AB20: 0001 | AC20: CH55 0900 0000 9000 0492 6 | AD20: =Auszahlungen!AI19 -> 49800
... A83: 90 | B83: Gaiserwald | C83: =IF(F83=0,"","G"&A83) -> G90 | D83: 0001 | E83: CH84 0900 0000 9000 9131 6 | F83: =Auszahlungen!H82 -> 69100 | I83: 90 | J83: Gaiserwald | K83: =IF(N83=0,"","G"&I83) -> G90 | L83: 0001 | M83: CH84 0900 0000 9000 9131 6 | N83: =Auszahlungen!Q82 -> 69100 | Q83: 90 | R83: Gaiserwald | S83: =IF(V83=0,"","G"&Q83) -> G90 | T83: 0001 | U83: CH84 0900 0000 9000 9131 6 | V83: =Auszahlungen!Z82 -> 69100 | Y83: 90 | Z83: Gaiserwald | AA83: =IF(AD83=0,"","G"&Y83) -> G90 | AB83: 0001 | AC83: CH84 0900 0000 9000 9131 6 | AD83: =Auszahlungen!AI82 -> 73000
B84: Total | F84: =SUM(F9:F83) -> 58561500 | J84: Total | N84: =SUM(N9:N83) -> 58561500 | R84: Total | V84: =SUM(V9:V83) -> 58516800 | Z84: Total | AD84: =SUM(AD9:AD83) -> 58648500

Sheet Kontierungsbelege
A1: Kanton St.Gallen | G1: Kanton St.Gallen | M1: Kanton St.Gallen | S1: Kanton St.Gallen
A2: Amt für Gemeinden und Bürgerrecht | G2: Amt für Gemeinden und Bürgerrecht | M2: Amt für Gemeinden und Bürgerrecht | S2: Amt für Gemeinden und Bürgerrecht
A5: Finanzausgleich 2025 | G5: Finanzausgleich 2025 | M5: Finanzausgleich 2025 | S5: Finanzausgleich 2025
A6: Kontierungsbeleg | G6: Kontierungsbeleg | M6: Kontierungsbeleg | S6: Kontierungsbeleg
A8: 1. Auszahlung innerkantonaler Finanzausgleich gemäss Art. 47 Finanzausgleichsgesetz (sGS 813.1; abgekürzt FAG) | G8: 2. Auszahlung innerkantonaler Finanzausgleich gemäss Art. 47 Finanzausgleichsgesetz (sGS 813.1; abgekürzt FAG) | M8: 3. Auszahlung innerkantonaler Finanzausgleich gemäss Art. 47 Finanzausgleichsgesetz (sGS 813.1; abgekürzt FAG) | S8: 4. Auszahlung innerkantonaler Finanzausgleich gemäss Art. 47 Finanzausgleichsgesetz (sGS 813.1; abgekürzt FAG)
A12: Die Finanzausgleichsbeiträge für die Auszahlung vom 15. März 2024 setzen sich die folgt zusammen (siehe auch Beilage): | G12: Die Finanzausgleichsbeiträge für die Auszahlung vom 15. Juni 2024 setzen sich die folgt zusammen (siehe auch Beilage): | M12: Die Finanzausgleichsbeiträge für die Auszahlung vom 15. September 2024 setzen sich die folgt zusammen (siehe auch Beilage): | S12: Die Finanzausgleichsbeiträge für die Auszahlung vom 15. Dezember 2024 setzen sich die folgt zusammen (siehe auch Beilage):
A15: Ressourcenausgleich (1. Rate; Art. 5 ff. FAG) AFGB 3700001000.347200 an AFGB 200399 / 3P.FA | D15: Fr. | E15: =Auszahlungen!C83 -> 30267800 | G15: Ressourcenausgleich (2. Rate; Art. 5 ff. FAG) AFGB 3700001000.347200 an AFGB 200399 / 3P.FA | J15: Fr. | K15: =Auszahlungen!L83 -> 30267800 | M15: Ressourcenausgleich (3. Rate; Art. 5 ff. FAG) AFGB 3700001000.347200 an AFGB 200399 / 3P.FA | P15: Fr. | Q15: =Auszahlungen!U83 -> 30267800 | S15: Ressourcenausgleich (4. Rate; Art. 5 ff. FAG) AFGB 3700001000.347200 an AFGB 200399 / 3P.FA | V15: Fr. | W15: =Auszahlungen!AD83 -> 30264400
A18: Sonderlastenausgleich Weite (1. Rate; Art. 11 ff. FAG) AFGB 3700001000.347211 an AFGB 200399 / 3P.FA | D18: Fr. | E18: =Auszahlungen!D83 -> 8888600 | G18: Sonderlastenausgleich Weite (2. Rate; Art. 11 ff. FAG) AFGB 3700001000.347211 an AFGB 200399 / 3P.FA | J18: Fr. | K18: =Auszahlungen!M83 -> 8888600 | M18: Sonderlastenausgleich Weite (3. Rate; Art. 11 ff. FAG) AFGB 3700001000.347211 an AFGB 200399 / 3P.FA | P18: Fr. | Q18: =Auszahlungen!V83 -> 8888600 | S18: Sonderlastenausgleich Weite (4. Rate; Art. 11 ff. FAG) AFGB 3700001000.347211 an AFGB 200399 / 3P.FA | V18: Fr. | W18: =Auszahlungen!AE83 -> 8886700
A21: Sonderlastenausgleich Schule (1. Rate; Art. 18 ff. FAG) AFGB 3700001000.347212 an AFGB 200399 / 3P.FA | D21: Fr. | E21: =Auszahlungen!E83 -> 8263200 | G21: Sonderlastenausgleich Schule (2. Rate; Art. 18 ff. FAG) AFGB 3700001000.347212 an AFGB 200399 / 3P.FA | J21: Fr. | K21: =Auszahlungen!N83 -> 8263200 | M21: Sonderlastenausgleich Schule (3. Rate; Art. 18 ff. FAG) AFGB 3700001000.347212 an AFGB 200399 / 3P.FA | P21: Fr. | Q21: =Auszahlungen!W83 -> 8263200 | S21: Sonderlastenausgleich Schule (4. Rate; Art. 18 ff. FAG) AFGB 3700001000.347212 an AFGB 200399 / 3P.FA | V21: Fr. | W21: =Auszahlungen!AF83 -> 8265300
A24: Soziodemographischer Sonderlastenausgleich (1. Rate; Art. 17a ff. FAG) AFGB 3700001000.347214 an AFGB 200399 / 3P.FA | D24: Fr. | E24: =Auszahlungen!F83 -> 6807600 | G24: Soziodemographischer Sonderlastenausgleich (2. Rate; Art. 17a ff. FAG) AFGB 3700001000.347214 an AFGB 200399 / 3P.FA | J24: Fr. | K24: =Auszahlungen!O83 -> 6807600 | M24: Soziodemographischer Sonderlastenausgleich (3. Rate; Art. 17a ff. FAG) AFGB 3700001000.347214 an AFGB 200399 / 3P.FA | P24: Fr. | Q24: =Auszahlungen!X83 -> 6762900 | S24: Soziodemographischer Sonderlastenausgleich (4. Rate; Art. 17a ff. FAG) AFGB 3700001000.347214 an AFGB 200399 / 3P.FA | V24: Fr. | W24: =Auszahlungen!AG83 -> 6897700
A27: Sonderlastenausgleich Stadt (1. Rate; Art. 24 ff. FAG) AFGB 3700001000.347213 an AFGB 200399 / 3P.FA | D27: Fr. | E27: =Auszahlungen!G83 -> 4334300 | G27: Sonderlastenausgleich Stadt (2. Rate; Art. 24 ff. FAG) AFGB 3700001000.347213 an AFGB 200399 / 3P.FA | J27: Fr. | K27: =Auszahlungen!P83 -> 4334300 | M27: Sonderlastenausgleich Stadt (3. Rate; Art. 24 ff. FAG) AFGB 3700001000.347213 an AFGB 200399 / 3P.FA | P27: Fr. | Q27: =Auszahlungen!Y83 -> 4334300 | S27: Sonderlastenausgleich Stadt (4. Rate; Art. 24 ff. FAG) AFGB 3700001000.347213 an AFGB 200399 / 3P.FA | V27: Fr. | W27: =Auszahlungen!AH83 -> 4334400
A30: Total | D30: Fr. | E30: =Auszahlungen!H83 -> 58561500 | G30: Total | J30: Fr. | K30: =Auszahlungen!Q83 -> 58561500 | M30: Total | P30: Fr. | Q30: =Auszahlungen!Z83 -> 58516800 | S30: Total | V30: Fr. | W30: =Auszahlungen!AI83 -> 58648500

Sheet Serienbrief Verfügung
A1: Gemeinde | B1: Ressourcenausgleich | C1: Sonderlastenausgleich Weite | D1: Sonderlastenausgleich Schule | E1: Soziodemographischer Sonderlastenausgleich | F1: Sonderlastenausgleich Stadt St.Gallen | G1: Total | H1: Rat | I1: Adresse | J1: PLZ | K1: Ort
A2: St.Gallen | B2: =Total!C8 -> 0 | C2: =Total!D8 -> 0 | D2: =Total!E8 -> 0 | E2: =Total!F8 -> 16803100 | F2: =Total!G8 -> 17337300 | G2: =Total!H8 -> 34140400 | H2: Stadt | I2: Rathaus | J2: 9001 | K2: St.Gallen
A3: Wittenbach | B3: =Total!C9 -> 5419100 | C3: =Total!D9 -> 0 | D3: =Total!E9 -> 557200 | E3: =Total!F9 -> 653000 | F3: =Total!G9 -> 0 | G3: =Total!H9 -> 6629300 | H3: Gemeinde | I3: Dottenwilerstrasse 2 | J3: 9301 | K3: Wittenbach
A4: Häggenschwil | B4: =Total!C10 -> 598300 | C4: =Total!D10 -> 386600 | D4: =Total!E10 -> 560400 | E4: =Total!F10 -> 0 | F4: =Total!G10 -> 0 | G4: =Total!H10 -> 1545300 | H4: Gemeinde | I4: Dorfstrasse 18 | J4: 9312 | K4: Häggenschwil
A5: Muolen | B5: =Total!C11 -> 834600 | C5: =Total!D11 -> 624800 | D5: =Total!E11 -> 97300 | E5: =Total!F11 -> 0 | F5: =Total!G11 -> 0 | G5: =Total!H11 -> 1556700 | H5: Gemeinde | I5: Dorfstrasse 9 | J5: 9313 | K5: Muolen
A6: Mörschwil | B6: =Total!C12 -> 0 | C6: =Total!D12 -> 0 | D6: =Total!E12 -> 0 | E6: =Total!F12 -> 0 | F6: =Total!G12 -> 0 | G6: =Total!H12 -> 0 | H6: Gemeinde | I6: Schulstrasse 3 | J6: 9402 | K6: Mörschwil
A7: Goldach | B7: =Total!C13 -> 0 | C7: =Total!D13 -> 0 | D7: =Total!E13 -> 0 | E7: =Total!F13 -> 589900 | F7: =Total!G13 -> 0 | G7: =Total!H13 -> 589900 | H7: Gemeinde | I7: Hauptstrasse 2 | J7: 9403 | K7: Goldach
A8: Steinach | B8: =Total!C14 -> 254100 | C8: =Total!D14 -> 0 | D8: =Total!E14 -> 0 | E8: =Total!F14 -> 0 | F8: =Total!G14 -> 0 | G8: =Total!H14 -> 254100 | H8: Gemeinde | I8: Schulstrasse 5 | J8: 9323 | K8: Steinach
A9: Berg | B9: =Total!C15 -> 0 | C9: =Total!D15 -> 8100 | D9: =Total!E15 -> 40200 | E9: =Total!F15 -> 12100 | F9: =Total!G15 -> 0 | G9: =Total!H15 -> 60400 | H9: Gemeinde | I9: Dorfstrasse 17 | J9: 9305 | K9: Berg
A10: Tübach | B10: =Total!C16 -> 0 | C10: =Total!D16 -> 0 | D10: =Total!E16 -> 113700 | E10: =Total!F16 -> 0 | F10: =Total!G16 -> 0 | G10: =Total!H16 -> 113700 | H10: Gemeinde | I10: Kirchstrasse 18 | J10: 9327 | K10: Tübach
A11: Untereggen | B11: =Total!C17 -> 239500 | C11: =Total!D17 -> 298300 | D11: =Total!E17 -> 222200 | E11: =Total!F17 -> 0 | F11: =Total!G17 -> 0 | G11: =Total!H17 -> 760000 | H11: Gemeinde | I11: Mittlerhof 30 | J11: 9033 | K11: Untereggen
A12: Eggersriet | B12: =Total!C18 -> 288800 | C12: =Total!D18 -> 618300 | D12: =Total!E18 -> 361600 | E12: =Total!F18 -> 0 | F12: =Total!G18 -> 0 | G12: =Total!H18 -> 1268700 | H12: Gemeinde | I12: Heidenerstrasse 5 | J12: 9034 | K12: Eggersriet
A13: Rorschacherberg | B13: =Total!C19 -> 0 | C13: =Total!D19 -> 0 | D13: =Total!E19 -> 0 | E13: =Total!F19 -> 189300 | F13: =Total!G19 -> 0 | G13: =Total!H19 -> 189300 | H13: Gemeinde | I13: Goldacher Strasse 67 | J13: 9404 | K13: Rorschacherberg
... A76: Gaiserwald | B76: =Total!C82 -> 0 | C76: =Total!D82 -> 0 | D76: =Total!E82 -> 274000 | E76: =Total!F82 -> 6300 | F76: =Total!G82 -> 0 | G76: =Total!H82 -> 280300 | H76: Gemeinde | I76: Hauptstrasse 21 | J76: 9030 | K76: Abtwil
B77: =SUM(B2:B76) -> 121067800 | C77: =SUM(C2:C76) -> 35552500 | D77: =SUM(D2:D76) -> 33054900 | E77: =SUM(E2:E76) -> 27275800 | F77: =SUM(F2:F76) -> 17337300 | G77: =SUM(G2:G76) -> 234288300

Sheet Finanzausgleichsbeiträge
A1: Kanton St.Gallen
A2: Amt für Gemeinden und Bürgerrecht
A5: Definitive Finanzausgleichsbeiträge 2025
A7: Politische Gemeinde: | B7: bitte Gemeinde auswählen | H7: Nachkalkulation vom 05.11.2025
A10: Zusammensetzung und Raten
A12: Ausgleichsgefäss | D12: Total (bisher) | E12: Total (neu) | F12: 1. Rate (15. März) | G12: 2. Rate (15. Juni) | H12: 3. Rate (15. Sept.) | I12: 4. Rate (15. Dez.)
A13: Ressourcenausgleich | C13: Details | D13: =VLOOKUP(B7,Total!B7:O83,9,FALSE) -> #N/A | E13: =VLOOKUP(B7,Total!B7:H83,2,FALSE) -> #N/A | F13: =VLOOKUP(B7,Auszahlungen!B7:Z83,2,FALSE) -> #N/A | G13: =VLOOKUP(B7,Auszahlungen!B7:Z83,11,FALSE) -> #N/A | H13: =VLOOKUP(B7,Auszahlungen!B7:Z83,20,FALSE) -> #N/A | I13: =E13-F13-G13-H13 -> #N/A
A14: Sonderlastenausgleich Weite | C14: Details | D14: =VLOOKUP(B7,Total!B7:O83,10,FALSE) -> #N/A | E14: =VLOOKUP(B7,Total!B7:H83,3,FALSE) -> #N/A | F14: =VLOOKUP(B7,Auszahlungen!B7:Z83,3,FALSE) -> #N/A | G14: =VLOOKUP(B7,Auszahlungen!B7:Z83,12,FALSE) -> #N/A | H14: =VLOOKUP(B7,Auszahlungen!B7:Z83,21,FALSE) -> #N/A | I14: =E14-F14-G14-H14 -> #N/A
A15: Sonderlastenausgleich Schule | C15: Details | D15: =VLOOKUP(B7,Total!B7:O83,11,FALSE) -> #N/A | E15: =VLOOKUP(B7,Total!B7:H83,4,FALSE) -> #N/A | F15: =VLOOKUP(B7,Auszahlungen!B7:Z83,4,FALSE) -> #N/A | G15: =VLOOKUP(B7,Auszahlungen!B7:Z83,13,FALSE) -> #N/A | H15: =VLOOKUP(B7,Auszahlungen!B7:Z83,22,FALSE) -> #N/A | I15: =E15-F15-G15-H15 -> #N/A
A16: Soziodemographischer Sonderlastenausgleich | C16: Details | D16: =VLOOKUP(B7,Total!B7:O83,12,FALSE) -> #N/A | E16: =VLOOKUP(B7,Total!B7:H83,5,FALSE) -> #N/A | F16: =VLOOKUP(B7,Auszahlungen!B7:Z83,5,FALSE) -> #N/A | G16: =VLOOKUP(B7,Auszahlungen!B7:Z83,14,FALSE) -> #N/A | H16: =VLOOKUP(B7,Auszahlungen!B7:Z83,23,FALSE) -> #N/A | I16: =E16-F16-G16-H16 -> #N/A
A17: Sonderlastenausgleich Stadt | C17: Details | D17: =VLOOKUP(B7,Total!B7:O83,13,FALSE) -> #N/A | E17: =VLOOKUP(B7,Total!B7:H83,6,FALSE) -> #N/A | F17: =VLOOKUP(B7,Auszahlungen!B7:Z83,6,FALSE) -> #N/A | G17: =VLOOKUP(B7,Auszahlungen!B7:Z83,15,FALSE) -> #N/A | H17: =VLOOKUP(B7,Auszahlungen!B7:Z83,24,FALSE) -> #N/A | I17: =E17-F17-G17-H17 -> #N/A
A18: Total definitive Finanzausgleichsbeiträge | D18: =SUM(D13:D17) -> #N/A | E18: =SUM(E13:E17) -> #N/A | F18: =SUM(F13:F17) -> #N/A | G18: =SUM(G13:G17) -> #N/A | H18: =SUM(H13:H17) -> #N/A | I18: =SUM(I13:I17) -> #N/A
H20: =IF(B7="Gossau","Betrag von 29'800 Franken wurde der Stadt Gossau am 26.08.2025 in Rechnung gestellt.","")
A43: bitte Gemeinde auswählen
A44: Altstätten
A45: Amden
A46: Andwil
A47: Au
A48: Bad Ragaz
A49: Balgach
A50: Benken
A51: Berg
A52: Berneck
A53: Buchs
A54: Bütschwil-Ganterschwil
... A118: Zuzwil

Sheet Details Ressourcenausgleich
A1: Kanton St.Gallen
A2: Amt für Gemeinden und Bürgerrecht
A5: Ressourcenausgleich 2025
B7: für die Berechnung relevante Basisdaten
C9: Total | D9: =Finanzausgleichsbeiträge!B7 -> bitte Gemeinde auswählen
A11: 1.) | B11: ='Ressourcenausgleich Basis'!B10 -> Steuerdaten 2023
A13: 1.1) | B13: ='Ressourcenausgleich Basis'!B12 -> Einkommens-/Vermögenssteuer
B14: ='Ressourcenausgleich Basis'!B13 -> Steuerfuss | C14: =HLOOKUP(C$9,'Ressourcenausgleich Basis'!$C$8:$BZ$151,6,FALSE) -> 1.112714 | D14: =HLOOKUP(D$9,'Ressourcenausgleich Basis'!$C$8:$BZ$151,6,FALSE) -> #N/A
B16: ='Ressourcenausgleich Basis'!B15 -> Einfache Steuer Brutto | C16: =HLOOKUP(C$9,'Ressourcenausgleich Basis'!$C$8:$BZ$151,8,FALSE) -> 1.267089e+09 | D16: =HLOOKUP(D$9,'Ressourcenausgleich Basis'!$C$8:$BZ$151,8,FALSE) -> #N/A
B17: ='Ressourcenausgleich Basis'!B16 -> Abschreibungen | C17: =HLOOKUP(C$9,'Ressourcenausgleich Basis'!$C$8:$BZ$151,9,FALSE) -> 3942852.1 | D17: =HLOOKUP(D$9,'Ressourcenausgleich Basis'!$C$8:$BZ$151,9,FALSE) -> #N/A
B18: ='Ressourcenausgleich Basis'!B17 -> Einfache Steuer Netto | C18: =HLOOKUP(C$9,'Ressourcenausgleich Basis'!$C$8:$BZ$151,10,FALSE) -> 1.2631462e+09 | D18: =HLOOKUP(D$9,'Ressourcenausgleich Basis'!$C$8:$BZ$151,10,FALSE) -> #N/A
B20: ='Ressourcenausgleich Basis'!B19 -> Effektiver Nettoertrag | C20: =HLOOKUP(C$9,'Ressourcenausgleich Basis'!$C$8:$BZ$151,12,FALSE) -> 1.4055204e+09 | D20: =HLOOKUP($D$9,'Ressourcenausgleich Basis'!$C$8:$BZ$151,12,FALSE) -> #N/A
B22: ='Ressourcenausgleich Basis'!B21 -> Standardisierter Ertrag | C22: =HLOOKUP(C$9,'Ressourcenausgleich Basis'!$C$8:$BZ$151,14,FALSE) -> 1.4055204e+09 | D22: =HLOOKUP($D$9,'Ressourcenausgleich Basis'!$C$8:$BZ$151,14,FALSE) -> #N/A
A24: 1.2) | B24: ='Ressourcenausgleich Basis'!B23 -> Quellensteuer
B25: ='Ressourcenausgleich Basis'!B24 -> Bruttoertrag | C25: =HLOOKUP(C$9,'Ressourcenausgleich Basis'!$C$8:$BZ$151,17,FALSE) -> 82950711 | D25: =HLOOKUP(D$9,'Ressourcenausgleich Basis'!$C$8:$BZ$151,17,FALSE) -> #N/A
B26: ='Ressourcenausgleich Basis'!B25 -> Abschreibungen | C26: =HLOOKUP(C$9,'Ressourcenausgleich Basis'!$C$8:$BZ$151,18,FALSE) -> 545968.24 | D26: =HLOOKUP(D$9,'Ressourcenausgleich Basis'!$C$8:$BZ$151,18,FALSE) -> #N/A
B27: ='Ressourcenausgleich Basis'!B26 -> Nettoertrag (standardisierter Ertrag) | C27: =HLOOKUP(C$9,'Ressourcenausgleich Basis'!$C$8:$BZ$151,19,FALSE) -> 82404742 | D27: =HLOOKUP(D$9,'Ressourcenausgleich Basis'!$C$8:$BZ$151,19,FALSE) -> #N/A
A29: 1.3) | B29: ='Ressourcenausgleich Basis'!B28 -> Gewinn- und Kapitalsteuer
B30: ='Ressourcenausgleich Basis'!B29 -> Bruttoertrag | C30: =HLOOKUP(C$9,'Ressourcenausgleich Basis'!$C$8:$BZ$151,22,FALSE) -> 1.9263074e+08 | D30: =HLOOKUP(D$9,'Ressourcenausgleich Basis'!$C$8:$BZ$151,22,FALSE) -> #N/A
B31: ='Ressourcenausgleich Basis'!B30 -> Abschreibungen | C31: =HLOOKUP(C$9,'Ressourcenausgleich Basis'!$C$8:$BZ$151,23,FALSE) -> 1363211 | D31: =HLOOKUP(D$9,'Ressourcenausgleich Basis'!$C$8:$BZ$151,23,FALSE) -> #N/A
B32: ='Ressourcenausgleich Basis'!B31 -> pauschale Steueranrechnung | C32: =HLOOKUP(C$9,'Ressourcenausgleich Basis'!$C$8:$BZ$151,24,FALSE) -> 672651.9 | D32: =HLOOKUP(D$9,'Ressourcenausgleich Basis'!$C$8:$BZ$151,24,FALSE) -> #N/A
B33: ='Ressourcenausgleich Basis'!B32 -> Nettoertrag (standardisierter Ertrag) | C33: =HLOOKUP(C$9,'Ressourcenausgleich Basis'!$C$8:$BZ$151,25,FALSE) -> 1.9059488e+08 | D33: =HLOOKUP(D$9,'Ressourcenausgleich Basis'!$C$8:$BZ$151,25,FALSE) -> #N/A
A35: 1.4) | B35: ='Ressourcenausgleich Basis'!B34 -> Grundsteuer (ord. Satz)
B36: ='Ressourcenausgleich Basis'!B35 -> Steuersatz in ‰ | C36: =HLOOKUP(C$9,'Ressourcenausgleich Basis'!$C$8:$BZ$151,28,FALSE) -> 0.68623685 | D36: =HLOOKUP(D$9,'Ressourcenausgleich Basis'!$C$8:$BZ$151,28,FALSE) -> #N/A
B38: ='Ressourcenausgleich Basis'!B37 -> Bruttoertrag | C38: =HLOOKUP(C$9,'Ressourcenausgleich Basis'!$C$8:$BZ$151,30,FALSE) -> 1.0333655e+08 | D38: =HLOOKUP(D$9,'Ressourcenausgleich Basis'!$C$8:$BZ$151,30,FALSE) -> #N/A
B39: ='Ressourcenausgleich Basis'!B38 -> Erlasse/Verluste | C39: =HLOOKUP(C$9,'Ressourcenausgleich Basis'!$C$8:$BZ$151,31,FALSE) -> 2871.4 | D39: =HLOOKUP(D$9,'Ressourcenausgleich Basis'!$C$8:$BZ$151,31,FALSE) -> #N/A
B40: ='Ressourcenausgleich Basis'!B39 -> Nettoertrag | C40: =HLOOKUP(C$9,'Ressourcenausgleich Basis'!$C$8:$BZ$151,32,FALSE) -> 1.0333367e+08 | D40: =HLOOKUP(D$9,'Ressourcenausgleich Basis'!$C$8:$BZ$151,32,FALSE) -> #N/A
B42: ='Ressourcenausgleich Basis'!B41 -> Ertrag bei Satz von 1‰ | C42: =HLOOKUP(C$9,'Ressourcenausgleich Basis'!$C$8:$BZ$151,34,FALSE) -> 1.5058019e+08 | D42: =HLOOKUP(D$9,'Ressourcenausgleich Basis'!$C$8:$BZ$151,34,FALSE) -> #N/A
B44: ='Ressourcenausgleich Basis'!B43 -> Standardisierter Ertrag | C44: =HLOOKUP(C$9,'Ressourcenausgleich Basis'!$C$8:$BZ$151,36,FALSE) -> 1.0333367e+08 | D44: =HLOOKUP(D$9,'Ressourcenausgleich Basis'!$C$8:$BZ$151,36,FALSE) -> #N/A
A46: 1.5) | B46: ='Ressourcenausgleich Basis'!B45 -> Grundsteuer (Spezialsatz)
B47: ='Ressourcenausgleich Basis'!B46 -> Bruttoertrag | C47: =HLOOKUP(C$9,'Ressourcenausgleich Basis'!$C$8:$BZ$151,39,FALSE) -> 1630051.2 | D47: =HLOOKUP(D$9,'Ressourcenausgleich Basis'!$C$8:$BZ$151,39,FALSE) -> #N/A
B48: ='Ressourcenausgleich Basis'!B47 -> Erlasse/Verluste | C48: =HLOOKUP(C$9,'Ressourcenausgleich Basis'!$C$8:$BZ$151,40,FALSE) -> 12.11 | D48: =HLOOKUP(D$9,'Ressourcenausgleich Basis'!$C$8:$BZ$151,40,FALSE) -> #N/A
B49: ='Ressourcenausgleich Basis'!B48 -> Nettoertrag (standardisierter Ertrag) | C49: =HLOOKUP(C$9,'Ressourcenausgleich Basis'!$C$8:$BZ$151,41,FALSE) -> 1630039.1 | D49: =HLOOKUP(D$9,'Ressourcenausgleich Basis'!$C$8:$BZ$151,41,FALSE) -> #N/A
A51: 1.6) | B51: ='Ressourcenausgleich Basis'!B50 -> Handänderungssteuer
B52: ='Ressourcenausgleich Basis'!B51 -> Bruttoertrag | C52: =HLOOKUP(C$9,'Ressourcenausgleich Basis'!$C$8:$BZ$151,44,FALSE) -> 59811726 | D52: =HLOOKUP(D$9,'Ressourcenausgleich Basis'!$C$8:$BZ$151,44,FALSE) -> #N/A
B53: ='Ressourcenausgleich Basis'!B52 -> Erlasse/Verluste | C53: =HLOOKUP(C$9,'Ressourcenausgleich Basis'!$C$8:$BZ$151,45,FALSE) -> 0 | D53: =HLOOKUP(D$9,'Ressourcenausgleich Basis'!$C$8:$BZ$151,45,FALSE) -> #N/A
B54: ='Ressourcenausgleich Basis'!B53 -> Nettoertrag (standardisierter Ertrag) | C54: =HLOOKUP(C$9,'Ressourcenausgleich Basis'!$C$8:$BZ$151,46,FALSE) -> 59811726 | D54: =HLOOKUP(D$9,'Ressourcenausgleich Basis'!$C$8:$BZ$151,46,FALSE) -> #N/A
A56: 1.7) | B56: ='Ressourcenausgleich Basis'!B55 -> Grundstückgewinnsteuer
B57: ='Ressourcenausgleich Basis'!B56 -> Bruttoertrag | C57: =HLOOKUP(C$9,'Ressourcenausgleich Basis'!$C$8:$BZ$151,49,FALSE) -> 93028694 | D57: =HLOOKUP(D$9,'Ressourcenausgleich Basis'!$C$8:$BZ$151,49,FALSE) -> #N/A
B58: ='Ressourcenausgleich Basis'!B57 -> Abschreibungen | C58: =HLOOKUP(C$9,'Ressourcenausgleich Basis'!$C$8:$BZ$151,50,FALSE) -> 3924.45 | D58: =HLOOKUP(D$9,'Ressourcenausgleich Basis'!$C$8:$BZ$151,50,FALSE) -> #N/A
B59: ='Ressourcenausgleich Basis'!B58 -> Nettoertrag (standardisierter Ertrag) | C59: =HLOOKUP(C$9,'Ressourcenausgleich Basis'!$C$8:$BZ$151,51,FALSE) -> 93024770 | D59: =HLOOKUP(D$9,'Ressourcenausgleich Basis'!$C$8:$BZ$151,51,FALSE) -> #N/A
A62: 2.) | B62: ='Ressourcenausgleich Basis'!B61 -> Steuerdaten 2022
A64: 2.1) | B64: ='Ressourcenausgleich Basis'!B63 -> Einkommens-/Vermögenssteuer
B65: ='Ressourcenausgleich Basis'!B64 -> Steuerfuss | C65: =HLOOKUP(C$9,'Ressourcenausgleich Basis'!$C$8:$BZ$151,57,FALSE) -> 1.1243039 | D65: =HLOOKUP(D$9,'Ressourcenausgleich Basis'!$C$8:$BZ$151,57,FALSE) -> #N/A
B67: ='Ressourcenausgleich Basis'!B66 -> Einfache Steuer Brutto | C67: =HLOOKUP(C$9,'Ressourcenausgleich Basis'!$C$8:$BZ$151,59,FALSE) -> 1.1902545e+09 | D67: =HLOOKUP(D$9,'Ressourcenausgleich Basis'!$C$8:$BZ$151,59,FALSE) -> #N/A
B68: ='Ressourcenausgleich Basis'!B67 -> Abschreibungen | C68: =HLOOKUP(C$9,'Ressourcenausgleich Basis'!$C$8:$BZ$151,60,FALSE) -> 4194886.4 | D68: =HLOOKUP(D$9,'Ressourcenausgleich Basis'!$C$8:$BZ$151,60,FALSE) -> #N/A
B69: ='Ressourcenausgleich Basis'!B68 -> Einfache Steuer Netto | C69: =HLOOKUP(C$9,'Ressourcenausgleich Basis'!$C$8:$BZ$151,61,FALSE) -> 1.1860596e+09 | D69: =HLOOKUP(D$9,'Ressourcenausgleich Basis'!$C$8:$BZ$151,61,FALSE) -> #N/A
B71: ='Ressourcenausgleich Basis'!B70 -> Effektiver Nettoertrag | C71: =HLOOKUP(C$9,'Ressourcenausgleich Basis'!$C$8:$BZ$151,63,FALSE) -> 1.3334915e+09 | D71: =HLOOKUP(D$9,'Ressourcenausgleich Basis'!$C$8:$BZ$151,63,FALSE) -> #N/A
B73: ='Ressourcenausgleich Basis'!B72 -> Standardisierter Ertrag | C73: =HLOOKUP(C$9,'Ressourcenausgleich Basis'!$C$8:$BZ$151,65,FALSE) -> 1.3334915e+09 | D73: =HLOOKUP(D$9,'Ressourcenausgleich Basis'!$C$8:$BZ$151,65,FALSE) -> #N/A
A75: 2.2) | B75: ='Ressourcenausgleich Basis'!B74 -> Quellensteuer
B76: ='Ressourcenausgleich Basis'!B75 -> Bruttoertrag | C76: =HLOOKUP(C$9,'Ressourcenausgleich Basis'!$C$8:$BZ$151,68,FALSE) -> 71317459 | D76: =HLOOKUP(D$9,'Ressourcenausgleich Basis'!$C$8:$BZ$151,68,FALSE) -> #N/A
B77: ='Ressourcenausgleich Basis'!B76 -> Abschreibungen | C77: =HLOOKUP(C$9,'Ressourcenausgleich Basis'!$C$8:$BZ$151,69,FALSE) -> 761087.46 | D77: =HLOOKUP(D$9,'Ressourcenausgleich Basis'!$C$8:$BZ$151,69,FALSE) -> #N/A
B78: ='Ressourcenausgleich Basis'!B77 -> Nettoertrag (standardisierter Ertrag) | C78: =HLOOKUP(C$9,'Ressourcenausgleich Basis'!$C$8:$BZ$151,70,FALSE) -> 70556371 | D78: =HLOOKUP(D$9,'Ressourcenausgleich Basis'!$C$8:$BZ$151,70,FALSE) -> #N/A
A80: 2.3) | B80: ='Ressourcenausgleich Basis'!B79 -> Gewinn- und Kapitalsteuer
B81: ='Ressourcenausgleich Basis'!B80 -> Bruttoertrag | C81: =HLOOKUP(C$9,'Ressourcenausgleich Basis'!$C$8:$BZ$151,73,FALSE) -> 1.967179e+08 | D81: =HLOOKUP(D$9,'Ressourcenausgleich Basis'!$C$8:$BZ$151,73,FALSE) -> #N/A
B82: ='Ressourcenausgleich Basis'!B81 -> Abschreibungen | C82: =HLOOKUP(C$9,'Ressourcenausgleich Basis'!$C$8:$BZ$151,74,FALSE) -> 1744133.5 | D82: =HLOOKUP(D$9,'Ressourcenausgleich Basis'!$C$8:$BZ$151,74,FALSE) -> #N/A
B83: ='Ressourcenausgleich Basis'!B82 -> pauschale Steueranrechnung | C83: =HLOOKUP(C$9,'Ressourcenausgleich Basis'!$C$8:$BZ$151,75,FALSE) -> 276894.85 | D83: =HLOOKUP(D$9,'Ressourcenausgleich Basis'!$C$8:$BZ$151,75,FALSE) -> #N/A
B84: ='Ressourcenausgleich Basis'!B83 -> Nettoertrag (standardisierter Ertrag) | C84: =HLOOKUP(C$9,'Ressourcenausgleich Basis'!$C$8:$BZ$151,76,FALSE) -> 1.9469687e+08 | D84: =HLOOKUP(D$9,'Ressourcenausgleich Basis'!$C$8:$BZ$151,76,FALSE) -> #N/A
A86: 2.4) | B86: ='Ressourcenausgleich Basis'!B85 -> Grundsteuer (ord. Satz)
B87: ='Ressourcenausgleich Basis'!B86 -> Steuersatz in ‰ | C87: =HLOOKUP(C$9,'Ressourcenausgleich Basis'!$C$8:$BZ$151,79,FALSE) -> 0.69112917 | D87: =HLOOKUP(D$9,'Ressourcenausgleich Basis'!$C$8:$BZ$151,79,FALSE) -> #N/A
B89: ='Ressourcenausgleich Basis'!B88 -> Bruttoertrag | C89: =HLOOKUP(C$9,'Ressourcenausgleich Basis'!$C$8:$BZ$151,81,FALSE) -> 1.0026633e+08 | D89: =HLOOKUP(D$9,'Ressourcenausgleich Basis'!$C$8:$BZ$151,81,FALSE) -> #N/A
B90: ='Ressourcenausgleich Basis'!B89 -> Erlasse/Verluste | C90: =HLOOKUP(C$9,'Ressourcenausgleich Basis'!$C$8:$BZ$151,82,FALSE) -> 16646.19 | D90: =HLOOKUP(D$9,'Ressourcenausgleich Basis'!$C$8:$BZ$151,82,FALSE) -> #N/A
B91: ='Ressourcenausgleich Basis'!B90 -> Nettoertrag | C91: =HLOOKUP(C$9,'Ressourcenausgleich Basis'!$C$8:$BZ$151,83,FALSE) -> 1.0024968e+08 | D91: =HLOOKUP(D$9,'Ressourcenausgleich Basis'!$C$8:$BZ$151,83,FALSE) -> #N/A
B93: ='Ressourcenausgleich Basis'!B92 -> Ertrag bei Satz von 1‰ | C93: =HLOOKUP(C$9,'Ressourcenausgleich Basis'!$C$8:$BZ$151,85,FALSE) -> 1.4505202e+08 | D93: =HLOOKUP(D$9,'Ressourcenausgleich Basis'!$C$8:$BZ$151,85,FALSE) -> #N/A
B95: ='Ressourcenausgleich Basis'!B94 -> Standardisierter Ertrag | C95: =HLOOKUP(C$9,'Ressourcenausgleich Basis'!$C$8:$BZ$151,87,FALSE) -> 1.0024968e+08 | D95: =HLOOKUP(D$9,'Ressourcenausgleich Basis'!$C$8:$BZ$151,87,FALSE) -> #N/A
A97: 2.5) | B97: ='Ressourcenausgleich Basis'!B96 -> Grundsteuer (Spezialsatz)
B98: ='Ressourcenausgleich Basis'!B97 -> Bruttoertrag | C98: =HLOOKUP(C$9,'Ressourcenausgleich Basis'!$C$8:$BZ$151,90,FALSE) -> 1616929.5 | D98: =HLOOKUP(D$9,'Ressourcenausgleich Basis'!$C$8:$BZ$151,90,FALSE) -> #N/A
B99: ='Ressourcenausgleich Basis'!B98 -> Erlasse/Verluste | C99: =HLOOKUP(C$9,'Ressourcenausgleich Basis'!$C$8:$BZ$151,91,FALSE) -> 11.92 | D99: =HLOOKUP(D$9,'Ressourcenausgleich Basis'!$C$8:$BZ$151,91,FALSE) -> #N/A
B100: ='Ressourcenausgleich Basis'!B99 -> Nettoertrag (standardisierter Ertrag) | C100: =HLOOKUP(C$9,'Ressourcenausgleich Basis'!$C$8:$BZ$151,92,FALSE) -> 1616917.6 | D100: =HLOOKUP(D$9,'Ressourcenausgleich Basis'!$C$8:$BZ$151,92,FALSE) -> #N/A
A102: 2.6) | B102: ='Ressourcenausgleich Basis'!B101 -> Handänderungssteuer
B103: ='Ressourcenausgleich Basis'!B102 -> Bruttoertrag | C103: =HLOOKUP(C$9,'Ressourcenausgleich Basis'!$C$8:$BZ$151,95,FALSE) -> 66697906 | D103: =HLOOKUP(D$9,'Ressourcenausgleich Basis'!$C$8:$BZ$151,95,FALSE) -> #N/A
B104: ='Ressourcenausgleich Basis'!B103 -> Erlasse/Verluste | C104: =HLOOKUP(C$9,'Ressourcenausgleich Basis'!$C$8:$BZ$151,96,FALSE) -> 0 | D104: =HLOOKUP(D$9,'Ressourcenausgleich Basis'!$C$8:$BZ$151,96,FALSE) -> #N/A
B105: ='Ressourcenausgleich Basis'!B104 -> Nettoertrag (standardisierter Ertrag) | C105: =HLOOKUP(C$9,'Ressourcenausgleich Basis'!$C$8:$BZ$151,97,FALSE) -> 66697906 | D105: =HLOOKUP(D$9,'Ressourcenausgleich Basis'!$C$8:$BZ$151,97,FALSE) -> #N/A
A107: 2.7) | B107: ='Ressourcenausgleich Basis'!B106 -> Grundstückgewinnsteuer
B108: ='Ressourcenausgleich Basis'!B107 -> Bruttoertrag | C108: =HLOOKUP(C$9,'Ressourcenausgleich Basis'!$C$8:$BZ$151,100,FALSE) -> 1.0440682e+08 | D108: =HLOOKUP(D$9,'Ressourcenausgleich Basis'!$C$8:$BZ$151,100,FALSE) -> #N/A
B109: ='Ressourcenausgleich Basis'!B108 -> Abschreibungen | C109: =HLOOKUP(C$9,'Ressourcenausgleich Basis'!$C$8:$BZ$151,101,FALSE) -> 21810.15 | D109: =HLOOKUP(D$9,'Ressourcenausgleich Basis'!$C$8:$BZ$151,101,FALSE) -> #N/A
B110: ='Ressourcenausgleich Basis'!B109 -> Nettoertrag (standardisierter Ertrag) | C110: =HLOOKUP(C$9,'Ressourcenausgleich Basis'!$C$8:$BZ$151,102,FALSE) -> 1.0438501e+08 | D110: =HLOOKUP(D$9,'Ressourcenausgleich Basis'!$C$8:$BZ$151,102,FALSE) -> #N/A
A113: 3.) | B113: ='Ressourcenausgleich Basis'!B112 -> Berechnung der technischen Steuerkraft
A115: 3.1) | B115: ='Ressourcenausgleich Basis'!B114 -> Technische Steuerkraft 2023
B116: ='Ressourcenausgleich Basis'!B115 -> Einkommens-/Vermögenssteuer | C116: =HLOOKUP(C$9,'Ressourcenausgleich Basis'!$C$8:$BZ$151,108,FALSE) -> 1.4055204e+09 | D116: =HLOOKUP(D$9,'Ressourcenausgleich Basis'!$C$8:$BZ$151,108,FALSE) -> #N/A
B117: ='Ressourcenausgleich Basis'!B116 -> Quellensteuer | C117: =HLOOKUP(C$9,'Ressourcenausgleich Basis'!$C$8:$BZ$151,109,FALSE) -> 82404742 | D117: =HLOOKUP(D$9,'Ressourcenausgleich Basis'!$C$8:$BZ$151,109,FALSE) -> #N/A
B118: ='Ressourcenausgleich Basis'!B117 -> Gewinn- und Kapitalsteuer | C118: =HLOOKUP(C$9,'Ressourcenausgleich Basis'!$C$8:$BZ$151,110,FALSE) -> 1.9059488e+08 | D118: =HLOOKUP(D$9,'Ressourcenausgleich Basis'!$C$8:$BZ$151,110,FALSE) -> #N/A
B119: ='Ressourcenausgleich Basis'!B118 -> Grundsteuer (ord. Satz) | C119: =HLOOKUP(C$9,'Ressourcenausgleich Basis'!$C$8:$BZ$151,111,FALSE) -> 1.0333367e+08 | D119: =HLOOKUP(D$9,'Ressourcenausgleich Basis'!$C$8:$BZ$151,111,FALSE) -> #N/A
B120: ='Ressourcenausgleich Basis'!B119 -> Grundsteuer (Spezialsatz) | C120: =HLOOKUP(C$9,'Ressourcenausgleich Basis'!$C$8:$BZ$151,112,FALSE) -> 1630039.1 | D120: =HLOOKUP(D$9,'Ressourcenausgleich Basis'!$C$8:$BZ$151,112,FALSE) -> #N/A
B121: ='Ressourcenausgleich Basis'!B120 -> Handänderungssteuer | C121: =HLOOKUP(C$9,'Ressourcenausgleich Basis'!$C$8:$BZ$151,113,FALSE) -> 59811726 | D121: =HLOOKUP(D$9,'Ressourcenausgleich Basis'!$C$8:$BZ$151,113,FALSE) -> #N/A
B122: ='Ressourcenausgleich Basis'!B121 -> Grundstückgewinnsteuer | C122: =HLOOKUP(C$9,'Ressourcenausgleich Basis'!$C$8:$BZ$151,114,FALSE) -> 93024770 | D122: =HLOOKUP(D$9,'Ressourcenausgleich Basis'!$C$8:$BZ$151,114,FALSE) -> #N/A
B123: ='Ressourcenausgleich Basis'!B122 -> Total | C123: =HLOOKUP(C$9,'Ressourcenausgleich Basis'!$C$8:$BZ$151,115,FALSE) -> 1.9363202e+09 | D123: =HLOOKUP(D$9,'Ressourcenausgleich Basis'!$C$8:$BZ$151,115,FALSE) -> #N/A
B125: ='Ressourcenausgleich Basis'!B124 -> Einwohnerzahl per 31.12. | C125: =HLOOKUP(C$9,'Ressourcenausgleich Basis'!$C$8:$BZ$151,117,FALSE) -> 535114 | D125: =HLOOKUP(D$9,'Ressourcenausgleich Basis'!$C$8:$BZ$151,117,FALSE) -> #N/A
B127: ='Ressourcenausgleich Basis'!B126 -> Technische Steuerkraft pro Einwohner | C127: =HLOOKUP(C$9,'Ressourcenausgleich Basis'!$C$8:$BZ$151,119,FALSE) -> 3618.5191 | D127: =HLOOKUP(D$9,'Ressourcenausgleich Basis'!$C$8:$BZ$151,119,FALSE) -> #N/A
A129: 3.2) | B129: ='Ressourcenausgleich Basis'!B128 -> Technische Steuerkraft 2022
B130: ='Ressourcenausgleich Basis'!B129 -> Einkommens-/Vermögenssteuer | C130: =HLOOKUP(C$9,'Ressourcenausgleich Basis'!$C$8:$BZ$151,122,FALSE) -> 1.3334915e+09 | D130: =HLOOKUP(D$9,'Ressourcenausgleich Basis'!$C$8:$BZ$151,122,FALSE) -> #N/A
B131: ='Ressourcenausgleich Basis'!B130 -> Quellensteuer | C131: =HLOOKUP(C$9,'Ressourcenausgleich Basis'!$C$8:$BZ$151,123,FALSE) -> 70556371 | D131: =HLOOKUP(D$9,'Ressourcenausgleich Basis'!$C$8:$BZ$151,123,FALSE) -> #N/A
B132: ='Ressourcenausgleich Basis'!B131 -> Gewinn- und Kapitalsteuer | C132: =HLOOKUP(C$9,'Ressourcenausgleich Basis'!$C$8:$BZ$151,124,FALSE) -> 1.9469687e+08 | D132: =HLOOKUP(D$9,'Ressourcenausgleich Basis'!$C$8:$BZ$151,124,FALSE) -> #N/A
B133: ='Ressourcenausgleich Basis'!B132 -> Grundsteuer (ord. Satz) | C133: =HLOOKUP(C$9,'Ressourcenausgleich Basis'!$C$8:$BZ$151,125,FALSE) -> 1.0024968e+08 | D133: =HLOOKUP(D$9,'Ressourcenausgleich Basis'!$C$8:$BZ$151,125,FALSE) -> #N/A
B134: ='Ressourcenausgleich Basis'!B133 -> Grundsteuer (Spezialsatz) | C134: =HLOOKUP(C$9,'Ressourcenausgleich Basis'!$C$8:$BZ$151,126,FALSE) -> 1616917.6 | D134: =HLOOKUP(D$9,'Ressourcenausgleich Basis'!$C$8:$BZ$151,126,FALSE) -> #N/A
B135: ='Ressourcenausgleich Basis'!B134 -> Handänderungssteuer | C135: =HLOOKUP(C$9,'Ressourcenausgleich Basis'!$C$8:$BZ$151,127,FALSE) -> 66697906 | D135: =HLOOKUP(D$9,'Ressourcenausgleich Basis'!$C$8:$BZ$151,127,FALSE) -> #N/A
B136: ='Ressourcenausgleich Basis'!B135 -> Grundstückgewinnsteuer | C136: =HLOOKUP(C$9,'Ressourcenausgleich Basis'!$C$8:$BZ$151,128,FALSE) -> 1.0438501e+08 | D136: =HLOOKUP(D$9,'Ressourcenausgleich Basis'!$C$8:$BZ$151,128,FALSE) -> #N/A
B137: ='Ressourcenausgleich Basis'!B136 -> Total | C137: =HLOOKUP(C$9,'Ressourcenausgleich Basis'!$C$8:$BZ$151,129,FALSE) -> 1.8716942e+09 | D137: =HLOOKUP(D$9,'Ressourcenausgleich Basis'!$C$8:$BZ$151,129,FALSE) -> #N/A
B139: ='Ressourcenausgleich Basis'!B138 -> Einwohnerzahl per 31.12. | C139: =HLOOKUP(C$9,'Ressourcenausgleich Basis'!$C$8:$BZ$151,131,FALSE) -> 525967 | D139: =HLOOKUP(D$9,'Ressourcenausgleich Basis'!$C$8:$BZ$151,131,FALSE) -> #N/A
B141: ='Ressourcenausgleich Basis'!B140 -> Technische Steuerkraft pro Einwohner | C141: =HLOOKUP(C$9,'Ressourcenausgleich Basis'!$C$8:$BZ$151,133,FALSE) -> 3558.5773 | D141: =HLOOKUP(D$9,'Ressourcenausgleich Basis'!$C$8:$BZ$151,133,FALSE) -> #N/A
...

Sheet Details SL Weite
A1: Kanton St.Gallen
A2: Amt für Gemeinden und Bürgerrecht
A5: Sonderlastenausgleich Weite 2025
B7: für die Berechnung relevante Basisdaten
C9: Total | D9: =Finanzausgleichsbeiträge!B7 -> bitte Gemeinde auswählen
A11: 1.) | B11: ='SL Weite Basis'!B10 -> Allgemeine Daten
B13: ='SL Weite Basis'!B12 -> Einwohnerzahl per 31.12. | C13: =HLOOKUP(C$9,'SL Weite Basis'!$C$8:$BZ$74,5,FALSE) -> 535114 | D13: =HLOOKUP(D$9,'SL Weite Basis'!$C$8:$BZ$74,5,FALSE) -> #N/A
A16: 2.) | B16: ='SL Weite Basis'!B15 -> Berechnung Sonderlastenausgleich Weite
A18: 2.1) | B18: ='SL Weite Basis'!B17 -> Länge des Strassennetzes
B20: ='SL Weite Basis'!B19 -> gewichtete Strassenlänge in km per 31.12. | C20: =HLOOKUP(C$9,'SL Weite Basis'!$C$8:$BZ$74,12,FALSE) -> 125235.24 | D20: =HLOOKUP(D$9,'SL Weite Basis'!$C$8:$BZ$74,12,FALSE) -> #N/A
B21: ='SL Weite Basis'!B20 -> gewichtete Strassenlänge in km pro Einwohner | D21: =HLOOKUP(D$9,'SL Weite Basis'!$C$8:$BZ$74,13,FALSE) -> #N/A
B22: ='SL Weite Basis'!B21 -> Pauschalbeitrag je gewichtetem Kilometer | C22: =HLOOKUP(C$9,'SL Weite Basis'!$C$8:$BZ$74,14,FALSE) -> 1166
B23: ='SL Weite Basis'!B22 -> Beitrag je Einwohner | D23: =HLOOKUP(D$9,'SL Weite Basis'!$C$8:$BZ$74,15,FALSE) -> #N/A
B25: ='SL Weite Basis'!B24 -> Sonderlast total | D25: =HLOOKUP(D$9,'SL Weite Basis'!$C$8:$BZ$74,17,FALSE) -> #N/A
A27: 2.2) | B27: ='SL Weite Basis'!B26 -> Wohnbevölkerung mit Wohnsitz über 800 Metern über Meer
B29: ='SL Weite Basis'!B28 -> Einwohner über 800m per 31.12. | C29: =HLOOKUP(C$9,'SL Weite Basis'!$C$8:$BZ$74,21,FALSE) -> 21712 | D29: =HLOOKUP(D$9,'SL Weite Basis'!$C$8:$BZ$74,21,FALSE) -> #N/A
B30: ='SL Weite Basis'!B29 -> Anteil an Gesamtbevölkerung | D30: =HLOOKUP(D$9,'SL Weite Basis'!$C$8:$BZ$74,22,FALSE) -> #N/A
B31: ='SL Weite Basis'!B30 -> Pauschalbeitrag je Einwohner | C31: =HLOOKUP(C$9,'SL Weite Basis'!$C$8:$BZ$74,23,FALSE) -> 134
B32: ='SL Weite Basis'!B31 -> Beitrag je Einwohner | D32: =HLOOKUP(D$9,'SL Weite Basis'!$C$8:$BZ$74,24,FALSE) -> #N/A
B34: ='SL Weite Basis'!B33 -> Sonderlast total | D34: =HLOOKUP(D$9,'SL Weite Basis'!$C$8:$BZ$74,26,FALSE) -> #N/A
A36: 2.3) | B36: ='SL Weite Basis'!B35 -> Streuung des Siedlungsgebiets
B38: ='SL Weite Basis'!B37 -> Streuung des Siedlungsgebiets per 31.12. | C38: =HLOOKUP(C$9,'SL Weite Basis'!$C$8:$BZ$74,30,FALSE) -> 89559.804 | D38: =HLOOKUP(D$9,'SL Weite Basis'!$C$8:$BZ$74,30,FALSE) -> #N/A
B39: ='SL Weite Basis'!B38 -> Pauschalbeitrag je Einwohner | C39: =HLOOKUP(C$9,'SL Weite Basis'!$C$8:$BZ$74,31,FALSE) -> 0.008
B40: ='SL Weite Basis'!B39 -> Beitrag je Einwohner | D40: =HLOOKUP(D$9,'SL Weite Basis'!$C$8:$BZ$74,32,FALSE) -> #N/A
B42: ='SL Weite Basis'!B41 -> Sonderlast total | D42: =HLOOKUP(D$9,'SL Weite Basis'!$C$8:$BZ$74,34,FALSE) -> #N/A
A44: 2.4) | B44: ='SL Weite Basis'!B43 -> geringe Einwohnerdichte
B46: ='SL Weite Basis'!B45 -> Gemeindefläche in ha per 31.12. | C46: =HLOOKUP(C$9,'SL Weite Basis'!$C$8:$BZ$74,38,FALSE) -> 198379.11 | D46: =HLOOKUP(D$9,'SL Weite Basis'!$C$8:$BZ$74,38,FALSE) -> #N/A
B47: ='SL Weite Basis'!B46 -> Gemeindefläche je Einwohner | D47: =HLOOKUP(D$9,'SL Weite Basis'!$C$8:$BZ$74,39,FALSE) -> #N/A
B48: ='SL Weite Basis'!B47 -> Pauschalbeitrag je ha je Einwohner | C48: =HLOOKUP(C$9,'SL Weite Basis'!$C$8:$BZ$74,40,FALSE) -> 29
B49: ='SL Weite Basis'!B48 -> Beitrag je Einwohner | D49: =HLOOKUP(D$9,'SL Weite Basis'!$C$8:$BZ$74,41,FALSE) -> #N/A
B51: ='SL Weite Basis'!B50 -> Sonderlast total | D51: =HLOOKUP(D$9,'SL Weite Basis'!$C$8:$BZ$74,43,FALSE) -> #N/A
A53: 2.5) | B53: ='SL Weite Basis'!B52 -> Korrekturwert
B55: ='SL Weite Basis'!B54 -> Korrekturwert je Einwohner für mittlere Belastung | C55: =HLOOKUP(C$9,'SL Weite Basis'!$C$8:$BZ$74,47,FALSE) -> 320
B57: ='SL Weite Basis'!B56 -> Minderlast total | D57: =HLOOKUP(D$9,'SL Weite Basis'!$C$8:$BZ$74,49,FALSE) -> #N/A
A59: 2.6) | B59: ='SL Weite Basis'!B58 -> Sonderlastenausgleich Weite (vor allfälliger Kürzung)
A61: 2.7) | B61: ='SL Weite Basis'!B60 -> Kürzung infolge hoher technischer Steuerkraft
B63: ='SL Weite Basis'!B62 -> Technische Steuerkraft in % zum kantonalen Durchschnitt | D63: =HLOOKUP(D$9,'SL Weite Basis'!$C$8:$BZ$74,55,FALSE) -> #N/A
B65: ='SL Weite Basis'!B64 -> Kürzungsfaktor in % | D65: =HLOOKUP(D$9,'SL Weite Basis'!$C$8:$BZ$74,57,FALSE) -> #N/A
B66: ='SL Weite Basis'!B65 -> Kürzung in Fr. | D66: =HLOOKUP(D$9,'SL Weite Basis'!$C$8:$BZ$74,58,FALSE) -> #N/A
A69: 3.) | B69: ='SL Weite Basis'!B68 -> Zusammenfassung
B71: ='SL Weite Basis'!B70 -> Sonderlastenausgleich Weite (vor allfälliger Kürzung) | C71: =HLOOKUP(C$9,'SL Weite Basis'!$C$8:$BZ$74,63,FALSE) -> 37941178 | D71: =HLOOKUP(D$9,'SL Weite Basis'!$C$8:$BZ$74,63,FALSE) -> #N/A
B73: ='SL Weite Basis'!B72 -> Kürzung infolge hoher technischer Steuerkraft | C73: =HLOOKUP(C$9,'SL Weite Basis'!$C$8:$BZ$74,65,FALSE) -> -2388643.7 | D73: =HLOOKUP(D$9,'SL Weite Basis'!$C$8:$BZ$74,65,FALSE) -> #N/A
B75: ='SL Weite Basis'!B74 -> Beitrag Sonderlastenausgleich Weite | C75: =HLOOKUP(C$9,'SL Weite Basis'!$C$8:$BZ$74,67,FALSE) -> 35552500 | D75: =HLOOKUP(D$9,'SL Weite Basis'!$C$8:$BZ$74,67,FALSE) -> #N/A

Sheet Details SL Schule
A1: Kanton St.Gallen
A2: Amt für Gemeinden und Bürgerrecht
A5: Sonderlastenausgleich Schule 2025
B7: für die Berechnung relevante Basisdaten
C9: Total | D9: =Finanzausgleichsbeiträge!B7 -> bitte Gemeinde auswählen
A11: 1.) | B11: ='SL Schule Basis'!B10 -> Allgemeine Daten
B13: ='SL Schule Basis'!B12 -> Einwohnerzahl per 31.12. | C13: =HLOOKUP(C$9,'SL Schule Basis'!$C$8:$BZ$64,5,FALSE) -> 535114 | D13: =HLOOKUP(D$9,'SL Schule Basis'!$C$8:$BZ$64,5,FALSE) -> #N/A
B15: ='SL Schule Basis'!B14 -> Schülerzahlen Volksschule per 31.12.2023 | C15: =HLOOKUP(C$9,'SL Schule Basis'!$C$8:$BZ$64,7,FALSE) -> 60379 | D15: =HLOOKUP(D$9,'SL Schule Basis'!$C$8:$BZ$64,7,FALSE) -> #N/A
B16: ='SL Schule Basis'!B15 -> Schülerzahlen Sonderschule per 31.12.2023 | C16: =HLOOKUP(C$9,'SL Schule Basis'!$C$8:$BZ$64,8,FALSE) -> 1583 | D16: =HLOOKUP(D$9,'SL Schule Basis'!$C$8:$BZ$64,8,FALSE) -> #N/A
B18: ='SL Schule Basis'!B17 -> Nettoaufwand Schulrat in Einheitsgemeinden (Funktion 0121) | C18: =HLOOKUP(C$9,'SL Schule Basis'!$C$8:$BZ$64,10,FALSE) -> 6056128.4 | D18: =HLOOKUP(D$9,'SL Schule Basis'!$C$8:$BZ$64,10,FALSE) -> #N/A
B19: ='SL Schule Basis'!B18 -> Nettoaufwand Obligatorische Schule (Funktion 21) | C19: =HLOOKUP(C$9,'SL Schule Basis'!$C$8:$BZ$64,11,FALSE) -> 1.1954987e+09 | D19: =HLOOKUP(D$9,'SL Schule Basis'!$C$8:$BZ$64,11,FALSE) -> #N/A
B20: ='SL Schule Basis'!B19 -> Nettoaufwand Schulgesundheitsdienst in EHG (Funktion 433) | C20: =HLOOKUP(C$9,'SL Schule Basis'!$C$8:$BZ$64,12,FALSE) -> 3910715.7 | D20: =HLOOKUP(D$9,'SL Schule Basis'!$C$8:$BZ$64,12,FALSE) -> #N/A
B21: ='SL Schule Basis'!B20 -> Total | C21: =HLOOKUP(C$9,'SL Schule Basis'!$C$8:$BZ$64,13,FALSE) -> 1.2054656e+09 | D21: =HLOOKUP(D$9,'SL Schule Basis'!$C$8:$BZ$64,13,FALSE) -> #N/A
B23: ='SL Schule Basis'!B22 -> Kantonaler Durchschnitt Kosten je Schüler | C23: =HLOOKUP(C$9,'SL Schule Basis'!$C$8:$BZ$64,15,FALSE) -> 19964.981
A26: 2.) | B26: ='SL Schule Basis'!B25 -> Berechnung Sonderlastenausgleich Schule
A28: 2.1) | B28: ='SL Schule Basis'!B27 -> Sonder-/Minderlasten Volksschule
B30: ='SL Schule Basis'!B29 -> Beitragssatz Volksschule bei überdurchschnittlicher Belastung | C30: =HLOOKUP(C$9,'SL Schule Basis'!$C$8:$BZ$64,22,FALSE) -> 0.65
B31: ='SL Schule Basis'!B30 -> Beitragssatz Volksschule bei unterdurchschnittlicher Belastung | C31: =HLOOKUP(C$9,'SL Schule Basis'!$C$8:$BZ$64,23,FALSE) -> 0.2
B32: ='SL Schule Basis'!B31 -> Volksschüler je Einwohner | C32: =HLOOKUP(C$9,'SL Schule Basis'!$C$8:$BZ$64,24,FALSE) -> 0.1128339 | D32: =HLOOKUP(D$9,'SL Schule Basis'!$C$8:$BZ$64,24,FALSE) -> #N/A
B33: ='SL Schule Basis'!B32 -> BLD-Sozialindex per 31.12. | D33: =HLOOKUP(D$9,'SL Schule Basis'!$C$8:$BZ$64,25,FALSE) -> #N/A
B34: ='SL Schule Basis'!B33 -> reduzierter BLD-Sozialindex per 31.12. | D34: =HLOOKUP(D$9,'SL Schule Basis'!$C$8:$BZ$64,26,FALSE) -> #N/A
B36: ='SL Schule Basis'!B35 -> Sonder-/Minderlasten Volksschule (vor allfälliger Kürzung) | D36: =HLOOKUP(D$9,'SL Schule Basis'!$C$8:$BZ$64,28,FALSE) -> #N/A
A38: 2.2) | B38: ='SL Schule Basis'!B37 -> Sonderlasten Sonderschule
B40: ='SL Schule Basis'!B39 -> Pauschalbeitrag je Schüler in der Sonderschule | C40: =HLOOKUP(C$9,'SL Schule Basis'!$C$8:$BZ$64,32,FALSE) -> 11000
B41: ='SL Schule Basis'!B40 -> Beitragssatz Sonderschule | C41: =HLOOKUP(C$9,'SL Schule Basis'!$C$8:$BZ$64,33,FALSE) -> 0.65
B42: ='SL Schule Basis'!B41 -> Sonderschüler je Einwohner | C42: =HLOOKUP(C$9,'SL Schule Basis'!$C$8:$BZ$64,34,FALSE) -> 0.0029582481 | D42: =HLOOKUP(D$9,'SL Schule Basis'!$C$8:$BZ$64,34,FALSE) -> #N/A
B44: ='SL Schule Basis'!B43 -> Sonderlasten Sonderschule (vor allfälliger Kürzung) | D44: =HLOOKUP(D$9,'SL Schule Basis'!$C$8:$BZ$64,36,FALSE) -> #N/A
A46: 2.3) | B46: ='SL Schule Basis'!B45 -> Sonderlastenausgleich Schule (vor allfälliger Kürzung) | D46: =HLOOKUP(D$9,'SL Schule Basis'!$C$8:$BZ$64,38,FALSE) -> #N/A
A48: 2.4) | B48: ='SL Schule Basis'!B47 -> Kürzung infolge hoher technischer Steuerkraft
B50: ='SL Schule Basis'!B49 -> Technische Steuerkraft in % zum kantonalen Durchschnitt | D50: =HLOOKUP(D$9,'SL Schule Basis'!$C$8:$BZ$64,42,FALSE) -> #N/A
B52: ='SL Schule Basis'!B51 -> Kürzungsfaktor in % | D52: =HLOOKUP(D$9,'SL Schule Basis'!$C$8:$BZ$64,44,FALSE) -> #N/A
B53: ='SL Schule Basis'!B52 -> Kürzung in Fr. | D53: =HLOOKUP(D$9,'SL Schule Basis'!$C$8:$BZ$64,45,FALSE) -> #N/A
A56: 3.) | B56: ='SL Schule Basis'!B55 -> Zusammenfassung
B58: ='SL Schule Basis'!B57 -> Sonder-/Minderlasten Volksschule | C58: =HLOOKUP(C$9,'SL Schule Basis'!$C$8:$BZ$64,50,FALSE) -> 22242517 | D58: =HLOOKUP(D$9,'SL Schule Basis'!$C$8:$BZ$64,50,FALSE) -> #N/A
B59: ='SL Schule Basis'!B58 -> Sonderlasten Sonderschule | C59: =HLOOKUP(C$9,'SL Schule Basis'!$C$8:$BZ$64,51,FALSE) -> 1329536.9 | D59: =HLOOKUP(D$9,'SL Schule Basis'!$C$8:$BZ$64,51,FALSE) -> #N/A
B61: ='SL Schule Basis'!B60 -> Sonderlastenausgleich Schule (vor allfälliger Kürzung) | C61: =HLOOKUP(C$9,'SL Schule Basis'!$C$8:$BZ$64,53,FALSE) -> 34029883 | D61: =HLOOKUP(D$9,'SL Schule Basis'!$C$8:$BZ$64,53,FALSE) -> #N/A
B63: ='SL Schule Basis'!B62 -> Kürzung infolge hoher technischer Steuerkraft | C63: =HLOOKUP(C$9,'SL Schule Basis'!$C$8:$BZ$64,55,FALSE) -> -974984.31 | D63: =HLOOKUP(D$9,'SL Schule Basis'!$C$8:$BZ$64,55,FALSE) -> #N/A
B65: ='SL Schule Basis'!B64 -> Beitrag Sonderlastenausgleich Schule | C65: =HLOOKUP(C$9,'SL Schule Basis'!$C$8:$BZ$64,57,FALSE) -> 33054900 | D65: =HLOOKUP(D$9,'SL Schule Basis'!$C$8:$BZ$64,57,FALSE) -> #N/A

Sheet Details SL Sozio
A1: Kanton St.Gallen
A2: Amt für Gemeinden und Bürgerrecht
A5: Soziodemographischer Sonderlastenausgleich 2025
B7: für die Berechnung relevante Basisdaten
C9: Total | D9: =Finanzausgleichsbeiträge!B7 -> bitte Gemeinde auswählen
A11: 1.) | B11: ='SL Sozio Basis'!B10 -> Allgemeine Daten
B13: ='SL Sozio Basis'!B12 -> Einwohnerzahl per 31.12. | C13: =HLOOKUP(C$9,'SL Sozio Basis'!$C$8:$BZ$56,5,FALSE) -> 535114 | D13: =HLOOKUP(D$9,'SL Sozio Basis'!$C$8:$BZ$56,5,FALSE) -> #N/A
A16: 2.) | B16: ='SL Sozio Basis'!B15 -> Berechnung Soziodemographischer Sonderlastenausgleich
A18: 2.1) | B18: ='SL Sozio Basis'!B17 -> Sonderlasten Familie und Jugend
B20: ='SL Sozio Basis'!B19 -> Beitragssatz bei überdurchschnittlicher Belastung | C20: =HLOOKUP(C$9,'SL Sozio Basis'!$C$8:$BZ$56,12,FALSE) -> 0.6
B21: ='SL Sozio Basis'!B20 -> Beitragssatz bei unterdurchschnittlicher Belastung | C21: =HLOOKUP(C$9,'SL Sozio Basis'!$C$8:$BZ$56,13,FALSE) -> 0
B23: ='SL Sozio Basis'!B22 -> Nettoaufwand Familie und Jugend (Funktion 54) | C23: =HLOOKUP(C$9,'SL Sozio Basis'!$C$8:$BZ$56,15,FALSE) -> 72059794 | D23: =HLOOKUP(D$9,'SL Sozio Basis'!$C$8:$BZ$56,15,FALSE) -> #N/A
B24: ='SL Sozio Basis'!B23 -> Nettoaufwand Familie und Jugend pro Einwohner | C24: =HLOOKUP(C$9,'SL Sozio Basis'!$C$8:$BZ$56,16,FALSE) -> 134.66251 | D24: =HLOOKUP(D$9,'SL Sozio Basis'!$C$8:$BZ$56,16,FALSE) -> #N/A
B26: ='SL Sozio Basis'!B25 -> Sonderlasten Familie und Jugend | C26: =HLOOKUP(C$9,'SL Sozio Basis'!$C$8:$BZ$56,18,FALSE) -> 10062792 | D26: =HLOOKUP(D$9,'SL Sozio Basis'!$C$8:$BZ$56,18,FALSE) -> #N/A
A29: 2.2) | B29: ='SL Sozio Basis'!B28 -> Sonder-/Minderlasten Sozialhilfe
B31: ='SL Sozio Basis'!B30 -> Beitragssatz bei überdurchschnittlicher Belastung | C31: =HLOOKUP(C$9,'SL Sozio Basis'!$C$8:$BZ$56,23,FALSE) -> 0.6
B32: ='SL Sozio Basis'!B31 -> Beitragssatz bei unterdurchschnittlicher Belastung | C32: =HLOOKUP(C$9,'SL Sozio Basis'!$C$8:$BZ$56,24,FALSE) -> 0.2
B34: ='SL Sozio Basis'!B33 -> Nettoaufwand Finanzielle Sozialhilfe (Funktion 572) | C34: =HLOOKUP(C$9,'SL Sozio Basis'!$C$8:$BZ$56,26,FALSE) -> 63432251 | D34: =HLOOKUP(D$9,'SL Sozio Basis'!$C$8:$BZ$56,26,FALSE) -> #N/A
B35: ='SL Sozio Basis'!B34 -> Nettoaufwand Finanzielle Sozialhilfe pro Einwohner | C35: =HLOOKUP(C$9,'SL Sozio Basis'!$C$8:$BZ$56,27,FALSE) -> 118.5397 | D35: =HLOOKUP(D$9,'SL Sozio Basis'!$C$8:$BZ$56,27,FALSE) -> #N/A
B37: ='SL Sozio Basis'!B36 -> Sonder-/Minderlasten Sozialhilfe | C37: =HLOOKUP(C$9,'SL Sozio Basis'!$C$8:$BZ$56,29,FALSE) -> 7642281.4 | D37: =HLOOKUP(D$9,'SL Sozio Basis'!$C$8:$BZ$56,29,FALSE) -> #N/A
A40: 2.3) | B40: ='SL Sozio Basis'!B39 -> Sonder-/Minderlasten Stationäre Pflege
B42: ='SL Sozio Basis'!B41 -> Beitragssatz bei überdurchschnittlicher Belastung | C42: =HLOOKUP(C$9,'SL Sozio Basis'!$C$8:$BZ$56,34,FALSE) -> 0.6
B43: ='SL Sozio Basis'!B42 -> Beitragssatz bei unterdurchschnittlicher Belastung | C43: =HLOOKUP(C$9,'SL Sozio Basis'!$C$8:$BZ$56,35,FALSE) -> 0.2
B45: ='SL Sozio Basis'!B44 -> Nettoaufwand Stationäre Pflege | C45: =HLOOKUP(C$9,'SL Sozio Basis'!$C$8:$BZ$56,37,FALSE) -> 1.1522372e+08 | D45: =HLOOKUP(D$9,'SL Sozio Basis'!$C$8:$BZ$56,37,FALSE) -> #N/A
B46: ='SL Sozio Basis'!B45 -> Nettoaufwand Stationäre Pflege pro Einwohner | C46: =HLOOKUP(C$9,'SL Sozio Basis'!$C$8:$BZ$56,38,FALSE) -> 215.32556 | D46: =HLOOKUP(D$9,'SL Sozio Basis'!$C$8:$BZ$56,38,FALSE) -> #N/A
B48: ='SL Sozio Basis'!B47 -> Sonder-/Minderlasten Stationäre Pflege | C48: =HLOOKUP(C$9,'SL Sozio Basis'!$C$8:$BZ$56,40,FALSE) -> 4563466.9 | D48: =HLOOKUP(D$9,'SL Sozio Basis'!$C$8:$BZ$56,40,FALSE) -> #N/A
A51: 3.) | B51: ='SL Sozio Basis'!B50 -> Zusammenfassung
B53: ='SL Sozio Basis'!B52 -> Sonderlasten Familie und Jugend | C53: =HLOOKUP(C$9,'SL Sozio Basis'!$C$8:$BZ$56,45,FALSE) -> 10062792 | D53: =HLOOKUP(D$9,'SL Sozio Basis'!$C$8:$BZ$56,45,FALSE) -> #N/A
B54: ='SL Sozio Basis'!B53 -> Sonder-/Minderlasten Sozialhilfe | C54: =HLOOKUP(C$9,'SL Sozio Basis'!$C$8:$BZ$56,46,FALSE) -> 7642281.4 | D54: =HLOOKUP(D$9,'SL Sozio Basis'!$C$8:$BZ$56,46,FALSE) -> #N/A
B55: ='SL Sozio Basis'!B54 -> Sonder-/Minderlasten Stationäre Pflege | C55: =HLOOKUP(C$9,'SL Sozio Basis'!$C$8:$BZ$56,47,FALSE) -> 4563466.9 | D55: =HLOOKUP(D$9,'SL Sozio Basis'!$C$8:$BZ$56,47,FALSE) -> #N/A
B57: ='SL Sozio Basis'!B56 -> Beitrag Soziodemographischer Sonderlastenausgleich | C57: =HLOOKUP(C$9,'SL Sozio Basis'!$C$8:$BZ$56,49,FALSE) -> 27275800 | D57: =HLOOKUP(D$9,'SL Sozio Basis'!$C$8:$BZ$56,49,FALSE) -> #N/A

Sheet Details SL Stadt SG
A1: Kanton St.Gallen
A2: Amt für Gemeinden und Bürgerrecht
A5: Sonderlastenausgleich Stadt St.Gallen 2025
B7: für die Berechnung relevante Basisdaten
C9: =Finanzausgleichsbeiträge!B7 -> bitte Gemeinde auswählen
A11: 1.) | B11: ='SL Stadt SG Basis'!B10 -> Berechnung SL Stadt St.Gallen
B13: ='SL Stadt SG Basis'!B12 -> Ausgleichsbeitrag gemäss Art. 25 Abs. 1 FAG | C13: =HLOOKUP(C9,'SL Stadt SG Basis'!C8:C19,5,FALSE) -> #N/A
B14: ='SL Stadt SG Basis'!B13 -> zusätzlicher Ausgleichsbeitrag gemäss Art. 25 Abs. 2 FAG | C14: =HLOOKUP(C9,'SL Stadt SG Basis'!C8:C19,6,FALSE) -> #N/A
B16: ='SL Stadt SG Basis'!B15 -> Indexstand Juni 2007 (Basis) | C16: =HLOOKUP(C9,'SL Stadt SG Basis'!C8:C19,8,FALSE) -> #N/A | D16: (Dezember 2005 = 100)
B17: ='SL Stadt SG Basis'!B16 -> Indexstand Juni 2024 | C17: =HLOOKUP(C9,'SL Stadt SG Basis'!C8:C19,9,FALSE) -> #N/A
B19: ='SL Stadt SG Basis'!B18 -> Beitrag Sonderlastenausgleich Stadt St.Gallen | C19: =HLOOKUP(C9,'SL Stadt SG Basis'!C8:C19,11,FALSE) -> #N/A
